{
  "type": "Feature",
  "properties": {
    "gn:admin1_code":"15",
    "gn:admin2_code":"2090019",
    "gn:asciiname":"Lemau",
    "gn:country_code":"PG",
    "gn:dem":14,
    "gn:feature_class":"P",
    "gn:feature_code":"PPL",
    "gn:name":"Lemau",
    "gn:population":0,
    "gn:timezone":"Pacific/Port_Moresby",
    "iso:country":"PG",
    "wof:name":"Lemau",
    "wof:placetype":"locality"
},
  "geometry": {"coordinates":[151.63508000000004,-3.19587],"type":"Point"}
}