{
  "type": "Feature",
  "properties": {
    "gn:admin1_code":"18",
    "gn:asciiname":"Tumleo",
    "gn:country_code":"PG",
    "gn:dem":11,
    "gn:feature_class":"P",
    "gn:feature_code":"PPL",
    "gn:name":"Tumleo",
    "gn:population":0,
    "gn:timezone":"Pacific/Port_Moresby",
    "iso:country":"PG",
    "name:und_x_variant":[
        "Tumleo Hamlet",
        "Tumleo"
    ],
    "wof:name":"Tumleo",
    "wof:placetype":"locality"
},
  "geometry": {"coordinates":[142.39549,-3.12216],"type":"Point"}
}