{
  "type": "Feature",
  "properties": {
    "gn:admin1_code":"05",
    "gn:asciiname":"Segip",
    "gn:country_code":"PG",
    "gn:dem":2130,
    "gn:feature_class":"P",
    "gn:feature_code":"PPL",
    "gn:name":"Segip",
    "gn:population":0,
    "gn:timezone":"Pacific/Port_Moresby",
    "iso:country":"PG",
    "wof:name":"Segip",
    "wof:placetype":"locality"
},
  "geometry": {"coordinates":[143.66666999999995,-6.06667],"type":"Point"}
}