{
  "type": "Feature",
  "properties": {
    "gn:admin1_code":"11",
    "gn:asciiname":"Maprik 2",
    "gn:country_code":"PG",
    "gn:dem":205,
    "gn:feature_class":"P",
    "gn:feature_code":"PPL",
    "gn:name":"Maprik 2",
    "gn:population":0,
    "gn:timezone":"Pacific/Port_Moresby",
    "iso:country":"PG",
    "name:und_x_variant":[
        "Maprik Number 2",
        "Maprik 2"
    ],
    "wof:name":"Maprik 2",
    "wof:placetype":"locality"
},
  "geometry": {"coordinates":[143.03994,-3.63467],"type":"Point"}
}