{
  "type": "Feature",
  "properties": {
    "gn:admin1_code":"16",
    "gn:asciiname":"Kawga",
    "gn:country_code":"PG",
    "gn:dem":2622,
    "gn:feature_class":"P",
    "gn:feature_code":"PPL",
    "gn:name":"Kawga",
    "gn:population":0,
    "gn:timezone":"Pacific/Port_Moresby",
    "iso:country":"PG",
    "wof:name":"Kawga",
    "wof:placetype":"locality"
},
  "geometry": {"coordinates":[144.59999999999999,-5.98333],"type":"Point"}
}