{
  "type": "Feature",
  "properties": {
    "gn:admin1_code":"09",
    "gn:asciiname":"Kaininantu",
    "gn:country_code":"PG",
    "gn:dem":1614,
    "gn:feature_class":"P",
    "gn:feature_code":"PPL",
    "gn:name":"Kaininantu",
    "gn:population":0,
    "gn:timezone":"Pacific/Port_Moresby",
    "iso:country":"PG",
    "name:und_x_variant":[
        "Kaninantu",
        "Kaininantu"
    ],
    "wof:name":"Kaininantu",
    "wof:placetype":"locality"
},
  "geometry": {"coordinates":[145.90268999999995,-6.24745],"type":"Point"}
}