{
  "type": "Feature",
  "properties": {
    "gn:admin1_code":"14",
    "gn:asciiname":"Bwakugu",
    "gn:country_code":"PG",
    "gn:dem":1076,
    "gn:feature_class":"P",
    "gn:feature_code":"PPL",
    "gn:name":"Bwakugu",
    "gn:population":0,
    "gn:timezone":"Pacific/Port_Moresby",
    "iso:country":"PG",
    "wof:name":"Bwakugu",
    "wof:placetype":"locality"
},
  "geometry": {"coordinates":[147.5067,-6.44246],"type":"Point"}
}