{
  "type": "Feature",
  "properties": {
    "gn:admin1_code":"03",
    "gn:asciiname":"Kerepuna",
    "gn:cc2":"PG",
    "gn:country_code":"PG",
    "gn:dem":10,
    "gn:feature_class":"P",
    "gn:feature_code":"PPL",
    "gn:name":"Kerepuna",
    "gn:population":0,
    "gn:timezone":"Pacific/Port_Moresby",
    "iso:country":"PG",
    "name:und_x_variant":[
        "Kerepunu",
        "Keapara",
        "Kerepuna"
    ],
    "wof:name":"Kerepuna",
    "wof:placetype":"locality"
},
  "geometry": {"coordinates":[147.86345,-10.0999],"type":"Point"}
}