{
  "type": "Feature",
  "properties": {
    "gn:admin1_code":"07",
    "gn:asciiname":"Taki",
    "gn:country_code":"PG",
    "gn:dem":153,
    "gn:feature_class":"P",
    "gn:feature_code":"PPL",
    "gn:name":"Taki",
    "gn:population":0,
    "gn:timezone":"Pacific/Bougainville",
    "iso:country":"PG",
    "name:ben_x_preferred":[
        "\u099f\u09be\u0995\u09bf"
    ],
    "name:ceb_x_preferred":[
        "Taki"
    ],
    "name:deu_x_preferred":[
        "Taki"
    ],
    "name:fra_x_preferred":[
        "Taki"
    ],
    "name:ita_x_preferred":[
        "Taki"
    ],
    "name:msa_x_preferred":[
        "Taki"
    ],
    "name:rus_x_preferred":[
        "\u0422\u0430\u043a\u0438"
    ],
    "name:swe_x_preferred":[
        "Taki"
    ],
    "name:und_x_variant":[
        "Toki"
    ],
    "wof:name":"Taki",
    "wof:placetype":"locality"
},
  "geometry": {"coordinates":[155.82083,-6.47976],"type":"Point"}
}