{
  "type": "Feature",
  "properties": {
    "gn:admin1_code":"07",
    "gn:asciiname":"Taki",
    "gn:country_code":"PG",
    "gn:dem":153,
    "gn:feature_class":"P",
    "gn:feature_code":"PPL",
    "gn:name":"Taki",
    "gn:population":0,
    "gn:timezone":"Pacific/Bougainville",
    "iso:country":"PG",
    "name:und_x_variant":[
        "Toki",
        "Taki"
    ],
    "wof:name":"Taki",
    "wof:placetype":"locality"
},
  "geometry": {"coordinates":[155.82083,-6.47976],"type":"Point"}
}