{
  "type": "Feature",
  "properties": {
    "gn:admin1_code":"17",
    "gn:asciiname":"Babata",
    "gn:country_code":"PG",
    "gn:dem":450,
    "gn:feature_class":"P",
    "gn:feature_code":"PPL",
    "gn:name":"Babata",
    "gn:population":0,
    "gn:timezone":"Pacific/Port_Moresby",
    "iso:country":"PG",
    "wof:name":"Babata",
    "wof:placetype":"locality"
},
  "geometry": {"coordinates":[150.86628000000005,-5.65554],"type":"Point"}
}