{
  "type": "Feature",
  "properties": {
    "gn:admin1_code":"14",
    "gn:asciiname":"Badzuluo",
    "gn:country_code":"PG",
    "gn:dem":273,
    "gn:feature_class":"P",
    "gn:feature_code":"PPL",
    "gn:name":"Badzuluo",
    "gn:population":0,
    "gn:timezone":"Pacific/Port_Moresby",
    "iso:country":"PG",
    "wof:name":"Badzuluo",
    "wof:placetype":"locality"
},
  "geometry": {"coordinates":[147.79951,-6.40045],"type":"Point"}
}