{
  "type": "Feature",
  "properties": {
    "gn:admin1_code":"11",
    "gn:asciiname":"Yarapos",
    "gn:country_code":"PG",
    "gn:dem":9,
    "gn:feature_class":"P",
    "gn:feature_code":"PPL",
    "gn:name":"Yarapos",
    "gn:population":0,
    "gn:timezone":"Pacific/Port_Moresby",
    "iso:country":"PG",
    "name:und_x_variant":[
        "Yarapi",
        "Yarapos"
    ],
    "wof:name":"Yarapos",
    "wof:placetype":"locality"
},
  "geometry": {"coordinates":[143.56357,-3.52914],"type":"Point"}
}