{
  "type": "Feature",
  "properties": {
    "gn:admin1_code":"09",
    "gn:asciiname":"Losave",
    "gn:country_code":"PG",
    "gn:dem":1783,
    "gn:feature_class":"P",
    "gn:feature_code":"PPL",
    "gn:name":"Losave",
    "gn:population":0,
    "gn:timezone":"Pacific/Port_Moresby",
    "iso:country":"PG",
    "wof:name":"Losave",
    "wof:placetype":"locality"
},
  "geometry": {"coordinates":[145.30000000000001,-6.33333],"type":"Point"}
}