{
  "type": "Feature",
  "properties": {
    "gn:admin1_code":"06",
    "gn:asciiname":"Tobo",
    "gn:country_code":"PG",
    "gn:dem":1769,
    "gn:feature_class":"P",
    "gn:feature_code":"PPL",
    "gn:name":"Tobo",
    "gn:population":0,
    "gn:timezone":"Pacific/Port_Moresby",
    "iso:country":"PG",
    "wof:name":"Tobo",
    "wof:placetype":"locality"
},
  "geometry": {"coordinates":[142.71666999999999,-6.06667],"type":"Point"}
}