{
  "type": "Feature",
  "properties": {
    "gn:admin1_code":"06",
    "gn:asciiname":"Tobo",
    "gn:country_code":"PG",
    "gn:dem":1769,
    "gn:feature_class":"P",
    "gn:feature_code":"PPL",
    "gn:name":"Tobo",
    "gn:population":0,
    "gn:timezone":"Pacific/Port_Moresby",
    "iso:country":"PG",
    "name:ceb_x_preferred":[
        "Tobo"
    ],
    "name:epo_x_preferred":[
        "Tobo"
    ],
    "name:ita_x_preferred":[
        "Tobo"
    ],
    "name:nld_x_preferred":[
        "Tobo"
    ],
    "name:nno_x_preferred":[
        "Tobo"
    ],
    "name:nor_x_preferred":[
        "Tobo"
    ],
    "name:swe_x_preferred":[
        "Tobo"
    ],
    "wof:name":"Tobo",
    "wof:placetype":"locality"
},
  "geometry": {"coordinates":[142.71666999999999,-6.06667],"type":"Point"}
}