{
  "type": "Feature",
  "properties": {
    "gn:admin1_code":"01",
    "gn:asciiname":"Mava",
    "gn:country_code":"PG",
    "gn:dem":16,
    "gn:feature_class":"P",
    "gn:feature_code":"PPL",
    "gn:name":"Mava",
    "gn:population":0,
    "gn:timezone":"Pacific/Port_Moresby",
    "iso:country":"PG",
    "name:ceb_x_preferred":[
        "Mava"
    ],
    "name:swe_x_preferred":[
        "Mava"
    ],
    "wof:name":"Mava",
    "wof:placetype":"locality"
},
  "geometry": {"coordinates":[146.81666999999999,-9.01667],"type":"Point"}
}