{
  "type": "Feature",
  "properties": {
    "gn:admin1_code":"15",
    "gn:asciiname":"Farangot",
    "gn:country_code":"PG",
    "gn:dem":52,
    "gn:feature_class":"P",
    "gn:feature_code":"PPL",
    "gn:name":"Farangot",
    "gn:population":0,
    "gn:timezone":"Pacific/Port_Moresby",
    "iso:country":"PG",
    "wof:name":"Farangot",
    "wof:placetype":"locality"
},
  "geometry": {"coordinates":[153.64243000000005,-4.0191],"type":"Point"}
}