{
  "type": "Feature",
  "properties": {
    "gn:admin1_code":"17",
    "gn:asciiname":"Poi'iek",
    "gn:country_code":"PG",
    "gn:dem":1,
    "gn:feature_class":"P",
    "gn:feature_code":"PPL",
    "gn:name":"Poi\u2019iek",
    "gn:population":0,
    "gn:timezone":"Pacific/Port_Moresby",
    "iso:country":"PG",
    "wof:name":"Poi'iek",
    "wof:placetype":"locality"
},
  "geometry": {"coordinates":[149.78333000000001,-6.28333],"type":"Point"}
}