{
  "type": "Feature",
  "properties": {
    "gn:admin1_code":"04",
    "gn:asciiname":"Kuai",
    "gn:country_code":"PG",
    "gn:dem":784,
    "gn:feature_class":"P",
    "gn:feature_code":"PPL",
    "gn:name":"Kuai",
    "gn:population":0,
    "gn:timezone":"Pacific/Port_Moresby",
    "iso:country":"PG",
    "wof:name":"Kuai",
    "wof:placetype":"locality"
},
  "geometry": {"coordinates":[148.25436999999999,-9.18607],"type":"Point"}
}