{
  "type": "Feature",
  "properties": {
    "gn:admin1_code":"18",
    "gn:asciiname":"Naum",
    "gn:country_code":"PG",
    "gn:dem":75,
    "gn:feature_class":"P",
    "gn:feature_code":"PPL",
    "gn:name":"Naum",
    "gn:population":0,
    "gn:timezone":"Pacific/Port_Moresby",
    "iso:country":"PG",
    "name:bul_x_preferred":[
        "\u041d\u0430\u0443\u043c"
    ],
    "name:deu_x_preferred":[
        "Naum"
    ],
    "name:fra_x_preferred":[
        "Naum"
    ],
    "name:ita_x_preferred":[
        "Naum"
    ],
    "name:jpn_x_preferred":[
        "\u30ca\u30a6\u30e0"
    ],
    "name:rus_x_preferred":[
        "\u041d\u0430\u0443\u043c"
    ],
    "name:spa_x_preferred":[
        "Naum"
    ],
    "name:ukr_x_preferred":[
        "\u041d\u0430\u0443\u043c"
    ],
    "wof:name":"Naum",
    "wof:placetype":"locality"
},
  "geometry": {"coordinates":[141.86824999999999,-3.89104],"type":"Point"}
}