{
  "type": "Feature",
  "properties": {
    "gn:admin1_code":"18",
    "gn:asciiname":"Naum",
    "gn:country_code":"PG",
    "gn:dem":75,
    "gn:feature_class":"P",
    "gn:feature_code":"PPL",
    "gn:name":"Naum",
    "gn:population":0,
    "gn:timezone":"Pacific/Port_Moresby",
    "iso:country":"PG",
    "wof:name":"Naum",
    "wof:placetype":"locality"
},
  "geometry": {"coordinates":[141.86824999999999,-3.89104],"type":"Point"}
}