{
  "type": "Feature",
  "properties": {
    "gn:admin1_code":"09",
    "gn:asciiname":"Korova",
    "gn:country_code":"PG",
    "gn:dem":2044,
    "gn:feature_class":"P",
    "gn:feature_code":"PPL",
    "gn:name":"Korova",
    "gn:population":0,
    "gn:timezone":"Pacific/Port_Moresby",
    "iso:country":"PG",
    "name:und_x_variant":[
        "Korava",
        "Korova"
    ],
    "wof:name":"Korova",
    "wof:placetype":"locality"
},
  "geometry": {"coordinates":[145.28179,-6.34314],"type":"Point"}
}