{
  "type": "Feature",
  "properties": {
    "gn:admin1_code":"15",
    "gn:asciiname":"Tugitug",
    "gn:country_code":"PG",
    "gn:dem":1,
    "gn:feature_class":"P",
    "gn:feature_code":"PPL",
    "gn:name":"Tugitug",
    "gn:population":0,
    "gn:timezone":"Pacific/Port_Moresby",
    "iso:country":"PG",
    "name:und_x_variant":[
        "Toigitoig",
        "Tugitug"
    ],
    "wof:name":"Tugitug",
    "wof:placetype":"locality"
},
  "geometry": {"coordinates":[151.99761999999996,-2.76695],"type":"Point"}
}