{
  "type": "Feature",
  "properties": {
    "gn:admin1_code":"01",
    "gn:asciiname":"Labuka",
    "gn:country_code":"PG",
    "gn:dem":27,
    "gn:feature_class":"P",
    "gn:feature_code":"PPL",
    "gn:name":"Labuka",
    "gn:population":0,
    "gn:timezone":"Pacific/Port_Moresby",
    "iso:country":"PG",
    "name:und_x_variant":[
        "Rabuka",
        "Labuka"
    ],
    "wof:name":"Labuka",
    "wof:placetype":"locality"
},
  "geometry": {"coordinates":[147.34981000000005,-9.53268],"type":"Point"}
}