{
  "type": "Feature",
  "properties": {
    "gn:admin1_code":"08",
    "gn:asciiname":"Chuave",
    "gn:country_code":"PG",
    "gn:dem":1607,
    "gn:feature_class":"P",
    "gn:feature_code":"PPL",
    "gn:name":"Chuave",
    "gn:population":0,
    "gn:timezone":"Pacific/Port_Moresby",
    "iso:country":"PG",
    "wof:name":"Chuave",
    "wof:placetype":"locality"
},
  "geometry": {"coordinates":[145.13308000000001,-6.11391],"type":"Point"}
}