{
  "type": "Feature",
  "properties": {
    "gn:admin1_code":"13",
    "gn:asciiname":"Tingau Number 2",
    "gn:country_code":"PG",
    "gn:dem":329,
    "gn:feature_class":"P",
    "gn:feature_code":"PPL",
    "gn:name":"Tingau Number 2",
    "gn:population":0,
    "gn:timezone":"Pacific/Port_Moresby",
    "iso:country":"PG",
    "name:und_x_variant":[
        "Tingau 2",
        "Tingau Number 2"
    ],
    "wof:name":"Tingau Number 2",
    "wof:placetype":"locality"
},
  "geometry": {"coordinates":[147.08869999999999,-2.1041],"type":"Point"}
}