{
  "type": "Feature",
  "properties": {
    "gn:admin1_code":"13",
    "gn:asciiname":"Leihwa",
    "gn:country_code":"PG",
    "gn:dem":8,
    "gn:feature_class":"P",
    "gn:feature_code":"PPL",
    "gn:name":"Leihwa",
    "gn:population":0,
    "gn:timezone":"Pacific/Port_Moresby",
    "iso:country":"PG",
    "name:und_x_variant":[
        "Leihuwa",
        "Leihwa"
    ],
    "wof:name":"Leihwa",
    "wof:placetype":"locality"
},
  "geometry": {"coordinates":[146.92416,-1.97033],"type":"Point"}
}