{
  "type": "Feature",
  "properties": {
    "gn:admin1_code":"06",
    "gn:asciiname":"Pongaki",
    "gn:country_code":"PG",
    "gn:dem":32,
    "gn:feature_class":"P",
    "gn:feature_code":"PPL",
    "gn:name":"Pongaki",
    "gn:population":0,
    "gn:timezone":"Pacific/Port_Moresby",
    "iso:country":"PG",
    "name:und_x_variant":[
        "Pongali",
        "Pongati",
        "Pongal",
        "Pongaki"
    ],
    "wof:name":"Pongaki",
    "wof:placetype":"locality"
},
  "geometry": {"coordinates":[141.79651999999999,-8.70007],"type":"Point"}
}