{
  "type": "Feature",
  "properties": {
    "gn:admin1_code":"09",
    "gn:asciiname":"Amuyei",
    "gn:country_code":"PG",
    "gn:dem":1818,
    "gn:feature_class":"P",
    "gn:feature_code":"PPL",
    "gn:name":"Amuyei",
    "gn:population":0,
    "gn:timezone":"Pacific/Port_Moresby",
    "iso:country":"PG",
    "wof:name":"Amuyei",
    "wof:placetype":"locality"
},
  "geometry": {"coordinates":[145.46521000000001,-6.50106],"type":"Point"}
}