{
  "type": "Feature",
  "properties": {
    "gn:admin1_code":"01",
    "gn:asciiname":"Bidonagobu",
    "gn:country_code":"PG",
    "gn:dem":192,
    "gn:feature_class":"P",
    "gn:feature_code":"PPL",
    "gn:name":"Bidonagobu",
    "gn:population":0,
    "gn:timezone":"Pacific/Port_Moresby",
    "iso:country":"PG",
    "wof:name":"Bidonagobu",
    "wof:placetype":"locality"
},
  "geometry": {"coordinates":[148.00636,-9.74462],"type":"Point"}
}