{
  "type": "Feature",
  "properties": {
    "gn:admin1_code":"11",
    "gn:asciiname":"Baru",
    "gn:country_code":"PG",
    "gn:dem":31,
    "gn:feature_class":"P",
    "gn:feature_code":"PPL",
    "gn:name":"Baru",
    "gn:population":0,
    "gn:timezone":"Pacific/Port_Moresby",
    "iso:country":"PG",
    "name:ces_x_preferred":[
        "Baru"
    ],
    "name:nld_x_preferred":[
        "Baru"
    ],
    "name:spa_x_preferred":[
        "Baru"
    ],
    "wof:name":"Baru",
    "wof:placetype":"locality"
},
  "geometry": {"coordinates":[143.59999999999999,-3.35],"type":"Point"}
}