{
  "type": "Feature",
  "properties": {
    "gn:admin1_code":"01",
    "gn:asciiname":"Nora",
    "gn:country_code":"PG",
    "gn:dem":847,
    "gn:feature_class":"P",
    "gn:feature_code":"PPL",
    "gn:name":"Nora",
    "gn:population":0,
    "gn:timezone":"Pacific/Port_Moresby",
    "iso:country":"PG",
    "name:und_x_variant":[
        "Raekae",
        "Nora"
    ],
    "wof:name":"Nora",
    "wof:placetype":"locality"
},
  "geometry": {"coordinates":[149.57831000000004,-10.10339],"type":"Point"}
}