{
  "type": "Feature",
  "properties": {
    "gn:admin1_code":"11",
    "gn:asciiname":"Kamge",
    "gn:country_code":"PG",
    "gn:dem":85,
    "gn:feature_class":"P",
    "gn:feature_code":"PPL",
    "gn:name":"Kamge",
    "gn:population":0,
    "gn:timezone":"Pacific/Port_Moresby",
    "iso:country":"PG",
    "wof:name":"Kamge",
    "wof:placetype":"locality"
},
  "geometry": {"coordinates":[142.99958000000001,-3.77814],"type":"Point"}
}