{
  "type": "Feature",
  "properties": {
    "gn:admin1_code":"05",
    "gn:asciiname":"Mungura",
    "gn:country_code":"PG",
    "gn:dem":2107,
    "gn:feature_class":"P",
    "gn:feature_code":"PPL",
    "gn:name":"Mungura",
    "gn:population":0,
    "gn:timezone":"Pacific/Port_Moresby",
    "iso:country":"PG",
    "wof:name":"Mungura",
    "wof:placetype":"locality"
},
  "geometry": {"coordinates":[143.65000000000001,-6.01667],"type":"Point"}
}