{
  "type": "Feature",
  "properties": {
    "gn:admin1_code":"11",
    "gn:asciiname":"Sagasi",
    "gn:country_code":"PG",
    "gn:dem":134,
    "gn:feature_class":"P",
    "gn:feature_code":"PPL",
    "gn:name":"Sagasi",
    "gn:population":0,
    "gn:timezone":"Pacific/Port_Moresby",
    "iso:country":"PG",
    "name:und_x_variant":[
        "Sagasik",
        "Sagasi"
    ],
    "wof:name":"Sagasi",
    "wof:placetype":"locality"
},
  "geometry": {"coordinates":[143.15762000000001,-3.72914],"type":"Point"}
}