{
  "type": "Feature",
  "properties": {
    "gn:admin1_code":"12",
    "gn:asciiname":"Sorang",
    "gn:country_code":"PG",
    "gn:dem":230,
    "gn:feature_class":"P",
    "gn:feature_code":"PPL",
    "gn:name":"Sorang",
    "gn:population":0,
    "gn:timezone":"Pacific/Port_Moresby",
    "iso:country":"PG",
    "wof:name":"Sorang",
    "wof:placetype":"locality"
},
  "geometry": {"coordinates":[146.25479000000001,-5.62451],"type":"Point"}
}