{
  "type": "Feature",
  "properties": {
    "gn:admin1_code":"11",
    "gn:asciiname":"Waramuru",
    "gn:country_code":"PG",
    "gn:dem":618,
    "gn:feature_class":"P",
    "gn:feature_code":"PPL",
    "gn:name":"Waramuru",
    "gn:population":0,
    "gn:timezone":"Pacific/Port_Moresby",
    "iso:country":"PG",
    "wof:name":"Waramuru",
    "wof:placetype":"locality"
},
  "geometry": {"coordinates":[143.34786,-3.63449],"type":"Point"}
}