{
  "type": "Feature",
  "properties": {
    "gn:admin1_code":"15",
    "gn:asciiname":"Panamafei",
    "gn:country_code":"PG",
    "gn:dem":206,
    "gn:feature_class":"P",
    "gn:feature_code":"PPL",
    "gn:name":"Panamafei",
    "gn:population":0,
    "gn:timezone":"Pacific/Port_Moresby",
    "iso:country":"PG",
    "wof:name":"Panamafei",
    "wof:placetype":"locality"
},
  "geometry": {"coordinates":[151.17321999999999,-2.88697],"type":"Point"}
}