{
  "type": "Feature",
  "properties": {
    "gn:admin1_code":"03",
    "gn:asciiname":"Ulaolaoia",
    "gn:country_code":"PG",
    "gn:dem":463,
    "gn:feature_class":"P",
    "gn:feature_code":"PPL",
    "gn:name":"Ulaolaoia",
    "gn:population":0,
    "gn:timezone":"Pacific/Port_Moresby",
    "iso:country":"PG",
    "wof:name":"Ulaolaoia",
    "wof:placetype":"locality"
},
  "geometry": {"coordinates":[150.63333,-9.58333],"type":"Point"}
}