{
  "type": "Feature",
  "properties": {
    "gn:admin1_code":"09",
    "gn:asciiname":"Kirarigu",
    "gn:country_code":"PG",
    "gn:dem":1781,
    "gn:feature_class":"P",
    "gn:feature_code":"PPL",
    "gn:name":"Kirarigu",
    "gn:population":0,
    "gn:timezone":"Pacific/Port_Moresby",
    "iso:country":"PG",
    "wof:name":"Kirarigu",
    "wof:placetype":"locality"
},
  "geometry": {"coordinates":[145.18426000000005,-6.08292],"type":"Point"}
}