{
  "type": "Feature",
  "properties": {
    "gn:admin1_code":"15",
    "gn:asciiname":"Muliama",
    "gn:country_code":"PG",
    "gn:dem":231,
    "gn:feature_class":"P",
    "gn:feature_code":"PPL",
    "gn:name":"Muliama",
    "gn:population":0,
    "gn:timezone":"Pacific/Port_Moresby",
    "iso:country":"PG",
    "wof:name":"Muliama",
    "wof:placetype":"locality"
},
  "geometry": {"coordinates":[152.95813999999999,-4.06085],"type":"Point"}
}