{
  "type": "Feature",
  "properties": {
    "gn:admin1_code":"05",
    "gn:asciiname":"Taguanda",
    "gn:country_code":"PG",
    "gn:dem":2011,
    "gn:feature_class":"P",
    "gn:feature_code":"PPL",
    "gn:name":"Taguanda",
    "gn:population":0,
    "gn:timezone":"Pacific/Port_Moresby",
    "iso:country":"PG",
    "wof:name":"Taguanda",
    "wof:placetype":"locality"
},
  "geometry": {"coordinates":[143.98333,-6.41667],"type":"Point"}
}