{
  "type": "Feature",
  "properties": {
    "gn:admin1_code":"02",
    "gn:asciiname":"Ogomobu",
    "gn:cc2":"PG",
    "gn:country_code":"PG",
    "gn:dem":10,
    "gn:feature_class":"P",
    "gn:feature_code":"PPL",
    "gn:name":"Ogomobu",
    "gn:population":0,
    "gn:timezone":"Pacific/Port_Moresby",
    "iso:country":"PG",
    "name:und_x_variant":[
        "Ogamobu",
        "Ogomobu"
    ],
    "wof:name":"Ogomobu",
    "wof:placetype":"locality"
},
  "geometry": {"coordinates":[144.25,-7.38333],"type":"Point"}
}