{
  "type": "Feature",
  "properties": {
    "gn:admin1_code":"04",
    "gn:asciiname":"Savaia",
    "gn:country_code":"PG",
    "gn:dem":403,
    "gn:feature_class":"P",
    "gn:feature_code":"PPL",
    "gn:name":"Savaia",
    "gn:population":0,
    "gn:timezone":"Pacific/Port_Moresby",
    "iso:country":"PG",
    "name:ceb_x_preferred":[
        "Savaia"
    ],
    "wof:name":"Savaia",
    "wof:placetype":"locality"
},
  "geometry": {"coordinates":[147.71145000000001,-8.88796],"type":"Point"}
}