{
  "type": "Feature",
  "properties": {
    "gn:admin1_code":"17",
    "gn:asciiname":"Bolo",
    "gn:country_code":"PG",
    "gn:dem":199,
    "gn:feature_class":"P",
    "gn:feature_code":"PPL",
    "gn:name":"Bolo",
    "gn:population":0,
    "gn:timezone":"Pacific/Port_Moresby",
    "iso:country":"PG",
    "name:ceb_x_preferred":[
        "Bolo"
    ],
    "name:deu_x_preferred":[
        "Bolo"
    ],
    "name:fra_x_preferred":[
        "Bolo"
    ],
    "name:glg_x_preferred":[
        "Bolo"
    ],
    "name:nld_x_preferred":[
        "Bolo"
    ],
    "name:pol_x_preferred":[
        "Bolo"
    ],
    "name:por_x_preferred":[
        "Bolo"
    ],
    "name:spa_x_preferred":[
        "Bolo"
    ],
    "name:swe_x_preferred":[
        "Bolo"
    ],
    "name:tgl_x_preferred":[
        "Bolo"
    ],
    "name:und_x_variant":[
        "Bola",
        "Bolo"
    ],
    "wof:name":"Bolo",
    "wof:placetype":"locality"
},
  "geometry": {"coordinates":[149.13905,-5.60824],"type":"Point"}
}