{
  "type": "Feature",
  "properties": {
    "gn:admin1_code":"08",
    "gn:asciiname":"Waifo",
    "gn:country_code":"PG",
    "gn:dem":1770,
    "gn:feature_class":"P",
    "gn:feature_code":"PPL",
    "gn:name":"Waifo",
    "gn:population":0,
    "gn:timezone":"Pacific/Port_Moresby",
    "iso:country":"PG",
    "wof:name":"Waifo",
    "wof:placetype":"locality"
},
  "geometry": {"coordinates":[145.18971999999999,-6.18541],"type":"Point"}
}