{
  "type": "Feature",
  "properties": {
    "gn:admin1_code":"10",
    "gn:asciiname":"Vunatalia",
    "gn:country_code":"PG",
    "gn:dem":-9999,
    "gn:feature_class":"P",
    "gn:feature_code":"PPL",
    "gn:name":"Vunatalia",
    "gn:population":0,
    "gn:timezone":"Pacific/Port_Moresby",
    "iso:country":"PG",
    "wof:name":"Vunatalia",
    "wof:placetype":"locality"
},
  "geometry": {"coordinates":[151.83333000000005,-4.21667],"type":"Point"}
}