{
  "type": "Feature",
  "properties": {
    "gn:admin1_code":"04",
    "gn:asciiname":"Ombisusu",
    "gn:cc2":"PG",
    "gn:country_code":"PG",
    "gn:dem":123,
    "gn:feature_class":"P",
    "gn:feature_code":"PPL",
    "gn:name":"Ombisusu",
    "gn:population":0,
    "gn:timezone":"Pacific/Port_Moresby",
    "iso:country":"PG",
    "name:und_x_variant":[
        "Ombi",
        "Ombisusu"
    ],
    "wof:name":"Ombisusu",
    "wof:placetype":"locality"
},
  "geometry": {"coordinates":[147.98333,-8.88333],"type":"Point"}
}