{
  "type": "Feature",
  "properties": {
    "gn:admin1_code":"03",
    "gn:asciiname":"Darubia",
    "gn:country_code":"PG",
    "gn:dem":25,
    "gn:feature_class":"P",
    "gn:feature_code":"PPL",
    "gn:name":"Darubia",
    "gn:population":0,
    "gn:timezone":"Pacific/Port_Moresby",
    "iso:country":"PG",
    "name:und_x_variant":[
        "Darubia Mission",
        "Darubia"
    ],
    "wof:name":"Darubia",
    "wof:placetype":"locality"
},
  "geometry": {"coordinates":[150.99574999999999,-9.91939],"type":"Point"}
}