{
  "type": "Feature",
  "properties": {
    "gn:admin1_code":"04",
    "gn:asciiname":"Geite",
    "gn:country_code":"PG",
    "gn:dem":43,
    "gn:feature_class":"P",
    "gn:feature_code":"PPL",
    "gn:name":"Geite",
    "gn:population":0,
    "gn:timezone":"Pacific/Port_Moresby",
    "iso:country":"PG",
    "wof:name":"Geite",
    "wof:placetype":"locality"
},
  "geometry": {"coordinates":[148.15000000000001,-8.28333],"type":"Point"}
}