{
  "type": "Feature",
  "properties": {
    "gn:admin1_code":"14",
    "gn:asciiname":"Dokalang",
    "gn:country_code":"PG",
    "gn:dem":1673,
    "gn:feature_class":"P",
    "gn:feature_code":"PPL",
    "gn:name":"Dokalang",
    "gn:population":0,
    "gn:timezone":"Pacific/Port_Moresby",
    "iso:country":"PG",
    "name:und_x_variant":[
        "Dokaling",
        "Dokalang"
    ],
    "wof:name":"Dokalang",
    "wof:placetype":"locality"
},
  "geometry": {"coordinates":[146.98092,-6.38531],"type":"Point"}
}