{
  "type": "Feature",
  "properties": {
    "gn:admin1_code":"11",
    "gn:asciiname":"Badby",
    "gn:country_code":"PG",
    "gn:dem":27,
    "gn:feature_class":"P",
    "gn:feature_code":"PPL",
    "gn:name":"Badby",
    "gn:population":0,
    "gn:timezone":"Pacific/Port_Moresby",
    "iso:country":"PG",
    "name:ceb_x_preferred":[
        "Badby"
    ],
    "name:cym_x_preferred":[
        "Badby"
    ],
    "name:fas_x_preferred":[
        "\u0628\u062f\u0644\u06cc"
    ],
    "name:fra_x_preferred":[
        "Badby"
    ],
    "name:ita_x_preferred":[
        "Badby"
    ],
    "name:nld_x_preferred":[
        "Badby"
    ],
    "name:pol_x_preferred":[
        "Badby"
    ],
    "name:spa_x_preferred":[
        "Badby"
    ],
    "name:swe_x_preferred":[
        "Badby"
    ],
    "wof:name":"Badby",
    "wof:placetype":"locality"
},
  "geometry": {"coordinates":[143.09999999999999,-4.03333],"type":"Point"}
}