{
  "type": "Feature",
  "properties": {
    "gn:admin1_code":"12",
    "gn:asciiname":"Gwaringiri",
    "gn:country_code":"PG",
    "gn:dem":86,
    "gn:feature_class":"P",
    "gn:feature_code":"PPL",
    "gn:name":"Gwaringiri",
    "gn:population":0,
    "gn:timezone":"Pacific/Port_Moresby",
    "iso:country":"PG",
    "wof:name":"Gwaringiri",
    "wof:placetype":"locality"
},
  "geometry": {"coordinates":[144.89819,-5.10664],"type":"Point"}
}