{
  "type": "Feature",
  "properties": {
    "gn:admin1_code":"12",
    "gn:asciiname":"Jimenki",
    "gn:country_code":"PG",
    "gn:dem":62,
    "gn:feature_class":"P",
    "gn:feature_code":"PPL",
    "gn:name":"Jimenki",
    "gn:population":0,
    "gn:timezone":"Pacific/Port_Moresby",
    "iso:country":"PG",
    "name:und_x_variant":[
        "Jamenki"
    ],
    "wof:name":"Jimenki",
    "wof:placetype":"locality"
},
  "geometry": {"coordinates":[144.70507000000001,-5.11561],"type":"Point"}
}