{
  "type": "Feature",
  "properties": {
    "gn:admin1_code":"17",
    "gn:asciiname":"I'igi",
    "gn:country_code":"PG",
    "gn:dem":84,
    "gn:feature_class":"P",
    "gn:feature_code":"PPL",
    "gn:name":"I\u2019igi",
    "gn:population":0,
    "gn:timezone":"Pacific/Port_Moresby",
    "iso:country":"PG",
    "wof:name":"I'igi",
    "wof:placetype":"locality"
},
  "geometry": {"coordinates":[149.51667,-6.01667],"type":"Point"}
}