{
  "type": "Feature",
  "properties": {
    "gn:admin1_code":"03",
    "gn:asciiname":"Susukwai-Aleiwa",
    "gn:country_code":"PG",
    "gn:dem":161,
    "gn:feature_class":"P",
    "gn:feature_code":"PPL",
    "gn:name":"Susukwai-Aleiwa",
    "gn:population":0,
    "gn:timezone":"Pacific/Port_Moresby",
    "iso:country":"PG",
    "wof:name":"Susukwai-Aleiwa",
    "wof:placetype":"locality"
},
  "geometry": {"coordinates":[150.91666999999995,-9.85],"type":"Point"}
}