{
  "type": "Feature",
  "properties": {
    "gn:admin1_code":"03",
    "gn:asciiname":"Iapoa",
    "gn:country_code":"PG",
    "gn:dem":16,
    "gn:feature_class":"P",
    "gn:feature_code":"PPL",
    "gn:name":"Iapoa",
    "gn:population":0,
    "gn:timezone":"Pacific/Port_Moresby",
    "iso:country":"PG",
    "name:und_x_variant":[
        "Iopoa",
        "Iapoa"
    ],
    "wof:name":"Iapoa",
    "wof:placetype":"locality"
},
  "geometry": {"coordinates":[150.56943000000001,-10.25339],"type":"Point"}
}