{
  "type": "Feature",
  "properties": {
    "gn:admin1_code":"09",
    "gn:asciiname":"Ufagunofi",
    "gn:country_code":"PG",
    "gn:dem":2153,
    "gn:feature_class":"P",
    "gn:feature_code":"PPL",
    "gn:name":"Ufagunofi",
    "gn:population":0,
    "gn:timezone":"Pacific/Port_Moresby",
    "iso:country":"PG",
    "wof:name":"Ufagunofi",
    "wof:placetype":"locality"
},
  "geometry": {"coordinates":[145.69999999999999,-6.06667],"type":"Point"}
}