{
  "type": "Feature",
  "properties": {
    "gn:admin1_code":"10",
    "gn:asciiname":"Malasait",
    "gn:country_code":"PG",
    "gn:dem":410,
    "gn:feature_class":"P",
    "gn:feature_code":"PPL",
    "gn:name":"Malasait",
    "gn:population":0,
    "gn:timezone":"Pacific/Port_Moresby",
    "iso:country":"PG",
    "name:und_x_variant":[
        "Malaset",
        "Malasait"
    ],
    "wof:name":"Malasait",
    "wof:placetype":"locality"
},
  "geometry": {"coordinates":[151.87438,-4.46673],"type":"Point"}
}