{
  "type": "Feature",
  "properties": {
    "gn:admin1_code":"17",
    "gn:asciiname":"Angal",
    "gn:country_code":"PG",
    "gn:dem":364,
    "gn:feature_class":"P",
    "gn:feature_code":"PPL",
    "gn:name":"Angal",
    "gn:population":0,
    "gn:timezone":"Pacific/Port_Moresby",
    "iso:country":"PG",
    "wof:name":"Angal",
    "wof:placetype":"locality"
},
  "geometry": {"coordinates":[149.09544,-5.63671],"type":"Point"}
}