{
  "type": "Feature",
  "properties": {
    "gn:admin1_code":"12",
    "gn:asciiname":"Matafum",
    "gn:country_code":"PG",
    "gn:dem":39,
    "gn:feature_class":"P",
    "gn:feature_code":"PPL",
    "gn:name":"Matafum",
    "gn:population":0,
    "gn:timezone":"Pacific/Port_Moresby",
    "iso:country":"PG",
    "wof:name":"Matafum",
    "wof:placetype":"locality"
},
  "geometry": {"coordinates":[147.02077,-5.36485],"type":"Point"}
}