{
  "type": "Feature",
  "properties": {
    "gn:admin1_code":"01",
    "gn:asciiname":"Bore",
    "gn:country_code":"PG",
    "gn:dem":23,
    "gn:feature_class":"P",
    "gn:feature_code":"PPL",
    "gn:name":"Bore",
    "gn:population":0,
    "gn:timezone":"Pacific/Port_Moresby",
    "iso:country":"PG",
    "name:ceb_x_preferred":[
        "Bore"
    ],
    "name:deu_x_preferred":[
        "Bore"
    ],
    "name:fin_x_preferred":[
        "Bore"
    ],
    "name:fra_x_preferred":[
        "Bore"
    ],
    "name:hye_x_preferred":[
        "\u0532\u0578\u0580\u0565"
    ],
    "name:nld_x_preferred":[
        "Bore"
    ],
    "name:rus_x_preferred":[
        "\u0411\u043e\u0440\u0435"
    ],
    "name:srp_x_preferred":[
        "\u0411\u043e\u0440\u0435"
    ],
    "name:swe_x_preferred":[
        "Bore"
    ],
    "name:ukr_x_preferred":[
        "\u0411\u043e\u0440\u0435"
    ],
    "wof:name":"Bore",
    "wof:placetype":"locality"
},
  "geometry": {"coordinates":[147.75935000000001,-9.89453],"type":"Point"}
}