{
  "type": "Feature",
  "properties": {
    "gn:admin1_code":"12",
    "gn:asciiname":"Budamu",
    "gn:country_code":"PG",
    "gn:dem":1322,
    "gn:feature_class":"P",
    "gn:feature_code":"PPL",
    "gn:name":"Budamu",
    "gn:population":0,
    "gn:timezone":"Pacific/Port_Moresby",
    "iso:country":"PG",
    "wof:name":"Budamu",
    "wof:placetype":"locality"
},
  "geometry": {"coordinates":[146.04288,-5.68882],"type":"Point"}
}