{
  "type": "Feature",
  "properties": {
    "gn:admin1_code":"11",
    "gn:asciiname":"Selnau",
    "gn:country_code":"PG",
    "gn:dem":406,
    "gn:feature_class":"P",
    "gn:feature_code":"PPL",
    "gn:name":"Selnau",
    "gn:population":0,
    "gn:timezone":"Pacific/Port_Moresby",
    "iso:country":"PG",
    "wof:name":"Selnau",
    "wof:placetype":"locality"
},
  "geometry": {"coordinates":[142.85979,-3.53572],"type":"Point"}
}