{
  "type": "Feature",
  "properties": {
    "gn:admin1_code":"04",
    "gn:asciiname":"Gobe",
    "gn:country_code":"PG",
    "gn:dem":20,
    "gn:feature_class":"P",
    "gn:feature_code":"PPL",
    "gn:name":"Gobe",
    "gn:population":0,
    "gn:timezone":"Pacific/Port_Moresby",
    "iso:country":"PG",
    "name:ceb_x_preferred":[
        "Gobe"
    ],
    "name:swe_x_preferred":[
        "Gobe"
    ],
    "wof:name":"Gobe",
    "wof:placetype":"locality"
},
  "geometry": {"coordinates":[149.00692000000001,-9.06851],"type":"Point"}
}