{
  "type": "Feature",
  "properties": {
    "gn:admin1_code":"06",
    "gn:asciiname":"Hukim",
    "gn:country_code":"PG",
    "gn:dem":175,
    "gn:feature_class":"P",
    "gn:feature_code":"PPL",
    "gn:name":"Hukim",
    "gn:population":0,
    "gn:timezone":"Pacific/Port_Moresby",
    "iso:country":"PG",
    "wof:name":"Hukim",
    "wof:placetype":"locality"
},
  "geometry": {"coordinates":[141.05373,-5.55836],"type":"Point"}
}