{
  "type": "Feature",
  "properties": {
    "gn:admin1_code":"01",
    "gn:asciiname":"Mukunaroka",
    "gn:country_code":"PG",
    "gn:dem":412,
    "gn:feature_class":"P",
    "gn:feature_code":"PPL",
    "gn:name":"Mukunaroka",
    "gn:population":0,
    "gn:timezone":"Pacific/Port_Moresby",
    "iso:country":"PG",
    "wof:name":"Mukunaroka",
    "wof:placetype":"locality"
},
  "geometry": {"coordinates":[147.85893999999999,-9.80557],"type":"Point"}
}