{
  "type": "Feature",
  "properties": {
    "gn:admin1_code":"01",
    "gn:asciiname":"Old Berebei",
    "gn:country_code":"PG",
    "gn:dem":560,
    "gn:feature_class":"P",
    "gn:feature_code":"PPL",
    "gn:name":"Old Berebei",
    "gn:population":0,
    "gn:timezone":"Pacific/Port_Moresby",
    "iso:country":"PG",
    "name:und_x_variant":[
        "Berebei",
        "Birribi",
        "Old Berebei"
    ],
    "wof:name":"Old Berebei",
    "wof:placetype":"locality"
},
  "geometry": {"coordinates":[147.45813999999999,-9.50409],"type":"Point"}
}