{
  "type": "Feature",
  "properties": {
    "gn:admin1_code":"11",
    "gn:asciiname":"Tauhundon",
    "gn:country_code":"PG",
    "gn:dem":217,
    "gn:feature_class":"P",
    "gn:feature_code":"PPL",
    "gn:name":"Tauhundon",
    "gn:population":0,
    "gn:timezone":"Pacific/Port_Moresby",
    "iso:country":"PG",
    "name:und_x_variant":[
        "Tauhundor",
        "Tauhundon"
    ],
    "wof:name":"Tauhundon",
    "wof:placetype":"locality"
},
  "geometry": {"coordinates":[142.7183,-3.66335],"type":"Point"}
}