{
  "type": "Feature",
  "properties": {
    "gn:admin1_code":"11",
    "gn:asciiname":"Bulamita",
    "gn:country_code":"PG",
    "gn:dem":253,
    "gn:feature_class":"P",
    "gn:feature_code":"PPL",
    "gn:name":"Bulamita",
    "gn:population":0,
    "gn:timezone":"Pacific/Port_Moresby",
    "iso:country":"PG",
    "wof:name":"Bulamita",
    "wof:placetype":"locality"
},
  "geometry": {"coordinates":[142.89245,-3.58951],"type":"Point"}
}