{
  "type": "Feature",
  "properties": {
    "gn:admin1_code":"14",
    "gn:asciiname":"Mumunggan",
    "gn:country_code":"PG",
    "gn:dem":1843,
    "gn:feature_class":"P",
    "gn:feature_code":"PPL",
    "gn:name":"Mumunggan",
    "gn:population":0,
    "gn:timezone":"Pacific/Port_Moresby",
    "iso:country":"PG",
    "wof:name":"Mumunggan",
    "wof:placetype":"locality"
},
  "geometry": {"coordinates":[147.09721000000005,-6.19052],"type":"Point"}
}