{
  "type": "Feature",
  "properties": {
    "gn:admin1_code":"10",
    "gn:asciiname":"Vunapope",
    "gn:country_code":"PG",
    "gn:dem":29,
    "gn:feature_class":"P",
    "gn:feature_code":"PPL",
    "gn:name":"Vunapope",
    "gn:population":0,
    "gn:timezone":"Pacific/Port_Moresby",
    "iso:country":"PG",
    "wof:name":"Vunapope",
    "wof:placetype":"locality"
},
  "geometry": {"coordinates":[152.28333000000001,-4.35],"type":"Point"}
}