{
  "type": "Feature",
  "properties": {
    "gn:admin1_code":"09",
    "gn:asciiname":"Woibo",
    "gn:country_code":"PG",
    "gn:dem":1776,
    "gn:feature_class":"P",
    "gn:feature_code":"PPL",
    "gn:name":"Woibo",
    "gn:population":0,
    "gn:timezone":"Pacific/Port_Moresby",
    "iso:country":"PG",
    "wof:name":"Woibo",
    "wof:placetype":"locality"
},
  "geometry": {"coordinates":[145.88146,-6.82053],"type":"Point"}
}