{
  "type": "Feature",
  "properties": {
    "gn:admin1_code":"14",
    "gn:asciiname":"Menyi",
    "gn:country_code":"PG",
    "gn:dem":1464,
    "gn:feature_class":"P",
    "gn:feature_code":"PPL",
    "gn:name":"Menyi",
    "gn:population":0,
    "gn:timezone":"Pacific/Port_Moresby",
    "iso:country":"PG",
    "wof:name":"Menyi",
    "wof:placetype":"locality"
},
  "geometry": {"coordinates":[146.44999999999999,-7.26667],"type":"Point"}
}