{
  "type": "Feature",
  "properties": {
    "gn:admin1_code":"05",
    "gn:asciiname":"Arawia",
    "gn:country_code":"PG",
    "gn:dem":1663,
    "gn:feature_class":"P",
    "gn:feature_code":"PPL",
    "gn:name":"Arawia",
    "gn:population":0,
    "gn:timezone":"Pacific/Port_Moresby",
    "iso:country":"PG",
    "wof:name":"Arawia",
    "wof:placetype":"locality"
},
  "geometry": {"coordinates":[143.86667,-6.38333],"type":"Point"}
}