{
  "type": "Feature",
  "properties": {
    "gn:admin1_code":"11",
    "gn:asciiname":"Nilu 1",
    "gn:country_code":"PG",
    "gn:dem":497,
    "gn:feature_class":"P",
    "gn:feature_code":"PPL",
    "gn:name":"Nilu 1",
    "gn:population":0,
    "gn:timezone":"Pacific/Port_Moresby",
    "iso:country":"PG",
    "name:und_x_variant":[
        "Nilu",
        "Nilu 1"
    ],
    "wof:name":"Nilu 1",
    "wof:placetype":"locality"
},
  "geometry": {"coordinates":[142.95188999999999,-3.53714],"type":"Point"}
}