{
  "type": "Feature",
  "properties": {
    "gn:admin1_code":"18",
    "gn:asciiname":"Wainda",
    "gn:country_code":"PG",
    "gn:dem":742,
    "gn:feature_class":"P",
    "gn:feature_code":"PPL",
    "gn:name":"Wainda",
    "gn:population":0,
    "gn:timezone":"Pacific/Port_Moresby",
    "iso:country":"PG",
    "wof:name":"Wainda",
    "wof:placetype":"locality"
},
  "geometry": {"coordinates":[141.04560000000001,-3.27091],"type":"Point"}
}