{
  "type": "Feature",
  "properties": {
    "gn:admin1_code":"09",
    "gn:asciiname":"Punano Number 1",
    "gn:country_code":"PG",
    "gn:dem":1661,
    "gn:feature_class":"P",
    "gn:feature_code":"PPL",
    "gn:name":"Punano Number 1",
    "gn:population":0,
    "gn:timezone":"Pacific/Port_Moresby",
    "iso:country":"PG",
    "name:und_x_variant":[
        "Punana 1",
        "Punano Number 1"
    ],
    "wof:name":"Punano Number 1",
    "wof:placetype":"locality"
},
  "geometry": {"coordinates":[145.88032999999999,-6.20884],"type":"Point"}
}