{
  "type": "Feature",
  "properties": {
    "gn:admin1_code":"12",
    "gn:asciiname":"Koguman",
    "gn:country_code":"PG",
    "gn:dem":881,
    "gn:feature_class":"P",
    "gn:feature_code":"PPL",
    "gn:name":"Koguman",
    "gn:population":0,
    "gn:timezone":"Pacific/Port_Moresby",
    "iso:country":"PG",
    "wof:name":"Koguman",
    "wof:placetype":"locality"
},
  "geometry": {"coordinates":[145.28276,-4.80934],"type":"Point"}
}