{
  "type": "Feature",
  "properties": {
    "gn:admin1_code":"09",
    "gn:asciiname":"Mei'auna",
    "gn:country_code":"PG",
    "gn:dem":1692,
    "gn:feature_class":"P",
    "gn:feature_code":"PPL",
    "gn:name":"Mei\u2019auna",
    "gn:population":0,
    "gn:timezone":"Pacific/Port_Moresby",
    "iso:country":"PG",
    "wof:name":"Mei'auna",
    "wof:placetype":"locality"
},
  "geometry": {"coordinates":[145.76667,-6.53333],"type":"Point"}
}