{
  "type": "Feature",
  "properties": {
    "gn:country":"PG",
    "gn:fcode":"PPL",
    "gn:pop":1638,
    "iso:country":"PG",
    "name:ceb_x_preferred":[
        "Samarai"
    ],
    "name:eng_x_preferred":[
        "Samarai"
    ],
    "name:fra_x_preferred":[
        "Samarai"
    ],
    "name:ita_x_preferred":[
        "Samarai"
    ],
    "name:jpn_x_preferred":[
        "\u30b5\u30de\u30e9\u30a4"
    ],
    "name:nld_x_preferred":[
        "Samarai"
    ],
    "name:pnb_x_preferred":[
        "\u0633\u0627\u0645\u0627\u0631\u0627\u0626\u06cc"
    ],
    "name:unk_x_variant":[
        "Samaria"
    ],
    "name:zho_x_preferred":[
        "\u85a9\u99ac\u8cf4"
    ],
    "qs:name":"Samarai",
    "qs:photos_9r":0,
    "qs:photos_sr":0,
    "qs:pop_sr":"3",
    "wd:wordcount":810,
    "wof:name":"Samarai",
    "wof:placetype":"locality",
    "wof:population":1638
},
  "geometry": {"coordinates":[150.66667000000001,-10.61667],"type":"Point"}
}