{
  "type": "Feature",
  "properties": {
    "gn:admin1_code":"08",
    "gn:asciiname":"Kiraigu",
    "gn:country_code":"PG",
    "gn:dem":1681,
    "gn:feature_class":"P",
    "gn:feature_code":"PPL",
    "gn:name":"Kiraigu",
    "gn:population":0,
    "gn:timezone":"Pacific/Port_Moresby",
    "iso:country":"PG",
    "wof:name":"Kiraigu",
    "wof:placetype":"locality"
},
  "geometry": {"coordinates":[145.09999999999999,-6.21667],"type":"Point"}
}