{
  "type": "Feature",
  "properties": {
    "gn:admin1_code":"04",
    "gn:asciiname":"Angara",
    "gn:country_code":"PG",
    "gn:dem":473,
    "gn:feature_class":"P",
    "gn:feature_code":"PPL",
    "gn:name":"Angara",
    "gn:population":0,
    "gn:timezone":"Pacific/Port_Moresby",
    "iso:country":"PG",
    "wof:name":"Angara",
    "wof:placetype":"locality"
},
  "geometry": {"coordinates":[148.01667,-9.01667],"type":"Point"}
}