{
  "type": "Feature",
  "properties": {
    "gn:admin1_code":"18",
    "gn:asciiname":"Yiriwand",
    "gn:country_code":"PG",
    "gn:dem":189,
    "gn:feature_class":"P",
    "gn:feature_code":"PPL",
    "gn:name":"Yiriwand",
    "gn:population":0,
    "gn:timezone":"Pacific/Port_Moresby",
    "iso:country":"PG",
    "name:und_x_variant":[
        "Yiriwandi",
        "Yiriwand"
    ],
    "wof:name":"Yiriwand",
    "wof:placetype":"locality"
},
  "geometry": {"coordinates":[142.58121,-3.67445],"type":"Point"}
}