{
  "type": "Feature",
  "properties": {
    "gn:admin1_code":"07",
    "gn:asciiname":"Tapsanwara",
    "gn:country_code":"PG",
    "gn:dem":63,
    "gn:feature_class":"P",
    "gn:feature_code":"PPL",
    "gn:name":"Tapsanwara",
    "gn:population":0,
    "gn:timezone":"Pacific/Bougainville",
    "iso:country":"PG",
    "name:und_x_variant":[
        "Tapsadawata",
        "Tapsanwara"
    ],
    "wof:name":"Tapsanwara",
    "wof:placetype":"locality"
},
  "geometry": {"coordinates":[154.76129,-5.45665],"type":"Point"}
}