{
  "type": "Feature",
  "properties": {
    "gn:admin1_code":"06",
    "gn:asciiname":"Sagero",
    "gn:cc2":"PG",
    "gn:country_code":"PG",
    "gn:dem":1,
    "gn:feature_class":"P",
    "gn:feature_code":"PPL",
    "gn:name":"Sagero",
    "gn:population":0,
    "gn:timezone":"Pacific/Port_Moresby",
    "iso:country":"PG",
    "name:und_x_variant":[
        "Segara",
        "Segera",
        "Sagero"
    ],
    "wof:name":"Sagero",
    "wof:placetype":"locality"
},
  "geometry": {"coordinates":[143.53333000000001,-8.23333],"type":"Point"}
}