{
  "type": "Feature",
  "properties": {
    "gn:admin1_code":"14",
    "gn:asciiname":"Woimbo",
    "gn:country_code":"PG",
    "gn:dem":1670,
    "gn:feature_class":"P",
    "gn:feature_code":"PPL",
    "gn:name":"Woimbo",
    "gn:population":0,
    "gn:timezone":"Pacific/Port_Moresby",
    "iso:country":"PG",
    "wof:name":"Woimbo",
    "wof:placetype":"locality"
},
  "geometry": {"coordinates":[145.96666999999999,-7.08333],"type":"Point"}
}