{
  "type": "Feature",
  "properties": {
    "gn:admin1_code":"17",
    "gn:asciiname":"Elobe",
    "gn:country_code":"PG",
    "gn:dem":383,
    "gn:feature_class":"P",
    "gn:feature_code":"PPL",
    "gn:name":"Elobe",
    "gn:population":0,
    "gn:timezone":"Pacific/Port_Moresby",
    "iso:country":"PG",
    "wof:name":"Elobe",
    "wof:placetype":"locality"
},
  "geometry": {"coordinates":[150.90376000000001,-5.59359],"type":"Point"}
}