{
  "type": "Feature",
  "properties": {
    "gn:admin1_code":"05",
    "gn:asciiname":"Heoka",
    "gn:cc2":"PG",
    "gn:country_code":"PG",
    "gn:dem":1184,
    "gn:feature_class":"P",
    "gn:feature_code":"PPL",
    "gn:name":"Heoka",
    "gn:population":0,
    "gn:timezone":"Pacific/Port_Moresby",
    "iso:country":"PG",
    "name:und_x_variant":[
        "Heora",
        "Heoka"
    ],
    "wof:name":"Heoka",
    "wof:placetype":"locality"
},
  "geometry": {"coordinates":[142.94999999999999,-6.06667],"type":"Point"}
}