{
  "type": "Feature",
  "properties": {
    "gn:admin1_code":"14",
    "gn:asciiname":"Saiko",
    "gn:country_code":"PG",
    "gn:dem":1833,
    "gn:feature_class":"P",
    "gn:feature_code":"PPL",
    "gn:name":"Saiko",
    "gn:population":0,
    "gn:timezone":"Pacific/Port_Moresby",
    "iso:country":"PG",
    "name:deu_x_preferred":[
        "Saiko"
    ],
    "name:fra_x_preferred":[
        "Saiko"
    ],
    "name:ita_x_preferred":[
        "Saiko"
    ],
    "wof:name":"Saiko",
    "wof:placetype":"locality"
},
  "geometry": {"coordinates":[147.05671000000001,-7.95343],"type":"Point"}
}