{
  "type": "Feature",
  "properties": {
    "gn:admin1_code":"09",
    "gn:asciiname":"Napaiyufa",
    "gn:country_code":"PG",
    "gn:dem":2283,
    "gn:feature_class":"P",
    "gn:feature_code":"PPL",
    "gn:name":"Napaiyufa",
    "gn:population":0,
    "gn:timezone":"Pacific/Port_Moresby",
    "iso:country":"PG",
    "wof:name":"Napaiyufa",
    "wof:placetype":"locality"
},
  "geometry": {"coordinates":[145.51667,-6.06667],"type":"Point"}
}