{
  "type": "Feature",
  "properties": {
    "gn:admin1_code":"10",
    "gn:asciiname":"Lopun",
    "gn:country_code":"PG",
    "gn:dem":160,
    "gn:feature_class":"P",
    "gn:feature_code":"PPL",
    "gn:name":"Lopun",
    "gn:population":0,
    "gn:timezone":"Pacific/Port_Moresby",
    "iso:country":"PG",
    "wof:name":"Lopun",
    "wof:placetype":"locality"
},
  "geometry": {"coordinates":[150.70773,-5.946],"type":"Point"}
}