{
  "type": "Feature",
  "properties": {
    "gn:admin1_code":"14",
    "gn:asciiname":"Lakona",
    "gn:country_code":"PG",
    "gn:dem":64,
    "gn:feature_class":"P",
    "gn:feature_code":"PPL",
    "gn:name":"Lakona",
    "gn:population":0,
    "gn:timezone":"Pacific/Port_Moresby",
    "iso:country":"PG",
    "wof:name":"Lakona",
    "wof:placetype":"locality"
},
  "geometry": {"coordinates":[147.82761000000005,-6.38197],"type":"Point"}
}