{
  "type": "Feature",
  "properties": {
    "gn:admin1_code":"10",
    "gn:asciiname":"Ulaulatava",
    "gn:country_code":"PG",
    "gn:dem":238,
    "gn:feature_class":"P",
    "gn:feature_code":"PPL",
    "gn:name":"Ulaulatava",
    "gn:population":0,
    "gn:timezone":"Pacific/Port_Moresby",
    "iso:country":"PG",
    "wof:name":"Ulaulatava",
    "wof:placetype":"locality"
},
  "geometry": {"coordinates":[152.21666999999999,-4.38333],"type":"Point"}
}