{
  "type": "Feature",
  "properties": {
    "gn:admin1_code":"19",
    "gn:asciiname":"Rege",
    "gn:country_code":"PG",
    "gn:dem":1872,
    "gn:feature_class":"P",
    "gn:feature_code":"PPL",
    "gn:name":"Rege",
    "gn:population":0,
    "gn:timezone":"Pacific/Port_Moresby",
    "iso:country":"PG",
    "name:fas_x_preferred":[
        "\u067e\u0627\u062f\u0634\u0627\u0647"
    ],
    "name:mar_x_preferred":[
        "\u0930\u0947\u0917\u0947"
    ],
    "wof:name":"Rege",
    "wof:placetype":"locality"
},
  "geometry": {"coordinates":[143.76151000000004,-5.50232],"type":"Point"}
}