{
  "type": "Feature",
  "properties": {
    "gn:admin1_code":"17",
    "gn:asciiname":"Woganakai",
    "gn:country_code":"PG",
    "gn:dem":12,
    "gn:feature_class":"P",
    "gn:feature_code":"PPL",
    "gn:name":"Woganakai",
    "gn:population":0,
    "gn:timezone":"Pacific/Port_Moresby",
    "iso:country":"PG",
    "name:und_x_variant":[
        "Wongankai",
        "Woganakai"
    ],
    "wof:name":"Woganakai",
    "wof:placetype":"locality"
},
  "geometry": {"coordinates":[150.01333,-5.22203],"type":"Point"}
}