{
  "type": "Feature",
  "properties": {
    "gn:admin1_code":"04",
    "gn:asciiname":"Marua",
    "gn:country_code":"PG",
    "gn:dem":19,
    "gn:feature_class":"P",
    "gn:feature_code":"PPL",
    "gn:name":"Marua",
    "gn:population":0,
    "gn:timezone":"Pacific/Port_Moresby",
    "iso:country":"PG",
    "wof:name":"Marua",
    "wof:placetype":"locality"
},
  "geometry": {"coordinates":[149.30851999999999,-9.51454],"type":"Point"}
}