{
  "type": "Feature",
  "properties": {
    "gn:admin1_code":"02",
    "gn:asciiname":"Ara'ava",
    "gn:country_code":"PG",
    "gn:dem":2,
    "gn:feature_class":"P",
    "gn:feature_code":"PPL",
    "gn:name":"Ara\u2019ava",
    "gn:population":0,
    "gn:timezone":"Pacific/Port_Moresby",
    "iso:country":"PG",
    "wof:name":"Ara'ava",
    "wof:placetype":"locality"
},
  "geometry": {"coordinates":[144.94999999999999,-7.58333],"type":"Point"}
}