{
  "type": "Feature",
  "properties": {
    "gn:admin1_code":"08",
    "gn:asciiname":"Ogondiye",
    "gn:country_code":"PG",
    "gn:dem":2389,
    "gn:feature_class":"P",
    "gn:feature_code":"PPL",
    "gn:name":"Ogondiye",
    "gn:population":0,
    "gn:timezone":"Pacific/Port_Moresby",
    "iso:country":"PG",
    "wof:name":"Ogondiye",
    "wof:placetype":"locality"
},
  "geometry": {"coordinates":[145.06666999999999,-5.91667],"type":"Point"}
}