{
  "type": "Feature",
  "properties": {
    "gn:admin1_code":"18",
    "gn:asciiname":"Krisa",
    "gn:country_code":"PG",
    "gn:dem":203,
    "gn:feature_class":"P",
    "gn:feature_code":"PPL",
    "gn:name":"Krisa",
    "gn:population":0,
    "gn:timezone":"Pacific/Port_Moresby",
    "iso:country":"PG",
    "name:ceb_x_preferred":[
        "Krisa"
    ],
    "name:pol_x_preferred":[
        "Krisa"
    ],
    "name:und_x_variant":[
        "Krisi",
        "Krisa"
    ],
    "wof:name":"Krisa",
    "wof:placetype":"locality"
},
  "geometry": {"coordinates":[141.28291000000004,-2.85271],"type":"Point"}
}