{
  "type": "Feature",
  "properties": {
    "gn:admin1_code":"01",
    "gn:asciiname":"Mororo",
    "gn:country_code":"PG",
    "gn:dem":236,
    "gn:feature_class":"P",
    "gn:feature_code":"PPL",
    "gn:name":"Mororo",
    "gn:population":0,
    "gn:timezone":"Pacific/Port_Moresby",
    "iso:country":"PG",
    "wof:name":"Mororo",
    "wof:placetype":"locality"
},
  "geometry": {"coordinates":[147.59999999999999,-9.43333],"type":"Point"}
}