{
  "type": "Feature",
  "properties": {
    "gn:admin1_code":"05",
    "gn:asciiname":"Ekela",
    "gn:country_code":"PG",
    "gn:dem":2285,
    "gn:feature_class":"P",
    "gn:feature_code":"PPL",
    "gn:name":"Ekela",
    "gn:population":0,
    "gn:timezone":"Pacific/Port_Moresby",
    "iso:country":"PG",
    "wof:name":"Ekela",
    "wof:placetype":"locality"
},
  "geometry": {"coordinates":[143.80000000000001,-6.16667],"type":"Point"}
}