{
  "type": "Feature",
  "properties": {
    "gn:admin1_code":"12",
    "gn:asciiname":"Kominimung",
    "gn:country_code":"PG",
    "gn:dem":33,
    "gn:feature_class":"P",
    "gn:feature_code":"PPL",
    "gn:name":"Kominimung",
    "gn:population":0,
    "gn:timezone":"Pacific/Port_Moresby",
    "iso:country":"PG",
    "wof:name":"Kominimung",
    "wof:placetype":"locality"
},
  "geometry": {"coordinates":[144.7192,-4.64957],"type":"Point"}
}