{
  "type": "Feature",
  "properties": {
    "gn:admin1_code":"12",
    "gn:asciiname":"Bongu",
    "gn:country_code":"PG",
    "gn:dem":20,
    "gn:feature_class":"P",
    "gn:feature_code":"PPL",
    "gn:name":"Bongu",
    "gn:population":0,
    "gn:timezone":"Pacific/Port_Moresby",
    "iso:country":"PG",
    "wof:name":"Bongu",
    "wof:placetype":"locality"
},
  "geometry": {"coordinates":[145.80615,-5.49454],"type":"Point"}
}