{
  "type": "Feature",
  "properties": {
    "gn:admin1_code":"02",
    "gn:asciiname":"Gauri",
    "gn:country_code":"PG",
    "gn:dem":15,
    "gn:feature_class":"P",
    "gn:feature_code":"PPL",
    "gn:name":"Gauri",
    "gn:population":0,
    "gn:timezone":"Pacific/Port_Moresby",
    "iso:country":"PG",
    "name:ceb_x_preferred":[
        "Gauri"
    ],
    "name:fra_x_preferred":[
        "Gaur\u00ee"
    ],
    "name:hin_x_preferred":[
        "\u0917\u094c\u0930\u0940"
    ],
    "name:kor_x_preferred":[
        "\uac00\uc6b0\ub9ac"
    ],
    "name:ori_x_preferred":[
        "\u0b17\u0b4c\u0b30\u0b40"
    ],
    "name:und_x_variant":[
        "Dau Pai"
    ],
    "wof:name":"Gauri",
    "wof:placetype":"locality"
},
  "geometry": {"coordinates":[144.49656000000004,-7.48708],"type":"Point"}
}