{
  "type": "Feature",
  "properties": {
    "gn:admin1_code":"12",
    "gn:asciiname":"Yedikum",
    "gn:country_code":"PG",
    "gn:dem":18,
    "gn:feature_class":"P",
    "gn:feature_code":"PPL",
    "gn:name":"Yedikum",
    "gn:population":0,
    "gn:timezone":"Pacific/Port_Moresby",
    "iso:country":"PG",
    "wof:name":"Yedikum",
    "wof:placetype":"locality"
},
  "geometry": {"coordinates":[145.63333,-4.71667],"type":"Point"}
}