{
  "type": "Feature",
  "properties": {
    "gn:admin1_code":"03",
    "gn:asciiname":"Agaun",
    "gn:country_code":"PG",
    "gn:dem":1005,
    "gn:feature_class":"P",
    "gn:feature_code":"PPLL",
    "gn:name":"Agaun",
    "gn:population":0,
    "gn:timezone":"Pacific/Port_Moresby",
    "iso:country":"PG",
    "name:eng_x_preferred":[
        "Agaun"
    ],
    "wof:name":"Agaun",
    "wof:placetype":"locality"
},
  "geometry": {"coordinates":[149.39489,-9.93057],"type":"Point"}
}