{
  "type": "Feature",
  "properties": {
    "gn:admin1_code":"08",
    "gn:asciiname":"Kenangi",
    "gn:country_code":"PG",
    "gn:dem":1652,
    "gn:feature_class":"P",
    "gn:feature_code":"PPL",
    "gn:name":"Kenangi",
    "gn:population":0,
    "gn:timezone":"Pacific/Port_Moresby",
    "iso:country":"PG",
    "wof:name":"Kenangi",
    "wof:placetype":"locality"
},
  "geometry": {"coordinates":[145.14721,-6.08657],"type":"Point"}
}