{
  "type": "Feature",
  "properties": {
    "gn:admin1_code":"04",
    "gn:asciiname":"Ahora",
    "gn:country_code":"PG",
    "gn:dem":45,
    "gn:feature_class":"P",
    "gn:feature_code":"PPL",
    "gn:name":"Ahora",
    "gn:population":0,
    "gn:timezone":"Pacific/Port_Moresby",
    "iso:country":"PG",
    "name:spa_x_preferred":[
        "Ahora"
    ],
    "wof:name":"Ahora",
    "wof:placetype":"locality"
},
  "geometry": {"coordinates":[148.22909000000001,-8.68437],"type":"Point"}
}