{
  "type": "Feature",
  "properties": {
    "gn:admin1_code":"01",
    "gn:asciiname":"Edebu",
    "gn:country_code":"PG",
    "gn:dem":52,
    "gn:feature_class":"P",
    "gn:feature_code":"PPL",
    "gn:name":"Edebu",
    "gn:population":0,
    "gn:timezone":"Pacific/Port_Moresby",
    "iso:country":"PG",
    "wof:name":"Edebu",
    "wof:placetype":"locality"
},
  "geometry": {"coordinates":[147.2878,-9.19475],"type":"Point"}
}