{
  "type": "Feature",
  "properties": {
    "gn:admin1_code":"06",
    "gn:asciiname":"Kaiumevim",
    "gn:country_code":"PG",
    "gn:dem":392,
    "gn:feature_class":"P",
    "gn:feature_code":"PPL",
    "gn:name":"Kaiumevim",
    "gn:population":0,
    "gn:timezone":"Pacific/Port_Moresby",
    "iso:country":"PG",
    "wof:name":"Kaiumevim",
    "wof:placetype":"locality"
},
  "geometry": {"coordinates":[141.05000000000001,-5.36667],"type":"Point"}
}