{
  "type": "Feature",
  "properties": {
    "gn:admin1_code":"08",
    "gn:asciiname":"Yawai",
    "gn:country_code":"PG",
    "gn:dem":1439,
    "gn:feature_class":"P",
    "gn:feature_code":"PPL",
    "gn:name":"Yawai",
    "gn:population":0,
    "gn:timezone":"Pacific/Port_Moresby",
    "iso:country":"PG",
    "wof:name":"Yawai",
    "wof:placetype":"locality"
},
  "geometry": {"coordinates":[145.15000000000001,-6.33333],"type":"Point"}
}