{
  "type": "Feature",
  "properties": {
    "gn:admin1_code":"08",
    "gn:asciiname":"Saigo Number 2",
    "gn:cc2":"PG",
    "gn:country_code":"PG",
    "gn:dem":2401,
    "gn:feature_class":"P",
    "gn:feature_code":"PPL",
    "gn:name":"Saigo Number 2",
    "gn:population":0,
    "gn:timezone":"Pacific/Port_Moresby",
    "iso:country":"PG",
    "name:und_x_variant":[
        "Saigo 2",
        "Saigo Number 2"
    ],
    "wof:name":"Saigo Number 2",
    "wof:placetype":"locality"
},
  "geometry": {"coordinates":[145.09999999999999,-5.85],"type":"Point"}
}