{
  "type": "Feature",
  "properties": {
    "gn:admin1_code":"03",
    "gn:asciiname":"Dumoakarifei",
    "gn:country_code":"PG",
    "gn:dem":193,
    "gn:feature_class":"P",
    "gn:feature_code":"PPL",
    "gn:name":"Dumoakarifei",
    "gn:population":0,
    "gn:timezone":"Pacific/Port_Moresby",
    "iso:country":"PG",
    "wof:name":"Dumoakarifei",
    "wof:placetype":"locality"
},
  "geometry": {"coordinates":[150.31666999999999,-10.41667],"type":"Point"}
}