{
  "type": "Feature",
  "properties": {
    "gn:admin1_code":"15",
    "gn:asciiname":"Kabien Number 2",
    "gn:country_code":"PG",
    "gn:dem":20,
    "gn:feature_class":"P",
    "gn:feature_code":"PPL",
    "gn:name":"Kabien Number 2",
    "gn:population":0,
    "gn:timezone":"Pacific/Port_Moresby",
    "iso:country":"PG",
    "name:und_x_variant":[
        "Tunschui",
        "Kawin",
        "Kabien",
        "Kabien 2",
        "Kabien Number 2"
    ],
    "wof:name":"Kabien Number 2",
    "wof:placetype":"locality"
},
  "geometry": {"coordinates":[150.73976000000005,-2.7497],"type":"Point"}
}