{
  "type": "Feature",
  "properties": {
    "gn:admin1_code":"11",
    "gn:asciiname":"Ambambindo",
    "gn:country_code":"PG",
    "gn:dem":13,
    "gn:feature_class":"P",
    "gn:feature_code":"PPL",
    "gn:name":"Ambambindo",
    "gn:population":0,
    "gn:timezone":"Pacific/Port_Moresby",
    "iso:country":"PG",
    "wof:name":"Ambambindo",
    "wof:placetype":"locality"
},
  "geometry": {"coordinates":[143.98333,-4.06667],"type":"Point"}
}