{
  "type": "Feature",
  "properties": {
    "gn:admin1_code":"04",
    "gn:asciiname":"Aimare",
    "gn:country_code":"PG",
    "gn:dem":568,
    "gn:feature_class":"P",
    "gn:feature_code":"PPL",
    "gn:name":"Aimare",
    "gn:population":0,
    "gn:timezone":"Pacific/Port_Moresby",
    "iso:country":"PG",
    "name:und_x_variant":[
        "Auwaka",
        "Aimara",
        "Aimare"
    ],
    "wof:name":"Aimare",
    "wof:placetype":"locality"
},
  "geometry": {"coordinates":[148.45982000000001,-9.71243],"type":"Point"}
}