{
  "type": "Feature",
  "properties": {
    "gn:admin1_code":"14",
    "gn:asciiname":"Zare",
    "gn:country_code":"PG",
    "gn:dem":11,
    "gn:feature_class":"P",
    "gn:feature_code":"PPL",
    "gn:name":"Zare",
    "gn:population":0,
    "gn:timezone":"Pacific/Port_Moresby",
    "iso:country":"PG",
    "name:deu_x_preferred":[
        "Zare"
    ],
    "name:und_x_variant":[
        "Zari",
        "Zaribiria"
    ],
    "wof:name":"Zare",
    "wof:placetype":"locality"
},
  "geometry": {"coordinates":[147.64524,-7.85322],"type":"Point"}
}