{
  "type": "Feature",
  "properties": {
    "gn:admin1_code":"11",
    "gn:asciiname":"Soarin",
    "gn:country_code":"PG",
    "gn:dem":32,
    "gn:feature_class":"P",
    "gn:feature_code":"PPL",
    "gn:name":"Soarin",
    "gn:population":0,
    "gn:timezone":"Pacific/Port_Moresby",
    "iso:country":"PG",
    "wof:name":"Soarin",
    "wof:placetype":"locality"
},
  "geometry": {"coordinates":[143.69999999999999,-3.61667],"type":"Point"}
}