{
  "type": "Feature",
  "properties": {
    "gn:admin1_code":"05",
    "gn:asciiname":"Mungoro",
    "gn:country_code":"PG",
    "gn:dem":1747,
    "gn:feature_class":"P",
    "gn:feature_code":"PPL",
    "gn:name":"Mungoro",
    "gn:population":0,
    "gn:timezone":"Pacific/Port_Moresby",
    "iso:country":"PG",
    "wof:name":"Mungoro",
    "wof:placetype":"locality"
},
  "geometry": {"coordinates":[143.89457999999999,-6.3449],"type":"Point"}
}