{
  "type": "Feature",
  "properties": {
    "gn:admin1_code":"15",
    "gn:asciiname":"Putput Number 2",
    "gn:country_code":"PG",
    "gn:dem":-9999,
    "gn:feature_class":"P",
    "gn:feature_code":"PPL",
    "gn:name":"Putput Number 2",
    "gn:population":0,
    "gn:timezone":"Pacific/Port_Moresby",
    "iso:country":"PG",
    "name:und_x_variant":[
        "Put Put 2",
        "Putput Number 2"
    ],
    "wof:name":"Putput Number 2",
    "wof:placetype":"locality"
},
  "geometry": {"coordinates":[152.66327999999999,-3.13512],"type":"Point"}
}