{
  "type": "Feature",
  "properties": {
    "gn:admin1_code":"09",
    "gn:asciiname":"Koibi",
    "gn:cc2":"PG",
    "gn:country_code":"PG",
    "gn:dem":1604,
    "gn:feature_class":"P",
    "gn:feature_code":"PPL",
    "gn:name":"Koibi",
    "gn:population":0,
    "gn:timezone":"Pacific/Port_Moresby",
    "iso:country":"PG",
    "name:und_x_variant":[
        "Kiobi",
        "Koibi"
    ],
    "wof:name":"Koibi",
    "wof:placetype":"locality"
},
  "geometry": {"coordinates":[145.16666999999995,-6.45],"type":"Point"}
}