{
  "type": "Feature",
  "properties": {
    "gn:admin1_code":"14",
    "gn:asciiname":"Pobung",
    "gn:country_code":"PG",
    "gn:dem":2288,
    "gn:feature_class":"P",
    "gn:feature_code":"PPL",
    "gn:name":"Pobung",
    "gn:population":0,
    "gn:timezone":"Pacific/Port_Moresby",
    "iso:country":"PG",
    "wof:name":"Pobung",
    "wof:placetype":"locality"
},
  "geometry": {"coordinates":[147.05793,-6.16866],"type":"Point"}
}