{
  "type": "Feature",
  "properties": {
    "gn:admin1_code":"10",
    "gn:asciiname":"Tol",
    "gn:country_code":"PG",
    "gn:dem":16,
    "gn:feature_class":"P",
    "gn:feature_code":"PPL",
    "gn:name":"Tol",
    "gn:population":0,
    "gn:timezone":"Pacific/Port_Moresby",
    "iso:country":"PG",
    "name:ceb_x_preferred":[
        "Tol"
    ],
    "name:deu_x_preferred":[
        "Tol"
    ],
    "name:eng_x_preferred":[
        "Tol"
    ],
    "name:fra_x_preferred":[
        "Tol"
    ],
    "name:jpn_x_preferred":[
        "\u30c8\u30eb"
    ],
    "name:nld_x_preferred":[
        "Tol"
    ],
    "name:rus_x_preferred":[
        "\u0422\u043e\u043b\u044c"
    ],
    "name:swe_x_preferred":[
        "Tol"
    ],
    "name:uzb_x_preferred":[
        "Tol"
    ],
    "wof:name":"Tol",
    "wof:placetype":"locality"
},
  "geometry": {"coordinates":[152.00588999999999,-4.97915],"type":"Point"}
}