{
  "type": "Feature",
  "properties": {
    "gn:admin1_code":"12",
    "gn:asciiname":"Dudula",
    "gn:country_code":"PG",
    "gn:dem":467,
    "gn:feature_class":"P",
    "gn:feature_code":"PPL",
    "gn:name":"Dudula",
    "gn:population":0,
    "gn:timezone":"Pacific/Port_Moresby",
    "iso:country":"PG",
    "name:und_x_variant":[
        "Dudala",
        "Dudula"
    ],
    "wof:name":"Dudula",
    "wof:placetype":"locality"
},
  "geometry": {"coordinates":[145.63650000000001,-4.9364],"type":"Point"}
}