{
  "type": "Feature",
  "properties": {
    "gn:admin1_code":"05",
    "gn:asciiname":"Sugwa",
    "gn:country_code":"PG",
    "gn:dem":90,
    "gn:feature_class":"P",
    "gn:feature_code":"PPL",
    "gn:name":"Sugwa",
    "gn:population":0,
    "gn:timezone":"Pacific/Port_Moresby",
    "iso:country":"PG",
    "wof:name":"Sugwa",
    "wof:placetype":"locality"
},
  "geometry": {"coordinates":[143.54142999999999,-6.80515],"type":"Point"}
}