{
  "type": "Feature",
  "properties": {
    "gn:admin1_code":"08",
    "gn:asciiname":"Kobuni 1",
    "gn:country_code":"PG",
    "gn:dem":1679,
    "gn:feature_class":"P",
    "gn:feature_code":"PPL",
    "gn:name":"Kobuni 1",
    "gn:population":0,
    "gn:timezone":"Pacific/Port_Moresby",
    "iso:country":"PG",
    "wof:name":"Kobuni 1",
    "wof:placetype":"locality"
},
  "geometry": {"coordinates":[145.23333,-6.16667],"type":"Point"}
}