{
  "type": "Feature",
  "properties": {
    "gn:admin1_code":"12",
    "gn:asciiname":"Asas",
    "gn:country_code":"PG",
    "gn:dem":174,
    "gn:feature_class":"P",
    "gn:feature_code":"PPL",
    "gn:name":"Asas",
    "gn:population":0,
    "gn:timezone":"Pacific/Port_Moresby",
    "iso:country":"PG",
    "wof:name":"Asas",
    "wof:placetype":"locality"
},
  "geometry": {"coordinates":[145.56101999999996,-5.72244],"type":"Point"}
}