{
  "type": "Feature",
  "properties": {
    "gn:admin1_code":"02",
    "gn:asciiname":"Kauberau",
    "gn:country_code":"PG",
    "gn:dem":71,
    "gn:feature_class":"P",
    "gn:feature_code":"PPL",
    "gn:name":"Kauberau",
    "gn:population":0,
    "gn:timezone":"Pacific/Port_Moresby",
    "iso:country":"PG",
    "name:und_x_variant":[
        "Kabarau",
        "Kauberau"
    ],
    "wof:name":"Kauberau",
    "wof:placetype":"locality"
},
  "geometry": {"coordinates":[144.25904,-7.2136],"type":"Point"}
}