{
  "type": "Feature",
  "properties": {
    "gn:admin1_code":"12",
    "gn:asciiname":"Mior",
    "gn:country_code":"PG",
    "gn:dem":107,
    "gn:feature_class":"P",
    "gn:feature_code":"PPL",
    "gn:name":"Mior",
    "gn:population":0,
    "gn:timezone":"Pacific/Port_Moresby",
    "iso:country":"PG",
    "wof:name":"Mior",
    "wof:placetype":"locality"
},
  "geometry": {"coordinates":[146.48333,-5.66667],"type":"Point"}
}