{
  "type": "Feature",
  "properties": {
    "gn:admin1_code":"18",
    "gn:admin2_code":"2085584",
    "gn:asciiname":"Telefomin",
    "gn:country_code":"PG",
    "gn:dem":1508,
    "gn:feature_class":"P",
    "gn:feature_code":"PPL",
    "gn:name":"Telefomin",
    "gn:population":0,
    "gn:timezone":"Pacific/Port_Moresby",
    "iso:country":"PG",
    "name:deu_x_preferred":[
        "Telefomin"
    ],
    "name:fas_x_preferred":[
        "\u062a\u0644\u0641\u0648\u0645\u06cc\u0646"
    ],
    "name:fra_x_preferred":[
        "Telefomin"
    ],
    "name:spa_x_preferred":[
        "Telefomin"
    ],
    "name:und_x_variant":[
        "Telefolmin"
    ],
    "name:zho_x_preferred":[
        "\u7279\u840a\u798f\u660e"
    ],
    "wof:name":"Telefomin",
    "wof:placetype":"locality"
},
  "geometry": {"coordinates":[141.63986,-5.12476],"type":"Point"}
}