{
  "type": "Feature",
  "properties": {
    "gn:admin1_code":"18",
    "gn:admin2_code":"2085584",
    "gn:asciiname":"Telefomin",
    "gn:country_code":"PG",
    "gn:dem":1508,
    "gn:feature_class":"P",
    "gn:feature_code":"PPL",
    "gn:name":"Telefomin",
    "gn:population":0,
    "gn:timezone":"Pacific/Port_Moresby",
    "iso:country":"PG",
    "name:und_x_variant":[
        "Telefolmin"
    ],
    "wof:name":"Telefomin",
    "wof:placetype":"locality"
},
  "geometry": {"coordinates":[141.63986,-5.12476],"type":"Point"}
}