{
  "type": "Feature",
  "properties": {
    "gn:admin1_code":"09",
    "gn:asciiname":"Kamariumba",
    "gn:country_code":"PG",
    "gn:dem":1594,
    "gn:feature_class":"P",
    "gn:feature_code":"PPL",
    "gn:name":"Kamariumba",
    "gn:population":0,
    "gn:timezone":"Pacific/Port_Moresby",
    "iso:country":"PG",
    "wof:name":"Kamariumba",
    "wof:placetype":"locality"
},
  "geometry": {"coordinates":[145.88357999999999,-6.77975],"type":"Point"}
}