{
  "type": "Feature",
  "properties": {
    "gn:admin1_code":"02",
    "gn:asciiname":"Sumakarimo",
    "gn:country_code":"PG",
    "gn:dem":24,
    "gn:feature_class":"P",
    "gn:feature_code":"PPL",
    "gn:name":"Sumakarimo",
    "gn:population":0,
    "gn:timezone":"Pacific/Port_Moresby",
    "iso:country":"PG",
    "name:und_x_variant":[
        "Sumakarimu"
    ],
    "wof:name":"Sumakarimo",
    "wof:placetype":"locality"
},
  "geometry": {"coordinates":[143.32307,-7.18377],"type":"Point"}
}