{
  "type": "Feature",
  "properties": {
    "gn:admin1_code":"03",
    "gn:asciiname":"Sirimo",
    "gn:country_code":"PG",
    "gn:dem":4,
    "gn:feature_class":"P",
    "gn:feature_code":"PPL",
    "gn:name":"Sirimo",
    "gn:population":0,
    "gn:timezone":"Pacific/Port_Moresby",
    "iso:country":"PG",
    "wof:name":"Sirimo",
    "wof:placetype":"locality"
},
  "geometry": {"coordinates":[149.66666999999995,-9.61667],"type":"Point"}
}