{
  "type": "Feature",
  "properties": {
    "gn:admin1_code":"12",
    "gn:asciiname":"Gunts",
    "gn:country_code":"PG",
    "gn:dem":1334,
    "gn:feature_class":"P",
    "gn:feature_code":"PPL",
    "gn:name":"Gunts",
    "gn:population":0,
    "gn:timezone":"Pacific/Port_Moresby",
    "iso:country":"PG",
    "wof:name":"Gunts",
    "wof:placetype":"locality"
},
  "geometry": {"coordinates":[144.80000000000001,-5.45],"type":"Point"}
}