{
  "type": "Feature",
  "properties": {
    "gn:admin1_code":"06",
    "gn:asciiname":"Bimedebun",
    "gn:country_code":"PG",
    "gn:dem":29,
    "gn:feature_class":"P",
    "gn:feature_code":"PPL",
    "gn:name":"Bimedebun",
    "gn:population":0,
    "gn:timezone":"Pacific/Port_Moresby",
    "iso:country":"PG",
    "name:und_x_variant":[
        "Bimadibun",
        "Bimedebun"
    ],
    "wof:name":"Bimedebun",
    "wof:placetype":"locality"
},
  "geometry": {"coordinates":[142.00711000000001,-8.66497],"type":"Point"}
}