{
  "type": "Feature",
  "properties": {
    "gn:admin1_code":"14",
    "gn:asciiname":"Maniag",
    "gn:country_code":"PG",
    "gn:dem":219,
    "gn:feature_class":"P",
    "gn:feature_code":"PPL",
    "gn:name":"Maniag",
    "gn:population":0,
    "gn:timezone":"Pacific/Port_Moresby",
    "iso:country":"PG",
    "wof:name":"Maniag",
    "wof:placetype":"locality"
},
  "geometry": {"coordinates":[146.31594999999999,-6.35607],"type":"Point"}
}