{
  "type": "Feature",
  "properties": {
    "gn:admin1_code":"10",
    "gn:asciiname":"Kaubademki",
    "gn:country_code":"PG",
    "gn:dem":24,
    "gn:feature_class":"P",
    "gn:feature_code":"PPL",
    "gn:name":"Kaubademki",
    "gn:population":0,
    "gn:timezone":"Pacific/Port_Moresby",
    "iso:country":"PG",
    "wof:name":"Kaubademki",
    "wof:placetype":"locality"
},
  "geometry": {"coordinates":[151.97378,-4.9598],"type":"Point"}
}