{
  "type": "Feature",
  "properties": {
    "gn:admin1_code":"11",
    "gn:asciiname":"Dusin",
    "gn:country_code":"PG",
    "gn:dem":1707,
    "gn:feature_class":"P",
    "gn:feature_code":"PPL",
    "gn:name":"Dusin",
    "gn:population":0,
    "gn:timezone":"Pacific/Port_Moresby",
    "iso:country":"PG",
    "name:pol_x_preferred":[
        "Dusin"
    ],
    "name:ukr_x_preferred":[
        "\u0414\u0443\u0441\u0456\u043d"
    ],
    "name:vie_x_preferred":[
        "Dusin"
    ],
    "wof:name":"Dusin",
    "wof:placetype":"locality"
},
  "geometry": {"coordinates":[144.41654,-5.18909],"type":"Point"}
}