{
  "type": "Feature",
  "properties": {
    "gn:admin1_code":"12",
    "gn:asciiname":"Mataloi",
    "gn:country_code":"PG",
    "gn:dem":411,
    "gn:feature_class":"P",
    "gn:feature_code":"PPL",
    "gn:name":"Mataloi",
    "gn:population":0,
    "gn:timezone":"Pacific/Port_Moresby",
    "iso:country":"PG",
    "wof:name":"Mataloi",
    "wof:placetype":"locality"
},
  "geometry": {"coordinates":[145.56609,-5.61099],"type":"Point"}
}