{
  "type": "Feature",
  "properties": {
    "gn:admin1_code":"03",
    "gn:asciiname":"Danawan",
    "gn:country_code":"PG",
    "gn:dem":671,
    "gn:feature_class":"P",
    "gn:feature_code":"PPL",
    "gn:name":"Danawan",
    "gn:population":0,
    "gn:timezone":"Pacific/Port_Moresby",
    "iso:country":"PG",
    "name:und_x_variant":[
        "Danawana",
        "Danawan"
    ],
    "wof:name":"Danawan",
    "wof:placetype":"locality"
},
  "geometry": {"coordinates":[149.46555000000001,-9.86361],"type":"Point"}
}