{
  "type": "Feature",
  "properties": {
    "gn:admin1_code":"11",
    "gn:asciiname":"Kusanabu",
    "gn:country_code":"PG",
    "gn:dem":143,
    "gn:feature_class":"P",
    "gn:feature_code":"PPL",
    "gn:name":"Kusanabu",
    "gn:population":0,
    "gn:timezone":"Pacific/Port_Moresby",
    "iso:country":"PG",
    "wof:name":"Kusanabu",
    "wof:placetype":"locality"
},
  "geometry": {"coordinates":[143.11213999999995,-3.701],"type":"Point"}
}