{
  "type": "Feature",
  "properties": {
    "gn:admin1_code":"04",
    "gn:asciiname":"Ejaro",
    "gn:country_code":"PG",
    "gn:dem":757,
    "gn:feature_class":"P",
    "gn:feature_code":"PPL",
    "gn:name":"Ejaro",
    "gn:population":0,
    "gn:timezone":"Pacific/Port_Moresby",
    "iso:country":"PG",
    "wof:name":"Ejaro",
    "wof:placetype":"locality"
},
  "geometry": {"coordinates":[148.04546999999999,-9.13542],"type":"Point"}
}