{
  "type": "Feature",
  "properties": {
    "gn:admin1_code":"09",
    "gn:asciiname":"Yago",
    "gn:country_code":"PG",
    "gn:dem":1855,
    "gn:feature_class":"P",
    "gn:feature_code":"PPL",
    "gn:name":"Yago",
    "gn:population":0,
    "gn:timezone":"Pacific/Port_Moresby",
    "iso:country":"PG",
    "name:ceb_x_preferred":[
        "Yago"
    ],
    "name:deu_x_preferred":[
        "Yago"
    ],
    "name:por_x_preferred":[
        "Yago"
    ],
    "name:swe_x_preferred":[
        "Yago"
    ],
    "wof:name":"Yago",
    "wof:placetype":"locality"
},
  "geometry": {"coordinates":[145.55183,-6.38629],"type":"Point"}
}