{
  "type": "Feature",
  "properties": {
    "gn:admin1_code":"17",
    "gn:asciiname":"Giring",
    "gn:country_code":"PG",
    "gn:dem":73,
    "gn:feature_class":"P",
    "gn:feature_code":"PPL",
    "gn:name":"Giring",
    "gn:population":0,
    "gn:timezone":"Pacific/Port_Moresby",
    "iso:country":"PG",
    "wof:name":"Giring",
    "wof:placetype":"locality"
},
  "geometry": {"coordinates":[149.34999999999999,-5.98333],"type":"Point"}
}