{
  "type": "Feature",
  "properties": {
    "gn:admin1_code":"18",
    "gn:asciiname":"Nareitei",
    "gn:country_code":"PG",
    "gn:dem":501,
    "gn:feature_class":"P",
    "gn:feature_code":"PPL",
    "gn:name":"Nareitei",
    "gn:population":0,
    "gn:timezone":"Pacific/Port_Moresby",
    "iso:country":"PG",
    "wof:name":"Nareitei",
    "wof:placetype":"locality"
},
  "geometry": {"coordinates":[142.06896,-3.47207],"type":"Point"}
}