{
  "type": "Feature",
  "properties": {
    "gn:admin1_code":"11",
    "gn:asciiname":"Nambari 2",
    "gn:country_code":"PG",
    "gn:dem":179,
    "gn:feature_class":"P",
    "gn:feature_code":"PPL",
    "gn:name":"Nambari 2",
    "gn:population":0,
    "gn:timezone":"Pacific/Port_Moresby",
    "iso:country":"PG",
    "name:und_x_variant":[
        "Nambari Number 2",
        "Nambari 2"
    ],
    "wof:name":"Nambari 2",
    "wof:placetype":"locality"
},
  "geometry": {"coordinates":[143.24553999999995,-3.68414],"type":"Point"}
}