{
  "type": "Feature",
  "properties": {
    "gn:admin1_code":"06",
    "gn:asciiname":"Oriomo",
    "gn:country_code":"PG",
    "gn:dem":24,
    "gn:feature_class":"P",
    "gn:feature_code":"PPL",
    "gn:name":"Oriomo",
    "gn:population":0,
    "gn:timezone":"Pacific/Port_Moresby",
    "iso:country":"PG",
    "wof:name":"Oriomo",
    "wof:placetype":"locality"
},
  "geometry": {"coordinates":[143.17070000000001,-8.87604],"type":"Point"}
}