{
  "type": "Feature",
  "properties": {
    "gn:admin1_code":"08",
    "gn:asciiname":"Wantige-Wopana",
    "gn:country_code":"PG",
    "gn:dem":2602,
    "gn:feature_class":"P",
    "gn:feature_code":"PPL",
    "gn:name":"Wantige-Wopana",
    "gn:population":0,
    "gn:timezone":"Pacific/Port_Moresby",
    "iso:country":"PG",
    "wof:name":"Wantige-Wopana",
    "wof:placetype":"locality"
},
  "geometry": {"coordinates":[145.08333000000005,-5.83333],"type":"Point"}
}