{
  "type": "Feature",
  "properties": {
    "gn:admin1_code":"08",
    "gn:asciiname":"Tambandikani",
    "gn:country_code":"PG",
    "gn:dem":1990,
    "gn:feature_class":"P",
    "gn:feature_code":"PPL",
    "gn:name":"Tambandikani",
    "gn:population":0,
    "gn:timezone":"Pacific/Port_Moresby",
    "iso:country":"PG",
    "wof:name":"Tambandikani",
    "wof:placetype":"locality"
},
  "geometry": {"coordinates":[145.03333000000001,-6.01667],"type":"Point"}
}