{
  "type": "Feature",
  "properties": {
    "gn:admin1_code":"18",
    "gn:asciiname":"Ibagum",
    "gn:country_code":"PG",
    "gn:dem":445,
    "gn:feature_class":"P",
    "gn:feature_code":"PPL",
    "gn:name":"Ibagum",
    "gn:population":0,
    "gn:timezone":"Pacific/Port_Moresby",
    "iso:country":"PG",
    "wof:name":"Ibagum",
    "wof:placetype":"locality"
},
  "geometry": {"coordinates":[141.19994,-3.58209],"type":"Point"}
}