{
  "type": "Feature",
  "properties": {
    "gn:admin1_code":"12",
    "gn:asciiname":"Yabuk",
    "gn:country_code":"PG",
    "gn:dem":357,
    "gn:feature_class":"P",
    "gn:feature_code":"PPL",
    "gn:name":"Yabuk",
    "gn:population":0,
    "gn:timezone":"Pacific/Port_Moresby",
    "iso:country":"PG",
    "wof:name":"Yabuk",
    "wof:placetype":"locality"
},
  "geometry": {"coordinates":[145.65000000000001,-4.88333],"type":"Point"}
}