{
  "type": "Feature",
  "properties": {
    "gn:admin1_code":"14",
    "gn:asciiname":"Apo",
    "gn:country_code":"PG",
    "gn:dem":14,
    "gn:feature_class":"P",
    "gn:feature_code":"PPL",
    "gn:name":"Apo",
    "gn:population":0,
    "gn:timezone":"Pacific/Port_Moresby",
    "iso:country":"PG",
    "name:ceb_x_preferred":[
        "Apo"
    ],
    "name:diq_x_preferred":[
        "Apo"
    ],
    "name:fin_x_preferred":[
        "Apo"
    ],
    "name:nld_x_preferred":[
        "Apo"
    ],
    "name:por_x_preferred":[
        "Apo"
    ],
    "name:swe_x_preferred":[
        "Apo"
    ],
    "name:tgl_x_preferred":[
        "Apo"
    ],
    "name:tur_x_preferred":[
        "Apo"
    ],
    "wof:name":"Apo",
    "wof:placetype":"locality"
},
  "geometry": {"coordinates":[147.14157,-6.69981],"type":"Point"}
}