{
  "type": "Feature",
  "properties": {
    "gn:admin1_code":"09",
    "gn:asciiname":"Kunugu",
    "gn:country_code":"PG",
    "gn:dem":1568,
    "gn:feature_class":"P",
    "gn:feature_code":"PPL",
    "gn:name":"Kunugu",
    "gn:population":0,
    "gn:timezone":"Pacific/Port_Moresby",
    "iso:country":"PG",
    "wof:name":"Kunugu",
    "wof:placetype":"locality"
},
  "geometry": {"coordinates":[145.43333000000001,-6.35],"type":"Point"}
}