{
  "type": "Feature",
  "properties": {
    "gn:admin1_code":"05",
    "gn:asciiname":"Pegara",
    "gn:country_code":"PG",
    "gn:dem":1794,
    "gn:feature_class":"P",
    "gn:feature_code":"PPL",
    "gn:name":"Pegara",
    "gn:population":0,
    "gn:timezone":"Pacific/Port_Moresby",
    "iso:country":"PG",
    "wof:name":"Pegara",
    "wof:placetype":"locality"
},
  "geometry": {"coordinates":[143.65258,-6.12101],"type":"Point"}
}