{
  "type": "Feature",
  "properties": {
    "gn:admin1_code":"11",
    "gn:asciiname":"Gavien",
    "gn:country_code":"PG",
    "gn:dem":79,
    "gn:feature_class":"P",
    "gn:feature_code":"PPL",
    "gn:name":"Gavien",
    "gn:population":0,
    "gn:timezone":"Pacific/Port_Moresby",
    "iso:country":"PG",
    "wof:name":"Gavien",
    "wof:placetype":"locality"
},
  "geometry": {"coordinates":[144.08484999999999,-3.93247],"type":"Point"}
}