{
  "type": "Feature",
  "properties": {
    "gn:admin1_code":"01",
    "gn:asciiname":"Boridi",
    "gn:country_code":"PG",
    "gn:dem":1112,
    "gn:feature_class":"P",
    "gn:feature_code":"PPL",
    "gn:name":"Boridi",
    "gn:population":0,
    "gn:timezone":"Pacific/Port_Moresby",
    "iso:country":"PG",
    "name:ceb_x_preferred":[
        "Boridi"
    ],
    "name:fas_x_preferred":[
        "\u0628\u0648\u0631\u06cc\u062f\u06cc"
    ],
    "wof:name":"Boridi",
    "wof:placetype":"locality"
},
  "geometry": {"coordinates":[147.63444999999999,-9.07546],"type":"Point"}
}