{
  "type": "Feature",
  "properties": {
    "gn:admin1_code":"14",
    "gn:asciiname":"Kwasang",
    "gn:country_code":"PG",
    "gn:dem":1832,
    "gn:feature_class":"P",
    "gn:feature_code":"PPL",
    "gn:name":"Kwasang",
    "gn:population":0,
    "gn:timezone":"Pacific/Port_Moresby",
    "iso:country":"PG",
    "name:und_x_variant":[
        "Kwasang 1",
        "Kwasang"
    ],
    "wof:name":"Kwasang",
    "wof:placetype":"locality"
},
  "geometry": {"coordinates":[146.70984999999999,-6.97224],"type":"Point"}
}