{
  "type": "Feature",
  "properties": {
    "gn:admin1_code":"08",
    "gn:asciiname":"Oltokane",
    "gn:country_code":"PG",
    "gn:dem":2100,
    "gn:feature_class":"P",
    "gn:feature_code":"PPL",
    "gn:name":"Oltokane",
    "gn:population":0,
    "gn:timezone":"Pacific/Port_Moresby",
    "iso:country":"PG",
    "wof:name":"Oltokane",
    "wof:placetype":"locality"
},
  "geometry": {"coordinates":[144.90000000000001,-5.86667],"type":"Point"}
}