{
  "type": "Feature",
  "properties": {
    "gn:admin1_code":"14",
    "gn:asciiname":"Sikwong",
    "gn:country_code":"PG",
    "gn:dem":1536,
    "gn:feature_class":"P",
    "gn:feature_code":"PPL",
    "gn:name":"Sikwong",
    "gn:population":0,
    "gn:timezone":"Pacific/Port_Moresby",
    "iso:country":"PG",
    "wof:name":"Sikwong",
    "wof:placetype":"locality"
},
  "geometry": {"coordinates":[146.10679999999999,-7.24353],"type":"Point"}
}