{
  "type": "Feature",
  "properties": {
    "gn:admin1_code":"12",
    "gn:asciiname":"Sepen Number 1",
    "gn:country_code":"PG",
    "gn:dem":36,
    "gn:feature_class":"P",
    "gn:feature_code":"PPL",
    "gn:name":"Sepen Number 1",
    "gn:population":0,
    "gn:timezone":"Pacific/Port_Moresby",
    "iso:country":"PG",
    "wof:name":"Sepen Number 1",
    "wof:placetype":"locality"
},
  "geometry": {"coordinates":[144.79640000000001,-4.22954],"type":"Point"}
}