{
  "type": "Feature",
  "properties": {
    "gn:admin1_code":"02",
    "gn:asciiname":"Novihoho",
    "gn:country_code":"PG",
    "gn:dem":34,
    "gn:feature_class":"P",
    "gn:feature_code":"PPL",
    "gn:name":"Novihoho",
    "gn:population":0,
    "gn:timezone":"Pacific/Port_Moresby",
    "iso:country":"PG",
    "name:und_x_variant":[
        "Dohehoho",
        "Novihoho"
    ],
    "wof:name":"Novihoho",
    "wof:placetype":"locality"
},
  "geometry": {"coordinates":[145.52178000000001,-7.90745],"type":"Point"}
}