{
  "type": "Feature",
  "properties": {
    "gn:admin1_code":"14",
    "gn:asciiname":"Gasam",
    "gn:country_code":"PG",
    "gn:dem":379,
    "gn:feature_class":"P",
    "gn:feature_code":"PPL",
    "gn:name":"Gasam",
    "gn:population":0,
    "gn:timezone":"Pacific/Port_Moresby",
    "iso:country":"PG",
    "wof:name":"Gasam",
    "wof:placetype":"locality"
},
  "geometry": {"coordinates":[147.81489999999999,-5.59064],"type":"Point"}
}