{
  "type": "Feature",
  "properties": {
    "gn:admin1_code":"17",
    "gn:asciiname":"Kauptimete",
    "gn:country_code":"PG",
    "gn:dem":9,
    "gn:feature_class":"P",
    "gn:feature_code":"PPL",
    "gn:name":"Kauptimete",
    "gn:population":0,
    "gn:timezone":"Pacific/Port_Moresby",
    "iso:country":"PG",
    "wof:name":"Kauptimete",
    "wof:placetype":"locality"
},
  "geometry": {"coordinates":[148.93633,-6.18042],"type":"Point"}
}