{
  "type": "Feature",
  "properties": {
    "gn:admin1_code":"09",
    "gn:asciiname":"Sinei",
    "gn:country_code":"PG",
    "gn:dem":1122,
    "gn:feature_class":"P",
    "gn:feature_code":"PPL",
    "gn:name":"Sinei",
    "gn:population":0,
    "gn:timezone":"Pacific/Port_Moresby",
    "iso:country":"PG",
    "wof:name":"Sinei",
    "wof:placetype":"locality"
},
  "geometry": {"coordinates":[145.73333,-7.11667],"type":"Point"}
}