{
  "type": "Feature",
  "properties": {
    "gn:admin1_code":"06",
    "gn:asciiname":"Hedamabi",
    "gn:country_code":"PG",
    "gn:dem":226,
    "gn:feature_class":"P",
    "gn:feature_code":"PPL",
    "gn:name":"Hedamabi",
    "gn:population":0,
    "gn:timezone":"Pacific/Port_Moresby",
    "iso:country":"PG",
    "wof:name":"Hedamabi",
    "wof:placetype":"locality"
},
  "geometry": {"coordinates":[142.38333,-6.36667],"type":"Point"}
}