{
  "type": "Feature",
  "properties": {
    "gn:admin1_code":"06",
    "gn:asciiname":"Buseki",
    "gn:country_code":"PG",
    "gn:dem":19,
    "gn:feature_class":"P",
    "gn:feature_code":"PPL",
    "gn:name":"Buseki",
    "gn:population":0,
    "gn:timezone":"Pacific/Port_Moresby",
    "iso:country":"PG",
    "wof:name":"Buseki",
    "wof:placetype":"locality"
},
  "geometry": {"coordinates":[141.43194,-6.74887],"type":"Point"}
}