{
  "type": "Feature",
  "properties": {
    "gn:admin1_code":"18",
    "gn:asciiname":"Utai",
    "gn:country_code":"PG",
    "gn:dem":218,
    "gn:feature_class":"P",
    "gn:feature_code":"PPL",
    "gn:name":"Utai",
    "gn:population":0,
    "gn:timezone":"Pacific/Port_Moresby",
    "iso:country":"PG",
    "wof:name":"Utai",
    "wof:placetype":"locality"
},
  "geometry": {"coordinates":[141.58533,-3.38427],"type":"Point"}
}