{
  "type": "Feature",
  "properties": {
    "gn:admin1_code":"04",
    "gn:asciiname":"Tipakofari",
    "gn:country_code":"PG",
    "gn:dem":36,
    "gn:feature_class":"P",
    "gn:feature_code":"PPL",
    "gn:name":"Tipakofari",
    "gn:population":0,
    "gn:timezone":"Pacific/Port_Moresby",
    "iso:country":"PG",
    "wof:name":"Tipakofari",
    "wof:placetype":"locality"
},
  "geometry": {"coordinates":[148.41666999999995,-8.75],"type":"Point"}
}