{
  "type": "Feature",
  "properties": {
    "gn:admin1_code":"19",
    "gn:asciiname":"Sauanda",
    "gn:country_code":"PG",
    "gn:dem":1740,
    "gn:feature_class":"P",
    "gn:feature_code":"PPL",
    "gn:name":"Sauanda",
    "gn:population":0,
    "gn:timezone":"Pacific/Port_Moresby",
    "iso:country":"PG",
    "wof:name":"Sauanda",
    "wof:placetype":"locality"
},
  "geometry": {"coordinates":[143.85423,-5.38018],"type":"Point"}
}