{
  "type": "Feature",
  "properties": {
    "gn:admin1_code":"13",
    "gn:asciiname":"Mokerang",
    "gn:country_code":"PG",
    "gn:dem":19,
    "gn:feature_class":"P",
    "gn:feature_code":"PPL",
    "gn:name":"Mokerang",
    "gn:population":0,
    "gn:timezone":"Pacific/Port_Moresby",
    "iso:country":"PG",
    "name:und_x_variant":[
        "Mokareng",
        "Moakareng",
        "Moakereng",
        "Mokerang"
    ],
    "wof:name":"Mokerang",
    "wof:placetype":"locality"
},
  "geometry": {"coordinates":[147.39937,-2.00032],"type":"Point"}
}