{
  "type": "Feature",
  "properties": {
    "gn:admin1_code":"11",
    "gn:asciiname":"Walahuta 1",
    "gn:country_code":"PG",
    "gn:dem":249,
    "gn:feature_class":"P",
    "gn:feature_code":"PPL",
    "gn:name":"Walahuta 1",
    "gn:population":0,
    "gn:timezone":"Pacific/Port_Moresby",
    "iso:country":"PG",
    "wof:name":"Walahuta 1",
    "wof:placetype":"locality"
},
  "geometry": {"coordinates":[142.96124,-3.59868],"type":"Point"}
}