{
  "type": "Feature",
  "properties": {
    "gn:admin1_code":"06",
    "gn:asciiname":"Suki",
    "gn:country_code":"PG",
    "gn:dem":9,
    "gn:feature_class":"P",
    "gn:feature_code":"PPL",
    "gn:name":"Suki",
    "gn:population":0,
    "gn:timezone":"Pacific/Port_Moresby",
    "iso:country":"PG",
    "name:msa_x_preferred":[
        "Suki"
    ],
    "name:pol_x_preferred":[
        "Suki"
    ],
    "name:spa_x_preferred":[
        "Suki"
    ],
    "wof:name":"Suki",
    "wof:placetype":"locality"
},
  "geometry": {"coordinates":[141.72283000000004,-8.04247],"type":"Point"}
}