{
  "type": "Feature",
  "properties": {
    "gn:admin1_code":"14",
    "gn:asciiname":"Rebafu",
    "gn:country_code":"PG",
    "gn:dem":1350,
    "gn:feature_class":"P",
    "gn:feature_code":"PPL",
    "gn:name":"Rebafu",
    "gn:population":0,
    "gn:timezone":"Pacific/Port_Moresby",
    "iso:country":"PG",
    "name:und_x_variant":[
        "Rabafu",
        "Rebafu"
    ],
    "wof:name":"Rebafu",
    "wof:placetype":"locality"
},
  "geometry": {"coordinates":[147.59366,-6.28812],"type":"Point"}
}