{
  "type": "Feature",
  "properties": {
    "gn:admin1_code":"02",
    "gn:asciiname":"Herehere Number 1",
    "gn:country_code":"PG",
    "gn:dem":18,
    "gn:feature_class":"P",
    "gn:feature_code":"PPL",
    "gn:name":"Herehere Number 1",
    "gn:population":0,
    "gn:timezone":"Pacific/Port_Moresby",
    "iso:country":"PG",
    "name:und_x_variant":[
        "Herehere",
        "Herehere 1",
        "Herehere Number 1"
    ],
    "wof:name":"Herehere Number 1",
    "wof:placetype":"locality"
},
  "geometry": {"coordinates":[145.56916000000001,-7.93826],"type":"Point"}
}