{
  "type": "Feature",
  "properties": {
    "gn:admin1_code":"09",
    "gn:asciiname":"Liborei",
    "gn:country_code":"PG",
    "gn:dem":1882,
    "gn:feature_class":"P",
    "gn:feature_code":"PPL",
    "gn:name":"Liborei",
    "gn:population":0,
    "gn:timezone":"Pacific/Port_Moresby",
    "iso:country":"PG",
    "wof:name":"Liborei",
    "wof:placetype":"locality"
},
  "geometry": {"coordinates":[145.10554999999999,-6.43576],"type":"Point"}
}