{
  "type": "Feature",
  "properties": {
    "gn:admin1_code":"14",
    "gn:asciiname":"Aningi",
    "gn:country_code":"PG",
    "gn:dem":1032,
    "gn:feature_class":"P",
    "gn:feature_code":"PPL",
    "gn:name":"Aningi",
    "gn:population":0,
    "gn:timezone":"Pacific/Port_Moresby",
    "iso:country":"PG",
    "wof:name":"Aningi",
    "wof:placetype":"locality"
},
  "geometry": {"coordinates":[146.34804,-7.41404],"type":"Point"}
}