{
  "type": "Feature",
  "properties": {
    "gn:admin1_code":"17",
    "gn:asciiname":"Baia",
    "gn:country_code":"PG",
    "gn:dem":-9999,
    "gn:feature_class":"P",
    "gn:feature_code":"PPL",
    "gn:name":"Baia",
    "gn:population":0,
    "gn:timezone":"Pacific/Port_Moresby",
    "iso:country":"PG",
    "name:ara_x_preferred":[
        "\u0628\u0627\u064a\u0627"
    ],
    "name:ceb_x_preferred":[
        "Comuna Baia"
    ],
    "name:deu_x_preferred":[
        "Baia"
    ],
    "name:epo_x_preferred":[
        "Baia"
    ],
    "name:fas_x_preferred":[
        "\u0628\u0627\u06cc\u0627"
    ],
    "name:fra_x_preferred":[
        "Baia"
    ],
    "name:ita_x_preferred":[
        "Baia"
    ],
    "name:lit_x_preferred":[
        "Baja"
    ],
    "name:msa_x_preferred":[
        "Baia"
    ],
    "name:pol_x_preferred":[
        "Baia"
    ],
    "name:por_x_preferred":[
        "Baia"
    ],
    "name:ron_x_preferred":[
        "Comuna Baia"
    ],
    "name:srp_x_preferred":[
        "\u041e\u043f\u0448\u0442\u0438\u043d\u0430 \u0411\u0430\u0458\u0430"
    ],
    "name:ukr_x_preferred":[
        "\u0411\u0430\u044f"
    ],
    "name:vie_x_preferred":[
        "Baia"
    ],
    "name:vol_x_preferred":[
        "Baia"
    ],
    "name:zho_x_preferred":[
        "\u5df4\u4e9e\u9109"
    ],
    "wof:name":"Baia",
    "wof:placetype":"locality"
},
  "geometry": {"coordinates":[151.52598,-4.92344],"type":"Point"}
}