{
  "type": "Feature",
  "properties": {
    "gn:admin1_code":"17",
    "gn:asciiname":"Patanga",
    "gn:country_code":"PG",
    "gn:dem":65,
    "gn:feature_class":"P",
    "gn:feature_code":"PPL",
    "gn:name":"Patanga",
    "gn:population":0,
    "gn:timezone":"Pacific/Port_Moresby",
    "iso:country":"PG",
    "wof:name":"Patanga",
    "wof:placetype":"locality"
},
  "geometry": {"coordinates":[150.06594999999999,-5.39603],"type":"Point"}
}