{
  "type": "Feature",
  "properties": {
    "gn:admin1_code":"08",
    "gn:asciiname":"Genaku",
    "gn:country_code":"PG",
    "gn:dem":1853,
    "gn:feature_class":"P",
    "gn:feature_code":"PPL",
    "gn:name":"Genaku",
    "gn:population":0,
    "gn:timezone":"Pacific/Port_Moresby",
    "iso:country":"PG",
    "wof:name":"Genaku",
    "wof:placetype":"locality"
},
  "geometry": {"coordinates":[144.98677000000001,-6.05957],"type":"Point"}
}