{
  "type": "Feature",
  "properties": {
    "gn:admin1_code":"05",
    "gn:asciiname":"Pumi",
    "gn:country_code":"PG",
    "gn:dem":1938,
    "gn:feature_class":"P",
    "gn:feature_code":"PPL",
    "gn:name":"Pumi",
    "gn:population":0,
    "gn:timezone":"Pacific/Port_Moresby",
    "iso:country":"PG",
    "wof:name":"Pumi",
    "wof:placetype":"locality"
},
  "geometry": {"coordinates":[143.60311000000004,-6.23898],"type":"Point"}
}