{
  "type": "Feature",
  "properties": {
    "gn:admin1_code":"02",
    "gn:asciiname":"Sam",
    "gn:country_code":"PG",
    "gn:dem":561,
    "gn:feature_class":"P",
    "gn:feature_code":"PPL",
    "gn:name":"Sam",
    "gn:population":0,
    "gn:timezone":"Pacific/Port_Moresby",
    "iso:country":"PG",
    "wof:name":"Sam",
    "wof:placetype":"locality"
},
  "geometry": {"coordinates":[145.83333000000005,-7.71667],"type":"Point"}
}