{
  "type": "Feature",
  "properties": {
    "gn:admin1_code":"12",
    "gn:asciiname":"Igom",
    "gn:cc2":"PG",
    "gn:country_code":"PG",
    "gn:dem":80,
    "gn:feature_class":"P",
    "gn:feature_code":"PPL",
    "gn:name":"Igom",
    "gn:population":0,
    "gn:timezone":"Pacific/Port_Moresby",
    "iso:country":"PG",
    "name:und_x_variant":[
        "Miss",
        "Igom"
    ],
    "wof:name":"Igom",
    "wof:placetype":"locality"
},
  "geometry": {"coordinates":[144.81666999999999,-4.43333],"type":"Point"}
}