{
  "type": "Feature",
  "properties": {
    "gn:admin1_code":"11",
    "gn:asciiname":"Wosambu",
    "gn:country_code":"PG",
    "gn:dem":119,
    "gn:feature_class":"P",
    "gn:feature_code":"PPL",
    "gn:name":"Wosambu",
    "gn:population":0,
    "gn:timezone":"Pacific/Port_Moresby",
    "iso:country":"PG",
    "wof:name":"Wosambu",
    "wof:placetype":"locality"
},
  "geometry": {"coordinates":[142.68528000000001,-3.75279],"type":"Point"}
}