{
  "type": "Feature",
  "properties": {
    "gn:admin1_code":"01",
    "gn:asciiname":"Kido",
    "gn:country_code":"PG",
    "gn:dem":7,
    "gn:feature_class":"P",
    "gn:feature_code":"PPL",
    "gn:name":"Kido",
    "gn:population":0,
    "gn:timezone":"Pacific/Port_Moresby",
    "iso:country":"PG",
    "wof:name":"Kido",
    "wof:placetype":"locality"
},
  "geometry": {"coordinates":[146.90716,-9.27105],"type":"Point"}
}