{
  "type": "Feature",
  "properties": {
    "gn:admin1_code":"11",
    "gn:asciiname":"Munyiten",
    "gn:country_code":"PG",
    "gn:dem":27,
    "gn:feature_class":"P",
    "gn:feature_code":"PPL",
    "gn:name":"Munyiten",
    "gn:population":0,
    "gn:timezone":"Pacific/Port_Moresby",
    "iso:country":"PG",
    "name:und_x_variant":[
        "Munyaten",
        "Munyatem",
        "Munyiten"
    ],
    "wof:name":"Munyiten",
    "wof:placetype":"locality"
},
  "geometry": {"coordinates":[144.08922999999999,-4.52445],"type":"Point"}
}