{
  "type": "Feature",
  "properties": {
    "gn:admin1_code":"15",
    "gn:asciiname":"Kulungei",
    "gn:cc2":"PG",
    "gn:country_code":"PG",
    "gn:dem":9,
    "gn:feature_class":"P",
    "gn:feature_code":"PPL",
    "gn:name":"Kulungei",
    "gn:population":0,
    "gn:timezone":"Pacific/Port_Moresby",
    "iso:country":"PG",
    "name:und_x_variant":[
        "Kulingai",
        "Kulungei"
    ],
    "wof:name":"Kulungei",
    "wof:placetype":"locality"
},
  "geometry": {"coordinates":[150.43333000000001,-2.56667],"type":"Point"}
}