{
  "type": "Feature",
  "properties": {
    "gn:admin1_code":"15",
    "gn:asciiname":"Kowamarara",
    "gn:country_code":"PG",
    "gn:dem":61,
    "gn:feature_class":"P",
    "gn:feature_code":"PPL",
    "gn:name":"Kowamarara",
    "gn:population":0,
    "gn:timezone":"Pacific/Port_Moresby",
    "iso:country":"PG",
    "name:und_x_variant":[
        "Kowamanara",
        "Kowamarara"
    ],
    "wof:name":"Kowamarara",
    "wof:placetype":"locality"
},
  "geometry": {"coordinates":[151.95508000000001,-2.88091],"type":"Point"}
}