{
  "type": "Feature",
  "properties": {
    "gn:admin1_code":"18",
    "gn:asciiname":"Isu 2",
    "gn:country_code":"PG",
    "gn:dem":49,
    "gn:feature_class":"P",
    "gn:feature_code":"PPL",
    "gn:name":"Isu 2",
    "gn:population":0,
    "gn:timezone":"Pacific/Port_Moresby",
    "iso:country":"PG",
    "name:und_x_variant":[
        "Isu",
        "Isu 2"
    ],
    "wof:name":"Isu 2",
    "wof:placetype":"locality"
},
  "geometry": {"coordinates":[141.12203,-4.0847],"type":"Point"}
}