{
  "type": "Feature",
  "properties": {
    "gn:admin1_code":"08",
    "gn:asciiname":"Nebigu",
    "gn:country_code":"PG",
    "gn:dem":1828,
    "gn:feature_class":"P",
    "gn:feature_code":"PPL",
    "gn:name":"Nebigu",
    "gn:population":0,
    "gn:timezone":"Pacific/Port_Moresby",
    "iso:country":"PG",
    "wof:name":"Nebigu",
    "wof:placetype":"locality"
},
  "geometry": {"coordinates":[144.90476000000001,-6.19192],"type":"Point"}
}