{
  "type": "Feature",
  "properties": {
    "gn:admin1_code":"08",
    "gn:asciiname":"Indugwagane",
    "gn:country_code":"PG",
    "gn:dem":1966,
    "gn:feature_class":"P",
    "gn:feature_code":"PPL",
    "gn:name":"Indugwagane",
    "gn:population":0,
    "gn:timezone":"Pacific/Port_Moresby",
    "iso:country":"PG",
    "wof:name":"Indugwagane",
    "wof:placetype":"locality"
},
  "geometry": {"coordinates":[144.91666999999995,-5.96667],"type":"Point"}
}