{
  "type": "Feature",
  "properties": {
    "gn:admin1_code":"02",
    "gn:asciiname":"Uyeiwata",
    "gn:country_code":"PG",
    "gn:dem":712,
    "gn:feature_class":"P",
    "gn:feature_code":"PPL",
    "gn:name":"Uyeiwata",
    "gn:population":0,
    "gn:timezone":"Pacific/Port_Moresby",
    "iso:country":"PG",
    "wof:name":"Uyeiwata",
    "wof:placetype":"locality"
},
  "geometry": {"coordinates":[146.15013999999999,-7.57296],"type":"Point"}
}