{
  "type": "Feature",
  "properties": {
    "gn:admin1_code":"14",
    "gn:asciiname":"Wauit",
    "gn:cc2":"PG",
    "gn:country_code":"PG",
    "gn:dem":1623,
    "gn:feature_class":"P",
    "gn:feature_code":"PPL",
    "gn:name":"Wauit",
    "gn:population":0,
    "gn:timezone":"Pacific/Port_Moresby",
    "iso:country":"PG",
    "name:und_x_variant":[
        "Warit",
        "Wauit"
    ],
    "wof:name":"Wauit",
    "wof:placetype":"locality"
},
  "geometry": {"coordinates":[147.16666999999995,-6.08333],"type":"Point"}
}