{
  "type": "Feature",
  "properties": {
    "gn:admin1_code":"11",
    "gn:asciiname":"Kaubari",
    "gn:country_code":"PG",
    "gn:dem":364,
    "gn:feature_class":"P",
    "gn:feature_code":"PPL",
    "gn:name":"Kaubari",
    "gn:population":0,
    "gn:timezone":"Pacific/Port_Moresby",
    "iso:country":"PG",
    "wof:name":"Kaubari",
    "wof:placetype":"locality"
},
  "geometry": {"coordinates":[143.71666999999999,-3.68333],"type":"Point"}
}