{
  "type": "Feature",
  "properties": {
    "gn:admin1_code":"11",
    "gn:asciiname":"Nungori 1",
    "gn:country_code":"PG",
    "gn:dem":218,
    "gn:feature_class":"P",
    "gn:feature_code":"PPL",
    "gn:name":"Nungori 1",
    "gn:population":0,
    "gn:timezone":"Pacific/Port_Moresby",
    "iso:country":"PG",
    "wof:name":"Nungori 1",
    "wof:placetype":"locality"
},
  "geometry": {"coordinates":[143.46202,-3.69627],"type":"Point"}
}