{
  "type": "Feature",
  "properties": {
    "gn:admin1_code":"14",
    "gn:asciiname":"Hamuni",
    "gn:country_code":"PG",
    "gn:dem":1197,
    "gn:feature_class":"P",
    "gn:feature_code":"PPL",
    "gn:name":"Hamuni",
    "gn:population":0,
    "gn:timezone":"Pacific/Port_Moresby",
    "iso:country":"PG",
    "name:und_x_variant":[
        "Hamuini",
        "Hamuni"
    ],
    "wof:name":"Hamuni",
    "wof:placetype":"locality"
},
  "geometry": {"coordinates":[146.35783999999995,-7.49262],"type":"Point"}
}