{
  "type": "Feature",
  "properties": {
    "gn:admin1_code":"11",
    "gn:asciiname":"Haruwa",
    "gn:country_code":"PG",
    "gn:dem":156,
    "gn:feature_class":"P",
    "gn:feature_code":"PPL",
    "gn:name":"Haruwa",
    "gn:population":0,
    "gn:timezone":"Pacific/Port_Moresby",
    "iso:country":"PG",
    "wof:name":"Haruwa",
    "wof:placetype":"locality"
},
  "geometry": {"coordinates":[143.35773999999995,-3.71158],"type":"Point"}
}