{
  "type": "Feature",
  "properties": {
    "gn:admin1_code":"17",
    "gn:asciiname":"Pomete",
    "gn:country_code":"PG",
    "gn:dem":91,
    "gn:feature_class":"P",
    "gn:feature_code":"PPL",
    "gn:name":"Pomete",
    "gn:population":0,
    "gn:timezone":"Pacific/Port_Moresby",
    "iso:country":"PG",
    "wof:name":"Pomete",
    "wof:placetype":"locality"
},
  "geometry": {"coordinates":[149.53333000000001,-6.18333],"type":"Point"}
}