{
  "type": "Feature",
  "properties": {
    "gn:admin1_code":"14",
    "gn:asciiname":"Baup",
    "gn:country_code":"PG",
    "gn:dem":2178,
    "gn:feature_class":"P",
    "gn:feature_code":"PPL",
    "gn:name":"Baup",
    "gn:population":0,
    "gn:timezone":"Pacific/Port_Moresby",
    "iso:country":"PG",
    "wof:name":"Baup",
    "wof:placetype":"locality"
},
  "geometry": {"coordinates":[146.64381,-5.91976],"type":"Point"}
}