{
  "type": "Feature",
  "properties": {
    "gn:admin1_code":"09",
    "gn:asciiname":"Avia",
    "gn:country_code":"PG",
    "gn:dem":2423,
    "gn:feature_class":"P",
    "gn:feature_code":"PPL",
    "gn:name":"Avia",
    "gn:population":0,
    "gn:timezone":"Pacific/Port_Moresby",
    "iso:country":"PG",
    "name:ces_x_preferred":[
        "Avia"
    ],
    "name:ckb_x_preferred":[
        "\u0626\u06d5\u06a4\u06cc\u0627"
    ],
    "name:deu_x_preferred":[
        "Avia"
    ],
    "name:fra_x_preferred":[
        "Avia"
    ],
    "name:hun_x_preferred":[
        "Avia"
    ],
    "name:ita_x_preferred":[
        "Avia"
    ],
    "name:lav_x_preferred":[
        "Avia"
    ],
    "name:nld_x_preferred":[
        "Avia"
    ],
    "name:pol_x_preferred":[
        "Avia"
    ],
    "name:por_x_preferred":[
        "Avia"
    ],
    "name:rus_x_preferred":[
        "Avia"
    ],
    "name:slk_x_preferred":[
        "Avia"
    ],
    "name:spa_x_preferred":[
        "Avia"
    ],
    "name:tur_x_preferred":[
        "Avia"
    ],
    "name:ukr_x_preferred":[
        "Avia"
    ],
    "wof:name":"Avia",
    "wof:placetype":"locality"
},
  "geometry": {"coordinates":[145.75,-6.48333],"type":"Point"}
}