{
  "type": "Feature",
  "properties": {
    "gn:admin1_code":"09",
    "gn:asciiname":"Avia",
    "gn:country_code":"PG",
    "gn:dem":2423,
    "gn:feature_class":"P",
    "gn:feature_code":"PPL",
    "gn:name":"Avia",
    "gn:population":0,
    "gn:timezone":"Pacific/Port_Moresby",
    "iso:country":"PG",
    "wof:name":"Avia",
    "wof:placetype":"locality"
},
  "geometry": {"coordinates":[145.75,-6.48333],"type":"Point"}
}