{
  "type": "Feature",
  "properties": {
    "gn:admin1_code":"07",
    "gn:asciiname":"Poriwon",
    "gn:country_code":"PG",
    "gn:dem":22,
    "gn:feature_class":"P",
    "gn:feature_code":"PPL",
    "gn:name":"Poriwon",
    "gn:population":0,
    "gn:timezone":"Pacific/Bougainville",
    "iso:country":"PG",
    "wof:name":"Poriwon",
    "wof:placetype":"locality"
},
  "geometry": {"coordinates":[154.20211,-4.46684],"type":"Point"}
}