{
  "type": "Feature",
  "properties": {
    "gn:admin1_code":"12",
    "gn:asciiname":"Guhu",
    "gn:country_code":"PG",
    "gn:dem":1219,
    "gn:feature_class":"P",
    "gn:feature_code":"PPL",
    "gn:name":"Guhu",
    "gn:population":0,
    "gn:timezone":"Pacific/Port_Moresby",
    "iso:country":"PG",
    "wof:name":"Guhu",
    "wof:placetype":"locality"
},
  "geometry": {"coordinates":[146.10801999999995,-5.69648],"type":"Point"}
}