{
  "type": "Feature",
  "properties": {
    "gn:admin1_code":"15",
    "gn:asciiname":"Kurumut Number 1",
    "gn:country_code":"PG",
    "gn:dem":153,
    "gn:feature_class":"P",
    "gn:feature_code":"PPL",
    "gn:name":"Kurumut Number 1",
    "gn:population":0,
    "gn:timezone":"Pacific/Port_Moresby",
    "iso:country":"PG",
    "name:und_x_variant":[
        "Kurumut 1",
        "Kurumut Number 1"
    ],
    "wof:name":"Kurumut Number 1",
    "wof:placetype":"locality"
},
  "geometry": {"coordinates":[152.37466000000001,-3.70555],"type":"Point"}
}