{
  "type": "Feature",
  "properties": {
    "gn:admin1_code":"12",
    "gn:asciiname":"Kwanje",
    "gn:country_code":"PG",
    "gn:dem":450,
    "gn:feature_class":"P",
    "gn:feature_code":"PPL",
    "gn:name":"Kwanje",
    "gn:population":0,
    "gn:timezone":"Pacific/Port_Moresby",
    "iso:country":"PG",
    "name:und_x_variant":[
        "Amuson",
        "Kwanje"
    ],
    "wof:name":"Kwanje",
    "wof:placetype":"locality"
},
  "geometry": {"coordinates":[145.7664,-5.66852],"type":"Point"}
}