{
  "type": "Feature",
  "properties": {
    "gn:admin1_code":"10",
    "gn:asciiname":"Vunagalip",
    "gn:country_code":"PG",
    "gn:dem":46,
    "gn:feature_class":"P",
    "gn:feature_code":"PPL",
    "gn:name":"Vunagalip",
    "gn:population":0,
    "gn:timezone":"Pacific/Port_Moresby",
    "iso:country":"PG",
    "wof:name":"Vunagalip",
    "wof:placetype":"locality"
},
  "geometry": {"coordinates":[151.69999999999999,-4.25],"type":"Point"}
}