{
  "type": "Feature",
  "properties": {
    "iso:country":"PG",
    "name:bul_x_preferred":[
        "\u041a\u043e\u043a\u043e\u0434\u0430"
    ],
    "name:cat_x_preferred":[
        "Kokoda"
    ],
    "name:ceb_x_preferred":[
        "Kokoda"
    ],
    "name:ces_x_preferred":[
        "Kokoda"
    ],
    "name:deu_x_preferred":[
        "Kokoda"
    ],
    "name:eng_x_preferred":[
        "Kokoda"
    ],
    "name:fas_x_preferred":[
        "\u06a9\u0648\u06a9\u0648\u062f\u0627"
    ],
    "name:fra_x_preferred":[
        "Kokoda"
    ],
    "name:heb_x_preferred":[
        "\u05e7\u05d5\u05e7\u05d5\u05d3\u05d4"
    ],
    "name:jpn_x_preferred":[
        "\u30b3\u30b3\u30c0"
    ],
    "name:nld_x_preferred":[
        "Kokoda"
    ],
    "name:pol_x_preferred":[
        "Kokoda"
    ],
    "name:rus_x_preferred":[
        "\u041a\u043e\u043a\u043e\u0434\u0430"
    ],
    "name:ukr_x_preferred":[
        "\u041a\u043e\u043a\u043e\u0434\u0430"
    ],
    "name:und_x_variant":[
        "Kodoka"
    ],
    "name:zho_x_preferred":[
        "\u79d1\u79d1\u9054"
    ],
    "qs:gn_country":"PG",
    "qs:gn_fcode":"PPL",
    "qs:gn_pop":6199,
    "qs:name":"Kokoda",
    "qs:name_adm0":"Papua New Guinea",
    "qs:name_adm1":"Northern",
    "qs:photos":126,
    "qs:photos_1k":26,
    "qs:photos_9k":1,
    "qs:photos_9r":3,
    "qs:photos_all":126,
    "qs:photos_sr":3,
    "qs:placetype":"Town",
    "qs:pop_sr":"5",
    "qs:woe_adm0":23424926,
    "wd:wordcount":257,
    "wof:name":"Kokoda",
    "wof:placetype":"locality",
    "wof:population":6199
},
  "geometry": {"coordinates":[147.74073000000001,-8.87853],"type":"Point"}
}