{
  "type": "Feature",
  "properties": {
    "gn:admin1_code":"12",
    "gn:asciiname":"Gegeri",
    "gn:country_code":"PG",
    "gn:dem":211,
    "gn:feature_class":"P",
    "gn:feature_code":"PPL",
    "gn:name":"Gegeri",
    "gn:population":0,
    "gn:timezone":"Pacific/Port_Moresby",
    "iso:country":"PG",
    "name:und_x_variant":[
        "Gegiri",
        "Gegeri"
    ],
    "wof:name":"Gegeri",
    "wof:placetype":"locality"
},
  "geometry": {"coordinates":[145.72136,-5.09947],"type":"Point"}
}