{
  "type": "Feature",
  "properties": {
    "gn:admin1_code":"11",
    "gn:asciiname":"Kusauga",
    "gn:country_code":"PG",
    "gn:dem":80,
    "gn:feature_class":"P",
    "gn:feature_code":"PPL",
    "gn:name":"Kusauga",
    "gn:population":0,
    "gn:timezone":"Pacific/Port_Moresby",
    "iso:country":"PG",
    "name:und_x_variant":[
        "Kausaga",
        "Kusauga"
    ],
    "wof:name":"Kusauga",
    "wof:placetype":"locality"
},
  "geometry": {"coordinates":[143.00295,-3.80229],"type":"Point"}
}