{
  "type": "Feature",
  "properties": {
    "gn:admin1_code":"09",
    "gn:asciiname":"Kamira",
    "gn:country_code":"PG",
    "gn:dem":1793,
    "gn:feature_class":"P",
    "gn:feature_code":"PPL",
    "gn:name":"Kamira",
    "gn:population":0,
    "gn:timezone":"Pacific/Port_Moresby",
    "iso:country":"PG",
    "name:lit_x_preferred":[
        "Kamira"
    ],
    "wof:name":"Kamira",
    "wof:placetype":"locality"
},
  "geometry": {"coordinates":[145.58539999999999,-6.63479],"type":"Point"}
}