{
  "type": "Feature",
  "properties": {
    "gn:admin1_code":"11",
    "gn:asciiname":"Ilahita Villages",
    "gn:country_code":"PG",
    "gn:dem":134,
    "gn:feature_class":"P",
    "gn:feature_code":"PPL",
    "gn:name":"Ilahita Villages",
    "gn:population":0,
    "gn:timezone":"Pacific/Port_Moresby",
    "iso:country":"PG",
    "wof:name":"Ilahita Villages",
    "wof:placetype":"locality"
},
  "geometry": {"coordinates":[142.93647000000001,-3.68055],"type":"Point"}
}