{
  "type": "Feature",
  "properties": {
    "gn:admin1_code":"11",
    "gn:asciiname":"Sevenbuk",
    "gn:country_code":"PG",
    "gn:dem":34,
    "gn:feature_class":"P",
    "gn:feature_code":"PPL",
    "gn:name":"Sevenbuk",
    "gn:population":0,
    "gn:timezone":"Pacific/Port_Moresby",
    "iso:country":"PG",
    "wof:name":"Sevenbuk",
    "wof:placetype":"locality"
},
  "geometry": {"coordinates":[143.36563000000001,-4.59589],"type":"Point"}
}