{
  "type": "Feature",
  "properties": {
    "gn:admin1_code":"14",
    "gn:asciiname":"Gumun",
    "gn:country_code":"PG",
    "gn:dem":2317,
    "gn:feature_class":"P",
    "gn:feature_code":"PPL",
    "gn:name":"Gumun",
    "gn:population":0,
    "gn:timezone":"Pacific/Port_Moresby",
    "iso:country":"PG",
    "wof:name":"Gumun",
    "wof:placetype":"locality"
},
  "geometry": {"coordinates":[147.19842,-6.25447],"type":"Point"}
}