{
  "type": "Feature",
  "properties": {
    "gn:admin1_code":"07",
    "gn:asciiname":"Melilup",
    "gn:country_code":"PG",
    "gn:dem":921,
    "gn:feature_class":"P",
    "gn:feature_code":"PPL",
    "gn:name":"Melilup",
    "gn:population":0,
    "gn:timezone":"Pacific/Bougainville",
    "iso:country":"PG",
    "wof:name":"Melilup",
    "wof:placetype":"locality"
},
  "geometry": {"coordinates":[154.93518999999995,-5.69541],"type":"Point"}
}