{
  "type": "Feature",
  "properties": {
    "gn:admin1_code":"15",
    "gn:asciiname":"Belfamfal",
    "gn:country_code":"PG",
    "gn:dem":14,
    "gn:feature_class":"P",
    "gn:feature_code":"PPL",
    "gn:name":"Belfamfal",
    "gn:population":0,
    "gn:timezone":"Pacific/Port_Moresby",
    "iso:country":"PG",
    "name:und_x_variant":[
        "Belamfar",
        "Belfamfal"
    ],
    "wof:name":"Belfamfal",
    "wof:placetype":"locality"
},
  "geometry": {"coordinates":[153.18107000000001,-3.50106],"type":"Point"}
}