{
  "type": "Feature",
  "properties": {
    "gn:admin1_code":"06",
    "gn:asciiname":"Domori",
    "gn:country_code":"PG",
    "gn:dem":14,
    "gn:feature_class":"P",
    "gn:feature_code":"PPL",
    "gn:name":"Domori",
    "gn:population":0,
    "gn:timezone":"Pacific/Port_Moresby",
    "iso:country":"PG",
    "name:eng_x_preferred":[
        "Domori"
    ],
    "name:zho_x_preferred":[
        "Domori"
    ],
    "wof:name":"Domori",
    "wof:placetype":"locality"
},
  "geometry": {"coordinates":[142.88380000000001,-8.32096],"type":"Point"}
}