{
  "type": "Feature",
  "properties": {
    "gn:admin1_code":"15",
    "gn:asciiname":"Kanamarandan",
    "gn:country_code":"PG",
    "gn:dem":65,
    "gn:feature_class":"P",
    "gn:feature_code":"PPL",
    "gn:name":"Kanamarandan",
    "gn:population":0,
    "gn:timezone":"Pacific/Port_Moresby",
    "iso:country":"PG",
    "name:und_x_variant":[
        "Kanamarandon",
        "Kanamarandan"
    ],
    "wof:name":"Kanamarandan",
    "wof:placetype":"locality"
},
  "geometry": {"coordinates":[151.87698999999995,-3.39044],"type":"Point"}
}