{
  "type": "Feature",
  "properties": {
    "gn:admin1_code":"14",
    "gn:asciiname":"Muniau",
    "gn:cc2":"PG",
    "gn:country_code":"PG",
    "gn:dem":1177,
    "gn:feature_class":"P",
    "gn:feature_code":"PPL",
    "gn:name":"Muniau",
    "gn:population":0,
    "gn:timezone":"Pacific/Port_Moresby",
    "iso:country":"PG",
    "name:und_x_variant":[
        "Muriau",
        "Muniau"
    ],
    "wof:name":"Muniau",
    "wof:placetype":"locality"
},
  "geometry": {"coordinates":[146.78333000000001,-6.83333],"type":"Point"}
}