{
  "type": "Feature",
  "properties": {
    "gn:admin1_code":"12",
    "gn:asciiname":"Urugan",
    "gn:country_code":"PG",
    "gn:dem":199,
    "gn:feature_class":"P",
    "gn:feature_code":"PPL",
    "gn:name":"Urugan",
    "gn:population":0,
    "gn:timezone":"Pacific/Port_Moresby",
    "iso:country":"PG",
    "wof:name":"Urugan",
    "wof:placetype":"locality"
},
  "geometry": {"coordinates":[145.69135,-5.22192],"type":"Point"}
}