{
  "type": "Feature",
  "properties": {
    "gn:admin1_code":"11",
    "gn:asciiname":"Kwowi",
    "gn:country_code":"PG",
    "gn:dem":421,
    "gn:feature_class":"P",
    "gn:feature_code":"PPL",
    "gn:name":"Kwowi",
    "gn:population":0,
    "gn:timezone":"Pacific/Port_Moresby",
    "iso:country":"PG",
    "wof:name":"Kwowi",
    "wof:placetype":"locality"
},
  "geometry": {"coordinates":[143.29626000000005,-3.60997],"type":"Point"}
}