{
  "type": "Feature",
  "properties": {
    "gn:admin1_code":"12",
    "gn:asciiname":"Diugumbi",
    "gn:country_code":"PG",
    "gn:dem":42,
    "gn:feature_class":"P",
    "gn:feature_code":"PPL",
    "gn:name":"Diugumbi",
    "gn:population":0,
    "gn:timezone":"Pacific/Port_Moresby",
    "iso:country":"PG",
    "wof:name":"Diugumbi",
    "wof:placetype":"locality"
},
  "geometry": {"coordinates":[144.69488999999999,-5.01906],"type":"Point"}
}