{
  "type": "Feature",
  "properties": {
    "gn:admin1_code":"11",
    "gn:asciiname":"Albulum",
    "gn:country_code":"PG",
    "gn:dem":366,
    "gn:feature_class":"P",
    "gn:feature_code":"PPL",
    "gn:name":"Albulum",
    "gn:population":0,
    "gn:timezone":"Pacific/Port_Moresby",
    "iso:country":"PG",
    "wof:name":"Albulum",
    "wof:placetype":"locality"
},
  "geometry": {"coordinates":[142.67056000000005,-3.55679],"type":"Point"}
}