{
  "type": "Feature",
  "properties": {
    "gn:admin1_code":"06",
    "gn:asciiname":"Wando",
    "gn:country_code":"PG",
    "gn:dem":2,
    "gn:feature_class":"P",
    "gn:feature_code":"PPL",
    "gn:name":"Wando",
    "gn:population":0,
    "gn:timezone":"Pacific/Port_Moresby",
    "iso:country":"PG",
    "name:und_x_variant":[
        "Kau",
        "Wando"
    ],
    "wof:name":"Wando",
    "wof:placetype":"locality"
},
  "geometry": {"coordinates":[141.26456999999999,-8.90271],"type":"Point"}
}