{
  "type": "Feature",
  "properties": {
    "gn:admin1_code":"05",
    "gn:asciiname":"Hegiso",
    "gn:country_code":"PG",
    "gn:dem":791,
    "gn:feature_class":"P",
    "gn:feature_code":"PPL",
    "gn:name":"Hegiso",
    "gn:population":0,
    "gn:timezone":"Pacific/Port_Moresby",
    "iso:country":"PG",
    "wof:name":"Hegiso",
    "wof:placetype":"locality"
},
  "geometry": {"coordinates":[143.48333,-6.46667],"type":"Point"}
}