{
  "type": "Feature",
  "properties": {
    "gn:admin1_code":"11",
    "gn:asciiname":"Bombita",
    "gn:country_code":"PG",
    "gn:dem":270,
    "gn:feature_class":"P",
    "gn:feature_code":"PPL",
    "gn:name":"Bombita",
    "gn:population":0,
    "gn:timezone":"Pacific/Port_Moresby",
    "iso:country":"PG",
    "wof:name":"Bombita",
    "wof:placetype":"locality"
},
  "geometry": {"coordinates":[142.86896000000004,-3.62973],"type":"Point"}
}