{
  "type": "Feature",
  "properties": {
    "gn:admin1_code":"01",
    "gn:asciiname":"Imidiru",
    "gn:country_code":"PG",
    "gn:dem":908,
    "gn:feature_class":"P",
    "gn:feature_code":"PPL",
    "gn:name":"Imidiru",
    "gn:population":0,
    "gn:timezone":"Pacific/Port_Moresby",
    "iso:country":"PG",
    "wof:name":"Imidiru",
    "wof:placetype":"locality"
},
  "geometry": {"coordinates":[147.90860000000001,-9.49896],"type":"Point"}
}