{
  "type": "Feature",
  "properties": {
    "gn:admin1_code":"03",
    "gn:asciiname":"Gulewa",
    "gn:country_code":"PG",
    "gn:dem":46,
    "gn:feature_class":"P",
    "gn:feature_code":"PPL",
    "gn:name":"Gulewa",
    "gn:population":0,
    "gn:timezone":"Pacific/Port_Moresby",
    "iso:country":"PG",
    "wof:name":"Gulewa",
    "wof:placetype":"locality"
},
  "geometry": {"coordinates":[152.72783000000001,-10.64137],"type":"Point"}
}