{
  "type": "Feature",
  "properties": {
    "gn:admin1_code":"14",
    "gn:asciiname":"Chimbuluk",
    "gn:country_code":"PG",
    "gn:dem":1187,
    "gn:feature_class":"P",
    "gn:feature_code":"PPL",
    "gn:name":"Chimbuluk",
    "gn:population":0,
    "gn:timezone":"Pacific/Port_Moresby",
    "iso:country":"PG",
    "name:und_x_variant":[
        "Chimbulok",
        "Chimbuluk"
    ],
    "wof:name":"Chimbuluk",
    "wof:placetype":"locality"
},
  "geometry": {"coordinates":[146.74440000000001,-6.90422],"type":"Point"}
}