{
  "type": "Feature",
  "properties": {
    "gn:admin1_code":"10",
    "gn:asciiname":"Ralubang",
    "gn:cc2":"PG",
    "gn:country_code":"PG",
    "gn:dem":200,
    "gn:feature_class":"P",
    "gn:feature_code":"PPL",
    "gn:name":"Ralubang",
    "gn:population":0,
    "gn:timezone":"Pacific/Port_Moresby",
    "iso:country":"PG",
    "name:und_x_variant":[
        "Ralabang",
        "Ralubang"
    ],
    "wof:name":"Ralubang",
    "wof:placetype":"locality"
},
  "geometry": {"coordinates":[152.30000000000001,-4.43333],"type":"Point"}
}