{
  "type": "Feature",
  "properties": {
    "gn:admin1_code":"03",
    "gn:asciiname":"Kwahaula",
    "gn:country_code":"PG",
    "gn:dem":399,
    "gn:feature_class":"P",
    "gn:feature_code":"PPL",
    "gn:name":"Kwahaula",
    "gn:population":0,
    "gn:timezone":"Pacific/Port_Moresby",
    "iso:country":"PG",
    "wof:name":"Kwahaula",
    "wof:placetype":"locality"
},
  "geometry": {"coordinates":[151.23333,-10.08333],"type":"Point"}
}