{
  "type": "Feature",
  "properties": {
    "gn:admin1_code":"03",
    "gn:asciiname":"Dombasaina",
    "gn:country_code":"PG",
    "gn:dem":512,
    "gn:feature_class":"P",
    "gn:feature_code":"PPL",
    "gn:name":"Dombasaina",
    "gn:population":0,
    "gn:timezone":"Pacific/Port_Moresby",
    "iso:country":"PG",
    "name:und_x_variant":[
        "Domboisaina",
        "Dombasaina"
    ],
    "wof:name":"Dombasaina",
    "wof:placetype":"locality"
},
  "geometry": {"coordinates":[149.74906999999999,-10.08041],"type":"Point"}
}