{
  "type": "Feature",
  "properties": {
    "gn:admin1_code":"18",
    "gn:asciiname":"Weiki Villages",
    "gn:country_code":"PG",
    "gn:dem":538,
    "gn:feature_class":"P",
    "gn:feature_code":"PPL",
    "gn:name":"Weiki Villages",
    "gn:population":0,
    "gn:timezone":"Pacific/Port_Moresby",
    "iso:country":"PG",
    "name:und_x_variant":[
        "Weiki",
        "Weiki Villages"
    ],
    "wof:name":"Weiki Villages",
    "wof:placetype":"locality"
},
  "geometry": {"coordinates":[142.39949999999999,-3.43711],"type":"Point"}
}