{
  "type": "Feature",
  "properties": {
    "gn:admin1_code":"05",
    "gn:asciiname":"Posulim",
    "gn:country_code":"PG",
    "gn:dem":2107,
    "gn:feature_class":"P",
    "gn:feature_code":"PPL",
    "gn:name":"Posulim",
    "gn:population":0,
    "gn:timezone":"Pacific/Port_Moresby",
    "iso:country":"PG",
    "wof:name":"Posulim",
    "wof:placetype":"locality"
},
  "geometry": {"coordinates":[143.59999999999999,-6.03333],"type":"Point"}
}