{
  "type": "Feature",
  "properties": {
    "gn:admin1_code":"14",
    "gn:asciiname":"Kwampiang",
    "gn:country_code":"PG",
    "gn:dem":1137,
    "gn:feature_class":"P",
    "gn:feature_code":"PPL",
    "gn:name":"Kwampiang",
    "gn:population":0,
    "gn:timezone":"Pacific/Port_Moresby",
    "iso:country":"PG",
    "wof:name":"Kwampiang",
    "wof:placetype":"locality"
},
  "geometry": {"coordinates":[146.34999999999999,-7.43333],"type":"Point"}
}