{
  "type": "Feature",
  "properties": {
    "gn:admin1_code":"18",
    "gn:asciiname":"Atebin",
    "gn:country_code":"PG",
    "gn:dem":953,
    "gn:feature_class":"P",
    "gn:feature_code":"PPL",
    "gn:name":"Atebin",
    "gn:population":0,
    "gn:timezone":"Pacific/Port_Moresby",
    "iso:country":"PG",
    "wof:name":"Atebin",
    "wof:placetype":"locality"
},
  "geometry": {"coordinates":[141.16666999999995,-4.83333],"type":"Point"}
}