{
  "type": "Feature",
  "properties": {
    "gn:admin1_code":"04",
    "gn:asciiname":"Harigo",
    "gn:country_code":"PG",
    "gn:dem":-9999,
    "gn:feature_class":"P",
    "gn:feature_code":"PPL",
    "gn:name":"Harigo",
    "gn:population":0,
    "gn:timezone":"Pacific/Port_Moresby",
    "iso:country":"PG",
    "name:und_x_variant":[
        "Hariko",
        "Harigo"
    ],
    "wof:name":"Harigo",
    "wof:placetype":"locality"
},
  "geometry": {"coordinates":[148.45459,-8.71661],"type":"Point"}
}