{
  "type": "Feature",
  "properties": {
    "gn:admin1_code":"06",
    "gn:asciiname":"Kuda",
    "gn:country_code":"PG",
    "gn:dem":117,
    "gn:feature_class":"P",
    "gn:feature_code":"PPL",
    "gn:name":"Kuda",
    "gn:population":0,
    "gn:timezone":"Pacific/Port_Moresby",
    "iso:country":"PG",
    "wof:name":"Kuda",
    "wof:placetype":"locality"
},
  "geometry": {"coordinates":[141.90291000000005,-6.27686],"type":"Point"}
}