{
  "type": "Feature",
  "properties": {
    "gn:admin1_code":"03",
    "gn:asciiname":"Abuaro",
    "gn:country_code":"PG",
    "gn:dem":16,
    "gn:feature_class":"P",
    "gn:feature_code":"PPL",
    "gn:name":"Abuaro",
    "gn:population":0,
    "gn:timezone":"Pacific/Port_Moresby",
    "iso:country":"PG",
    "name:und_x_variant":[
        "Abuaru",
        "Abuaro"
    ],
    "wof:name":"Abuaro",
    "wof:placetype":"locality"
},
  "geometry": {"coordinates":[149.88403,-9.75687],"type":"Point"}
}