{
  "type": "Feature",
  "properties": {
    "gn:admin1_code":"12",
    "gn:asciiname":"Ainan",
    "gn:country_code":"PG",
    "gn:dem":1305,
    "gn:feature_class":"P",
    "gn:feature_code":"PPL",
    "gn:name":"Ainan",
    "gn:population":0,
    "gn:timezone":"Pacific/Port_Moresby",
    "iso:country":"PG",
    "wof:name":"Ainan",
    "wof:placetype":"locality"
},
  "geometry": {"coordinates":[145.53333000000001,-4.96667],"type":"Point"}
}