{
  "type": "Feature",
  "properties": {
    "gn:admin1_code":"11",
    "gn:asciiname":"Brikiti",
    "gn:country_code":"PG",
    "gn:dem":182,
    "gn:feature_class":"P",
    "gn:feature_code":"PPL",
    "gn:name":"Brikiti",
    "gn:population":0,
    "gn:timezone":"Pacific/Port_Moresby",
    "iso:country":"PG",
    "wof:name":"Brikiti",
    "wof:placetype":"locality"
},
  "geometry": {"coordinates":[143.00667000000001,-3.62226],"type":"Point"}
}