{
  "type": "Feature",
  "properties": {
    "gn:admin1_code":"09",
    "gn:asciiname":"Tombena",
    "gn:country_code":"PG",
    "gn:dem":1579,
    "gn:feature_class":"P",
    "gn:feature_code":"PPL",
    "gn:name":"Tombena",
    "gn:population":0,
    "gn:timezone":"Pacific/Port_Moresby",
    "iso:country":"PG",
    "wof:name":"Tombena",
    "wof:placetype":"locality"
},
  "geometry": {"coordinates":[145.95006999999995,-6.37066],"type":"Point"}
}