{
  "type": "Feature",
  "properties": {
    "gn:gn_country":"PG",
    "gn:gn_fcode":"PPL",
    "gn:gn_pop":1604,
    "gn:population":1604,
    "iso:country":"PG",
    "name:eng_x_preferred":[
        "Angoram"
    ],
    "name:fas_x_preferred":[
        "\u0622\u0646\u06af\u0648\u0631\u0627\u0645"
    ],
    "name:jpn_x_preferred":[
        "\u30a2\u30f3\u30b4\u30e9\u30e0"
    ],
    "name:nld_x_preferred":[
        "Angoram"
    ],
    "name:pol_x_preferred":[
        "Angoram"
    ],
    "name:por_x_preferred":[
        "Angoram"
    ],
    "name:rus_x_preferred":[
        "\u0410\u043d\u0433\u043e\u0440\u0430\u043c"
    ],
    "name:ukr_x_preferred":[
        "\u0410\u043d\u0433\u043e\u0440\u0430"
    ],
    "name:unk_x_variant":[
        "Angorum"
    ],
    "qs_pg:aaroncc":"PG",
    "qs_pg:gn_country":"PG",
    "qs_pg:gn_fcode":"PPL",
    "qs_pg:gn_pop":1604,
    "qs_pg:name":"Angoram",
    "qs_pg:photos_9r":0,
    "qs_pg:photos_sr":0,
    "qs_pg:pop_sr":3,
    "qs_pg:qs_pg_placetype":"locality",
    "wof:name":"Angoram",
    "wof:placetype":"locality",
    "wof:population":1604
},
  "geometry": {"coordinates":[144.06609,-4.06253],"type":"Point"}
}