{
  "type": "Feature",
  "properties": {
    "gn:admin1_code":"14",
    "gn:asciiname":"Tikeling",
    "gn:country_code":"PG",
    "gn:dem":48,
    "gn:feature_class":"P",
    "gn:feature_code":"PPL",
    "gn:name":"Tikeling",
    "gn:population":0,
    "gn:timezone":"Pacific/Port_Moresby",
    "iso:country":"PG",
    "wof:name":"Tikeling",
    "wof:placetype":"locality"
},
  "geometry": {"coordinates":[147.09999999999999,-6.68333],"type":"Point"}
}