{
  "type": "Feature",
  "properties": {
    "gn:admin1_code":"02",
    "gn:asciiname":"Babaguina",
    "gn:country_code":"PG",
    "gn:dem":20,
    "gn:feature_class":"P",
    "gn:feature_code":"PPL",
    "gn:name":"Babaguina",
    "gn:population":0,
    "gn:timezone":"Pacific/Port_Moresby",
    "iso:country":"PG",
    "wof:name":"Babaguina",
    "wof:placetype":"locality"
},
  "geometry": {"coordinates":[144.24545000000001,-7.47553],"type":"Point"}
}