{
  "type": "Feature",
  "properties": {
    "gn:admin1_code":"12",
    "gn:asciiname":"Haimo",
    "gn:country_code":"PG",
    "gn:dem":503,
    "gn:feature_class":"P",
    "gn:feature_code":"PPL",
    "gn:name":"Haimo",
    "gn:population":0,
    "gn:timezone":"Pacific/Port_Moresby",
    "iso:country":"PG",
    "name:fra_x_preferred":[
        "Haimo"
    ],
    "wof:name":"Haimo",
    "wof:placetype":"locality"
},
  "geometry": {"coordinates":[145.69394,-5.0542],"type":"Point"}
}