{
  "type": "Feature",
  "properties": {
    "gn:admin1_code":"01",
    "gn:asciiname":"Ibaradoku",
    "gn:country_code":"PG",
    "gn:dem":1081,
    "gn:feature_class":"P",
    "gn:feature_code":"PPL",
    "gn:name":"Ibaradoku",
    "gn:population":0,
    "gn:timezone":"Pacific/Port_Moresby",
    "iso:country":"PG",
    "wof:name":"Ibaradoku",
    "wof:placetype":"locality"
},
  "geometry": {"coordinates":[147.91284999999999,-9.50197],"type":"Point"}
}