{
  "type": "Feature",
  "properties": {
    "gn:admin1_code":"06",
    "gn:asciiname":"Berewogo",
    "gn:country_code":"PG",
    "gn:dem":492,
    "gn:feature_class":"P",
    "gn:feature_code":"PPL",
    "gn:name":"Berewogo",
    "gn:population":0,
    "gn:timezone":"Pacific/Port_Moresby",
    "iso:country":"PG",
    "wof:name":"Berewogo",
    "wof:placetype":"locality"
},
  "geometry": {"coordinates":[141.18333000000001,-5.38333],"type":"Point"}
}