{
  "type": "Feature",
  "properties": {
    "gn:admin1_code":"06",
    "gn:asciiname":"Ieran",
    "gn:country_code":"PG",
    "gn:dem":26,
    "gn:feature_class":"P",
    "gn:feature_code":"PPL",
    "gn:name":"Ieran",
    "gn:population":0,
    "gn:timezone":"Pacific/Port_Moresby",
    "iso:country":"PG",
    "wof:name":"Ieran",
    "wof:placetype":"locality"
},
  "geometry": {"coordinates":[141.10761000000005,-5.98074],"type":"Point"}
}