{
  "type": "Feature",
  "properties": {
    "gn:admin1_code":"04",
    "gn:asciiname":"Mudi",
    "gn:country_code":"PG",
    "gn:dem":431,
    "gn:feature_class":"P",
    "gn:feature_code":"PPL",
    "gn:name":"Mudi",
    "gn:population":0,
    "gn:timezone":"Pacific/Port_Moresby",
    "iso:country":"PG",
    "wof:name":"Mudi",
    "wof:placetype":"locality"
},
  "geometry": {"coordinates":[148.26667,-9.43333],"type":"Point"}
}