{
  "type": "Feature",
  "properties": {
    "gn:admin1_code":"05",
    "gn:asciiname":"Panduaka Mission",
    "gn:country_code":"PG",
    "gn:dem":2402,
    "gn:feature_class":"P",
    "gn:feature_code":"PPL",
    "gn:name":"Panduaka Mission",
    "gn:population":0,
    "gn:timezone":"Pacific/Port_Moresby",
    "iso:country":"PG",
    "wof:name":"Panduaka Mission",
    "wof:placetype":"locality"
},
  "geometry": {"coordinates":[143.30906000000004,-5.83428],"type":"Point"}
}