{
  "type": "Feature",
  "properties": {
    "gn:admin1_code":"02",
    "gn:asciiname":"Kemei",
    "gn:country_code":"PG",
    "gn:dem":28,
    "gn:feature_class":"P",
    "gn:feature_code":"PPL",
    "gn:name":"Kemei",
    "gn:population":0,
    "gn:timezone":"Pacific/Port_Moresby",
    "iso:country":"PG",
    "wof:name":"Kemei",
    "wof:placetype":"locality"
},
  "geometry": {"coordinates":[144.90141,-7.44268],"type":"Point"}
}