{
  "type": "Feature",
  "properties": {
    "gn:admin1_code":"03",
    "gn:asciiname":"Simagahi",
    "gn:country_code":"PG",
    "gn:dem":13,
    "gn:feature_class":"P",
    "gn:feature_code":"PPL",
    "gn:name":"Simagahi",
    "gn:population":0,
    "gn:timezone":"Pacific/Port_Moresby",
    "iso:country":"PG",
    "wof:name":"Simagahi",
    "wof:placetype":"locality"
},
  "geometry": {"coordinates":[150.66609,-10.51111],"type":"Point"}
}