{
  "type": "Feature",
  "properties": {
    "gn:admin1_code":"17",
    "gn:asciiname":"Atuo",
    "gn:country_code":"PG",
    "gn:dem":60,
    "gn:feature_class":"P",
    "gn:feature_code":"PPL",
    "gn:name":"Atuo",
    "gn:population":0,
    "gn:timezone":"Pacific/Port_Moresby",
    "iso:country":"PG",
    "name:und_x_variant":[
        "Atua",
        "Atuo"
    ],
    "wof:name":"Atuo",
    "wof:placetype":"locality"
},
  "geometry": {"coordinates":[150.03413999999995,-6.28061],"type":"Point"}
}