{
  "type": "Feature",
  "properties": {
    "gn:admin1_code":"06",
    "gn:asciiname":"Kaukwi",
    "gn:country_code":"PG",
    "gn:dem":177,
    "gn:feature_class":"P",
    "gn:feature_code":"PPL",
    "gn:name":"Kaukwi",
    "gn:population":0,
    "gn:timezone":"Pacific/Port_Moresby",
    "iso:country":"PG",
    "wof:name":"Kaukwi",
    "wof:placetype":"locality"
},
  "geometry": {"coordinates":[141.12256000000005,-5.5421],"type":"Point"}
}