{
  "type": "Feature",
  "properties": {
    "gn:admin1_code":"11",
    "gn:asciiname":"Koragul",
    "gn:country_code":"PG",
    "gn:dem":424,
    "gn:feature_class":"P",
    "gn:feature_code":"PPL",
    "gn:name":"Koragul",
    "gn:population":0,
    "gn:timezone":"Pacific/Port_Moresby",
    "iso:country":"PG",
    "wof:name":"Koragul",
    "wof:placetype":"locality"
},
  "geometry": {"coordinates":[143.58333000000005,-3.35],"type":"Point"}
}