{
  "type": "Feature",
  "properties": {
    "gn:admin1_code":"11",
    "gn:asciiname":"Bonahoitum",
    "gn:country_code":"PG",
    "gn:dem":401,
    "gn:feature_class":"P",
    "gn:feature_code":"PPL",
    "gn:name":"Bonahoitum",
    "gn:population":0,
    "gn:timezone":"Pacific/Port_Moresby",
    "iso:country":"PG",
    "name:und_x_variant":[
        "Bonahoitam",
        "Bonahoitum"
    ],
    "wof:name":"Bonahoitum",
    "wof:placetype":"locality"
},
  "geometry": {"coordinates":[143.19767999999999,-3.61925],"type":"Point"}
}