{
  "type": "Feature",
  "properties": {
    "gn:admin1_code":"18",
    "gn:asciiname":"Aurump",
    "gn:country_code":"PG",
    "gn:dem":33,
    "gn:feature_class":"P",
    "gn:feature_code":"PPL",
    "gn:name":"Aurump",
    "gn:population":0,
    "gn:timezone":"Pacific/Port_Moresby",
    "iso:country":"PG",
    "wof:name":"Aurump",
    "wof:placetype":"locality"
},
  "geometry": {"coordinates":[141.21666999999999,-8.61667],"type":"Point"}
}