{
  "type": "Feature",
  "properties": {
    "gn:admin1_code":"04",
    "gn:asciiname":"Kakeipo",
    "gn:country_code":"PG",
    "gn:dem":3097,
    "gn:feature_class":"P",
    "gn:feature_code":"PPL",
    "gn:name":"Kakeipo",
    "gn:population":0,
    "gn:timezone":"Pacific/Port_Moresby",
    "iso:country":"PG",
    "wof:name":"Kakeipo",
    "wof:placetype":"locality"
},
  "geometry": {"coordinates":[147.30192,-8.28459],"type":"Point"}
}