{
  "type": "Feature",
  "properties": {
    "gn:admin1_code":"14",
    "gn:asciiname":"Kukihe",
    "gn:country_code":"PG",
    "gn:dem":1100,
    "gn:feature_class":"P",
    "gn:feature_code":"PPL",
    "gn:name":"Kukihe",
    "gn:population":0,
    "gn:timezone":"Pacific/Port_Moresby",
    "iso:country":"PG",
    "wof:name":"Kukihe",
    "wof:placetype":"locality"
},
  "geometry": {"coordinates":[146.20889,-7.55843],"type":"Point"}
}