{
  "type": "Feature",
  "properties": {
    "gn:admin1_code":"11",
    "gn:asciiname":"Wombak",
    "gn:country_code":"PG",
    "gn:dem":253,
    "gn:feature_class":"P",
    "gn:feature_code":"PPL",
    "gn:name":"Wombak",
    "gn:population":0,
    "gn:timezone":"Pacific/Port_Moresby",
    "iso:country":"PG",
    "name:und_x_variant":[
        "Wambak",
        "Wombak"
    ],
    "wof:name":"Wombak",
    "wof:placetype":"locality"
},
  "geometry": {"coordinates":[143.03208999999995,-3.59741],"type":"Point"}
}