{
  "type": "Feature",
  "properties": {
    "gn:admin1_code":"06",
    "gn:asciiname":"Emeti",
    "gn:country_code":"PG",
    "gn:dem":12,
    "gn:feature_class":"P",
    "gn:feature_code":"PPL",
    "gn:name":"Emeti",
    "gn:population":0,
    "gn:timezone":"Pacific/Port_Moresby",
    "iso:country":"PG",
    "name:und_x_variant":[
        "Buruburu Mission",
        "Emeti"
    ],
    "wof:name":"Emeti",
    "wof:placetype":"locality"
},
  "geometry": {"coordinates":[143.25028,-7.8622],"type":"Point"}
}