{
  "type": "Feature",
  "properties": {
    "gn:admin1_code":"04",
    "gn:asciiname":"Bauwame",
    "gn:country_code":"PG",
    "gn:dem":58,
    "gn:feature_class":"P",
    "gn:feature_code":"PPL",
    "gn:name":"Bauwame",
    "gn:population":0,
    "gn:timezone":"Pacific/Port_Moresby",
    "iso:country":"PG",
    "wof:name":"Bauwame",
    "wof:placetype":"locality"
},
  "geometry": {"coordinates":[149.28946000000005,-9.1212],"type":"Point"}
}