{
  "type": "Feature",
  "properties": {
    "gn:admin1_code":"11",
    "gn:asciiname":"Saina",
    "gn:country_code":"PG",
    "gn:dem":285,
    "gn:feature_class":"P",
    "gn:feature_code":"PPL",
    "gn:name":"Saina",
    "gn:population":0,
    "gn:timezone":"Pacific/Port_Moresby",
    "iso:country":"PG",
    "wof:name":"Saina",
    "wof:placetype":"locality"
},
  "geometry": {"coordinates":[143.32939999999999,-3.65312],"type":"Point"}
}