{
  "type": "Feature",
  "properties": {
    "gn:admin1_code":"05",
    "gn:asciiname":"Moguta",
    "gn:cc2":"PG",
    "gn:country_code":"PG",
    "gn:dem":1856,
    "gn:feature_class":"P",
    "gn:feature_code":"PPL",
    "gn:name":"Moguta",
    "gn:population":0,
    "gn:timezone":"Pacific/Port_Moresby",
    "iso:country":"PG",
    "name:und_x_variant":[
        "Mogunda",
        "Moguta"
    ],
    "wof:name":"Moguta",
    "wof:placetype":"locality"
},
  "geometry": {"coordinates":[143.66666999999995,-6.31667],"type":"Point"}
}