{
  "type": "Feature",
  "properties": {
    "gn:admin1_code":"18",
    "gn:asciiname":"Wugubli",
    "gn:country_code":"PG",
    "gn:dem":328,
    "gn:feature_class":"P",
    "gn:feature_code":"PPL",
    "gn:name":"Wugubli",
    "gn:population":0,
    "gn:timezone":"Pacific/Port_Moresby",
    "iso:country":"PG",
    "wof:name":"Wugubli",
    "wof:placetype":"locality"
},
  "geometry": {"coordinates":[141.98443,-3.35869],"type":"Point"}
}