{
  "type": "Feature",
  "properties": {
    "gn:admin1_code":"04",
    "gn:asciiname":"Sia",
    "gn:country_code":"PG",
    "gn:dem":20,
    "gn:feature_class":"P",
    "gn:feature_code":"PPL",
    "gn:name":"Sia",
    "gn:population":0,
    "gn:timezone":"Pacific/Port_Moresby",
    "iso:country":"PG",
    "name:ceb_x_preferred":[
        "Sia"
    ],
    "name:ces_x_preferred":[
        "Sia"
    ],
    "name:dan_x_preferred":[
        "Sia"
    ],
    "name:deu_x_preferred":[
        "Sia"
    ],
    "name:est_x_preferred":[
        "Sia"
    ],
    "name:hye_x_preferred":[
        "\u054d\u056b\u0561"
    ],
    "name:isl_x_preferred":[
        "S\u00eda"
    ],
    "name:lat_x_preferred":[
        "Sia"
    ],
    "name:nld_x_preferred":[
        "Sia"
    ],
    "name:por_x_preferred":[
        "Sia"
    ],
    "name:sco_x_preferred":[
        "Sia"
    ],
    "name:slk_x_preferred":[
        "Sia"
    ],
    "name:spa_x_preferred":[
        "Sia"
    ],
    "name:swe_x_preferred":[
        "Sia"
    ],
    "wof:name":"Sia",
    "wof:placetype":"locality"
},
  "geometry": {"coordinates":[148.02943999999999,-8.15426],"type":"Point"}
}