{
  "type": "Feature",
  "properties": {
    "gn:admin1_code":"05",
    "gn:asciiname":"Mapkebol",
    "gn:country_code":"PG",
    "gn:dem":2179,
    "gn:feature_class":"P",
    "gn:feature_code":"PPL",
    "gn:name":"Mapkebol",
    "gn:population":0,
    "gn:timezone":"Pacific/Port_Moresby",
    "iso:country":"PG",
    "wof:name":"Mapkebol",
    "wof:placetype":"locality"
},
  "geometry": {"coordinates":[143.51816000000005,-6.0942],"type":"Point"}
}