{
  "type": "Feature",
  "properties": {
    "gn:admin1_code":"11",
    "gn:asciiname":"Yueriman",
    "gn:country_code":"PG",
    "gn:dem":9,
    "gn:feature_class":"P",
    "gn:feature_code":"PPL",
    "gn:name":"Yueriman",
    "gn:population":0,
    "gn:timezone":"Pacific/Port_Moresby",
    "iso:country":"PG",
    "name:und_x_variant":[
        "Yuerima",
        "Yueriman"
    ],
    "wof:name":"Yueriman",
    "wof:placetype":"locality"
},
  "geometry": {"coordinates":[143.88667000000001,-4.1524],"type":"Point"}
}