{
  "type": "Feature",
  "properties": {
    "gn:admin1_code":"18",
    "gn:asciiname":"Sonbui",
    "gn:cc2":"PG",
    "gn:country_code":"PG",
    "gn:dem":179,
    "gn:feature_class":"P",
    "gn:feature_code":"PPL",
    "gn:name":"Sonbui",
    "gn:population":0,
    "gn:timezone":"Pacific/Port_Moresby",
    "iso:country":"PG",
    "name:und_x_variant":[
        "New Sonbui",
        "Sonbui"
    ],
    "wof:name":"Sonbui",
    "wof:placetype":"locality"
},
  "geometry": {"coordinates":[141.15000000000001,-3.03333],"type":"Point"}
}