{
  "type": "Feature",
  "properties": {
    "gn:admin1_code":"04",
    "gn:asciiname":"Hungiri",
    "gn:country_code":"PG",
    "gn:dem":94,
    "gn:feature_class":"P",
    "gn:feature_code":"PPL",
    "gn:name":"Hungiri",
    "gn:population":0,
    "gn:timezone":"Pacific/Port_Moresby",
    "iso:country":"PG",
    "wof:name":"Hungiri",
    "wof:placetype":"locality"
},
  "geometry": {"coordinates":[147.97513000000001,-8.83012],"type":"Point"}
}