{
  "type": "Feature",
  "properties": {
    "gn:admin1_code":"04",
    "gn:asciiname":"Sila",
    "gn:country_code":"PG",
    "gn:dem":700,
    "gn:feature_class":"P",
    "gn:feature_code":"PPL",
    "gn:name":"Sila",
    "gn:population":0,
    "gn:timezone":"Pacific/Port_Moresby",
    "iso:country":"PG",
    "wof:name":"Sila",
    "wof:placetype":"locality"
},
  "geometry": {"coordinates":[148.37528,-9.06811],"type":"Point"}
}