{
  "type": "Feature",
  "properties": {
    "gn:admin1_code":"05",
    "gn:asciiname":"Iande",
    "gn:country_code":"PG",
    "gn:dem":1562,
    "gn:feature_class":"P",
    "gn:feature_code":"PPL",
    "gn:name":"Iande",
    "gn:population":0,
    "gn:timezone":"Pacific/Port_Moresby",
    "iso:country":"PG",
    "wof:name":"Iande",
    "wof:placetype":"locality"
},
  "geometry": {"coordinates":[142.88333,-6.06667],"type":"Point"}
}