{
  "type": "Feature",
  "properties": {
    "gn:admin1_code":"06",
    "gn:asciiname":"Debromosom",
    "gn:country_code":"PG",
    "gn:dem":123,
    "gn:feature_class":"P",
    "gn:feature_code":"PPL",
    "gn:name":"Debromosom",
    "gn:population":0,
    "gn:timezone":"Pacific/Port_Moresby",
    "iso:country":"PG",
    "wof:name":"Debromosom",
    "wof:placetype":"locality"
},
  "geometry": {"coordinates":[142.31145000000001,-6.27828],"type":"Point"}
}