{
  "type": "Feature",
  "properties": {
    "gn:admin1_code":"08",
    "gn:asciiname":"Pendaku",
    "gn:country_code":"PG",
    "gn:dem":1529,
    "gn:feature_class":"P",
    "gn:feature_code":"PPL",
    "gn:name":"Pendaku",
    "gn:population":0,
    "gn:timezone":"Pacific/Port_Moresby",
    "iso:country":"PG",
    "wof:name":"Pendaku",
    "wof:placetype":"locality"
},
  "geometry": {"coordinates":[144.83333000000005,-5.98333],"type":"Point"}
}