{
  "type": "Feature",
  "properties": {
    "gn:admin1_code":"04",
    "gn:asciiname":"Muni",
    "gn:country_code":"PG",
    "gn:dem":946,
    "gn:feature_class":"P",
    "gn:feature_code":"PPL",
    "gn:name":"Muni",
    "gn:population":0,
    "gn:timezone":"Pacific/Port_Moresby",
    "iso:country":"PG",
    "name:ceb_x_preferred":[
        "Muni"
    ],
    "name:ces_x_preferred":[
        "Muni"
    ],
    "name:deu_x_preferred":[
        "Muni"
    ],
    "name:fra_x_preferred":[
        "Muni"
    ],
    "name:nld_x_preferred":[
        "Muni"
    ],
    "name:por_x_preferred":[
        "Muni"
    ],
    "name:spa_x_preferred":[
        "Muni"
    ],
    "name:swe_x_preferred":[
        "Muni"
    ],
    "name:tam_x_preferred":[
        "\u0bae\u0bc1\u0ba9\u0bbf"
    ],
    "wof:name":"Muni",
    "wof:placetype":"locality"
},
  "geometry": {"coordinates":[148.05000000000001,-9.15],"type":"Point"}
}