{
  "type": "Feature",
  "properties": {
    "gn:admin1_code":"18",
    "gn:asciiname":"Marok",
    "gn:country_code":"PG",
    "gn:dem":26,
    "gn:feature_class":"P",
    "gn:feature_code":"PPL",
    "gn:name":"Marok",
    "gn:population":0,
    "gn:timezone":"Pacific/Port_Moresby",
    "iso:country":"PG",
    "wof:name":"Marok",
    "wof:placetype":"locality"
},
  "geometry": {"coordinates":[142.26078999999999,-3.1879],"type":"Point"}
}