{
  "type": "Feature",
  "properties": {
    "gn:admin1_code":"11",
    "gn:asciiname":"Wawat 1",
    "gn:country_code":"PG",
    "gn:dem":339,
    "gn:feature_class":"P",
    "gn:feature_code":"PPL",
    "gn:name":"Wawat 1",
    "gn:population":0,
    "gn:timezone":"Pacific/Port_Moresby",
    "iso:country":"PG",
    "name:und_x_variant":[
        "Wawat Number 1",
        "Wawat 1"
    ],
    "wof:name":"Wawat 1",
    "wof:placetype":"locality"
},
  "geometry": {"coordinates":[143.73868999999999,-3.70705],"type":"Point"}
}