{
  "type": "Feature",
  "properties": {
    "gn:admin1_code":"04",
    "gn:asciiname":"Umboworo",
    "gn:country_code":"PG",
    "gn:dem":782,
    "gn:feature_class":"P",
    "gn:feature_code":"PPL",
    "gn:name":"Umboworo",
    "gn:population":0,
    "gn:timezone":"Pacific/Port_Moresby",
    "iso:country":"PG",
    "wof:name":"Umboworo",
    "wof:placetype":"locality"
},
  "geometry": {"coordinates":[148.27418,-9.117],"type":"Point"}
}