{
  "type": "Feature",
  "properties": {
    "gn:admin1_code":"01",
    "gn:asciiname":"Gurumunumu",
    "gn:country_code":"PG",
    "gn:dem":549,
    "gn:feature_class":"P",
    "gn:feature_code":"PPL",
    "gn:name":"Gurumunumu",
    "gn:population":0,
    "gn:timezone":"Pacific/Port_Moresby",
    "iso:country":"PG",
    "wof:name":"Gurumunumu",
    "wof:placetype":"locality"
},
  "geometry": {"coordinates":[147.44155000000001,-9.46456],"type":"Point"}
}