{
  "type": "Feature",
  "properties": {
    "gn:admin1_code":"19",
    "gn:asciiname":"Saposa",
    "gn:country_code":"PG",
    "gn:dem":2138,
    "gn:feature_class":"P",
    "gn:feature_code":"PPL",
    "gn:name":"Saposa",
    "gn:population":0,
    "gn:timezone":"Pacific/Port_Moresby",
    "iso:country":"PG",
    "wof:name":"Saposa",
    "wof:placetype":"locality"
},
  "geometry": {"coordinates":[143.79903999999999,-5.63478],"type":"Point"}
}