{
  "type": "Feature",
  "properties": {
    "gn:admin1_code":"10",
    "gn:asciiname":"Morena",
    "gn:country_code":"PG",
    "gn:dem":400,
    "gn:feature_class":"P",
    "gn:feature_code":"PPL",
    "gn:name":"Morena",
    "gn:population":0,
    "gn:timezone":"Pacific/Port_Moresby",
    "iso:country":"PG",
    "name:ben_x_preferred":[
        "\u09ae\u09cb\u09b0\u09c7\u09a8\u09be"
    ],
    "name:bih_x_preferred":[
        "\u092e\u0941\u0930\u0948\u0928\u093e"
    ],
    "name:bpy_x_preferred":[
        "\u09ae\u09cb\u09b0\u09c7\u09a8\u09be"
    ],
    "name:ceb_x_preferred":[
        "Morena"
    ],
    "name:fra_x_preferred":[
        "Morena"
    ],
    "name:guj_x_preferred":[
        "\u0aae\u0ac1\u0ab0\u0ac8\u0aa8\u0abe"
    ],
    "name:hin_x_preferred":[
        "\u092e\u0941\u0930\u0948\u0928\u093e"
    ],
    "name:ita_x_preferred":[
        "Morena"
    ],
    "name:mar_x_preferred":[
        "\u092e\u094b\u0930\u0947\u0928\u093e"
    ],
    "name:msa_x_preferred":[
        "Morena"
    ],
    "name:nep_x_preferred":[
        "\u092e\u0941\u0930\u0948\u0928\u093e"
    ],
    "name:new_x_preferred":[
        "\u092e\u094b\u0930\u0947\u0928\u093e"
    ],
    "name:nor_x_preferred":[
        "Morena"
    ],
    "name:ori_x_preferred":[
        "\u0b2e\u0b4b\u0b30\u0b47\u0b28\u0b3e"
    ],
    "name:por_x_preferred":[
        "Morena"
    ],
    "name:rus_x_preferred":[
        "\u041c\u043e\u0440\u0435\u043d\u0430"
    ],
    "name:san_x_preferred":[
        "\u092e\u0941\u0930\u0948\u0928\u093e"
    ],
    "name:spa_x_preferred":[
        "Morena"
    ],
    "name:srp_x_preferred":[
        "\u041c\u043e\u0440\u0435\u043d\u0430"
    ],
    "name:swe_x_preferred":[
        "Morena"
    ],
    "name:urd_x_preferred":[
        "\u0645\u0648\u0631\u06cc\u0646\u0627"
    ],
    "name:vie_x_preferred":[
        "Morena"
    ],
    "name:war_x_preferred":[
        "Morena"
    ],
    "name:zho_x_preferred":[
        "\u83ab\u96f7\u7eb3"
    ],
    "wof:name":"Morena",
    "wof:placetype":"locality"
},
  "geometry": {"coordinates":[151.43333000000001,-5.16667],"type":"Point"}
}