{
  "type": "Feature",
  "properties": {
    "gn:admin1_code":"09",
    "gn:asciiname":"Kambienggwi",
    "gn:country_code":"PG",
    "gn:dem":2696,
    "gn:feature_class":"P",
    "gn:feature_code":"PPL",
    "gn:name":"Kambienggwi",
    "gn:population":0,
    "gn:timezone":"Pacific/Port_Moresby",
    "iso:country":"PG",
    "wof:name":"Kambienggwi",
    "wof:placetype":"locality"
},
  "geometry": {"coordinates":[145.18333000000001,-5.96667],"type":"Point"}
}