{
  "type": "Feature",
  "properties": {
    "gn:admin1_code":"06",
    "gn:asciiname":"Tai",
    "gn:country_code":"PG",
    "gn:dem":17,
    "gn:feature_class":"P",
    "gn:feature_code":"PPL",
    "gn:name":"Tai",
    "gn:population":0,
    "gn:timezone":"Pacific/Port_Moresby",
    "iso:country":"PG",
    "name:cat_x_preferred":[
        "Tai"
    ],
    "name:ceb_x_preferred":[
        "Tai"
    ],
    "name:fin_x_preferred":[
        "Tai"
    ],
    "name:fur_x_preferred":[
        "Tai"
    ],
    "name:kor_x_preferred":[
        "\ud0c0\uc774"
    ],
    "name:oci_x_preferred":[
        "Tai"
    ],
    "name:rus_x_preferred":[
        "\u0422\u0430\u0439"
    ],
    "name:spa_x_preferred":[
        "Tai"
    ],
    "name:swe_x_preferred":[
        "Tai"
    ],
    "name:tur_x_preferred":[
        "Tai"
    ],
    "name:ukr_x_preferred":[
        "\u0422\u0430\u0439"
    ],
    "wof:name":"Tai",
    "wof:placetype":"locality"
},
  "geometry": {"coordinates":[142.90545,-8.00706],"type":"Point"}
}