{
  "type": "Feature",
  "properties": {
    "gn:admin1_code":"17",
    "gn:asciiname":"Penatabotong",
    "gn:country_code":"PG",
    "gn:dem":94,
    "gn:feature_class":"P",
    "gn:feature_code":"PPL",
    "gn:name":"Penatabotong",
    "gn:population":0,
    "gn:timezone":"Pacific/Port_Moresby",
    "iso:country":"PG",
    "name:und_x_variant":[
        "Penatabutong",
        "Penatabotong"
    ],
    "wof:name":"Penatabotong",
    "wof:placetype":"locality"
},
  "geometry": {"coordinates":[149.14176,-4.91239],"type":"Point"}
}