{
  "type": "Feature",
  "properties": {
    "gn:admin1_code":"01",
    "gn:asciiname":"Manumu",
    "gn:country_code":"PG",
    "gn:dem":571,
    "gn:feature_class":"P",
    "gn:feature_code":"PPL",
    "gn:name":"Manumu",
    "gn:population":0,
    "gn:timezone":"Pacific/Port_Moresby",
    "iso:country":"PG",
    "wof:name":"Manumu",
    "wof:placetype":"locality"
},
  "geometry": {"coordinates":[147.57064,-9.07104],"type":"Point"}
}