{
  "type": "Feature",
  "properties": {
    "gn:admin1_code":"04",
    "gn:asciiname":"Dareki 2",
    "gn:country_code":"PG",
    "gn:dem":628,
    "gn:feature_class":"P",
    "gn:feature_code":"PPL",
    "gn:name":"Dareki 2",
    "gn:population":0,
    "gn:timezone":"Pacific/Port_Moresby",
    "iso:country":"PG",
    "wof:name":"Dareki 2",
    "wof:placetype":"locality"
},
  "geometry": {"coordinates":[148.43369999999999,-9.0863],"type":"Point"}
}