{
  "type": "Feature",
  "properties": {
    "gn:admin1_code":"12",
    "gn:asciiname":"Bunabun",
    "gn:country_code":"PG",
    "gn:dem":24,
    "gn:feature_class":"P",
    "gn:feature_code":"PPL",
    "gn:name":"Bunabun",
    "gn:population":0,
    "gn:timezone":"Pacific/Port_Moresby",
    "iso:country":"PG",
    "name:und_x_variant":[
        "Bunabufi",
        "Bunabun 1",
        "Bunabun"
    ],
    "wof:name":"Bunabun",
    "wof:placetype":"locality"
},
  "geometry": {"coordinates":[145.51893999999999,-4.58458],"type":"Point"}
}