{
  "type": "Feature",
  "properties": {
    "gn:admin1_code":"06",
    "gn:asciiname":"Mabaduan",
    "gn:country_code":"PG",
    "gn:dem":13,
    "gn:feature_class":"P",
    "gn:feature_code":"PPL",
    "gn:name":"Mabaduan",
    "gn:population":0,
    "gn:timezone":"Pacific/Port_Moresby",
    "iso:country":"PG",
    "wof:name":"Mabaduan",
    "wof:placetype":"locality"
},
  "geometry": {"coordinates":[142.72098,-9.27243],"type":"Point"}
}