{
  "type": "Feature",
  "properties": {
    "gn:admin1_code":"02",
    "gn:asciiname":"Veiru",
    "gn:country_code":"PG",
    "gn:dem":34,
    "gn:feature_class":"P",
    "gn:feature_code":"PPL",
    "gn:name":"Veiru",
    "gn:population":0,
    "gn:timezone":"Pacific/Port_Moresby",
    "iso:country":"PG",
    "name:und_x_variant":[
        "Babagwina",
        "Babauguina",
        "Veiru"
    ],
    "wof:name":"Veiru",
    "wof:placetype":"locality"
},
  "geometry": {"coordinates":[144.24732,-7.47915],"type":"Point"}
}