{
  "type": "Feature",
  "properties": {
    "gn:admin1_code":"14",
    "gn:asciiname":"Derongge",
    "gn:country_code":"PG",
    "gn:dem":116,
    "gn:feature_class":"P",
    "gn:feature_code":"PPL",
    "gn:name":"Derongge",
    "gn:population":0,
    "gn:timezone":"Pacific/Port_Moresby",
    "iso:country":"PG",
    "name:und_x_variant":[
        "Darongge",
        "Derongge"
    ],
    "wof:name":"Derongge",
    "wof:placetype":"locality"
},
  "geometry": {"coordinates":[146.83404999999999,-5.88225],"type":"Point"}
}