{
  "type": "Feature",
  "properties": {
    "gn:admin1_code":"12",
    "gn:asciiname":"Sirikin",
    "gn:country_code":"PG",
    "gn:dem":279,
    "gn:feature_class":"P",
    "gn:feature_code":"PPL",
    "gn:name":"Sirikin",
    "gn:population":0,
    "gn:timezone":"Pacific/Port_Moresby",
    "iso:country":"PG",
    "name:und_x_variant":[
        "Siriken",
        "Sirikin"
    ],
    "wof:name":"Sirikin",
    "wof:placetype":"locality"
},
  "geometry": {"coordinates":[144.91081,-4.48736],"type":"Point"}
}