{
  "type": "Feature",
  "properties": {
    "gn:admin1_code":"18",
    "gn:asciiname":"Rafin No 1",
    "gn:country_code":"PG",
    "gn:dem":208,
    "gn:feature_class":"P",
    "gn:feature_code":"PPL",
    "gn:name":"Rafin No 1",
    "gn:population":0,
    "gn:timezone":"Pacific/Port_Moresby",
    "iso:country":"PG",
    "wof:name":"Rafin No 1",
    "wof:placetype":"locality"
},
  "geometry": {"coordinates":[141.10741000000004,-4.56854],"type":"Point"}
}