{
  "type": "Feature",
  "properties": {
    "gn:admin1_code":"11",
    "gn:asciiname":"Yambumumba",
    "gn:country_code":"PG",
    "gn:dem":27,
    "gn:feature_class":"P",
    "gn:feature_code":"PPL",
    "gn:name":"Yambumumba",
    "gn:population":0,
    "gn:timezone":"Pacific/Port_Moresby",
    "iso:country":"PG",
    "name:und_x_variant":[
        "Yambunumbu",
        "Yambumumba"
    ],
    "wof:name":"Yambumumba",
    "wof:placetype":"locality"
},
  "geometry": {"coordinates":[142.40964,-4.27194],"type":"Point"}
}