{
  "type": "Feature",
  "properties": {
    "gn:admin1_code":"11",
    "gn:asciiname":"Suanam",
    "gn:country_code":"PG",
    "gn:dem":25,
    "gn:feature_class":"P",
    "gn:feature_code":"PPL",
    "gn:name":"Suanam",
    "gn:population":0,
    "gn:timezone":"Pacific/Port_Moresby",
    "iso:country":"PG",
    "name:und_x_variant":[
        "Suanum",
        "Suanan",
        "Suanam"
    ],
    "wof:name":"Suanam",
    "wof:placetype":"locality"
},
  "geometry": {"coordinates":[143.84305000000001,-3.68788],"type":"Point"}
}