{
  "type": "Feature",
  "properties": {
    "gn:admin1_code":"19",
    "gn:asciiname":"Tambul",
    "gn:country_code":"PG",
    "gn:dem":2286,
    "gn:feature_class":"P",
    "gn:feature_code":"PPL",
    "gn:name":"Tambul",
    "gn:population":0,
    "gn:timezone":"Pacific/Port_Moresby",
    "iso:country":"PG",
    "wof:name":"Tambul",
    "wof:placetype":"locality"
},
  "geometry": {"coordinates":[143.94183000000001,-5.89756],"type":"Point"}
}