{
  "type": "Feature",
  "properties": {
    "gn:admin1_code":"18",
    "gn:asciiname":"Ekas",
    "gn:country_code":"PG",
    "gn:dem":250,
    "gn:feature_class":"P",
    "gn:feature_code":"PPL",
    "gn:name":"Ekas",
    "gn:population":0,
    "gn:timezone":"Pacific/Port_Moresby",
    "iso:country":"PG",
    "wof:name":"Ekas",
    "wof:placetype":"locality"
},
  "geometry": {"coordinates":[141.61369999999999,-3.37411],"type":"Point"}
}