{
  "type": "Feature",
  "properties": {
    "gn:admin1_code":"14",
    "gn:asciiname":"Yanuf",
    "gn:country_code":"PG",
    "gn:dem":141,
    "gn:feature_class":"P",
    "gn:feature_code":"PPL",
    "gn:name":"Yanuf",
    "gn:population":0,
    "gn:timezone":"Pacific/Port_Moresby",
    "iso:country":"PG",
    "name:und_x_variant":[
        "Yanof",
        "Yanuf"
    ],
    "wof:name":"Yanuf",
    "wof:placetype":"locality"
},
  "geometry": {"coordinates":[146.28558000000001,-6.53325],"type":"Point"}
}