{
  "type": "Feature",
  "properties": {
    "gn:admin1_code":"04",
    "gn:asciiname":"Dea",
    "gn:country_code":"PG",
    "gn:dem":853,
    "gn:feature_class":"P",
    "gn:feature_code":"PPL",
    "gn:name":"Dea",
    "gn:population":0,
    "gn:timezone":"Pacific/Port_Moresby",
    "iso:country":"PG",
    "name:ceb_x_preferred":[
        "Dea"
    ],
    "name:deu_x_preferred":[
        "Dea"
    ],
    "name:swe_x_preferred":[
        "Dea"
    ],
    "wof:name":"Dea",
    "wof:placetype":"locality"
},
  "geometry": {"coordinates":[148.32974999999999,-9.06476],"type":"Point"}
}