{
  "type": "Feature",
  "properties": {
    "gn:admin1_code":"15",
    "gn:asciiname":"Palawee",
    "gn:country_code":"PG",
    "gn:dem":25,
    "gn:feature_class":"P",
    "gn:feature_code":"PPL",
    "gn:name":"Palawee",
    "gn:population":0,
    "gn:timezone":"Pacific/Port_Moresby",
    "iso:country":"PG",
    "wof:name":"Palawee",
    "wof:placetype":"locality"
},
  "geometry": {"coordinates":[150.54166999999995,-2.675],"type":"Point"}
}