{
  "type": "Feature",
  "properties": {
    "gn:admin1_code":"11",
    "gn:asciiname":"Nogosop",
    "gn:country_code":"PG",
    "gn:dem":21,
    "gn:feature_class":"P",
    "gn:feature_code":"PPL",
    "gn:name":"Nogosop",
    "gn:population":0,
    "gn:timezone":"Pacific/Port_Moresby",
    "iso:country":"PG",
    "name:und_x_variant":[
        "Nagosap"
    ],
    "wof:name":"Nogosop",
    "wof:placetype":"locality"
},
  "geometry": {"coordinates":[143.29586,-4.10315],"type":"Point"}
}