{
  "type": "Feature",
  "properties": {
    "gn:admin1_code":"18",
    "gn:asciiname":"Imbio 1",
    "gn:country_code":"PG",
    "gn:dem":47,
    "gn:feature_class":"P",
    "gn:feature_code":"PPL",
    "gn:name":"Imbio 1",
    "gn:population":0,
    "gn:timezone":"Pacific/Port_Moresby",
    "iso:country":"PG",
    "name:und_x_variant":[
        "Imbio",
        "Imbio 1"
    ],
    "wof:name":"Imbio 1",
    "wof:placetype":"locality"
},
  "geometry": {"coordinates":[141.42923000000005,-2.90546],"type":"Point"}
}