{
  "type": "Feature",
  "properties": {
    "gn:admin1_code":"18",
    "gn:asciiname":"Lemieng",
    "gn:country_code":"PG",
    "gn:dem":10,
    "gn:feature_class":"P",
    "gn:feature_code":"PPL",
    "gn:name":"Lemieng",
    "gn:population":0,
    "gn:timezone":"Pacific/Port_Moresby",
    "iso:country":"PG",
    "name:und_x_variant":[
        "Lemieng Villages",
        "Lemieng",
        "Lemieng Mission"
    ],
    "wof:name":"Lemieng",
    "wof:placetype":"locality"
},
  "geometry": {"coordinates":[142.46057999999999,-3.19361],"type":"Point"}
}