{
  "type": "Feature",
  "properties": {
    "gn:admin1_code":"02",
    "gn:asciiname":"Uriri",
    "gn:country_code":"PG",
    "gn:dem":61,
    "gn:feature_class":"P",
    "gn:feature_code":"PPL",
    "gn:name":"Uriri",
    "gn:population":0,
    "gn:timezone":"Pacific/Port_Moresby",
    "iso:country":"PG",
    "name:und_x_variant":[
        "Ururi",
        "Uriri"
    ],
    "wof:name":"Uriri",
    "wof:placetype":"locality"
},
  "geometry": {"coordinates":[145.80208999999999,-7.98562],"type":"Point"}
}