{
  "type": "Feature",
  "properties": {
    "gn:admin1_code":"02",
    "gn:asciiname":"Grimm Point",
    "gn:cc2":"PG",
    "gn:country_code":"PG",
    "gn:dem":48,
    "gn:feature_class":"P",
    "gn:feature_code":"PPL",
    "gn:name":"Grimm Point",
    "gn:population":0,
    "gn:timezone":"Pacific/Port_Moresby",
    "iso:country":"PG",
    "name:und_x_variant":[
        "Grimm",
        "Grimm Point"
    ],
    "wof:name":"Grimm Point",
    "wof:placetype":"locality"
},
  "geometry": {"coordinates":[146.36667,-7.85],"type":"Point"}
}