{
  "type": "Feature",
  "properties": {
    "gn:admin1_code":"15",
    "gn:asciiname":"Ambaba",
    "gn:country_code":"PG",
    "gn:dem":71,
    "gn:feature_class":"P",
    "gn:feature_code":"PPL",
    "gn:name":"Ambaba",
    "gn:population":0,
    "gn:timezone":"Pacific/Port_Moresby",
    "iso:country":"PG",
    "wof:name":"Ambaba",
    "wof:placetype":"locality"
},
  "geometry": {"coordinates":[153.31336999999999,-3.38079],"type":"Point"}
}