{
  "type": "Feature",
  "properties": {
    "gn:admin1_code":"12",
    "gn:asciiname":"Guirak",
    "gn:country_code":"PG",
    "gn:dem":136,
    "gn:feature_class":"P",
    "gn:feature_code":"PPL",
    "gn:name":"Guirak",
    "gn:population":0,
    "gn:timezone":"Pacific/Port_Moresby",
    "iso:country":"PG",
    "name:und_x_variant":[
        "Guiarak",
        "Guirak"
    ],
    "wof:name":"Guirak",
    "wof:placetype":"locality"
},
  "geometry": {"coordinates":[146.51461,-5.69679],"type":"Point"}
}