{
  "type": "Feature",
  "properties": {
    "gn:admin1_code":"03",
    "gn:asciiname":"Waitaru",
    "gn:country_code":"PG",
    "gn:dem":460,
    "gn:feature_class":"P",
    "gn:feature_code":"PPL",
    "gn:name":"Waitaru",
    "gn:population":0,
    "gn:timezone":"Pacific/Port_Moresby",
    "iso:country":"PG",
    "wof:name":"Waitaru",
    "wof:placetype":"locality"
},
  "geometry": {"coordinates":[149.51667,-9.86667],"type":"Point"}
}