{
  "type": "Feature",
  "properties": {
    "gn:admin1_code":"18",
    "gn:asciiname":"Waina Hamlets",
    "gn:country_code":"PG",
    "gn:dem":346,
    "gn:feature_class":"P",
    "gn:feature_code":"PPL",
    "gn:name":"Waina Hamlets",
    "gn:population":0,
    "gn:timezone":"Pacific/Port_Moresby",
    "iso:country":"PG",
    "name:und_x_variant":[
        "Waina 2",
        "Waina 1",
        "Waina",
        "Waina Hamlets"
    ],
    "wof:name":"Waina Hamlets",
    "wof:placetype":"locality"
},
  "geometry": {"coordinates":[141.04683,-3.41125],"type":"Point"}
}