{
  "type": "Feature",
  "properties": {
    "gn:admin1_code":"14",
    "gn:asciiname":"Satwag",
    "gn:country_code":"PG",
    "gn:dem":1304,
    "gn:feature_class":"P",
    "gn:feature_code":"PPL",
    "gn:name":"Satwag",
    "gn:population":0,
    "gn:timezone":"Pacific/Port_Moresby",
    "iso:country":"PG",
    "wof:name":"Satwag",
    "wof:placetype":"locality"
},
  "geometry": {"coordinates":[147.28333000000001,-6.15],"type":"Point"}
}