{
  "type": "Feature",
  "properties": {
    "gn:admin1_code":"20",
    "gn:asciiname":"Port Moresby",
    "gn:country_code":"PG",
    "gn:dem":6,
    "gn:feature_class":"P",
    "gn:feature_code":"PPL",
    "gn:name":"Port Moresby",
    "gn:population":0,
    "gn:timezone":"Pacific/Port_Moresby",
    "iso:country":"PG",
    "wof:name":"Port Moresby",
    "wof:placetype":"locality"
},
  "geometry": {"coordinates":[147.14848000000001,-9.47789],"type":"Point"}
}