{
  "type": "Feature",
  "properties": {
    "gn:admin1_code":"12",
    "gn:asciiname":"Tugatuga",
    "gn:country_code":"PG",
    "gn:dem":48,
    "gn:feature_class":"P",
    "gn:feature_code":"PPL",
    "gn:name":"Tugatuga",
    "gn:population":0,
    "gn:timezone":"Pacific/Port_Moresby",
    "iso:country":"PG",
    "wof:name":"Tugatuga",
    "wof:placetype":"locality"
},
  "geometry": {"coordinates":[145.98333,-4.53333],"type":"Point"}
}