{
  "type": "Feature",
  "properties": {
    "gn:admin1_code":"12",
    "gn:asciiname":"Kikerei",
    "gn:country_code":"PG",
    "gn:dem":133,
    "gn:feature_class":"P",
    "gn:feature_code":"PPL",
    "gn:name":"Kikerei",
    "gn:population":0,
    "gn:timezone":"Pacific/Port_Moresby",
    "iso:country":"PG",
    "wof:name":"Kikerei",
    "wof:placetype":"locality"
},
  "geometry": {"coordinates":[145.31236000000001,-5.32166],"type":"Point"}
}