{
  "type": "Feature",
  "properties": {
    "gn:admin1_code":"04",
    "gn:asciiname":"Rabadi",
    "gn:country_code":"PG",
    "gn:dem":1,
    "gn:feature_class":"P",
    "gn:feature_code":"PPL",
    "gn:name":"Rabadi",
    "gn:population":0,
    "gn:timezone":"Pacific/Port_Moresby",
    "iso:country":"PG",
    "wof:name":"Rabadi",
    "wof:placetype":"locality"
},
  "geometry": {"coordinates":[149.31666999999999,-9.06667],"type":"Point"}
}