{
  "type": "Feature",
  "properties": {
    "gn:admin1_code":"09",
    "gn:asciiname":"Kenemote",
    "gn:country_code":"PG",
    "gn:dem":1494,
    "gn:feature_class":"P",
    "gn:feature_code":"PPL",
    "gn:name":"Kenemote",
    "gn:population":0,
    "gn:timezone":"Pacific/Port_Moresby",
    "iso:country":"PG",
    "wof:name":"Kenemote",
    "wof:placetype":"locality"
},
  "geometry": {"coordinates":[145.57111,-6.22502],"type":"Point"}
}