{
  "type": "Feature",
  "properties": {
    "gn:admin1_code":"11",
    "gn:asciiname":"Woginara 2",
    "gn:country_code":"PG",
    "gn:dem":257,
    "gn:feature_class":"P",
    "gn:feature_code":"PPL",
    "gn:name":"Woginara 2",
    "gn:population":0,
    "gn:timezone":"Pacific/Port_Moresby",
    "iso:country":"PG",
    "name:und_x_variant":[
        "Woginara Number 2",
        "Woginara 2"
    ],
    "wof:name":"Woginara 2",
    "wof:placetype":"locality"
},
  "geometry": {"coordinates":[143.29991999999999,-3.44469],"type":"Point"}
}