{
  "type": "Feature",
  "properties": {
    "gn:admin1_code":"11",
    "gn:asciiname":"Jame",
    "gn:country_code":"PG",
    "gn:dem":280,
    "gn:feature_class":"P",
    "gn:feature_code":"PPL",
    "gn:name":"Jame",
    "gn:population":0,
    "gn:timezone":"Pacific/Port_Moresby",
    "iso:country":"PG",
    "name:bos_x_preferred":[
        "Jame"
    ],
    "name:hrv_x_preferred":[
        "Jame"
    ],
    "name:hun_x_preferred":[
        "Jame"
    ],
    "name:nld_x_preferred":[
        "Jame"
    ],
    "name:slv_x_preferred":[
        "Jame"
    ],
    "name:spa_x_preferred":[
        "Jame"
    ],
    "name:srp_x_preferred":[
        "\u0408\u0430\u043c\u0435"
    ],
    "name:ukr_x_preferred":[
        "\u042f\u043c\u0435"
    ],
    "name:und_x_variant":[
        "Jamei",
        "Jame"
    ],
    "wof:name":"Jame",
    "wof:placetype":"locality"
},
  "geometry": {"coordinates":[143.09251,-3.62664],"type":"Point"}
}