{
  "type": "Feature",
  "properties": {
    "gn:admin1_code":"11",
    "gn:asciiname":"Kininyari",
    "gn:country_code":"PG",
    "gn:dem":191,
    "gn:feature_class":"P",
    "gn:feature_code":"PPL",
    "gn:name":"Kininyari",
    "gn:population":0,
    "gn:timezone":"Pacific/Port_Moresby",
    "iso:country":"PG",
    "name:und_x_variant":[
        "Kininyan",
        "Kininyari"
    ],
    "wof:name":"Kininyari",
    "wof:placetype":"locality"
},
  "geometry": {"coordinates":[143.36006,-3.70169],"type":"Point"}
}