{
  "type": "Feature",
  "properties": {
    "gn:admin1_code":"05",
    "gn:asciiname":"Poroyandale",
    "gn:country_code":"PG",
    "gn:dem":1645,
    "gn:feature_class":"P",
    "gn:feature_code":"PPL",
    "gn:name":"Poroyandale",
    "gn:population":0,
    "gn:timezone":"Pacific/Port_Moresby",
    "iso:country":"PG",
    "wof:name":"Poroyandale",
    "wof:placetype":"locality"
},
  "geometry": {"coordinates":[142.81666999999999,-6.03333],"type":"Point"}
}