{
  "type": "Feature",
  "properties": {
    "gn:admin1_code":"12",
    "gn:asciiname":"Labinsarik",
    "gn:country_code":"PG",
    "gn:dem":155,
    "gn:feature_class":"P",
    "gn:feature_code":"PPL",
    "gn:name":"Labinsarik",
    "gn:population":0,
    "gn:timezone":"Pacific/Port_Moresby",
    "iso:country":"PG",
    "wof:name":"Labinsarik",
    "wof:placetype":"locality"
},
  "geometry": {"coordinates":[145.30000000000001,-5.21667],"type":"Point"}
}