{
  "type": "Feature",
  "properties": {
    "gn:admin1_code":"01",
    "gn:asciiname":"Maini",
    "gn:country_code":"PG",
    "gn:dem":1840,
    "gn:feature_class":"P",
    "gn:feature_code":"PPL",
    "gn:name":"Maini",
    "gn:population":0,
    "gn:timezone":"Pacific/Port_Moresby",
    "iso:country":"PG",
    "name:fas_x_preferred":[
        "\u0645\u0627\u0626\u0646\u06cc"
    ],
    "name:urd_x_preferred":[
        "\u0645\u0627\u0626\u0646\u06cc"
    ],
    "wof:name":"Maini",
    "wof:placetype":"locality"
},
  "geometry": {"coordinates":[147.10006000000001,-8.32901],"type":"Point"}
}