{
  "type": "Feature",
  "properties": {
    "gn:admin1_code":"18",
    "gn:asciiname":"Yankok",
    "gn:country_code":"PG",
    "gn:dem":352,
    "gn:feature_class":"P",
    "gn:feature_code":"PPL",
    "gn:name":"Yankok",
    "gn:population":0,
    "gn:timezone":"Pacific/Port_Moresby",
    "iso:country":"PG",
    "name:und_x_variant":[
        "Yankok Villages",
        "Yankok"
    ],
    "wof:name":"Yankok",
    "wof:placetype":"locality"
},
  "geometry": {"coordinates":[142.22228999999999,-3.55521],"type":"Point"}
}