{
  "type": "Feature",
  "properties": {
    "gn:admin1_code":"14",
    "gn:asciiname":"Gewak",
    "gn:country_code":"PG",
    "gn:dem":1599,
    "gn:feature_class":"P",
    "gn:feature_code":"PPL",
    "gn:name":"Gewak",
    "gn:population":0,
    "gn:timezone":"Pacific/Port_Moresby",
    "iso:country":"PG",
    "name:und_x_variant":[
        "Gevak",
        "Gewak"
    ],
    "wof:name":"Gewak",
    "wof:placetype":"locality"
},
  "geometry": {"coordinates":[146.89568,-6.37835],"type":"Point"}
}