{
  "type": "Feature",
  "properties": {
    "gn:admin1_code":"11",
    "gn:asciiname":"Kowiro",
    "gn:country_code":"PG",
    "gn:dem":88,
    "gn:feature_class":"P",
    "gn:feature_code":"PPL",
    "gn:name":"Kowiro",
    "gn:population":0,
    "gn:timezone":"Pacific/Port_Moresby",
    "iso:country":"PG",
    "wof:name":"Kowiro",
    "wof:placetype":"locality"
},
  "geometry": {"coordinates":[143.63619,-3.82503],"type":"Point"}
}