{
  "type": "Feature",
  "properties": {
    "gn:admin1_code":"14",
    "gn:asciiname":"Bampa",
    "gn:country_code":"PG",
    "gn:dem":605,
    "gn:feature_class":"P",
    "gn:feature_code":"PPL",
    "gn:name":"Bampa",
    "gn:population":0,
    "gn:timezone":"Pacific/Port_Moresby",
    "iso:country":"PG",
    "wof:name":"Bampa",
    "wof:placetype":"locality"
},
  "geometry": {"coordinates":[146.20188999999999,-6.4688],"type":"Point"}
}