{
  "type": "Feature",
  "properties": {
    "gn:admin1_code":"19",
    "gn:asciiname":"Par",
    "gn:country_code":"PG",
    "gn:dem":2036,
    "gn:feature_class":"P",
    "gn:feature_code":"PPL",
    "gn:name":"Par",
    "gn:population":0,
    "gn:timezone":"Pacific/Port_Moresby",
    "iso:country":"PG",
    "wof:name":"Par",
    "wof:placetype":"locality"
},
  "geometry": {"coordinates":[143.75,-5.46667],"type":"Point"}
}