{
  "type": "Feature",
  "properties": {
    "gn:admin1_code":"16",
    "gn:asciiname":"Togban",
    "gn:country_code":"PG",
    "gn:dem":1436,
    "gn:feature_class":"P",
    "gn:feature_code":"PPL",
    "gn:name":"Togban",
    "gn:population":0,
    "gn:timezone":"Pacific/Port_Moresby",
    "iso:country":"PG",
    "wof:name":"Togban",
    "wof:placetype":"locality"
},
  "geometry": {"coordinates":[144.71186,-5.52321],"type":"Point"}
}