{
  "type": "Feature",
  "properties": {
    "gn:admin1_code":"06",
    "gn:asciiname":"Jarai",
    "gn:country_code":"PG",
    "gn:dem":1,
    "gn:feature_class":"P",
    "gn:feature_code":"PPL",
    "gn:name":"Jarai",
    "gn:population":0,
    "gn:timezone":"Pacific/Port_Moresby",
    "iso:country":"PG",
    "name:und_x_variant":[
        "Jara",
        "Jarai"
    ],
    "wof:name":"Jarai",
    "wof:placetype":"locality"
},
  "geometry": {"coordinates":[141.55889999999999,-9.20672],"type":"Point"}
}