{
  "type": "Feature",
  "properties": {
    "gn:admin1_code":"08",
    "gn:asciiname":"Kaualagu",
    "gn:country_code":"PG",
    "gn:dem":1456,
    "gn:feature_class":"P",
    "gn:feature_code":"PPL",
    "gn:name":"Kaualagu",
    "gn:population":0,
    "gn:timezone":"Pacific/Port_Moresby",
    "iso:country":"PG",
    "wof:name":"Kaualagu",
    "wof:placetype":"locality"
},
  "geometry": {"coordinates":[144.80953,-6.22994],"type":"Point"}
}