{
  "type": "Feature",
  "properties": {
    "gn:admin1_code":"14",
    "gn:asciiname":"Kangarua",
    "gn:country_code":"PG",
    "gn:dem":242,
    "gn:feature_class":"P",
    "gn:feature_code":"PPL",
    "gn:name":"Kangarua",
    "gn:population":0,
    "gn:timezone":"Pacific/Port_Moresby",
    "iso:country":"PG",
    "wof:name":"Kangarua",
    "wof:placetype":"locality"
},
  "geometry": {"coordinates":[147.71968000000001,-6.59712],"type":"Point"}
}