{
  "type": "Feature",
  "properties": {
    "gn:admin1_code":"06",
    "gn:asciiname":"Wisuamengre",
    "gn:country_code":"PG",
    "gn:dem":77,
    "gn:feature_class":"P",
    "gn:feature_code":"PPL",
    "gn:name":"Wisuamengre",
    "gn:population":0,
    "gn:timezone":"Pacific/Port_Moresby",
    "iso:country":"PG",
    "wof:name":"Wisuamengre",
    "wof:placetype":"locality"
},
  "geometry": {"coordinates":[141.36956999999995,-5.92217],"type":"Point"}
}