{
  "type": "Feature",
  "properties": {
    "gn:admin1_code":"13",
    "gn:asciiname":"Bowat Number 1",
    "gn:country_code":"PG",
    "gn:dem":186,
    "gn:feature_class":"P",
    "gn:feature_code":"PPL",
    "gn:name":"Bowat Number 1",
    "gn:population":0,
    "gn:timezone":"Pacific/Port_Moresby",
    "iso:country":"PG",
    "name:und_x_variant":[
        "Bowat 1",
        "Bowat",
        "Bowat Number 1"
    ],
    "wof:name":"Bowat Number 1",
    "wof:placetype":"locality"
},
  "geometry": {"coordinates":[147.15478999999999,-2.06918],"type":"Point"}
}