{
  "type": "Feature",
  "properties": {
    "gn:admin1_code":"20",
    "gn:asciiname":"Haima",
    "gn:country_code":"PG",
    "gn:dem":54,
    "gn:feature_class":"P",
    "gn:feature_code":"PPL",
    "gn:name":"Haima",
    "gn:population":0,
    "gn:timezone":"Pacific/Port_Moresby",
    "iso:country":"PG",
    "wof:name":"Haima",
    "wof:placetype":"locality"
},
  "geometry": {"coordinates":[147.19999999999999,-9.43333],"type":"Point"}
}