{
  "type": "Feature",
  "properties": {
    "gn:admin1_code":"09",
    "gn:asciiname":"Agiba",
    "gn:country_code":"PG",
    "gn:dem":1772,
    "gn:feature_class":"P",
    "gn:feature_code":"PPL",
    "gn:name":"Agiba",
    "gn:population":0,
    "gn:timezone":"Pacific/Port_Moresby",
    "iso:country":"PG",
    "wof:name":"Agiba",
    "wof:placetype":"locality"
},
  "geometry": {"coordinates":[145.19718,-6.45535],"type":"Point"}
}