{
  "type": "Feature",
  "properties": {
    "gn:admin1_code":"15",
    "gn:asciiname":"Lemkamin",
    "gn:country_code":"PG",
    "gn:dem":960,
    "gn:feature_class":"P",
    "gn:feature_code":"PPL",
    "gn:name":"Lemkamin",
    "gn:population":0,
    "gn:timezone":"Pacific/Port_Moresby",
    "iso:country":"PG",
    "name:und_x_variant":[
        "Lenkamen",
        "Lemkamin"
    ],
    "wof:name":"Lemkamin",
    "wof:placetype":"locality"
},
  "geometry": {"coordinates":[151.91793999999999,-3.31237],"type":"Point"}
}