{
  "type": "Feature",
  "properties": {
    "gn:admin1_code":"18",
    "gn:asciiname":"Merewe",
    "gn:country_code":"PG",
    "gn:dem":139,
    "gn:feature_class":"P",
    "gn:feature_code":"PPL",
    "gn:name":"Merewe",
    "gn:population":0,
    "gn:timezone":"Pacific/Port_Moresby",
    "iso:country":"PG",
    "name:und_x_variant":[
        "Meriwe",
        "Merewe"
    ],
    "wof:name":"Merewe",
    "wof:placetype":"locality"
},
  "geometry": {"coordinates":[141.21634,-3.77202],"type":"Point"}
}