{
  "type": "Feature",
  "properties": {
    "gn:admin1_code":"15",
    "gn:asciiname":"Nalula",
    "gn:cc2":"PG",
    "gn:country_code":"PG",
    "gn:dem":-9999,
    "gn:feature_class":"P",
    "gn:feature_code":"PPL",
    "gn:name":"Nalula",
    "gn:population":0,
    "gn:timezone":"Pacific/Port_Moresby",
    "iso:country":"PG",
    "name:und_x_variant":[
        "Nalulu",
        "Nalula"
    ],
    "wof:name":"Nalula",
    "wof:placetype":"locality"
},
  "geometry": {"coordinates":[153.65000000000001,-4.11667],"type":"Point"}
}