{
  "type": "Feature",
  "properties": {
    "gn:admin1_code":"11",
    "gn:asciiname":"Kwanabandu Villages",
    "gn:country_code":"PG",
    "gn:dem":127,
    "gn:feature_class":"P",
    "gn:feature_code":"PPL",
    "gn:name":"Kwanabandu Villages",
    "gn:population":0,
    "gn:timezone":"Pacific/Port_Moresby",
    "iso:country":"PG",
    "wof:name":"Kwanabandu Villages",
    "wof:placetype":"locality"
},
  "geometry": {"coordinates":[143.00169,-3.7186],"type":"Point"}
}