{
  "type": "Feature",
  "properties": {
    "gn:admin1_code":"12",
    "gn:asciiname":"Dangsai",
    "gn:country_code":"PG",
    "gn:dem":26,
    "gn:feature_class":"P",
    "gn:feature_code":"PPL",
    "gn:name":"Dangsai",
    "gn:population":0,
    "gn:timezone":"Pacific/Port_Moresby",
    "iso:country":"PG",
    "wof:name":"Dangsai",
    "wof:placetype":"locality"
},
  "geometry": {"coordinates":[145.94999999999999,-4.75],"type":"Point"}
}