{
  "type": "Feature",
  "properties": {
    "gn:admin1_code":"05",
    "gn:asciiname":"Lau'u",
    "gn:country_code":"PG",
    "gn:dem":1721,
    "gn:feature_class":"P",
    "gn:feature_code":"PPL",
    "gn:name":"Lau\u2019u",
    "gn:population":0,
    "gn:timezone":"Pacific/Port_Moresby",
    "iso:country":"PG",
    "name:und_x_variant":[
        "Lau\u2019v",
        "Lau\u2019u"
    ],
    "wof:name":"Lau'u",
    "wof:placetype":"locality"
},
  "geometry": {"coordinates":[143.08333000000005,-6.05],"type":"Point"}
}