{
  "type": "Feature",
  "properties": {
    "gn:admin1_code":"18",
    "gn:asciiname":"Keibam",
    "gn:country_code":"PG",
    "gn:dem":440,
    "gn:feature_class":"P",
    "gn:feature_code":"PPL",
    "gn:name":"Keibam",
    "gn:population":0,
    "gn:timezone":"Pacific/Port_Moresby",
    "iso:country":"PG",
    "wof:name":"Keibam",
    "wof:placetype":"locality"
},
  "geometry": {"coordinates":[142.09978000000001,-3.5022],"type":"Point"}
}