{
  "type": "Feature",
  "properties": {
    "gn:admin1_code":"08",
    "gn:asciiname":"Dinggigu",
    "gn:country_code":"PG",
    "gn:dem":1605,
    "gn:feature_class":"P",
    "gn:feature_code":"PPL",
    "gn:name":"Dinggigu",
    "gn:population":0,
    "gn:timezone":"Pacific/Port_Moresby",
    "iso:country":"PG",
    "wof:name":"Dinggigu",
    "wof:placetype":"locality"
},
  "geometry": {"coordinates":[144.86667,-5.95],"type":"Point"}
}