{
  "type": "Feature",
  "properties": {
    "gn:admin1_code":"10",
    "gn:asciiname":"Bira",
    "gn:country_code":"PG",
    "gn:dem":48,
    "gn:feature_class":"P",
    "gn:feature_code":"PPL",
    "gn:name":"Bira",
    "gn:population":0,
    "gn:timezone":"Pacific/Port_Moresby",
    "iso:country":"PG",
    "name:ceb_x_preferred":[
        "Bira"
    ],
    "name:dan_x_preferred":[
        "Bira"
    ],
    "name:deu_x_preferred":[
        "Bira"
    ],
    "name:fra_x_preferred":[
        "Bira"
    ],
    "name:ind_x_preferred":[
        "Bira"
    ],
    "name:ita_x_preferred":[
        "Bira"
    ],
    "name:por_x_preferred":[
        "Bira"
    ],
    "name:sco_x_preferred":[
        "Bira"
    ],
    "name:spa_x_preferred":[
        "Bira"
    ],
    "name:swe_x_preferred":[
        "Bira"
    ],
    "wof:name":"Bira",
    "wof:placetype":"locality"
},
  "geometry": {"coordinates":[152.34999999999999,-4.41667],"type":"Point"}
}