{
  "type": "Feature",
  "properties": {
    "gn:admin1_code":"02",
    "gn:asciiname":"Yandati",
    "gn:country_code":"PG",
    "gn:dem":1510,
    "gn:feature_class":"P",
    "gn:feature_code":"PPL",
    "gn:name":"Yandati",
    "gn:population":0,
    "gn:timezone":"Pacific/Port_Moresby",
    "iso:country":"PG",
    "wof:name":"Yandati",
    "wof:placetype":"locality"
},
  "geometry": {"coordinates":[145.86815000000001,-7.57951],"type":"Point"}
}