{
  "type": "Feature",
  "properties": {
    "gn:admin1_code":"03",
    "gn:asciiname":"Dabora",
    "gn:country_code":"PG",
    "gn:dem":419,
    "gn:feature_class":"P",
    "gn:feature_code":"PPL",
    "gn:name":"Dabora",
    "gn:population":0,
    "gn:timezone":"Pacific/Port_Moresby",
    "iso:country":"PG",
    "wof:name":"Dabora",
    "wof:placetype":"locality"
},
  "geometry": {"coordinates":[149.70161999999999,-9.91372],"type":"Point"}
}