{
  "type": "Feature",
  "properties": {
    "gn:admin1_code":"04",
    "gn:asciiname":"Borugasusu",
    "gn:country_code":"PG",
    "gn:dem":40,
    "gn:feature_class":"P",
    "gn:feature_code":"PPL",
    "gn:name":"Borugasusu",
    "gn:population":0,
    "gn:timezone":"Pacific/Port_Moresby",
    "iso:country":"PG",
    "wof:name":"Borugasusu",
    "wof:placetype":"locality"
},
  "geometry": {"coordinates":[147.92168999999996,-8.61039],"type":"Point"}
}