{
  "type": "Feature",
  "properties": {
    "gn:admin1_code":"14",
    "gn:asciiname":"Nuwu",
    "gn:country_code":"PG",
    "gn:dem":129,
    "gn:feature_class":"P",
    "gn:feature_code":"PPL",
    "gn:name":"Nuwu",
    "gn:population":0,
    "gn:timezone":"Pacific/Port_Moresby",
    "iso:country":"PG",
    "wof:name":"Nuwu",
    "wof:placetype":"locality"
},
  "geometry": {"coordinates":[146.47019,-6.51341],"type":"Point"}
}