{
  "type": "Feature",
  "properties": {
    "gn:admin1_code":"14",
    "gn:asciiname":"Lowai",
    "gn:country_code":"PG",
    "gn:dem":971,
    "gn:feature_class":"P",
    "gn:feature_code":"PPL",
    "gn:name":"Lowai",
    "gn:population":0,
    "gn:timezone":"Pacific/Port_Moresby",
    "iso:country":"PG",
    "wof:name":"Lowai",
    "wof:placetype":"locality"
},
  "geometry": {"coordinates":[146.65362999999999,-6.33571],"type":"Point"}
}