{
  "type": "Feature",
  "properties": {
    "gn:admin1_code":"06",
    "gn:asciiname":"Kurunti",
    "gn:country_code":"PG",
    "gn:dem":23,
    "gn:feature_class":"P",
    "gn:feature_code":"PPL",
    "gn:name":"Kurunti",
    "gn:population":0,
    "gn:timezone":"Pacific/Port_Moresby",
    "iso:country":"PG",
    "wof:name":"Kurunti",
    "wof:placetype":"locality"
},
  "geometry": {"coordinates":[142.65111999999999,-9.00117],"type":"Point"}
}