{
  "type": "Feature",
  "properties": {
    "gn:admin1_code":"04",
    "gn:asciiname":"Garuro",
    "gn:country_code":"PG",
    "gn:dem":13,
    "gn:feature_class":"P",
    "gn:feature_code":"PPL",
    "gn:name":"Garuro",
    "gn:population":0,
    "gn:timezone":"Pacific/Port_Moresby",
    "iso:country":"PG",
    "name:und_x_variant":[
        "Garuru",
        "Garuro"
    ],
    "wof:name":"Garuro",
    "wof:placetype":"locality"
},
  "geometry": {"coordinates":[148.46303,-8.74952],"type":"Point"}
}