{
  "type": "Feature",
  "properties": {
    "gn:admin1_code":"11",
    "gn:asciiname":"Parina 2",
    "gn:country_code":"PG",
    "gn:dem":291,
    "gn:feature_class":"P",
    "gn:feature_code":"PPL",
    "gn:name":"Parina 2",
    "gn:population":0,
    "gn:timezone":"Pacific/Port_Moresby",
    "iso:country":"PG",
    "wof:name":"Parina 2",
    "wof:placetype":"locality"
},
  "geometry": {"coordinates":[143.33333000000005,-3.65],"type":"Point"}
}