{
  "type": "Feature",
  "properties": {
    "gn:admin1_code":"05",
    "gn:asciiname":"Porani",
    "gn:country_code":"PG",
    "gn:dem":1641,
    "gn:feature_class":"P",
    "gn:feature_code":"PPL",
    "gn:name":"Porani",
    "gn:population":0,
    "gn:timezone":"Pacific/Port_Moresby",
    "iso:country":"PG",
    "wof:name":"Porani",
    "wof:placetype":"locality"
},
  "geometry": {"coordinates":[143.83333000000005,-6.38333],"type":"Point"}
}