{
  "type": "Feature",
  "properties": {
    "gn:admin1_code":"18",
    "gn:asciiname":"Baibai",
    "gn:country_code":"PG",
    "gn:dem":150,
    "gn:feature_class":"P",
    "gn:feature_code":"PPL",
    "gn:name":"Baibai",
    "gn:population":0,
    "gn:timezone":"Pacific/Port_Moresby",
    "iso:country":"PG",
    "wof:name":"Baibai",
    "wof:placetype":"locality"
},
  "geometry": {"coordinates":[141.36091000000005,-3.46331],"type":"Point"}
}