{
  "type": "Feature",
  "properties": {
    "gn:admin1_code":"11",
    "gn:asciiname":"Anganamei",
    "gn:country_code":"PG",
    "gn:dem":57,
    "gn:feature_class":"P",
    "gn:feature_code":"PPL",
    "gn:name":"Anganamei",
    "gn:population":0,
    "gn:timezone":"Pacific/Port_Moresby",
    "iso:country":"PG",
    "wof:name":"Anganamei",
    "wof:placetype":"locality"
},
  "geometry": {"coordinates":[143.27383999999995,-4.59189],"type":"Point"}
}