{
  "type": "Feature",
  "properties": {
    "gn:admin1_code":"05",
    "gn:asciiname":"Umbimi",
    "gn:country_code":"PG",
    "gn:dem":1767,
    "gn:feature_class":"P",
    "gn:feature_code":"PPL",
    "gn:name":"Umbimi",
    "gn:population":0,
    "gn:timezone":"Pacific/Port_Moresby",
    "iso:country":"PG",
    "name:und_x_variant":[
        "Jmbimi",
        "Umbimi"
    ],
    "wof:name":"Umbimi",
    "wof:placetype":"locality"
},
  "geometry": {"coordinates":[143.65932000000001,-6.13514],"type":"Point"}
}