{
  "type": "Feature",
  "properties": {
    "gn:admin1_code":"18",
    "gn:asciiname":"Telotei",
    "gn:country_code":"PG",
    "gn:dem":333,
    "gn:feature_class":"P",
    "gn:feature_code":"PPL",
    "gn:name":"Telotei",
    "gn:population":0,
    "gn:timezone":"Pacific/Port_Moresby",
    "iso:country":"PG",
    "wof:name":"Telotei",
    "wof:placetype":"locality"
},
  "geometry": {"coordinates":[142.06988999999999,-3.51288],"type":"Point"}
}