{
  "type": "Feature",
  "properties": {
    "gn:admin1_code":"04",
    "gn:asciiname":"Totore",
    "gn:country_code":"PG",
    "gn:dem":21,
    "gn:feature_class":"P",
    "gn:feature_code":"PPL",
    "gn:name":"Totore",
    "gn:population":0,
    "gn:timezone":"Pacific/Port_Moresby",
    "iso:country":"PG",
    "wof:name":"Totore",
    "wof:placetype":"locality"
},
  "geometry": {"coordinates":[148.91666999999995,-9.26667],"type":"Point"}
}