{
  "type": "Feature",
  "properties": {
    "gn:admin1_code":"11",
    "gn:asciiname":"Monjitok",
    "gn:cc2":"PG",
    "gn:country_code":"PG",
    "gn:dem":34,
    "gn:feature_class":"P",
    "gn:feature_code":"PPL",
    "gn:name":"Monjitok",
    "gn:population":0,
    "gn:timezone":"Pacific/Port_Moresby",
    "iso:country":"PG",
    "name:und_x_variant":[
        "Mongitok",
        "Monjitok"
    ],
    "wof:name":"Monjitok",
    "wof:placetype":"locality"
},
  "geometry": {"coordinates":[144.33333000000005,-4.73333],"type":"Point"}
}