{
  "type": "Feature",
  "properties": {
    "gn:admin1_code":"15",
    "gn:asciiname":"Konematalik",
    "gn:country_code":"PG",
    "gn:dem":14,
    "gn:feature_class":"P",
    "gn:feature_code":"PPL",
    "gn:name":"Konematalik",
    "gn:population":0,
    "gn:timezone":"Pacific/Port_Moresby",
    "iso:country":"PG",
    "name:und_x_variant":[
        "Konematelik",
        "Konematalik"
    ],
    "wof:name":"Konematalik",
    "wof:placetype":"locality"
},
  "geometry": {"coordinates":[150.42400000000001,-2.48664],"type":"Point"}
}