{
  "type": "Feature",
  "properties": {
    "gn:admin1_code":"05",
    "gn:asciiname":"Iamala",
    "gn:country_code":"PG",
    "gn:dem":2323,
    "gn:feature_class":"P",
    "gn:feature_code":"PPL",
    "gn:name":"Iamala",
    "gn:population":0,
    "gn:timezone":"Pacific/Port_Moresby",
    "iso:country":"PG",
    "wof:name":"Iamala",
    "wof:placetype":"locality"
},
  "geometry": {"coordinates":[143.89787999999999,-6.27254],"type":"Point"}
}