{
  "type": "Feature",
  "properties": {
    "gn:admin1_code":"14",
    "gn:asciiname":"Daia",
    "gn:country_code":"PG",
    "gn:dem":1954,
    "gn:feature_class":"P",
    "gn:feature_code":"PPL",
    "gn:name":"Daia",
    "gn:population":0,
    "gn:timezone":"Pacific/Port_Moresby",
    "iso:country":"PG",
    "wof:name":"Daia",
    "wof:placetype":"locality"
},
  "geometry": {"coordinates":[146.69999999999999,-6.31667],"type":"Point"}
}