{
  "type": "Feature",
  "properties": {
    "gn:admin1_code":"14",
    "gn:asciiname":"Daia",
    "gn:country_code":"PG",
    "gn:dem":1954,
    "gn:feature_class":"P",
    "gn:feature_code":"PPL",
    "gn:name":"Daia",
    "gn:population":0,
    "gn:timezone":"Pacific/Port_Moresby",
    "iso:country":"PG",
    "name:ceb_x_preferred":[
        "Comuna Daia"
    ],
    "name:ita_x_preferred":[
        "Daia"
    ],
    "name:msa_x_preferred":[
        "Daia"
    ],
    "name:nld_x_preferred":[
        "Daia"
    ],
    "name:por_x_preferred":[
        "Daia"
    ],
    "name:ron_x_preferred":[
        "Comuna Daia"
    ],
    "name:srp_x_preferred":[
        "\u041e\u043f\u0448\u0442\u0438\u043d\u0430 \u0414\u0430\u0458\u0430"
    ],
    "name:ukr_x_preferred":[
        "\u0414\u0430\u044f"
    ],
    "name:vie_x_preferred":[
        "Daia"
    ],
    "name:vol_x_preferred":[
        "Daia"
    ],
    "name:zho_x_preferred":[
        "\u9054\u4e9e\u9109"
    ],
    "wof:name":"Daia",
    "wof:placetype":"locality"
},
  "geometry": {"coordinates":[146.69999999999999,-6.31667],"type":"Point"}
}