{
  "type": "Feature",
  "properties": {
    "gn:admin1_code":"17",
    "gn:asciiname":"Kaiamu",
    "gn:country_code":"PG",
    "gn:dem":294,
    "gn:feature_class":"P",
    "gn:feature_code":"PPL",
    "gn:name":"Kaiamu",
    "gn:population":0,
    "gn:timezone":"Pacific/Port_Moresby",
    "iso:country":"PG",
    "name:und_x_variant":[
        "Kaiama",
        "Kiamu",
        "Kaiamu"
    ],
    "wof:name":"Kaiamu",
    "wof:placetype":"locality"
},
  "geometry": {"coordinates":[150.90819999999999,-5.46055],"type":"Point"}
}