{
  "type": "Feature",
  "properties": {
    "gn:admin1_code":"08",
    "gn:asciiname":"Boibienggauwa",
    "gn:country_code":"PG",
    "gn:dem":1675,
    "gn:feature_class":"P",
    "gn:feature_code":"PPL",
    "gn:name":"Boibienggauwa",
    "gn:population":0,
    "gn:timezone":"Pacific/Port_Moresby",
    "iso:country":"PG",
    "wof:name":"Boibienggauwa",
    "wof:placetype":"locality"
},
  "geometry": {"coordinates":[144.96666999999999,-6.18333],"type":"Point"}
}