{
  "type": "Feature",
  "properties": {
    "gn:admin1_code":"11",
    "gn:asciiname":"Gatnigum",
    "gn:country_code":"PG",
    "gn:dem":158,
    "gn:feature_class":"P",
    "gn:feature_code":"PPL",
    "gn:name":"Gatnigum",
    "gn:population":0,
    "gn:timezone":"Pacific/Port_Moresby",
    "iso:country":"PG",
    "wof:name":"Gatnigum",
    "wof:placetype":"locality"
},
  "geometry": {"coordinates":[143.01023999999995,-3.67771],"type":"Point"}
}