{
  "type": "Feature",
  "properties": {
    "gn:admin1_code":"06",
    "gn:asciiname":"Irupi",
    "gn:cc2":"PG",
    "gn:country_code":"PG",
    "gn:dem":12,
    "gn:feature_class":"P",
    "gn:feature_code":"PPL",
    "gn:name":"Irupi",
    "gn:population":0,
    "gn:timezone":"Pacific/Port_Moresby",
    "iso:country":"PG",
    "name:bpy_x_preferred":[
        "\u0987\u09b0\u09c1\u09aa\u09bf"
    ],
    "name:epo_x_preferred":[
        "Irupi"
    ],
    "name:eus_x_preferred":[
        "Irupi"
    ],
    "name:fra_x_preferred":[
        "Irupi"
    ],
    "name:hye_x_preferred":[
        "\u053b\u0580\u0578\u0582\u057a\u056b"
    ],
    "name:ita_x_preferred":[
        "Irupi"
    ],
    "name:kat_x_preferred":[
        "\u10d8\u10e0\u10e3\u10de\u10d8"
    ],
    "name:kaz_x_preferred":[
        "\u0418\u0440\u0443\u043f\u0438"
    ],
    "name:nld_x_preferred":[
        "Irupi"
    ],
    "name:nor_x_preferred":[
        "Irupi"
    ],
    "name:pol_x_preferred":[
        "Irupi"
    ],
    "name:por_x_preferred":[
        "Irupi"
    ],
    "name:ron_x_preferred":[
        "Irupi"
    ],
    "name:rus_x_preferred":[
        "\u0418\u0440\u0443\u043f\u0438"
    ],
    "name:und_x_variant":[
        "Triupi"
    ],
    "name:vie_x_preferred":[
        "Irupi"
    ],
    "name:vol_x_preferred":[
        "Irupi"
    ],
    "name:war_x_preferred":[
        "Irupi"
    ],
    "name:zho_x_preferred":[
        "\u4f0a\u9b6f\u76ae"
    ],
    "wof:name":"Irupi",
    "wof:placetype":"locality"
},
  "geometry": {"coordinates":[142.86667,-9.13333],"type":"Point"}
}