{
  "type": "Feature",
  "properties": {
    "gn:admin1_code":"06",
    "gn:asciiname":"Irupi",
    "gn:cc2":"PG",
    "gn:country_code":"PG",
    "gn:dem":12,
    "gn:feature_class":"P",
    "gn:feature_code":"PPL",
    "gn:name":"Irupi",
    "gn:population":0,
    "gn:timezone":"Pacific/Port_Moresby",
    "iso:country":"PG",
    "name:und_x_variant":[
        "Triupi",
        "Irupi"
    ],
    "wof:name":"Irupi",
    "wof:placetype":"locality"
},
  "geometry": {"coordinates":[142.86667,-9.13333],"type":"Point"}
}