{
  "type": "Feature",
  "properties": {
    "gn:admin1_code":"12",
    "gn:asciiname":"Urara",
    "gn:country_code":"PG",
    "gn:dem":143,
    "gn:feature_class":"P",
    "gn:feature_code":"PPL",
    "gn:name":"Urara",
    "gn:population":0,
    "gn:timezone":"Pacific/Port_Moresby",
    "iso:country":"PG",
    "wof:name":"Urara",
    "wof:placetype":"locality"
},
  "geometry": {"coordinates":[145.98333,-4.55],"type":"Point"}
}