{
  "type": "Feature",
  "properties": {
    "gn:admin1_code":"14",
    "gn:asciiname":"Nineia",
    "gn:country_code":"PG",
    "gn:dem":36,
    "gn:feature_class":"P",
    "gn:feature_code":"PPL",
    "gn:name":"Nineia",
    "gn:population":0,
    "gn:timezone":"Pacific/Port_Moresby",
    "iso:country":"PG",
    "wof:name":"Nineia",
    "wof:placetype":"locality"
},
  "geometry": {"coordinates":[146.90481,-5.90695],"type":"Point"}
}