{
  "type": "Feature",
  "properties": {
    "gn:admin1_code":"01",
    "gn:asciiname":"Aveni",
    "gn:cc2":"PG",
    "gn:country_code":"PG",
    "gn:dem":1939,
    "gn:feature_class":"P",
    "gn:feature_code":"PPL",
    "gn:name":"Aveni",
    "gn:population":0,
    "gn:timezone":"Pacific/Port_Moresby",
    "iso:country":"PG",
    "name:und_x_variant":[
        "Avena",
        "Aveni"
    ],
    "wof:name":"Aveni",
    "wof:placetype":"locality"
},
  "geometry": {"coordinates":[146.90000000000001,-8.06667],"type":"Point"}
}