{
  "type": "Feature",
  "properties": {
    "gn:admin1_code":"02",
    "gn:asciiname":"Taunamatua",
    "gn:country_code":"PG",
    "gn:dem":11,
    "gn:feature_class":"P",
    "gn:feature_code":"PPL",
    "gn:name":"Taunamatua",
    "gn:population":0,
    "gn:timezone":"Pacific/Port_Moresby",
    "iso:country":"PG",
    "wof:name":"Taunamatua",
    "wof:placetype":"locality"
},
  "geometry": {"coordinates":[144.75,-7.45],"type":"Point"}
}