{
  "type": "Feature",
  "properties": {
    "gn:admin1_code":"18",
    "gn:asciiname":"Wutung",
    "gn:country_code":"PG",
    "gn:dem":49,
    "gn:feature_class":"P",
    "gn:feature_code":"PPL",
    "gn:name":"Wutung",
    "gn:population":0,
    "gn:timezone":"Pacific/Port_Moresby",
    "iso:country":"PG",
    "name:und_x_variant":[
        "Wutong",
        "Watong",
        "Wutung"
    ],
    "wof:name":"Wutung",
    "wof:placetype":"locality"
},
  "geometry": {"coordinates":[141.00880000000001,-2.61192],"type":"Point"}
}