{
  "type": "Feature",
  "properties": {
    "gn:admin1_code":"08",
    "gn:asciiname":"Dorime",
    "gn:country_code":"PG",
    "gn:dem":2200,
    "gn:feature_class":"P",
    "gn:feature_code":"PPL",
    "gn:name":"Dorime",
    "gn:population":0,
    "gn:timezone":"Pacific/Port_Moresby",
    "iso:country":"PG",
    "wof:name":"Dorime",
    "wof:placetype":"locality"
},
  "geometry": {"coordinates":[145.03333000000001,-5.95],"type":"Point"}
}