{
  "type": "Feature",
  "properties": {
    "gn:admin1_code":"17",
    "gn:asciiname":"Marawop",
    "gn:country_code":"PG",
    "gn:dem":596,
    "gn:feature_class":"P",
    "gn:feature_code":"PPL",
    "gn:name":"Marawop",
    "gn:population":0,
    "gn:timezone":"Pacific/Port_Moresby",
    "iso:country":"PG",
    "wof:name":"Marawop",
    "wof:placetype":"locality"
},
  "geometry": {"coordinates":[151.66666999999995,-4.46667],"type":"Point"}
}