{
  "type": "Feature",
  "properties": {
    "gn:admin1_code":"18",
    "gn:asciiname":"Mango",
    "gn:country_code":"PG",
    "gn:dem":119,
    "gn:feature_class":"P",
    "gn:feature_code":"PPL",
    "gn:name":"Mango",
    "gn:population":0,
    "gn:timezone":"Pacific/Port_Moresby",
    "iso:country":"PG",
    "wof:name":"Mango",
    "wof:placetype":"locality"
},
  "geometry": {"coordinates":[141.39399,-3.58838],"type":"Point"}
}