{
  "type": "Feature",
  "properties": {
    "gn:admin1_code":"11",
    "gn:asciiname":"Kombio",
    "gn:cc2":"PG",
    "gn:country_code":"PG",
    "gn:dem":536,
    "gn:feature_class":"P",
    "gn:feature_code":"PPL",
    "gn:name":"Kombio",
    "gn:population":0,
    "gn:timezone":"Pacific/Port_Moresby",
    "iso:country":"PG",
    "name:und_x_variant":[
        "Kombio Hamlets",
        "Kombio Group",
        "Kombio"
    ],
    "wof:name":"Kombio",
    "wof:placetype":"locality"
},
  "geometry": {"coordinates":[142.73333,-3.43333],"type":"Point"}
}