{
  "type": "Feature",
  "properties": {
    "gn:admin1_code":"17",
    "gn:asciiname":"Ndolli",
    "gn:country_code":"PG",
    "gn:dem":18,
    "gn:feature_class":"P",
    "gn:feature_code":"PPL",
    "gn:name":"Ndolli",
    "gn:population":0,
    "gn:timezone":"Pacific/Port_Moresby",
    "iso:country":"PG",
    "name:und_x_variant":[
        "Ndoll",
        "Ndolli"
    ],
    "wof:name":"Ndolli",
    "wof:placetype":"locality"
},
  "geometry": {"coordinates":[149.54508999999999,-4.67493],"type":"Point"}
}