{
  "type": "Feature",
  "properties": {
    "gn:admin1_code":"14",
    "gn:asciiname":"Tori",
    "gn:country_code":"PG",
    "gn:dem":1217,
    "gn:feature_class":"P",
    "gn:feature_code":"PPL",
    "gn:name":"Tori",
    "gn:population":0,
    "gn:timezone":"Pacific/Port_Moresby",
    "iso:country":"PG",
    "wof:name":"Tori",
    "wof:placetype":"locality"
},
  "geometry": {"coordinates":[146.72293999999999,-7.74986],"type":"Point"}
}