{
  "type": "Feature",
  "properties": {
    "gn:admin1_code":"14",
    "gn:asciiname":"Tori",
    "gn:country_code":"PG",
    "gn:dem":1217,
    "gn:feature_class":"P",
    "gn:feature_code":"PPL",
    "gn:name":"Tori",
    "gn:population":0,
    "gn:timezone":"Pacific/Port_Moresby",
    "iso:country":"PG",
    "name:bul_x_preferred":[
        "\u0422\u043e\u0440\u0438"
    ],
    "name:ceb_x_preferred":[
        "Tori"
    ],
    "name:ces_x_preferred":[
        "Tori"
    ],
    "name:deu_x_preferred":[
        "Tori"
    ],
    "name:fin_x_preferred":[
        "Tori"
    ],
    "name:fra_x_preferred":[
        "Tori"
    ],
    "name:heb_x_preferred":[
        "\u05d8\u05d5\u05e8\u05d9"
    ],
    "name:hrv_x_preferred":[
        "Tori"
    ],
    "name:ita_x_preferred":[
        "Tori"
    ],
    "name:nld_x_preferred":[
        "Tori"
    ],
    "name:por_x_preferred":[
        "Tori"
    ],
    "name:ron_x_preferred":[
        "Tori"
    ],
    "name:srp_x_preferred":[
        "\u0422\u043e\u0440\u0438"
    ],
    "name:swe_x_preferred":[
        "Tori"
    ],
    "name:ukr_x_preferred":[
        "\u0422\u043e\u0440\u0456\u0441\u0456\u043c\u0430"
    ],
    "wof:name":"Tori",
    "wof:placetype":"locality"
},
  "geometry": {"coordinates":[146.72293999999999,-7.74986],"type":"Point"}
}