{
  "type": "Feature",
  "properties": {
    "gn:admin1_code":"05",
    "gn:asciiname":"Pua'a",
    "gn:country_code":"PG",
    "gn:dem":922,
    "gn:feature_class":"P",
    "gn:feature_code":"PPL",
    "gn:name":"Pua\u2019a",
    "gn:population":0,
    "gn:timezone":"Pacific/Port_Moresby",
    "iso:country":"PG",
    "name:und_x_variant":[
        "Paua",
        "Pua\u2019a"
    ],
    "wof:name":"Pua'a",
    "wof:placetype":"locality"
},
  "geometry": {"coordinates":[143.09816999999995,-6.27325],"type":"Point"}
}