{
  "type": "Feature",
  "properties": {
    "gn:admin1_code":"14",
    "gn:asciiname":"Kapiso",
    "gn:country_code":"PG",
    "gn:dem":718,
    "gn:feature_class":"P",
    "gn:feature_code":"PPL",
    "gn:name":"Kapiso",
    "gn:population":0,
    "gn:timezone":"Pacific/Port_Moresby",
    "iso:country":"PG",
    "wof:name":"Kapiso",
    "wof:placetype":"locality"
},
  "geometry": {"coordinates":[147.11068,-7.85102],"type":"Point"}
}