{
  "type": "Feature",
  "properties": {
    "gn:admin1_code":"19",
    "gn:asciiname":"Waribim",
    "gn:country_code":"PG",
    "gn:dem":2424,
    "gn:feature_class":"P",
    "gn:feature_code":"PPL",
    "gn:name":"Waribim",
    "gn:population":0,
    "gn:timezone":"Pacific/Port_Moresby",
    "iso:country":"PG",
    "name:und_x_variant":[
        "Waribim Number 1",
        "Waribim"
    ],
    "wof:name":"Waribim",
    "wof:placetype":"locality"
},
  "geometry": {"coordinates":[143.44194999999999,-5.6576],"type":"Point"}
}