{
  "type": "Feature",
  "properties": {
    "gn:admin1_code":"14",
    "gn:asciiname":"Masa",
    "gn:country_code":"PG",
    "gn:dem":1606,
    "gn:feature_class":"P",
    "gn:feature_code":"PPL",
    "gn:name":"Masa",
    "gn:population":0,
    "gn:timezone":"Pacific/Port_Moresby",
    "iso:country":"PG",
    "name:fra_x_preferred":[
        "Masa"
    ],
    "name:kor_x_preferred":[
        "\ub9c8\uc0ac"
    ],
    "name:msa_x_preferred":[
        "Masa"
    ],
    "name:ukr_x_preferred":[
        "\u041c\u0430\u0441\u0430"
    ],
    "name:zho_x_preferred":[
        "\u9a6c\u8428"
    ],
    "wof:name":"Masa",
    "wof:placetype":"locality"
},
  "geometry": {"coordinates":[147.61482000000001,-6.35692],"type":"Point"}
}