{
  "type": "Feature",
  "properties": {
    "gn:admin1_code":"12",
    "gn:asciiname":"Yorki",
    "gn:country_code":"PG",
    "gn:dem":1791,
    "gn:feature_class":"P",
    "gn:feature_code":"PPL",
    "gn:name":"Yorki",
    "gn:population":0,
    "gn:timezone":"Pacific/Port_Moresby",
    "iso:country":"PG",
    "wof:name":"Yorki",
    "wof:placetype":"locality"
},
  "geometry": {"coordinates":[146.25887,-5.78413],"type":"Point"}
}