{
  "type": "Feature",
  "properties": {
    "gn:admin1_code":"11",
    "gn:asciiname":"Bien",
    "gn:country_code":"PG",
    "gn:dem":0,
    "gn:feature_class":"P",
    "gn:feature_code":"PPL",
    "gn:name":"Bien",
    "gn:population":0,
    "gn:timezone":"Pacific/Port_Moresby",
    "iso:country":"PG",
    "name:ceb_x_preferred":[
        "Bien"
    ],
    "name:deu_x_preferred":[
        "Bien"
    ],
    "name:fra_x_preferred":[
        "Bien"
    ],
    "name:spa_x_preferred":[
        "Bien"
    ],
    "name:swe_x_preferred":[
        "Bien"
    ],
    "name:und_x_variant":[
        "New Bien",
        "Bien"
    ],
    "wof:name":"Bien",
    "wof:placetype":"locality"
},
  "geometry": {"coordinates":[144.33521000000005,-3.98774],"type":"Point"}
}