{
  "type": "Feature",
  "properties": {
    "gn:admin1_code":"11",
    "gn:asciiname":"Tau",
    "gn:country_code":"PG",
    "gn:dem":225,
    "gn:feature_class":"P",
    "gn:feature_code":"PPL",
    "gn:name":"Tau",
    "gn:population":0,
    "gn:timezone":"Pacific/Port_Moresby",
    "iso:country":"PG",
    "wof:name":"Tau",
    "wof:placetype":"locality"
},
  "geometry": {"coordinates":[142.73333,-3.66667],"type":"Point"}
}