{
  "type": "Feature",
  "properties": {
    "gn:admin1_code":"03",
    "gn:asciiname":"Niha Niha",
    "gn:country_code":"PG",
    "gn:dem":13,
    "gn:feature_class":"P",
    "gn:feature_code":"PPL",
    "gn:name":"Niha Niha",
    "gn:population":0,
    "gn:timezone":"Pacific/Port_Moresby",
    "iso:country":"PG",
    "wof:name":"Niha Niha",
    "wof:placetype":"locality"
},
  "geometry": {"coordinates":[150.31666999999999,-10.35],"type":"Point"}
}