{
  "type": "Feature",
  "properties": {
    "gn:admin1_code":"11",
    "gn:asciiname":"Autogi",
    "gn:country_code":"PG",
    "gn:dem":382,
    "gn:feature_class":"P",
    "gn:feature_code":"PPL",
    "gn:name":"Autogi",
    "gn:population":0,
    "gn:timezone":"Pacific/Port_Moresby",
    "iso:country":"PG",
    "wof:name":"Autogi",
    "wof:placetype":"locality"
},
  "geometry": {"coordinates":[143.34582,-3.45304],"type":"Point"}
}