{
  "type": "Feature",
  "properties": {
    "gn:admin1_code":"10",
    "gn:asciiname":"Taranga",
    "gn:country_code":"PG",
    "gn:dem":133,
    "gn:feature_class":"P",
    "gn:feature_code":"PPL",
    "gn:name":"Taranga",
    "gn:population":0,
    "gn:timezone":"Pacific/Port_Moresby",
    "iso:country":"PG",
    "name:ceb_x_preferred":[
        "Taranga"
    ],
    "name:mai_x_preferred":[
        "\u0924\u0930\u0919\u094d\u0917\u093e"
    ],
    "name:new_x_preferred":[
        "\u0924\u093e\u0930\u093e\u0902\u0917\u093e"
    ],
    "wof:name":"Taranga",
    "wof:placetype":"locality"
},
  "geometry": {"coordinates":[152.11667,-4.23333],"type":"Point"}
}