{
  "type": "Feature",
  "properties": {
    "gn:admin1_code":"18",
    "gn:asciiname":"Sengi",
    "gn:country_code":"PG",
    "gn:dem":426,
    "gn:feature_class":"P",
    "gn:feature_code":"PPL",
    "gn:name":"Sengi",
    "gn:population":0,
    "gn:timezone":"Pacific/Port_Moresby",
    "iso:country":"PG",
    "wof:name":"Sengi",
    "wof:placetype":"locality"
},
  "geometry": {"coordinates":[142.49698000000001,-3.48527],"type":"Point"}
}