{
  "type": "Feature",
  "properties": {
    "gn:admin1_code":"14",
    "gn:asciiname":"Singor",
    "gn:country_code":"PG",
    "gn:dem":124,
    "gn:feature_class":"P",
    "gn:feature_code":"PPL",
    "gn:name":"Singor",
    "gn:population":0,
    "gn:timezone":"Pacific/Port_Moresby",
    "iso:country":"PG",
    "wof:name":"Singor",
    "wof:placetype":"locality"
},
  "geometry": {"coordinates":[147.08333000000005,-5.96667],"type":"Point"}
}