{
  "type": "Feature",
  "properties": {
    "gn:admin1_code":"08",
    "gn:asciiname":"Dirima",
    "gn:country_code":"PG",
    "gn:dem":1650,
    "gn:feature_class":"P",
    "gn:feature_code":"PPL",
    "gn:name":"Dirima",
    "gn:population":0,
    "gn:timezone":"Pacific/Port_Moresby",
    "iso:country":"PG",
    "wof:name":"Dirima",
    "wof:placetype":"locality"
},
  "geometry": {"coordinates":[144.91542999999999,-6.18863],"type":"Point"}
}