{
  "type": "Feature",
  "properties": {
    "gn:admin1_code":"03",
    "gn:asciiname":"Poralebalebara",
    "gn:country_code":"PG",
    "gn:dem":36,
    "gn:feature_class":"P",
    "gn:feature_code":"PPL",
    "gn:name":"Poralebalebara",
    "gn:population":0,
    "gn:timezone":"Pacific/Port_Moresby",
    "iso:country":"PG",
    "wof:name":"Poralebalebara",
    "wof:placetype":"locality"
},
  "geometry": {"coordinates":[149.93299999999999,-9.75],"type":"Point"}
}