{
  "type": "Feature",
  "properties": {
    "gn:admin1_code":"08",
    "gn:asciiname":"Aremaku",
    "gn:country_code":"PG",
    "gn:dem":2331,
    "gn:feature_class":"P",
    "gn:feature_code":"PPL",
    "gn:name":"Aremaku",
    "gn:population":0,
    "gn:timezone":"Pacific/Port_Moresby",
    "iso:country":"PG",
    "wof:name":"Aremaku",
    "wof:placetype":"locality"
},
  "geometry": {"coordinates":[145.18333000000001,-6.21667],"type":"Point"}
}