{
  "type": "Feature",
  "properties": {
    "gn:admin1_code":"01",
    "gn:asciiname":"Obo Mission",
    "gn:country_code":"PG",
    "gn:dem":11,
    "gn:feature_class":"P",
    "gn:feature_code":"PPL",
    "gn:name":"Obo Mission",
    "gn:population":0,
    "gn:timezone":"Pacific/Port_Moresby",
    "iso:country":"PG",
    "wof:name":"Obo Mission",
    "wof:placetype":"locality"
},
  "geometry": {"coordinates":[146.66464999999999,-9.03166],"type":"Point"}
}