{
  "type": "Feature",
  "properties": {
    "gn:admin1_code":"04",
    "gn:asciiname":"Niniure",
    "gn:country_code":"PG",
    "gn:dem":659,
    "gn:feature_class":"P",
    "gn:feature_code":"PPL",
    "gn:name":"Niniure",
    "gn:population":0,
    "gn:timezone":"Pacific/Port_Moresby",
    "iso:country":"PG",
    "wof:name":"Niniure",
    "wof:placetype":"locality"
},
  "geometry": {"coordinates":[148.40898000000001,-9.12118],"type":"Point"}
}