{
  "type": "Feature",
  "properties": {
    "gn:admin1_code":"15",
    "gn:asciiname":"Tutuila",
    "gn:country_code":"PG",
    "gn:dem":216,
    "gn:feature_class":"P",
    "gn:feature_code":"PPL",
    "gn:name":"Tutuila",
    "gn:population":0,
    "gn:timezone":"Pacific/Port_Moresby",
    "iso:country":"PG",
    "name:bel_x_preferred":[
        "\u0422\u0443\u0442\u0443\u0456\u043b\u0430"
    ],
    "name:ben_x_preferred":[
        "\u099f\u09c1\u099f\u09c1\u0987\u09b2\u09be"
    ],
    "name:cat_x_preferred":[
        "Tutuila"
    ],
    "name:ceb_x_preferred":[
        "Tutuila Island"
    ],
    "name:cym_x_preferred":[
        "Tutuila"
    ],
    "name:dan_x_preferred":[
        "Tutuila"
    ],
    "name:deu_x_preferred":[
        "Tutuila"
    ],
    "name:ell_x_preferred":[
        "\u03a4\u03bf\u03c5\u03c4\u03bf\u03c5\u03af\u03bb\u03b1"
    ],
    "name:fao_x_preferred":[
        "Tutuila"
    ],
    "name:fas_x_preferred":[
        "\u062a\u0648\u062a\u0648\u0626\u06cc\u0644\u0627"
    ],
    "name:fin_x_preferred":[
        "Tutuila"
    ],
    "name:fra_x_preferred":[
        "Tutuila"
    ],
    "name:glg_x_preferred":[
        "Tutuila"
    ],
    "name:hin_x_preferred":[
        "\u0924\u0941\u0924\u0941\u0907\u0932\u093e"
    ],
    "name:hun_x_preferred":[
        "Tutuila"
    ],
    "name:ind_x_preferred":[
        "Pulau Tutuila"
    ],
    "name:ita_x_preferred":[
        "Tutuila"
    ],
    "name:jpn_x_preferred":[
        "\u30c8\u30a5\u30c8\u30a5\u30a4\u30e9\u5cf6"
    ],
    "name:kat_x_preferred":[
        "\u10e2\u10e3\u10e2\u10e3\u10d8\u10da\u10d0"
    ],
    "name:kor_x_preferred":[
        "\ud22c\ud22c\uc77c\ub77c"
    ],
    "name:lat_x_preferred":[
        "Tutuila"
    ],
    "name:lit_x_preferred":[
        "Tutuila"
    ],
    "name:mal_x_preferred":[
        "\u0d1f\u0d42\u0d1f\u0d42\u0d08\u0d32"
    ],
    "name:nld_x_preferred":[
        "Tutuila"
    ],
    "name:pol_x_preferred":[
        "Tutuila"
    ],
    "name:por_x_preferred":[
        "Tutuila"
    ],
    "name:rus_x_preferred":[
        "\u0422\u0443\u0442\u0443\u0438\u043b\u0430"
    ],
    "name:slk_x_preferred":[
        "Tutuila"
    ],
    "name:smo_x_preferred":[
        "Tutuila"
    ],
    "name:spa_x_preferred":[
        "Tutuila"
    ],
    "name:srp_x_preferred":[
        "\u0422\u0443\u0442\u0443\u0438\u043b\u0430"
    ],
    "name:swe_x_preferred":[
        "Tutuila"
    ],
    "name:tha_x_preferred":[
        "\u0e15\u0e39\u0e15\u0e39\u0e27\u0e35\u0e25\u0e32"
    ],
    "name:ukr_x_preferred":[
        "\u0422\u0443\u0442\u0443\u0439\u043b\u0430"
    ],
    "name:urd_x_preferred":[
        "\u0679\u0648\u0679\u0648\u06cc\u0644\u0627"
    ],
    "name:vie_x_preferred":[
        "Tutuila"
    ],
    "name:zho_x_preferred":[
        "\u56fe\u56fe\u4f0a\u62c9\u5c9b"
    ],
    "wof:name":"Tutuila",
    "wof:placetype":"locality"
},
  "geometry": {"coordinates":[150.09999999999999,-2.55],"type":"Point"}
}