{
  "type": "Feature",
  "properties": {
    "gn:admin1_code":"15",
    "gn:asciiname":"Tutuila",
    "gn:country_code":"PG",
    "gn:dem":216,
    "gn:feature_class":"P",
    "gn:feature_code":"PPL",
    "gn:name":"Tutuila",
    "gn:population":0,
    "gn:timezone":"Pacific/Port_Moresby",
    "iso:country":"PG",
    "wof:name":"Tutuila",
    "wof:placetype":"locality"
},
  "geometry": {"coordinates":[150.09999999999999,-2.55],"type":"Point"}
}