{
  "type": "Feature",
  "properties": {
    "gn:admin1_code":"12",
    "gn:asciiname":"Musak",
    "gn:country_code":"PG",
    "gn:dem":151,
    "gn:feature_class":"P",
    "gn:feature_code":"PPL",
    "gn:name":"Musak",
    "gn:population":0,
    "gn:timezone":"Pacific/Port_Moresby",
    "iso:country":"PG",
    "wof:name":"Musak",
    "wof:placetype":"locality"
},
  "geometry": {"coordinates":[145.25184999999999,-5.30512],"type":"Point"}
}