{
  "type": "Feature",
  "properties": {
    "gn:admin1_code":"18",
    "gn:asciiname":"Miriyami",
    "gn:country_code":"PG",
    "gn:dem":50,
    "gn:feature_class":"P",
    "gn:feature_code":"PPL",
    "gn:name":"Miriyami",
    "gn:population":0,
    "gn:timezone":"Pacific/Port_Moresby",
    "iso:country":"PG",
    "wof:name":"Miriyami",
    "wof:placetype":"locality"
},
  "geometry": {"coordinates":[141.75,-3.95],"type":"Point"}
}