{
  "type": "Feature",
  "properties": {
    "gn:admin1_code":"14",
    "gn:asciiname":"Kaurau",
    "gn:country_code":"PG",
    "gn:dem":1541,
    "gn:feature_class":"P",
    "gn:feature_code":"PPL",
    "gn:name":"Kaurau",
    "gn:population":0,
    "gn:timezone":"Pacific/Port_Moresby",
    "iso:country":"PG",
    "wof:name":"Kaurau",
    "wof:placetype":"locality"
},
  "geometry": {"coordinates":[146.92696999999995,-7.73381],"type":"Point"}
}