{
  "type": "Feature",
  "properties": {
    "gn:admin1_code":"18",
    "gn:asciiname":"Kongon",
    "gn:country_code":"PG",
    "gn:dem":1212,
    "gn:feature_class":"P",
    "gn:feature_code":"PPL",
    "gn:name":"Kongon",
    "gn:population":0,
    "gn:timezone":"Pacific/Port_Moresby",
    "iso:country":"PG",
    "wof:name":"Kongon",
    "wof:placetype":"locality"
},
  "geometry": {"coordinates":[141.15000000000001,-4.83333],"type":"Point"}
}