{
  "type": "Feature",
  "properties": {
    "gn:admin1_code":"06",
    "gn:asciiname":"Kadir",
    "gn:country_code":"PG",
    "gn:dem":58,
    "gn:feature_class":"P",
    "gn:feature_code":"PPL",
    "gn:name":"Kadir",
    "gn:population":0,
    "gn:timezone":"Pacific/Port_Moresby",
    "iso:country":"PG",
    "wof:name":"Kadir",
    "wof:placetype":"locality"
},
  "geometry": {"coordinates":[142.29506999999995,-8.61556],"type":"Point"}
}