{
  "type": "Feature",
  "properties": {
    "gn:admin1_code":"18",
    "gn:asciiname":"Yerisi",
    "gn:country_code":"PG",
    "gn:dem":345,
    "gn:feature_class":"P",
    "gn:feature_code":"PPL",
    "gn:name":"Yerisi",
    "gn:population":0,
    "gn:timezone":"Pacific/Port_Moresby",
    "iso:country":"PG",
    "wof:name":"Yerisi",
    "wof:placetype":"locality"
},
  "geometry": {"coordinates":[142.31614999999999,-3.52692],"type":"Point"}
}