{
  "type": "Feature",
  "properties": {
    "gn:admin1_code":"08",
    "gn:asciiname":"Wairo",
    "gn:country_code":"PG",
    "gn:dem":1138,
    "gn:feature_class":"P",
    "gn:feature_code":"PPL",
    "gn:name":"Wairo",
    "gn:population":0,
    "gn:timezone":"Pacific/Port_Moresby",
    "iso:country":"PG",
    "wof:name":"Wairo",
    "wof:placetype":"locality"
},
  "geometry": {"coordinates":[144.84638000000001,-6.5454],"type":"Point"}
}