{
  "type": "Feature",
  "properties": {
    "gn:admin1_code":"01",
    "gn:asciiname":"Belavista",
    "gn:country_code":"PG",
    "gn:dem":1464,
    "gn:feature_class":"P",
    "gn:feature_code":"PPL",
    "gn:name":"Belavista",
    "gn:population":0,
    "gn:timezone":"Pacific/Port_Moresby",
    "iso:country":"PG",
    "wof:name":"Belavista",
    "wof:placetype":"locality"
},
  "geometry": {"coordinates":[147.06108999999995,-8.53431],"type":"Point"}
}