{
  "type": "Feature",
  "properties": {
    "gn:admin1_code":"11",
    "gn:asciiname":"Kaiwaria",
    "gn:country_code":"PG",
    "gn:dem":30,
    "gn:feature_class":"P",
    "gn:feature_code":"PPL",
    "gn:name":"Kaiwaria",
    "gn:population":0,
    "gn:timezone":"Pacific/Port_Moresby",
    "iso:country":"PG",
    "wof:name":"Kaiwaria",
    "wof:placetype":"locality"
},
  "geometry": {"coordinates":[143.65173999999999,-4.43243],"type":"Point"}
}