{
  "type": "Feature",
  "properties": {
    "gn:admin1_code":"09",
    "gn:asciiname":"Tombendaka",
    "gn:country_code":"PG",
    "gn:dem":1391,
    "gn:feature_class":"P",
    "gn:feature_code":"PPL",
    "gn:name":"Tombendaka",
    "gn:population":0,
    "gn:timezone":"Pacific/Port_Moresby",
    "iso:country":"PG",
    "wof:name":"Tombendaka",
    "wof:placetype":"locality"
},
  "geometry": {"coordinates":[146.05552,-6.33411],"type":"Point"}
}