{
  "type": "Feature",
  "properties": {
    "gn:admin1_code":"09",
    "gn:asciiname":"Aruwini",
    "gn:country_code":"PG",
    "gn:dem":1399,
    "gn:feature_class":"P",
    "gn:feature_code":"PPL",
    "gn:name":"Aruwini",
    "gn:population":0,
    "gn:timezone":"Pacific/Port_Moresby",
    "iso:country":"PG",
    "wof:name":"Aruwini",
    "wof:placetype":"locality"
},
  "geometry": {"coordinates":[145.85646,-6.74273],"type":"Point"}
}