{
  "type": "Feature",
  "properties": {
    "gn:admin1_code":"12",
    "gn:asciiname":"Toto",
    "gn:country_code":"PG",
    "gn:dem":18,
    "gn:feature_class":"P",
    "gn:feature_code":"PPL",
    "gn:name":"Toto",
    "gn:population":0,
    "gn:timezone":"Pacific/Port_Moresby",
    "iso:country":"PG",
    "name:bul_x_preferred":[
        "\u0422\u043e\u0442\u043e"
    ],
    "name:ceb_x_preferred":[
        "Toto"
    ],
    "name:deu_x_preferred":[
        "Toto"
    ],
    "name:fin_x_preferred":[
        "Toto"
    ],
    "name:fra_x_preferred":[
        "Toto"
    ],
    "name:heb_x_preferred":[
        "\u05d8\u05d5\u05d8\u05d5"
    ],
    "name:hrv_x_preferred":[
        "Toto"
    ],
    "name:hun_x_preferred":[
        "Toto"
    ],
    "name:ind_x_preferred":[
        "Toto"
    ],
    "name:ita_x_preferred":[
        "Toto"
    ],
    "name:nds_x_preferred":[
        "Toto"
    ],
    "name:nld_x_preferred":[
        "Toto"
    ],
    "name:pol_x_preferred":[
        "Toto"
    ],
    "name:por_x_preferred":[
        "Toto"
    ],
    "name:rus_x_preferred":[
        "Toto"
    ],
    "name:slk_x_preferred":[
        "Toto"
    ],
    "name:swe_x_preferred":[
        "Toto"
    ],
    "name:tur_x_preferred":[
        "Toto"
    ],
    "name:ukr_x_preferred":[
        "\u0422\u043e\u0442\u043e"
    ],
    "wof:name":"Toto",
    "wof:placetype":"locality"
},
  "geometry": {"coordinates":[145.42129,-4.48362],"type":"Point"}
}