{
  "type": "Feature",
  "properties": {
    "gn:admin1_code":"12",
    "gn:asciiname":"Toto",
    "gn:country_code":"PG",
    "gn:dem":18,
    "gn:feature_class":"P",
    "gn:feature_code":"PPL",
    "gn:name":"Toto",
    "gn:population":0,
    "gn:timezone":"Pacific/Port_Moresby",
    "iso:country":"PG",
    "wof:name":"Toto",
    "wof:placetype":"locality"
},
  "geometry": {"coordinates":[145.42129,-4.48362],"type":"Point"}
}