{
  "type": "Feature",
  "properties": {
    "gn:admin1_code":"15",
    "gn:asciiname":"Kabunut",
    "gn:cc2":"PG",
    "gn:country_code":"PG",
    "gn:dem":153,
    "gn:feature_class":"P",
    "gn:feature_code":"PPL",
    "gn:name":"Kabunut",
    "gn:population":0,
    "gn:timezone":"Pacific/Port_Moresby",
    "iso:country":"PG",
    "name:und_x_variant":[
        "Kabanut",
        "Kabunut"
    ],
    "wof:name":"Kabunut",
    "wof:placetype":"locality"
},
  "geometry": {"coordinates":[152.48133000000001,-3.84173],"type":"Point"}
}