{
  "type": "Feature",
  "properties": {
    "gn:admin1_code":"11",
    "gn:asciiname":"Boram",
    "gn:country_code":"PG",
    "gn:dem":3,
    "gn:feature_class":"P",
    "gn:feature_code":"PPL",
    "gn:name":"Boram",
    "gn:population":0,
    "gn:timezone":"Pacific/Port_Moresby",
    "iso:country":"PG",
    "wof:name":"Boram",
    "wof:placetype":"locality"
},
  "geometry": {"coordinates":[143.66345999999999,-3.58164],"type":"Point"}
}