{
  "type": "Feature",
  "properties": {
    "gn:admin1_code":"11",
    "gn:asciiname":"Wabindumga Villages",
    "gn:country_code":"PG",
    "gn:dem":106,
    "gn:feature_class":"P",
    "gn:feature_code":"PPL",
    "gn:name":"Wabindumga Villages",
    "gn:population":0,
    "gn:timezone":"Pacific/Port_Moresby",
    "iso:country":"PG",
    "name:und_x_variant":[
        "Wabindumakag",
        "Wabindumga Villages"
    ],
    "wof:name":"Wabindumga Villages",
    "wof:placetype":"locality"
},
  "geometry": {"coordinates":[142.91804999999999,-3.78472],"type":"Point"}
}