{
  "type": "Feature",
  "properties": {
    "gn:admin1_code":"15",
    "gn:asciiname":"Dahana",
    "gn:country_code":"PG",
    "gn:dem":82,
    "gn:feature_class":"P",
    "gn:feature_code":"PPL",
    "gn:name":"Dahana",
    "gn:population":0,
    "gn:timezone":"Pacific/Port_Moresby",
    "iso:country":"PG",
    "name:ceb_x_preferred":[
        "Dahana"
    ],
    "name:ind_x_preferred":[
        "Dahana"
    ],
    "name:jav_x_preferred":[
        "Dahana"
    ],
    "name:nld_x_preferred":[
        "Dahana"
    ],
    "name:swe_x_preferred":[
        "Dahana"
    ],
    "name:tgk_x_preferred":[
        "\u0414\u0430\u04b3\u0430\u043d\u0430"
    ],
    "wof:name":"Dahana",
    "wof:placetype":"locality"
},
  "geometry": {"coordinates":[152.38333,-3.61667],"type":"Point"}
}