{
  "type": "Feature",
  "properties": {
    "gn:admin1_code":"12",
    "gn:asciiname":"Beire",
    "gn:country_code":"PG",
    "gn:dem":504,
    "gn:feature_class":"P",
    "gn:feature_code":"PPL",
    "gn:name":"Beire",
    "gn:population":0,
    "gn:timezone":"Pacific/Port_Moresby",
    "iso:country":"PG",
    "wof:name":"Beire",
    "wof:placetype":"locality"
},
  "geometry": {"coordinates":[145.40214,-5.43402],"type":"Point"}
}