{
  "type": "Feature",
  "properties": {
    "gn:admin1_code":"12",
    "gn:asciiname":"Beire",
    "gn:country_code":"PG",
    "gn:dem":504,
    "gn:feature_class":"P",
    "gn:feature_code":"PPL",
    "gn:name":"Beire",
    "gn:population":0,
    "gn:timezone":"Pacific/Port_Moresby",
    "iso:country":"PG",
    "name:arg_x_preferred":[
        "Beire"
    ],
    "name:ast_x_preferred":[
        "Beire"
    ],
    "name:bre_x_preferred":[
        "Beire"
    ],
    "name:cat_x_preferred":[
        "Beire"
    ],
    "name:ceb_x_preferred":[
        "Beire"
    ],
    "name:deu_x_preferred":[
        "Beire"
    ],
    "name:eus_x_preferred":[
        "Beire"
    ],
    "name:fra_x_preferred":[
        "Beire"
    ],
    "name:hun_x_preferred":[
        "Beire"
    ],
    "name:ita_x_preferred":[
        "Beire"
    ],
    "name:kaz_x_preferred":[
        "\u0411\u0435\u0439\u0440\u0435"
    ],
    "name:msa_x_preferred":[
        "Beire"
    ],
    "name:nld_x_preferred":[
        "Beire"
    ],
    "name:oci_x_preferred":[
        "Beire"
    ],
    "name:pol_x_preferred":[
        "Beire"
    ],
    "name:por_x_preferred":[
        "Beire"
    ],
    "name:rus_x_preferred":[
        "\u0411\u0435\u0439\u0440\u0435"
    ],
    "name:spa_x_preferred":[
        "Beire"
    ],
    "name:swe_x_preferred":[
        "Beire"
    ],
    "name:ukr_x_preferred":[
        "\u0411\u0435\u0439\u0440\u0435"
    ],
    "name:uzb_x_preferred":[
        "Beire"
    ],
    "name:vie_x_preferred":[
        "Beire"
    ],
    "name:war_x_preferred":[
        "Beire"
    ],
    "wof:name":"Beire",
    "wof:placetype":"locality"
},
  "geometry": {"coordinates":[145.40214,-5.43402],"type":"Point"}
}