{
  "type": "Feature",
  "properties": {
    "gn:admin1_code":"04",
    "gn:asciiname":"Ajeka",
    "gn:country_code":"PG",
    "gn:dem":149,
    "gn:feature_class":"P",
    "gn:feature_code":"PPL",
    "gn:name":"Ajeka",
    "gn:population":0,
    "gn:timezone":"Pacific/Port_Moresby",
    "iso:country":"PG",
    "wof:name":"Ajeka",
    "wof:placetype":"locality"
},
  "geometry": {"coordinates":[147.98613,-8.89679],"type":"Point"}
}