{
  "type": "Feature",
  "properties": {
    "gn:admin1_code":"14",
    "gn:asciiname":"Danatum",
    "gn:country_code":"PG",
    "gn:dem":2347,
    "gn:feature_class":"P",
    "gn:feature_code":"PPL",
    "gn:name":"Danatum",
    "gn:population":0,
    "gn:timezone":"Pacific/Port_Moresby",
    "iso:country":"PG",
    "wof:name":"Danatum",
    "wof:placetype":"locality"
},
  "geometry": {"coordinates":[146.66808999999995,-5.9688],"type":"Point"}
}