{
  "type": "Feature",
  "properties": {
    "gn:admin1_code":"10",
    "gn:asciiname":"Davaon",
    "gn:country_code":"PG",
    "gn:dem":191,
    "gn:feature_class":"P",
    "gn:feature_code":"PPL",
    "gn:name":"Davaon",
    "gn:population":0,
    "gn:timezone":"Pacific/Port_Moresby",
    "iso:country":"PG",
    "wof:name":"Davaon",
    "wof:placetype":"locality"
},
  "geometry": {"coordinates":[152.18333000000001,-4.31667],"type":"Point"}
}