{
  "type": "Feature",
  "properties": {
    "gn:admin1_code":"08",
    "gn:asciiname":"Kua",
    "gn:country_code":"PG",
    "gn:dem":1764,
    "gn:feature_class":"P",
    "gn:feature_code":"PPL",
    "gn:name":"Kua",
    "gn:population":0,
    "gn:timezone":"Pacific/Port_Moresby",
    "iso:country":"PG",
    "wof:name":"Kua",
    "wof:placetype":"locality"
},
  "geometry": {"coordinates":[144.84999999999999,-6.15],"type":"Point"}
}