{
  "type": "Feature",
  "properties": {
    "gn:admin1_code":"12",
    "gn:asciiname":"Waba",
    "gn:country_code":"PG",
    "gn:dem":73,
    "gn:feature_class":"P",
    "gn:feature_code":"PPL",
    "gn:name":"Waba",
    "gn:population":0,
    "gn:timezone":"Pacific/Port_Moresby",
    "iso:country":"PG",
    "wof:name":"Waba",
    "wof:placetype":"locality"
},
  "geometry": {"coordinates":[145.30000000000001,-4.48333],"type":"Point"}
}