{
  "type": "Feature",
  "properties": {
    "gn:admin1_code":"05",
    "gn:asciiname":"Dol",
    "gn:country_code":"PG",
    "gn:dem":1998,
    "gn:feature_class":"P",
    "gn:feature_code":"PPL",
    "gn:name":"Dol",
    "gn:population":0,
    "gn:timezone":"Pacific/Port_Moresby",
    "iso:country":"PG",
    "name:aze_x_preferred":[
        "Dol"
    ],
    "name:bos_x_preferred":[
        "Dol"
    ],
    "name:ceb_x_preferred":[
        "Dol"
    ],
    "name:ces_x_preferred":[
        "Dol"
    ],
    "name:deu_x_preferred":[
        "Dol"
    ],
    "name:fra_x_preferred":[
        "Dol"
    ],
    "name:hrv_x_preferred":[
        "Dol"
    ],
    "name:hun_x_preferred":[
        "Dol"
    ],
    "name:nld_x_preferred":[
        "Dol"
    ],
    "name:pol_x_preferred":[
        "Dol"
    ],
    "name:rus_x_preferred":[
        "\u0414\u043e\u043b"
    ],
    "name:slk_x_preferred":[
        "Dol"
    ],
    "name:slv_x_preferred":[
        "Dol"
    ],
    "name:srp_x_preferred":[
        "\u0414\u043e\u043b"
    ],
    "name:swe_x_preferred":[
        "Dol"
    ],
    "name:ukr_x_preferred":[
        "\u0414\u043e\u043b"
    ],
    "wof:name":"Dol",
    "wof:placetype":"locality"
},
  "geometry": {"coordinates":[143.65000000000001,-6.03333],"type":"Point"}
}