{
  "type": "Feature",
  "properties": {
    "gn:admin1_code":"18",
    "gn:asciiname":"Charok",
    "gn:country_code":"PG",
    "gn:dem":651,
    "gn:feature_class":"P",
    "gn:feature_code":"PPL",
    "gn:name":"Charok",
    "gn:population":0,
    "gn:timezone":"Pacific/Port_Moresby",
    "iso:country":"PG",
    "wof:name":"Charok",
    "wof:placetype":"locality"
},
  "geometry": {"coordinates":[142.84999999999999,-3.38333],"type":"Point"}
}