{
  "type": "Feature",
  "properties": {
    "gn:admin1_code":"14",
    "gn:asciiname":"Tunge",
    "gn:country_code":"PG",
    "gn:dem":649,
    "gn:feature_class":"P",
    "gn:feature_code":"PPL",
    "gn:name":"Tunge",
    "gn:population":0,
    "gn:timezone":"Pacific/Port_Moresby",
    "iso:country":"PG",
    "name:und_x_variant":[
        "Tunga",
        "Tunge"
    ],
    "wof:name":"Tunge",
    "wof:placetype":"locality"
},
  "geometry": {"coordinates":[147.61841999999999,-6.18073],"type":"Point"}
}