{
  "type": "Feature",
  "properties": {
    "gn:admin1_code":"15",
    "gn:asciiname":"Pakawala",
    "gn:country_code":"PG",
    "gn:dem":15,
    "gn:feature_class":"P",
    "gn:feature_code":"PPL",
    "gn:name":"Pakawala",
    "gn:population":0,
    "gn:timezone":"Pacific/Port_Moresby",
    "iso:country":"PG",
    "wof:name":"Pakawala",
    "wof:placetype":"locality"
},
  "geometry": {"coordinates":[151.43274,-2.92461],"type":"Point"}
}