{
  "type": "Feature",
  "properties": {
    "gn:admin1_code":"18",
    "gn:asciiname":"Yadagaro",
    "gn:country_code":"PG",
    "gn:dem":331,
    "gn:feature_class":"P",
    "gn:feature_code":"PPL",
    "gn:name":"Yadagaro",
    "gn:population":0,
    "gn:timezone":"Pacific/Port_Moresby",
    "iso:country":"PG",
    "name:und_x_variant":[
        "Yadagoro",
        "Yadagaro"
    ],
    "wof:name":"Yadagaro",
    "wof:placetype":"locality"
},
  "geometry": {"coordinates":[142.54798,-3.51367],"type":"Point"}
}