{
  "type": "Feature",
  "properties": {
    "gn:admin1_code":"12",
    "gn:asciiname":"Butelkud",
    "gn:country_code":"PG",
    "gn:dem":154,
    "gn:feature_class":"P",
    "gn:feature_code":"PPL",
    "gn:name":"Butelkud",
    "gn:population":0,
    "gn:timezone":"Pacific/Port_Moresby",
    "iso:country":"PG",
    "wof:name":"Butelkud",
    "wof:placetype":"locality"
},
  "geometry": {"coordinates":[145.74937,-5.14726],"type":"Point"}
}