{
  "type": "Feature",
  "properties": {
    "gn:admin1_code":"01",
    "gn:asciiname":"Mave",
    "gn:country_code":"PG",
    "gn:dem":1532,
    "gn:feature_class":"P",
    "gn:feature_code":"PPL",
    "gn:name":"Mave",
    "gn:population":0,
    "gn:timezone":"Pacific/Port_Moresby",
    "iso:country":"PG",
    "wof:name":"Mave",
    "wof:placetype":"locality"
},
  "geometry": {"coordinates":[147.13333,-8.56667],"type":"Point"}
}