{
  "type": "Feature",
  "properties": {
    "gn:admin1_code":"14",
    "gn:asciiname":"Atsunas",
    "gn:country_code":"PG",
    "gn:dem":411,
    "gn:feature_class":"P",
    "gn:feature_code":"PPL",
    "gn:name":"Atsunas",
    "gn:population":0,
    "gn:timezone":"Pacific/Port_Moresby",
    "iso:country":"PG",
    "name:und_x_variant":[
        "Atsonas",
        "Atsunas"
    ],
    "wof:name":"Atsunas",
    "wof:placetype":"locality"
},
  "geometry": {"coordinates":[146.11127999999999,-6.14004],"type":"Point"}
}