{
  "type": "Feature",
  "properties": {
    "gn:admin1_code":"03",
    "gn:asciiname":"Waeme",
    "gn:country_code":"PG",
    "gn:dem":386,
    "gn:feature_class":"P",
    "gn:feature_code":"PPL",
    "gn:name":"Waeme",
    "gn:population":0,
    "gn:timezone":"Pacific/Port_Moresby",
    "iso:country":"PG",
    "wof:name":"Waeme",
    "wof:placetype":"locality"
},
  "geometry": {"coordinates":[150.55000000000001,-10.31667],"type":"Point"}
}