{
  "type": "Feature",
  "properties": {
    "gn:admin1_code":"02",
    "gn:asciiname":"Koropai'iu",
    "gn:country_code":"PG",
    "gn:dem":80,
    "gn:feature_class":"P",
    "gn:feature_code":"PPL",
    "gn:name":"Koropai\u2019iu",
    "gn:population":0,
    "gn:timezone":"Pacific/Port_Moresby",
    "iso:country":"PG",
    "wof:name":"Koropai'iu",
    "wof:placetype":"locality"
},
  "geometry": {"coordinates":[143.59999999999999,-6.88333],"type":"Point"}
}