{
  "type": "Feature",
  "properties": {
    "gn:admin1_code":"17",
    "gn:asciiname":"Kokopo",
    "gn:country_code":"PG",
    "gn:dem":35,
    "gn:feature_class":"P",
    "gn:feature_code":"PPL",
    "gn:name":"Kokopo",
    "gn:population":0,
    "gn:timezone":"Pacific/Port_Moresby",
    "iso:country":"PG",
    "name:bre_x_preferred":[
        "Kokopo"
    ],
    "name:ceb_x_preferred":[
        "Kokopo"
    ],
    "name:deu_x_preferred":[
        "Kokopo"
    ],
    "name:est_x_preferred":[
        "Kokopo"
    ],
    "name:fas_x_preferred":[
        "\u06a9\u0648\u06a9\u0648\u067e\u0648"
    ],
    "name:fra_x_preferred":[
        "Kokopo"
    ],
    "name:glg_x_preferred":[
        "Kokopo"
    ],
    "name:heb_x_preferred":[
        "\u05e7\u05d5\u05e7\u05d5\u05e4\u05d5"
    ],
    "name:ita_x_preferred":[
        "Kokopo"
    ],
    "name:jpn_x_preferred":[
        "\u30b3\u30b3\u30dd"
    ],
    "name:kor_x_preferred":[
        "\ucf54\ucf54\ud3ec"
    ],
    "name:nld_x_preferred":[
        "Kokopo"
    ],
    "name:pol_x_preferred":[
        "Kokopo"
    ],
    "name:por_x_preferred":[
        "Kokopo"
    ],
    "name:rus_x_preferred":[
        "\u041a\u043e\u043a\u043e\u043f\u043e"
    ],
    "name:swe_x_preferred":[
        "Kokopo"
    ],
    "name:tpi_x_preferred":[
        "Kokopo"
    ],
    "name:und_x_variant":[
        "Warien",
        "Kokopo"
    ],
    "name:urd_x_preferred":[
        "\u06a9\u0648\u06a9\u0648\u067e\u0648"
    ],
    "name:zho_x_preferred":[
        "\u79d1\u53ef\u6ce2"
    ],
    "wof:name":"Kokopo",
    "wof:placetype":"locality"
},
  "geometry": {"coordinates":[148.67403000000004,-5.48959],"type":"Point"}
}