{
  "type": "Feature",
  "properties": {
    "gn:admin1_code":"17",
    "gn:asciiname":"Kokopo",
    "gn:country_code":"PG",
    "gn:dem":35,
    "gn:feature_class":"P",
    "gn:feature_code":"PPL",
    "gn:name":"Kokopo",
    "gn:population":0,
    "gn:timezone":"Pacific/Port_Moresby",
    "iso:country":"PG",
    "name:und_x_variant":[
        "Warien",
        "Kokopo"
    ],
    "wof:name":"Kokopo",
    "wof:placetype":"locality"
},
  "geometry": {"coordinates":[148.67403000000004,-5.48959],"type":"Point"}
}