{
  "type": "Feature",
  "properties": {
    "gn:admin1_code":"19",
    "gn:asciiname":"Torenam",
    "gn:country_code":"PG",
    "gn:dem":2337,
    "gn:feature_class":"P",
    "gn:feature_code":"PPL",
    "gn:name":"Torenam",
    "gn:population":0,
    "gn:timezone":"Pacific/Port_Moresby",
    "iso:country":"PG",
    "wof:name":"Torenam",
    "wof:placetype":"locality"
},
  "geometry": {"coordinates":[143.42854,-5.37582],"type":"Point"}
}