{
  "type": "Feature",
  "properties": {
    "gn:admin1_code":"10",
    "gn:asciiname":"Awungi",
    "gn:country_code":"PG",
    "gn:dem":493,
    "gn:feature_class":"P",
    "gn:feature_code":"PPL",
    "gn:name":"Awungi",
    "gn:population":0,
    "gn:timezone":"Pacific/Port_Moresby",
    "iso:country":"PG",
    "wof:name":"Awungi",
    "wof:placetype":"locality"
},
  "geometry": {"coordinates":[151.81666999999999,-4.78333],"type":"Point"}
}