{
  "type": "Feature",
  "properties": {
    "gn:admin1_code":"14",
    "gn:asciiname":"Lama",
    "gn:country_code":"PG",
    "gn:dem":1846,
    "gn:feature_class":"P",
    "gn:feature_code":"PPL",
    "gn:name":"Lama",
    "gn:population":0,
    "gn:timezone":"Pacific/Port_Moresby",
    "iso:country":"PG",
    "wof:name":"Lama",
    "wof:placetype":"locality"
},
  "geometry": {"coordinates":[147.23157,-6.26323],"type":"Point"}
}