{
  "type": "Feature",
  "properties": {
    "gn:admin1_code":"07",
    "gn:asciiname":"Monoitu",
    "gn:country_code":"PG",
    "gn:dem":68,
    "gn:feature_class":"P",
    "gn:feature_code":"PPL",
    "gn:name":"Monoitu",
    "gn:population":0,
    "gn:timezone":"Pacific/Bougainville",
    "iso:country":"PG",
    "wof:name":"Monoitu",
    "wof:placetype":"locality"
},
  "geometry": {"coordinates":[155.44166999999999,-6.68889],"type":"Point"}
}