{
  "type": "Feature",
  "properties": {
    "gn:admin1_code":"09",
    "gn:asciiname":"Awande",
    "gn:country_code":"PG",
    "gn:dem":1812,
    "gn:feature_class":"P",
    "gn:feature_code":"PPL",
    "gn:name":"Awande",
    "gn:population":0,
    "gn:timezone":"Pacific/Port_Moresby",
    "iso:country":"PG",
    "wof:name":"Awande",
    "wof:placetype":"locality"
},
  "geometry": {"coordinates":[145.5702,-6.51536],"type":"Point"}
}