{
  "type": "Feature",
  "properties": {
    "gn:admin1_code":"11",
    "gn:asciiname":"Selni",
    "gn:cc2":"PG",
    "gn:country_code":"PG",
    "gn:dem":300,
    "gn:feature_class":"P",
    "gn:feature_code":"PPL",
    "gn:name":"Selni",
    "gn:population":0,
    "gn:timezone":"Pacific/Port_Moresby",
    "iso:country":"PG",
    "name:und_x_variant":[
        "New Selni",
        "Selni"
    ],
    "wof:name":"Selni",
    "wof:placetype":"locality"
},
  "geometry": {"coordinates":[142.86667,-3.53333],"type":"Point"}
}