{
  "type": "Feature",
  "properties": {
    "gn:admin1_code":"04",
    "gn:asciiname":"Senani",
    "gn:country_code":"PG",
    "gn:dem":21,
    "gn:feature_class":"P",
    "gn:feature_code":"PPL",
    "gn:name":"Senani",
    "gn:population":0,
    "gn:timezone":"Pacific/Port_Moresby",
    "iso:country":"PG",
    "wof:name":"Senani",
    "wof:placetype":"locality"
},
  "geometry": {"coordinates":[148.19999999999999,-8.61667],"type":"Point"}
}