{
  "type": "Feature",
  "properties": {
    "gn:admin1_code":"10",
    "gn:asciiname":"Marmar",
    "gn:cc2":"PG",
    "gn:country_code":"PG",
    "gn:dem":155,
    "gn:feature_class":"P",
    "gn:feature_code":"PPL",
    "gn:name":"Marmar",
    "gn:population":0,
    "gn:timezone":"Pacific/Port_Moresby",
    "iso:country":"PG",
    "name:und_x_variant":[
        "Maramar",
        "Marmar"
    ],
    "wof:name":"Marmar",
    "wof:placetype":"locality"
},
  "geometry": {"coordinates":[152.33333000000005,-4.45],"type":"Point"}
}