{
  "type": "Feature",
  "properties": {
    "gn:admin1_code":"14",
    "gn:asciiname":"Lalang",
    "gn:country_code":"PG",
    "gn:dem":1237,
    "gn:feature_class":"P",
    "gn:feature_code":"PPL",
    "gn:name":"Lalang",
    "gn:population":0,
    "gn:timezone":"Pacific/Port_Moresby",
    "iso:country":"PG",
    "wof:name":"Lalang",
    "wof:placetype":"locality"
},
  "geometry": {"coordinates":[147.43333000000001,-6.36667],"type":"Point"}
}