{
  "type": "Feature",
  "properties": {
    "gn:admin1_code":"05",
    "gn:asciiname":"Kogoga",
    "gn:country_code":"PG",
    "gn:dem":2039,
    "gn:feature_class":"P",
    "gn:feature_code":"PPL",
    "gn:name":"Kogoga",
    "gn:population":0,
    "gn:timezone":"Pacific/Port_Moresby",
    "iso:country":"PG",
    "wof:name":"Kogoga",
    "wof:placetype":"locality"
},
  "geometry": {"coordinates":[144.00269,-6.27262],"type":"Point"}
}