{
  "type": "Feature",
  "properties": {
    "gn:admin1_code":"14",
    "gn:asciiname":"Nariawang",
    "gn:country_code":"PG",
    "gn:dem":672,
    "gn:feature_class":"P",
    "gn:feature_code":"PPL",
    "gn:name":"Nariawang",
    "gn:population":0,
    "gn:timezone":"Pacific/Port_Moresby",
    "iso:country":"PG",
    "wof:name":"Nariawang",
    "wof:placetype":"locality"
},
  "geometry": {"coordinates":[146.48333,-6.38333],"type":"Point"}
}