{
  "type": "Feature",
  "properties": {
    "gn:admin1_code":"02",
    "gn:asciiname":"Arehava Number 1",
    "gn:country_code":"PG",
    "gn:dem":16,
    "gn:feature_class":"P",
    "gn:feature_code":"PPL",
    "gn:name":"Arehava Number 1",
    "gn:population":0,
    "gn:timezone":"Pacific/Port_Moresby",
    "iso:country":"PG",
    "name:und_x_variant":[
        "Arihavo",
        "Arehava",
        "Arehava Number 1"
    ],
    "wof:name":"Arehava Number 1",
    "wof:placetype":"locality"
},
  "geometry": {"coordinates":[145.29809,-7.82899],"type":"Point"}
}