{
  "type": "Feature",
  "properties": {
    "gn:admin1_code":"02",
    "gn:asciiname":"Kitomave",
    "gn:country_code":"PG",
    "gn:dem":16,
    "gn:feature_class":"P",
    "gn:feature_code":"PPL",
    "gn:name":"Kitomave",
    "gn:population":0,
    "gn:timezone":"Pacific/Port_Moresby",
    "iso:country":"PG",
    "wof:name":"Kitomave",
    "wof:placetype":"locality"
},
  "geometry": {"coordinates":[144.25880000000001,-7.36508],"type":"Point"}
}