{
  "type": "Feature",
  "properties": {
    "gn:admin1_code":"06",
    "gn:asciiname":"Hosamrai",
    "gn:country_code":"PG",
    "gn:dem":61,
    "gn:feature_class":"P",
    "gn:feature_code":"PPL",
    "gn:name":"Hosamrai",
    "gn:population":0,
    "gn:timezone":"Pacific/Port_Moresby",
    "iso:country":"PG",
    "name:und_x_variant":[
        "Hosomrai",
        "Hosamrai"
    ],
    "wof:name":"Hosamrai",
    "wof:placetype":"locality"
},
  "geometry": {"coordinates":[141.33463999999995,-5.75358],"type":"Point"}
}