{
  "type": "Feature",
  "properties": {
    "gn:admin1_code":"11",
    "gn:asciiname":"Musingwa",
    "gn:country_code":"PG",
    "gn:dem":356,
    "gn:feature_class":"P",
    "gn:feature_code":"PPL",
    "gn:name":"Musingwa",
    "gn:population":0,
    "gn:timezone":"Pacific/Port_Moresby",
    "iso:country":"PG",
    "wof:name":"Musingwa",
    "wof:placetype":"locality"
},
  "geometry": {"coordinates":[142.73608999999999,-3.57822],"type":"Point"}
}