{
  "type": "Feature",
  "properties": {
    "gn:admin1_code":"11",
    "gn:asciiname":"Shauwer",
    "gn:cc2":"PG",
    "gn:country_code":"PG",
    "gn:dem":304,
    "gn:feature_class":"P",
    "gn:feature_code":"PPL",
    "gn:name":"Shauwer",
    "gn:population":0,
    "gn:timezone":"Pacific/Port_Moresby",
    "iso:country":"PG",
    "name:und_x_variant":[
        "Shower",
        "Shauwer"
    ],
    "wof:name":"Shauwer",
    "wof:placetype":"locality"
},
  "geometry": {"coordinates":[143.51667,-3.33333],"type":"Point"}
}