{
  "type": "Feature",
  "properties": {
    "gn:admin1_code":"06",
    "gn:asciiname":"Benna",
    "gn:country_code":"PG",
    "gn:dem":134,
    "gn:feature_class":"P",
    "gn:feature_code":"PPL",
    "gn:name":"Benna",
    "gn:population":0,
    "gn:timezone":"Pacific/Port_Moresby",
    "iso:country":"PG",
    "name:ceb_x_preferred":[
        "Benna"
    ],
    "name:deu_x_preferred":[
        "Benna"
    ],
    "name:epo_x_preferred":[
        "Benna"
    ],
    "name:fra_x_preferred":[
        "Benna"
    ],
    "name:ita_x_preferred":[
        "Benna"
    ],
    "name:swe_x_preferred":[
        "Benna"
    ],
    "wof:name":"Benna",
    "wof:placetype":"locality"
},
  "geometry": {"coordinates":[141.98333,-6.13333],"type":"Point"}
}