{
  "type": "Feature",
  "properties": {
    "gn:admin1_code":"09",
    "gn:asciiname":"Kemiu",
    "gn:country_code":"PG",
    "gn:dem":1837,
    "gn:feature_class":"P",
    "gn:feature_code":"PPL",
    "gn:name":"Kemiu",
    "gn:population":0,
    "gn:timezone":"Pacific/Port_Moresby",
    "iso:country":"PG",
    "wof:name":"Kemiu",
    "wof:placetype":"locality"
},
  "geometry": {"coordinates":[145.58333000000005,-6.43333],"type":"Point"}
}