{
  "type": "Feature",
  "properties": {
    "gn:admin1_code":"12",
    "gn:asciiname":"Delbangat",
    "gn:country_code":"PG",
    "gn:dem":623,
    "gn:feature_class":"P",
    "gn:feature_code":"PPL",
    "gn:name":"Delbangat",
    "gn:population":0,
    "gn:timezone":"Pacific/Port_Moresby",
    "iso:country":"PG",
    "wof:name":"Delbangat",
    "wof:placetype":"locality"
},
  "geometry": {"coordinates":[146.51623000000001,-5.72061],"type":"Point"}
}