{
  "type": "Feature",
  "properties": {
    "gn:admin1_code":"14",
    "gn:asciiname":"Nadzab",
    "gn:country_code":"PG",
    "gn:dem":37,
    "gn:feature_class":"P",
    "gn:feature_code":"PPL",
    "gn:name":"Nadzab",
    "gn:population":0,
    "gn:timezone":"Pacific/Port_Moresby",
    "iso:country":"PG",
    "name:fra_x_preferred":[
        "Nadzab"
    ],
    "name:spa_x_preferred":[
        "Nadzab"
    ],
    "name:und_x_variant":[
        "Nadzad",
        "Nadzab"
    ],
    "name:zho_x_preferred":[
        "\u7eb3\u624e\u5e03"
    ],
    "wof:name":"Nadzab",
    "wof:placetype":"locality"
},
  "geometry": {"coordinates":[146.81052,-6.59338],"type":"Point"}
}