{
  "type": "Feature",
  "properties": {
    "gn:admin1_code":"12",
    "gn:asciiname":"Zukin",
    "gn:country_code":"PG",
    "gn:dem":62,
    "gn:feature_class":"P",
    "gn:feature_code":"PPL",
    "gn:name":"Zukin",
    "gn:population":0,
    "gn:timezone":"Pacific/Port_Moresby",
    "iso:country":"PG",
    "wof:name":"Zukin",
    "wof:placetype":"locality"
},
  "geometry": {"coordinates":[144.81396000000001,-4.54216],"type":"Point"}
}