{
  "type": "Feature",
  "properties": {
    "gn:admin1_code":"01",
    "gn:asciiname":"Garima 1",
    "gn:country_code":"PG",
    "gn:dem":1365,
    "gn:feature_class":"P",
    "gn:feature_code":"PPL",
    "gn:name":"Garima 1",
    "gn:population":0,
    "gn:timezone":"Pacific/Port_Moresby",
    "iso:country":"PG",
    "name:und_x_variant":[
        "Garima Number 1",
        "Garima 1"
    ],
    "wof:name":"Garima 1",
    "wof:placetype":"locality"
},
  "geometry": {"coordinates":[147.11193,-8.52517],"type":"Point"}
}