{
  "type": "Feature",
  "properties": {
    "gn:admin1_code":"14",
    "gn:asciiname":"Wasu",
    "gn:country_code":"PG",
    "gn:dem":52,
    "gn:feature_class":"P",
    "gn:feature_code":"PPL",
    "gn:name":"Wasu",
    "gn:population":0,
    "gn:timezone":"Pacific/Port_Moresby",
    "iso:country":"PG",
    "name:fas_x_preferred":[
        "\u0648\u0627\u0633\u0648"
    ],
    "wof:name":"Wasu",
    "wof:placetype":"locality"
},
  "geometry": {"coordinates":[147.20317,-5.97056],"type":"Point"}
}