{
  "type": "Feature",
  "properties": {
    "gn:admin1_code":"11",
    "gn:asciiname":"Banwingei",
    "gn:country_code":"PG",
    "gn:dem":32,
    "gn:feature_class":"P",
    "gn:feature_code":"PPL",
    "gn:name":"Banwingei",
    "gn:population":0,
    "gn:timezone":"Pacific/Port_Moresby",
    "iso:country":"PG",
    "wof:name":"Banwingei",
    "wof:placetype":"locality"
},
  "geometry": {"coordinates":[142.958,-3.98684],"type":"Point"}
}