{
  "type": "Feature",
  "properties": {
    "gn:admin1_code":"06",
    "gn:asciiname":"Sonai",
    "gn:country_code":"PG",
    "gn:dem":58,
    "gn:feature_class":"P",
    "gn:feature_code":"PPL",
    "gn:name":"Sonai",
    "gn:population":0,
    "gn:timezone":"Pacific/Port_Moresby",
    "iso:country":"PG",
    "wof:name":"Sonai",
    "wof:placetype":"locality"
},
  "geometry": {"coordinates":[141.27771000000001,-5.77201],"type":"Point"}
}