{
  "type": "Feature",
  "properties": {
    "gn:admin1_code":"06",
    "gn:asciiname":"Kauruti",
    "gn:country_code":"PG",
    "gn:dem":25,
    "gn:feature_class":"P",
    "gn:feature_code":"PPL",
    "gn:name":"Kauruti",
    "gn:population":0,
    "gn:timezone":"Pacific/Port_Moresby",
    "iso:country":"PG",
    "wof:name":"Kauruti",
    "wof:placetype":"locality"
},
  "geometry": {"coordinates":[143.25,-8.91667],"type":"Point"}
}