{
  "type": "Feature",
  "properties": {
    "gn:admin1_code":"09",
    "gn:asciiname":"Amuraisa",
    "gn:country_code":"PG",
    "gn:dem":1503,
    "gn:feature_class":"P",
    "gn:feature_code":"PPL",
    "gn:name":"Amuraisa",
    "gn:population":0,
    "gn:timezone":"Pacific/Port_Moresby",
    "iso:country":"PG",
    "wof:name":"Amuraisa",
    "wof:placetype":"locality"
},
  "geometry": {"coordinates":[145.42005,-6.58137],"type":"Point"}
}