{
  "type": "Feature",
  "properties": {
    "gn:admin1_code":"09",
    "gn:asciiname":"Kosunoru Number 1",
    "gn:country_code":"PG",
    "gn:dem":1603,
    "gn:feature_class":"P",
    "gn:feature_code":"PPL",
    "gn:name":"Kosunoru Number 1",
    "gn:population":0,
    "gn:timezone":"Pacific/Port_Moresby",
    "iso:country":"PG",
    "name:und_x_variant":[
        "Kosunaru Number 1",
        "Kosunaru 1",
        "Kosunoru Number 1"
    ],
    "wof:name":"Kosunoru Number 1",
    "wof:placetype":"locality"
},
  "geometry": {"coordinates":[145.42436000000001,-6.5249],"type":"Point"}
}