{
  "type": "Feature",
  "properties": {
    "gn:admin1_code":"01",
    "gn:asciiname":"Sapphire",
    "gn:country_code":"PG",
    "gn:dem":176,
    "gn:feature_class":"P",
    "gn:feature_code":"PPL",
    "gn:name":"Sapphire",
    "gn:population":0,
    "gn:timezone":"Pacific/Port_Moresby",
    "iso:country":"PG",
    "wof:name":"Sapphire",
    "wof:placetype":"locality"
},
  "geometry": {"coordinates":[147.31666999999999,-9.41667],"type":"Point"}
}