{
  "type": "Feature",
  "properties": {
    "gn:admin1_code":"18",
    "gn:asciiname":"Lilal",
    "gn:country_code":"PG",
    "gn:dem":788,
    "gn:feature_class":"P",
    "gn:feature_code":"PPL",
    "gn:name":"Lilal",
    "gn:population":0,
    "gn:timezone":"Pacific/Port_Moresby",
    "iso:country":"PG",
    "wof:name":"Lilal",
    "wof:placetype":"locality"
},
  "geometry": {"coordinates":[142.18419,-3.4766],"type":"Point"}
}