{
  "type": "Feature",
  "properties": {
    "gn:admin1_code":"11",
    "gn:asciiname":"Mimbiok",
    "gn:country_code":"PG",
    "gn:dem":350,
    "gn:feature_class":"P",
    "gn:feature_code":"PPL",
    "gn:name":"Mimbiok",
    "gn:population":0,
    "gn:timezone":"Pacific/Port_Moresby",
    "iso:country":"PG",
    "wof:name":"Mimbiok",
    "wof:placetype":"locality"
},
  "geometry": {"coordinates":[142.62871000000001,-3.55837],"type":"Point"}
}