{
  "type": "Feature",
  "properties": {
    "gn:admin1_code":"18",
    "gn:asciiname":"Idoli",
    "gn:country_code":"PG",
    "gn:dem":167,
    "gn:feature_class":"P",
    "gn:feature_code":"PPL",
    "gn:name":"Idoli",
    "gn:population":0,
    "gn:timezone":"Pacific/Port_Moresby",
    "iso:country":"PG",
    "wof:name":"Idoli",
    "wof:placetype":"locality"
},
  "geometry": {"coordinates":[141.14146000000005,-3.02647],"type":"Point"}
}