{
  "type": "Feature",
  "properties": {
    "gn:admin1_code":"01",
    "gn:asciiname":"Kiriai",
    "gn:country_code":"PG",
    "gn:dem":1671,
    "gn:feature_class":"P",
    "gn:feature_code":"PPL",
    "gn:name":"Kiriai",
    "gn:population":0,
    "gn:timezone":"Pacific/Port_Moresby",
    "iso:country":"PG",
    "wof:name":"Kiriai",
    "wof:placetype":"locality"
},
  "geometry": {"coordinates":[147.13579999999999,-8.41309],"type":"Point"}
}