{
  "type": "Feature",
  "properties": {
    "gn:admin1_code":"12",
    "gn:asciiname":"Asui",
    "gn:country_code":"PG",
    "gn:dem":222,
    "gn:feature_class":"P",
    "gn:feature_code":"PPL",
    "gn:name":"Asui",
    "gn:population":0,
    "gn:timezone":"Pacific/Port_Moresby",
    "iso:country":"PG",
    "wof:name":"Asui",
    "wof:placetype":"locality"
},
  "geometry": {"coordinates":[145.67186999999996,-5.60057],"type":"Point"}
}