{
  "type": "Feature",
  "properties": {
    "gn:admin1_code":"15",
    "gn:asciiname":"Danu",
    "gn:country_code":"PG",
    "gn:dem":158,
    "gn:feature_class":"P",
    "gn:feature_code":"PPL",
    "gn:name":"Danu",
    "gn:population":0,
    "gn:timezone":"Pacific/Port_Moresby",
    "iso:country":"PG",
    "name:ceb_x_preferred":[
        "Danu"
    ],
    "name:cym_x_preferred":[
        "Danu"
    ],
    "name:deu_x_preferred":[
        "Danu"
    ],
    "name:eus_x_preferred":[
        "Danu"
    ],
    "name:fra_x_preferred":[
        "Danu"
    ],
    "name:ita_x_preferred":[
        "Danu"
    ],
    "name:nld_x_preferred":[
        "Danu"
    ],
    "name:ron_x_preferred":[
        "Danu"
    ],
    "name:rus_x_preferred":[
        "\u0414\u0430\u043d\u0443"
    ],
    "name:sco_x_preferred":[
        "Danu"
    ],
    "name:spa_x_preferred":[
        "Danu"
    ],
    "name:swe_x_preferred":[
        "Danu"
    ],
    "wof:name":"Danu",
    "wof:placetype":"locality"
},
  "geometry": {"coordinates":[151.93753000000001,-3.43017],"type":"Point"}
}