{
  "type": "Feature",
  "properties": {
    "gn:admin1_code":"01",
    "gn:asciiname":"Buri",
    "gn:cc2":"PG",
    "gn:country_code":"PG",
    "gn:dem":453,
    "gn:feature_class":"P",
    "gn:feature_code":"PPL",
    "gn:name":"Buri",
    "gn:population":0,
    "gn:timezone":"Pacific/Port_Moresby",
    "iso:country":"PG",
    "name:und_x_variant":[
        "Boru",
        "Bofu",
        "Buri"
    ],
    "wof:name":"Buri",
    "wof:placetype":"locality"
},
  "geometry": {"coordinates":[147.56666999999999,-8.56667],"type":"Point"}
}