{
  "type": "Feature",
  "properties": {
    "gn:admin1_code":"01",
    "gn:asciiname":"Buri",
    "gn:cc2":"PG",
    "gn:country_code":"PG",
    "gn:dem":453,
    "gn:feature_class":"P",
    "gn:feature_code":"PPL",
    "gn:name":"Buri",
    "gn:population":0,
    "gn:timezone":"Pacific/Port_Moresby",
    "iso:country":"PG",
    "name:bos_x_preferred":[
        "Buri"
    ],
    "name:cat_x_preferred":[
        "Buri"
    ],
    "name:ceb_x_preferred":[
        "Buri"
    ],
    "name:deu_x_preferred":[
        "Buri"
    ],
    "name:fra_x_preferred":[
        "Buri"
    ],
    "name:hrv_x_preferred":[
        "Buri"
    ],
    "name:ita_x_preferred":[
        "Buri"
    ],
    "name:lav_x_preferred":[
        "B\u016bri"
    ],
    "name:nld_x_preferred":[
        "Buri"
    ],
    "name:pol_x_preferred":[
        "Buri"
    ],
    "name:ron_x_preferred":[
        "Buri"
    ],
    "name:rus_x_preferred":[
        "\u0411\u0443\u0440\u0438"
    ],
    "name:swe_x_preferred":[
        "Buri"
    ],
    "name:ukr_x_preferred":[
        "\u0411\u0443\u0440\u0456"
    ],
    "name:und_x_variant":[
        "Boru",
        "Bofu",
        "Buri"
    ],
    "wof:name":"Buri",
    "wof:placetype":"locality"
},
  "geometry": {"coordinates":[147.56666999999999,-8.56667],"type":"Point"}
}