{
  "type": "Feature",
  "properties": {
    "gn:admin1_code":"11",
    "gn:asciiname":"Kambelyi",
    "gn:country_code":"PG",
    "gn:dem":336,
    "gn:feature_class":"P",
    "gn:feature_code":"PPL",
    "gn:name":"Kambelyi",
    "gn:population":0,
    "gn:timezone":"Pacific/Port_Moresby",
    "iso:country":"PG",
    "name:und_x_variant":[
        "Kembelyi",
        "Kambelyi"
    ],
    "wof:name":"Kambelyi",
    "wof:placetype":"locality"
},
  "geometry": {"coordinates":[143.30643000000001,-3.62486],"type":"Point"}
}