{
  "type": "Feature",
  "properties": {
    "gn:admin1_code":"01",
    "gn:asciiname":"Hoianurenda",
    "gn:country_code":"PG",
    "gn:dem":2381,
    "gn:feature_class":"P",
    "gn:feature_code":"PPL",
    "gn:name":"Hoianurenda",
    "gn:population":0,
    "gn:timezone":"Pacific/Port_Moresby",
    "iso:country":"PG",
    "wof:name":"Hoianurenda",
    "wof:placetype":"locality"
},
  "geometry": {"coordinates":[147.36646000000005,-8.6413],"type":"Point"}
}