{
  "type": "Feature",
  "properties": {
    "gn:admin1_code":"06",
    "gn:asciiname":"Uadagumbi",
    "gn:country_code":"PG",
    "gn:dem":137,
    "gn:feature_class":"P",
    "gn:feature_code":"PPL",
    "gn:name":"Uadagumbi",
    "gn:population":0,
    "gn:timezone":"Pacific/Port_Moresby",
    "iso:country":"PG",
    "name:und_x_variant":[
        "Odogumbi"
    ],
    "wof:name":"Uadagumbi",
    "wof:placetype":"locality"
},
  "geometry": {"coordinates":[142.24879999999999,-6.45338],"type":"Point"}
}