{
  "type": "Feature",
  "properties": {
    "gn:admin1_code":"11",
    "gn:asciiname":"Aurimbit",
    "gn:country_code":"PG",
    "gn:dem":31,
    "gn:feature_class":"P",
    "gn:feature_code":"PPL",
    "gn:name":"Aurimbit",
    "gn:population":0,
    "gn:timezone":"Pacific/Port_Moresby",
    "iso:country":"PG",
    "name:und_x_variant":[
        "Aurumbit",
        "Aulimbit",
        "Aurimbit"
    ],
    "wof:name":"Aurimbit",
    "wof:placetype":"locality"
},
  "geometry": {"coordinates":[143.17167000000001,-4.00769],"type":"Point"}
}