{
  "type": "Feature",
  "properties": {
    "gn:admin1_code":"03",
    "gn:asciiname":"Gurukwaia 1",
    "gn:country_code":"PG",
    "gn:dem":59,
    "gn:feature_class":"P",
    "gn:feature_code":"PPL",
    "gn:name":"Gurukwaia 1",
    "gn:population":0,
    "gn:timezone":"Pacific/Port_Moresby",
    "iso:country":"PG",
    "wof:name":"Gurukwaia 1",
    "wof:placetype":"locality"
},
  "geometry": {"coordinates":[149.58333000000005,-9.71667],"type":"Point"}
}