{
  "type": "Feature",
  "properties": {
    "gn:admin1_code":"13",
    "gn:asciiname":"Hus",
    "gn:country_code":"PG",
    "gn:dem":-9999,
    "gn:feature_class":"P",
    "gn:feature_code":"PPL",
    "gn:name":"Hus",
    "gn:population":0,
    "gn:timezone":"Pacific/Port_Moresby",
    "iso:country":"PG",
    "name:ceb_x_preferred":[
        "Hus"
    ],
    "name:dan_x_preferred":[
        "Hus"
    ],
    "name:deu_x_preferred":[
        "Hus"
    ],
    "name:fin_x_preferred":[
        "Hus"
    ],
    "name:fra_x_preferred":[
        "Hus"
    ],
    "name:fry_x_preferred":[
        "H\u00fbs"
    ],
    "name:nld_x_preferred":[
        "Hus"
    ],
    "name:nor_x_preferred":[
        "Hus"
    ],
    "name:slk_x_preferred":[
        "Hus"
    ],
    "name:swe_x_preferred":[
        "Hus"
    ],
    "wof:name":"Hus",
    "wof:placetype":"locality"
},
  "geometry": {"coordinates":[147.09999999999999,-1.93333],"type":"Point"}
}