{
  "type": "Feature",
  "properties": {
    "gn:admin1_code":"04",
    "gn:asciiname":"Adiabo",
    "gn:cc2":"PG",
    "gn:country_code":"PG",
    "gn:dem":388,
    "gn:feature_class":"P",
    "gn:feature_code":"PPL",
    "gn:name":"Adiabo",
    "gn:population":0,
    "gn:timezone":"Pacific/Port_Moresby",
    "iso:country":"PG",
    "name:und_x_variant":[
        "Adiobo",
        "Adiabo"
    ],
    "wof:name":"Adiabo",
    "wof:placetype":"locality"
},
  "geometry": {"coordinates":[148.38333,-9.46667],"type":"Point"}
}