{
  "type": "Feature",
  "properties": {
    "gn:admin1_code":"12",
    "gn:asciiname":"Kasu",
    "gn:country_code":"PG",
    "gn:dem":49,
    "gn:feature_class":"P",
    "gn:feature_code":"PPL",
    "gn:name":"Kasu",
    "gn:population":0,
    "gn:timezone":"Pacific/Port_Moresby",
    "iso:country":"PG",
    "name:ceb_x_preferred":[
        "Kasu"
    ],
    "name:swe_x_preferred":[
        "Kasu"
    ],
    "name:tel_x_preferred":[
        "\u0c15\u0c3e\u0c38\u0c41"
    ],
    "wof:name":"Kasu",
    "wof:placetype":"locality"
},
  "geometry": {"coordinates":[146.51953,-5.67573],"type":"Point"}
}