{
  "type": "Feature",
  "properties": {
    "gn:admin1_code":"12",
    "gn:asciiname":"Zanung",
    "gn:country_code":"PG",
    "gn:dem":15,
    "gn:feature_class":"P",
    "gn:feature_code":"PPL",
    "gn:name":"Zanung",
    "gn:population":0,
    "gn:timezone":"Pacific/Port_Moresby",
    "iso:country":"PG",
    "wof:name":"Zanung",
    "wof:placetype":"locality"
},
  "geometry": {"coordinates":[144.66666999999995,-4.31667],"type":"Point"}
}