{
  "type": "Feature",
  "properties": {
    "gn:admin1_code":"18",
    "gn:asciiname":"Busilmin Number 2",
    "gn:cc2":"PG",
    "gn:country_code":"PG",
    "gn:dem":1895,
    "gn:feature_class":"P",
    "gn:feature_code":"PPL",
    "gn:name":"Busilmin Number 2",
    "gn:population":0,
    "gn:timezone":"Pacific/Port_Moresby",
    "iso:country":"PG",
    "name:und_x_variant":[
        "Busilmin",
        "Busilmin 2",
        "Busilmin Number 2"
    ],
    "wof:name":"Busilmin Number 2",
    "wof:placetype":"locality"
},
  "geometry": {"coordinates":[141.08333000000005,-4.86667],"type":"Point"}
}