{
  "type": "Feature",
  "properties": {
    "gn:admin1_code":"05",
    "gn:asciiname":"Tagaru",
    "gn:country_code":"PG",
    "gn:dem":1520,
    "gn:feature_class":"P",
    "gn:feature_code":"PPL",
    "gn:name":"Tagaru",
    "gn:population":0,
    "gn:timezone":"Pacific/Port_Moresby",
    "iso:country":"PG",
    "name:ita_x_preferred":[
        "Tagaru"
    ],
    "name:kan_x_preferred":[
        "\u0c9f\u0c97\u0cb0\u0cc1"
    ],
    "name:tgl_x_preferred":[
        "Tagaru"
    ],
    "name:und_x_variant":[
        "Taguru",
        "Tagaru"
    ],
    "wof:name":"Tagaru",
    "wof:placetype":"locality"
},
  "geometry": {"coordinates":[144.15723,-6.41422],"type":"Point"}
}