{
  "type": "Feature",
  "properties": {
    "gn:admin1_code":"14",
    "gn:asciiname":"Bangalum Bridge",
    "gn:country_code":"PG",
    "gn:dem":583,
    "gn:feature_class":"P",
    "gn:feature_code":"PPL",
    "gn:name":"Bangalum Bridge",
    "gn:population":0,
    "gn:timezone":"Pacific/Port_Moresby",
    "iso:country":"PG",
    "wof:name":"Bangalum Bridge",
    "wof:placetype":"locality"
},
  "geometry": {"coordinates":[146.59999999999999,-7.05],"type":"Point"}
}