{
  "type": "Feature",
  "properties": {
    "gn:admin1_code":"04",
    "gn:asciiname":"Uwe",
    "gn:country_code":"PG",
    "gn:dem":17,
    "gn:feature_class":"P",
    "gn:feature_code":"PPL",
    "gn:name":"Uwe",
    "gn:population":0,
    "gn:timezone":"Pacific/Port_Moresby",
    "iso:country":"PG",
    "name:deu_x_preferred":[
        "Uwe"
    ],
    "name:pol_x_preferred":[
        "Uwe"
    ],
    "name:rus_x_preferred":[
        "\u0423\u0432\u0435"
    ],
    "name:und_x_variant":[
        "Uue",
        "Uwe"
    ],
    "wof:name":"Uwe",
    "wof:placetype":"locality"
},
  "geometry": {"coordinates":[149.23657,-9.21245],"type":"Point"}
}