{
  "type": "Feature",
  "properties": {
    "gn:admin1_code":"12",
    "gn:asciiname":"Meriman",
    "gn:country_code":"PG",
    "gn:dem":53,
    "gn:feature_class":"P",
    "gn:feature_code":"PPL",
    "gn:name":"Meriman",
    "gn:population":0,
    "gn:timezone":"Pacific/Port_Moresby",
    "iso:country":"PG",
    "wof:name":"Meriman",
    "wof:placetype":"locality"
},
  "geometry": {"coordinates":[145.38538,-4.46683],"type":"Point"}
}