{
  "type": "Feature",
  "properties": {
    "gn:admin1_code":"19",
    "gn:asciiname":"Karegari",
    "gn:country_code":"PG",
    "gn:dem":2619,
    "gn:feature_class":"P",
    "gn:feature_code":"PPL",
    "gn:name":"Karegari",
    "gn:population":0,
    "gn:timezone":"Pacific/Port_Moresby",
    "iso:country":"PG",
    "wof:name":"Karegari",
    "wof:placetype":"locality"
},
  "geometry": {"coordinates":[143.31738999999999,-5.617],"type":"Point"}
}