{
  "type": "Feature",
  "properties": {
    "gn:admin1_code":"03",
    "gn:asciiname":"Modeni",
    "gn:country_code":"PG",
    "gn:dem":955,
    "gn:feature_class":"P",
    "gn:feature_code":"PPL",
    "gn:name":"Modeni",
    "gn:population":0,
    "gn:timezone":"Pacific/Port_Moresby",
    "iso:country":"PG",
    "wof:name":"Modeni",
    "wof:placetype":"locality"
},
  "geometry": {"coordinates":[149.41666999999995,-9.91667],"type":"Point"}
}