{
  "type": "Feature",
  "properties": {
    "gn:admin1_code":"17",
    "gn:asciiname":"Asit",
    "gn:cc2":"PG",
    "gn:country_code":"PG",
    "gn:dem":149,
    "gn:feature_class":"P",
    "gn:feature_code":"PPL",
    "gn:name":"Asit",
    "gn:population":0,
    "gn:timezone":"Pacific/Port_Moresby",
    "iso:country":"PG",
    "name:und_x_variant":[
        "Ezit",
        "Asit"
    ],
    "wof:name":"Asit",
    "wof:placetype":"locality"
},
  "geometry": {"coordinates":[149.69999999999999,-6.18333],"type":"Point"}
}