{
  "type": "Feature",
  "properties": {
    "gn:admin1_code":"18",
    "gn:asciiname":"Saindei",
    "gn:country_code":"PG",
    "gn:dem":503,
    "gn:feature_class":"P",
    "gn:feature_code":"PPL",
    "gn:name":"Saindei",
    "gn:population":0,
    "gn:timezone":"Pacific/Port_Moresby",
    "iso:country":"PG",
    "wof:name":"Saindei",
    "wof:placetype":"locality"
},
  "geometry": {"coordinates":[142.10969,-3.47183],"type":"Point"}
}