{
  "type": "Feature",
  "properties": {
    "gn:admin1_code":"14",
    "gn:asciiname":"Tofmora",
    "gn:country_code":"PG",
    "gn:dem":407,
    "gn:feature_class":"P",
    "gn:feature_code":"PPL",
    "gn:name":"Tofmora",
    "gn:population":0,
    "gn:timezone":"Pacific/Port_Moresby",
    "iso:country":"PG",
    "wof:name":"Tofmora",
    "wof:placetype":"locality"
},
  "geometry": {"coordinates":[146.21708999999996,-6.17983],"type":"Point"}
}