{
  "type": "Feature",
  "properties": {
    "gn:admin1_code":"09",
    "gn:asciiname":"Tchetchai",
    "gn:country_code":"PG",
    "gn:dem":1408,
    "gn:feature_class":"P",
    "gn:feature_code":"PPL",
    "gn:name":"Tchetchai",
    "gn:population":0,
    "gn:timezone":"Pacific/Port_Moresby",
    "iso:country":"PG",
    "wof:name":"Tchetchai",
    "wof:placetype":"locality"
},
  "geometry": {"coordinates":[145.65000000000001,-6.93333],"type":"Point"}
}