{
  "type": "Feature",
  "properties": {
    "gn:admin1_code":"03",
    "gn:asciiname":"Maraia",
    "gn:country_code":"PG",
    "gn:dem":401,
    "gn:feature_class":"P",
    "gn:feature_code":"PPL",
    "gn:name":"Maraia",
    "gn:population":0,
    "gn:timezone":"Pacific/Port_Moresby",
    "iso:country":"PG",
    "wof:name":"Maraia",
    "wof:placetype":"locality"
},
  "geometry": {"coordinates":[149.98333,-10.13333],"type":"Point"}
}