{
  "type": "Feature",
  "properties": {
    "gn:admin1_code":"15",
    "gn:asciiname":"Kamiang",
    "gn:country_code":"PG",
    "gn:dem":137,
    "gn:feature_class":"P",
    "gn:feature_code":"PPL",
    "gn:name":"Kamiang",
    "gn:population":0,
    "gn:timezone":"Pacific/Port_Moresby",
    "iso:country":"PG",
    "wof:name":"Kamiang",
    "wof:placetype":"locality"
},
  "geometry": {"coordinates":[153.09405000000001,-4.3435],"type":"Point"}
}