{
  "type": "Feature",
  "properties": {
    "gn:admin1_code":"14",
    "gn:asciiname":"Ubaneng",
    "gn:country_code":"PG",
    "gn:dem":1114,
    "gn:feature_class":"P",
    "gn:feature_code":"PPL",
    "gn:name":"Ubaneng",
    "gn:population":0,
    "gn:timezone":"Pacific/Port_Moresby",
    "iso:country":"PG",
    "wof:name":"Ubaneng",
    "wof:placetype":"locality"
},
  "geometry": {"coordinates":[147.38333,-6.51667],"type":"Point"}
}