{
  "type": "Feature",
  "properties": {
    "gn:admin1_code":"05",
    "gn:asciiname":"Wambu",
    "gn:country_code":"PG",
    "gn:dem":1513,
    "gn:feature_class":"P",
    "gn:feature_code":"PPL",
    "gn:name":"Wambu",
    "gn:population":0,
    "gn:timezone":"Pacific/Port_Moresby",
    "iso:country":"PG",
    "wof:name":"Wambu",
    "wof:placetype":"locality"
},
  "geometry": {"coordinates":[143.62842000000001,-6.37534],"type":"Point"}
}