{
  "type": "Feature",
  "properties": {
    "gn:admin1_code":"01",
    "gn:admin2_code":"2096826",
    "gn:asciiname":"Hisiu",
    "gn:country_code":"PG",
    "gn:dem":10,
    "gn:feature_class":"P",
    "gn:feature_code":"PPL",
    "gn:name":"Hisiu",
    "gn:population":0,
    "gn:timezone":"Pacific/Port_Moresby",
    "iso:country":"PG",
    "name:und_x_variant":[
        "Isiu",
        "Hisiu"
    ],
    "wof:name":"Hisiu",
    "wof:placetype":"locality"
},
  "geometry": {"coordinates":[146.77361000000005,-9.04798],"type":"Point"}
}