{
  "type": "Feature",
  "properties": {
    "gn:admin1_code":"18",
    "gn:asciiname":"Tofungu",
    "gn:country_code":"PG",
    "gn:dem":694,
    "gn:feature_class":"P",
    "gn:feature_code":"PPL",
    "gn:name":"Tofungu",
    "gn:population":0,
    "gn:timezone":"Pacific/Port_Moresby",
    "iso:country":"PG",
    "wof:name":"Tofungu",
    "wof:placetype":"locality"
},
  "geometry": {"coordinates":[142.01667,-3.41667],"type":"Point"}
}