{
  "type": "Feature",
  "properties": {
    "gn:admin1_code":"08",
    "gn:asciiname":"Gwagu",
    "gn:country_code":"PG",
    "gn:dem":1556,
    "gn:feature_class":"P",
    "gn:feature_code":"PPL",
    "gn:name":"Gwagu",
    "gn:population":0,
    "gn:timezone":"Pacific/Port_Moresby",
    "iso:country":"PG",
    "wof:name":"Gwagu",
    "wof:placetype":"locality"
},
  "geometry": {"coordinates":[145.11667,-6.13333],"type":"Point"}
}