{
  "type": "Feature",
  "properties": {
    "gn:admin1_code":"03",
    "gn:asciiname":"Soluwo",
    "gn:country_code":"PG",
    "gn:dem":5,
    "gn:feature_class":"P",
    "gn:feature_code":"PPL",
    "gn:name":"Soluwo",
    "gn:population":0,
    "gn:timezone":"Pacific/Port_Moresby",
    "iso:country":"PG",
    "wof:name":"Soluwo",
    "wof:placetype":"locality"
},
  "geometry": {"coordinates":[153.23403999999999,-11.31499],"type":"Point"}
}