{
  "type": "Feature",
  "properties": {
    "gn:admin1_code":"04",
    "gn:asciiname":"Bibira Number 1",
    "gn:country_code":"PG",
    "gn:dem":137,
    "gn:feature_class":"P",
    "gn:feature_code":"PPL",
    "gn:name":"Bibira Number 1",
    "gn:population":0,
    "gn:timezone":"Pacific/Port_Moresby",
    "iso:country":"PG",
    "name:und_x_variant":[
        "Bibira",
        "Bibira Number 1"
    ],
    "wof:name":"Bibira Number 1",
    "wof:placetype":"locality"
},
  "geometry": {"coordinates":[148.63394,-9.56376],"type":"Point"}
}