{
  "type": "Feature",
  "properties": {
    "gn:admin1_code":"02",
    "gn:asciiname":"Chama",
    "gn:country_code":"PG",
    "gn:dem":595,
    "gn:feature_class":"P",
    "gn:feature_code":"PPL",
    "gn:name":"Chama",
    "gn:population":0,
    "gn:timezone":"Pacific/Port_Moresby",
    "iso:country":"PG",
    "wof:name":"Chama",
    "wof:placetype":"locality"
},
  "geometry": {"coordinates":[145.84999999999999,-7.71667],"type":"Point"}
}