{
  "type": "Feature",
  "properties": {
    "gn:admin1_code":"09",
    "gn:asciiname":"Kafonaga",
    "gn:country_code":"PG",
    "gn:dem":1806,
    "gn:feature_class":"P",
    "gn:feature_code":"PPL",
    "gn:name":"Kafonaga",
    "gn:population":0,
    "gn:timezone":"Pacific/Port_Moresby",
    "iso:country":"PG",
    "wof:name":"Kafonaga",
    "wof:placetype":"locality"
},
  "geometry": {"coordinates":[145.56666999999999,-6.01667],"type":"Point"}
}