{
  "type": "Feature",
  "properties": {
    "gn:admin1_code":"06",
    "gn:asciiname":"Somaikwankia",
    "gn:country_code":"PG",
    "gn:dem":67,
    "gn:feature_class":"P",
    "gn:feature_code":"PPL",
    "gn:name":"Somaikwankia",
    "gn:population":0,
    "gn:timezone":"Pacific/Port_Moresby",
    "iso:country":"PG",
    "wof:name":"Somaikwankia",
    "wof:placetype":"locality"
},
  "geometry": {"coordinates":[141.31766999999999,-5.8102],"type":"Point"}
}