{
  "type": "Feature",
  "properties": {
    "gn:admin1_code":"09",
    "gn:asciiname":"Benaga",
    "gn:country_code":"PG",
    "gn:dem":1883,
    "gn:feature_class":"P",
    "gn:feature_code":"PPL",
    "gn:name":"Benaga",
    "gn:population":0,
    "gn:timezone":"Pacific/Port_Moresby",
    "iso:country":"PG",
    "wof:name":"Benaga",
    "wof:placetype":"locality"
},
  "geometry": {"coordinates":[145.76238000000001,-6.36691],"type":"Point"}
}