{
  "type": "Feature",
  "properties": {
    "gn:admin1_code":"02",
    "gn:asciiname":"Tamenaiu",
    "gn:country_code":"PG",
    "gn:dem":258,
    "gn:feature_class":"P",
    "gn:feature_code":"PPL",
    "gn:name":"Tamenaiu",
    "gn:population":0,
    "gn:timezone":"Pacific/Port_Moresby",
    "iso:country":"PG",
    "wof:name":"Tamenaiu",
    "wof:placetype":"locality"
},
  "geometry": {"coordinates":[143.75,-7.11667],"type":"Point"}
}