{
  "type": "Feature",
  "properties": {
    "gn:admin1_code":"08",
    "gn:asciiname":"Sinuma",
    "gn:country_code":"PG",
    "gn:dem":2481,
    "gn:feature_class":"P",
    "gn:feature_code":"PPL",
    "gn:name":"Sinuma",
    "gn:population":0,
    "gn:timezone":"Pacific/Port_Moresby",
    "iso:country":"PG",
    "name:und_x_variant":[
        "Simuna",
        "Sinuma"
    ],
    "wof:name":"Sinuma",
    "wof:placetype":"locality"
},
  "geometry": {"coordinates":[144.87852000000001,-6.20414],"type":"Point"}
}