{
  "type": "Feature",
  "properties": {
    "gn:admin1_code":"04",
    "gn:asciiname":"Hamburata",
    "gn:country_code":"PG",
    "gn:dem":315,
    "gn:feature_class":"P",
    "gn:feature_code":"PPL",
    "gn:name":"Hamburata",
    "gn:population":0,
    "gn:timezone":"Pacific/Port_Moresby",
    "iso:country":"PG",
    "name:und_x_variant":[
        "Kongahambo",
        "Hamburata"
    ],
    "wof:name":"Hamburata",
    "wof:placetype":"locality"
},
  "geometry": {"coordinates":[148.05600000000001,-8.88344],"type":"Point"}
}