{
  "type": "Feature",
  "properties": {
    "gn:admin1_code":"05",
    "gn:asciiname":"Kaupena",
    "gn:country_code":"PG",
    "gn:dem":1450,
    "gn:feature_class":"P",
    "gn:feature_code":"PPL",
    "gn:name":"Kaupena",
    "gn:population":0,
    "gn:timezone":"Pacific/Port_Moresby",
    "iso:country":"PG",
    "wof:name":"Kaupena",
    "wof:placetype":"locality"
},
  "geometry": {"coordinates":[144.13801000000001,-6.10509],"type":"Point"}
}