{
  "type": "Feature",
  "properties": {
    "gn:admin1_code":"17",
    "gn:asciiname":"Ipuk",
    "gn:country_code":"PG",
    "gn:dem":110,
    "gn:feature_class":"P",
    "gn:feature_code":"PPL",
    "gn:name":"Ipuk",
    "gn:population":0,
    "gn:timezone":"Pacific/Port_Moresby",
    "iso:country":"PG",
    "wof:name":"Ipuk",
    "wof:placetype":"locality"
},
  "geometry": {"coordinates":[149.31666999999999,-5.98333],"type":"Point"}
}