{
  "type": "Feature",
  "properties": {
    "gn:admin1_code":"05",
    "gn:asciiname":"Kumbirepa",
    "gn:country_code":"PG",
    "gn:dem":1558,
    "gn:feature_class":"P",
    "gn:feature_code":"PPL",
    "gn:name":"Kumbirepa",
    "gn:population":0,
    "gn:timezone":"Pacific/Port_Moresby",
    "iso:country":"PG",
    "wof:name":"Kumbirepa",
    "wof:placetype":"locality"
},
  "geometry": {"coordinates":[144.08493000000001,-6.67961],"type":"Point"}
}