{
  "type": "Feature",
  "properties": {
    "gn:admin1_code":"11",
    "gn:admin2_code":"2091472",
    "gn:asciiname":"Maprik",
    "gn:country_code":"PG",
    "gn:dem":213,
    "gn:feature_class":"P",
    "gn:feature_code":"PPL",
    "gn:name":"Maprik",
    "gn:population":0,
    "gn:timezone":"Pacific/Port_Moresby",
    "iso:country":"PG",
    "name:ceb_x_preferred":[
        "Maprik"
    ],
    "name:fas_x_preferred":[
        "\u0645\u0646\u0637\u0642\u0647 \u0645\u0627\u067e\u0631\u06cc\u06a9"
    ],
    "name:und_x_variant":[
        "Kominibus",
        "Maprik"
    ],
    "name:zho_x_preferred":[
        "\u99ac\u666e\u91cc\u514b\u7e23"
    ],
    "wof:name":"Maprik",
    "wof:placetype":"locality"
},
  "geometry": {"coordinates":[143.05421999999999,-3.62714],"type":"Point"}
}