{
  "type": "Feature",
  "properties": {
    "gn:admin1_code":"12",
    "gn:asciiname":"Ikundum",
    "gn:country_code":"PG",
    "gn:dem":81,
    "gn:feature_class":"P",
    "gn:feature_code":"PPL",
    "gn:name":"Ikundum",
    "gn:population":0,
    "gn:timezone":"Pacific/Port_Moresby",
    "iso:country":"PG",
    "name:und_x_variant":[
        "Ikundun",
        "Ikundum"
    ],
    "wof:name":"Ikundum",
    "wof:placetype":"locality"
},
  "geometry": {"coordinates":[144.98926,-4.65201],"type":"Point"}
}