{
  "type": "Feature",
  "properties": {
    "gn:admin1_code":"09",
    "gn:asciiname":"Tauna",
    "gn:country_code":"PG",
    "gn:dem":1377,
    "gn:feature_class":"P",
    "gn:feature_code":"PPL",
    "gn:name":"Tauna",
    "gn:population":0,
    "gn:timezone":"Pacific/Port_Moresby",
    "iso:country":"PG",
    "name:fra_x_preferred":[
        "Tauna"
    ],
    "name:rus_x_preferred":[
        "\u0422\u0430\u0443\u043d\u0430"
    ],
    "wof:name":"Tauna",
    "wof:placetype":"locality"
},
  "geometry": {"coordinates":[145.72429,-6.60462],"type":"Point"}
}