{
  "type": "Feature",
  "properties": {
    "gn:admin1_code":"10",
    "gn:asciiname":"Ralman",
    "gn:country_code":"PG",
    "gn:dem":-9999,
    "gn:feature_class":"P",
    "gn:feature_code":"PPL",
    "gn:name":"Ralman",
    "gn:population":0,
    "gn:timezone":"Pacific/Port_Moresby",
    "iso:country":"PG",
    "wof:name":"Ralman",
    "wof:placetype":"locality"
},
  "geometry": {"coordinates":[152.05000000000001,-5.45],"type":"Point"}
}