{
  "type": "Feature",
  "properties": {
    "gn:admin1_code":"03",
    "gn:asciiname":"Gabutaia",
    "gn:country_code":"PG",
    "gn:dem":27,
    "gn:feature_class":"P",
    "gn:feature_code":"PPL",
    "gn:name":"Gabutaia",
    "gn:population":0,
    "gn:timezone":"Pacific/Port_Moresby",
    "iso:country":"PG",
    "wof:name":"Gabutaia",
    "wof:placetype":"locality"
},
  "geometry": {"coordinates":[150.75,-9.41667],"type":"Point"}
}