{
  "type": "Feature",
  "properties": {
    "gn:admin1_code":"04",
    "gn:asciiname":"Natanga",
    "gn:country_code":"PG",
    "gn:dem":866,
    "gn:feature_class":"P",
    "gn:feature_code":"PPL",
    "gn:name":"Natanga",
    "gn:population":0,
    "gn:timezone":"Pacific/Port_Moresby",
    "iso:country":"PG",
    "name:und_x_variant":[
        "Natunga",
        "Natanga"
    ],
    "wof:name":"Natanga",
    "wof:placetype":"locality"
},
  "geometry": {"coordinates":[148.29058999999995,-9.05911],"type":"Point"}
}