{
  "type": "Feature",
  "properties": {
    "gn:admin1_code":"14",
    "gn:asciiname":"Guswei",
    "gn:country_code":"PG",
    "gn:dem":1348,
    "gn:feature_class":"P",
    "gn:feature_code":"PPL",
    "gn:name":"Guswei",
    "gn:population":0,
    "gn:timezone":"Pacific/Port_Moresby",
    "iso:country":"PG",
    "wof:name":"Guswei",
    "wof:placetype":"locality"
},
  "geometry": {"coordinates":[146.96666999999999,-7.83333],"type":"Point"}
}