{
  "type": "Feature",
  "properties": {
    "gn:admin1_code":"09",
    "gn:asciiname":"Gohoyfa",
    "gn:cc2":"PG",
    "gn:country_code":"PG",
    "gn:dem":1749,
    "gn:feature_class":"P",
    "gn:feature_code":"PPL",
    "gn:name":"Gohoyfa",
    "gn:population":0,
    "gn:timezone":"Pacific/Port_Moresby",
    "iso:country":"PG",
    "name:und_x_variant":[
        "Gohoyufa",
        "Gohoyfa"
    ],
    "wof:name":"Gohoyfa",
    "wof:placetype":"locality"
},
  "geometry": {"coordinates":[145.33333000000005,-5.98333],"type":"Point"}
}