{
  "type": "Feature",
  "properties": {
    "gn:admin1_code":"04",
    "gn:asciiname":"Kuruaku",
    "gn:country_code":"PG",
    "gn:dem":71,
    "gn:feature_class":"P",
    "gn:feature_code":"PPL",
    "gn:name":"Kuruaku",
    "gn:population":0,
    "gn:timezone":"Pacific/Port_Moresby",
    "iso:country":"PG",
    "wof:name":"Kuruaku",
    "wof:placetype":"locality"
},
  "geometry": {"coordinates":[149.07291000000001,-9.09575],"type":"Point"}
}