{
  "type": "Feature",
  "properties": {
    "gn:admin1_code":"09",
    "gn:asciiname":"Bitebe",
    "gn:country_code":"PG",
    "gn:dem":1992,
    "gn:feature_class":"P",
    "gn:feature_code":"PPL",
    "gn:name":"Bitebe",
    "gn:population":0,
    "gn:timezone":"Pacific/Port_Moresby",
    "iso:country":"PG",
    "wof:name":"Bitebe",
    "wof:placetype":"locality"
},
  "geometry": {"coordinates":[145.69274999999999,-6.33806],"type":"Point"}
}