{
  "type": "Feature",
  "properties": {
    "gn:admin1_code":"06",
    "gn:asciiname":"Adulu",
    "gn:country_code":"PG",
    "gn:dem":15,
    "gn:feature_class":"P",
    "gn:feature_code":"PPL",
    "gn:name":"Adulu",
    "gn:population":0,
    "gn:timezone":"Pacific/Port_Moresby",
    "iso:country":"PG",
    "name:und_x_variant":[
        "Aduru",
        "Adulu"
    ],
    "wof:name":"Adulu",
    "wof:placetype":"locality"
},
  "geometry": {"coordinates":[143.01161999999999,-8.39075],"type":"Point"}
}