{
  "type": "Feature",
  "properties": {
    "gn:admin1_code":"14",
    "gn:asciiname":"Langa",
    "gn:country_code":"PG",
    "gn:dem":1029,
    "gn:feature_class":"P",
    "gn:feature_code":"PPL",
    "gn:name":"Langa",
    "gn:population":0,
    "gn:timezone":"Pacific/Port_Moresby",
    "iso:country":"PG",
    "wof:name":"Langa",
    "wof:placetype":"locality"
},
  "geometry": {"coordinates":[147.25543999999999,-6.15712],"type":"Point"}
}