{
  "type": "Feature",
  "properties": {
    "gn:admin1_code":"10",
    "gn:asciiname":"Peping",
    "gn:country_code":"PG",
    "gn:dem":374,
    "gn:feature_class":"P",
    "gn:feature_code":"PPL",
    "gn:name":"Peping",
    "gn:population":0,
    "gn:timezone":"Pacific/Port_Moresby",
    "iso:country":"PG",
    "wof:name":"Peping",
    "wof:placetype":"locality"
},
  "geometry": {"coordinates":[151.01660999999999,-5.89865],"type":"Point"}
}