{
  "type": "Feature",
  "properties": {
    "gn:admin1_code":"18",
    "gn:asciiname":"Nagatman",
    "gn:country_code":"PG",
    "gn:dem":64,
    "gn:feature_class":"P",
    "gn:feature_code":"PPL",
    "gn:name":"Nagatman",
    "gn:population":0,
    "gn:timezone":"Pacific/Port_Moresby",
    "iso:country":"PG",
    "name:und_x_variant":[
        "Nagatam",
        "Nagatman"
    ],
    "wof:name":"Nagatman",
    "wof:placetype":"locality"
},
  "geometry": {"coordinates":[141.47358,-3.74533],"type":"Point"}
}