{
  "type": "Feature",
  "properties": {
    "gn:admin1_code":"15",
    "gn:asciiname":"Selimun",
    "gn:country_code":"PG",
    "gn:dem":57,
    "gn:feature_class":"P",
    "gn:feature_code":"PPL",
    "gn:name":"Selimun",
    "gn:population":0,
    "gn:timezone":"Pacific/Port_Moresby",
    "iso:country":"PG",
    "wof:name":"Selimun",
    "wof:placetype":"locality"
},
  "geometry": {"coordinates":[152.46926999999999,-3.64967],"type":"Point"}
}