{
  "type": "Feature",
  "properties": {
    "gn:admin1_code":"08",
    "gn:asciiname":"Dinogobie",
    "gn:country_code":"PG",
    "gn:dem":1837,
    "gn:feature_class":"P",
    "gn:feature_code":"PPL",
    "gn:name":"Dinogobie",
    "gn:population":0,
    "gn:timezone":"Pacific/Port_Moresby",
    "iso:country":"PG",
    "wof:name":"Dinogobie",
    "wof:placetype":"locality"
},
  "geometry": {"coordinates":[145.05000000000001,-6.11667],"type":"Point"}
}