{
  "type": "Feature",
  "properties": {
    "gn:admin1_code":"09",
    "gn:asciiname":"Kindeimorofa",
    "gn:country_code":"PG",
    "gn:dem":2359,
    "gn:feature_class":"P",
    "gn:feature_code":"PPL",
    "gn:name":"Kindeimorofa",
    "gn:population":0,
    "gn:timezone":"Pacific/Port_Moresby",
    "iso:country":"PG",
    "wof:name":"Kindeimorofa",
    "wof:placetype":"locality"
},
  "geometry": {"coordinates":[145.21666999999999,-6.05],"type":"Point"}
}