{
  "type": "Feature",
  "properties": {
    "gn:admin1_code":"03",
    "gn:asciiname":"Elasi",
    "gn:country_code":"PG",
    "gn:dem":15,
    "gn:feature_class":"P",
    "gn:feature_code":"PPL",
    "gn:name":"Elasi",
    "gn:population":0,
    "gn:timezone":"Pacific/Port_Moresby",
    "iso:country":"PG",
    "name:und_x_variant":[
        "Elasi Mission",
        "Elasi"
    ],
    "wof:name":"Elasi",
    "wof:placetype":"locality"
},
  "geometry": {"coordinates":[151.14604,-10.02931],"type":"Point"}
}