{
  "type": "Feature",
  "properties": {
    "gn:admin1_code":"06",
    "gn:asciiname":"Wogam",
    "gn:country_code":"PG",
    "gn:dem":144,
    "gn:feature_class":"P",
    "gn:feature_code":"PPL",
    "gn:name":"Wogam",
    "gn:population":0,
    "gn:timezone":"Pacific/Port_Moresby",
    "iso:country":"PG",
    "wof:name":"Wogam",
    "wof:placetype":"locality"
},
  "geometry": {"coordinates":[141.12323000000001,-5.5899],"type":"Point"}
}