{
  "type": "Feature",
  "properties": {
    "gn:admin1_code":"06",
    "gn:asciiname":"Pisi",
    "gn:country_code":"PG",
    "gn:dem":7,
    "gn:feature_class":"P",
    "gn:feature_code":"PPL",
    "gn:name":"Pisi",
    "gn:population":0,
    "gn:timezone":"Pacific/Port_Moresby",
    "iso:country":"PG",
    "wof:name":"Pisi",
    "wof:placetype":"locality"
},
  "geometry": {"coordinates":[142.74821,-7.98768],"type":"Point"}
}