{
  "type": "Feature",
  "properties": {
    "gn:admin1_code":"08",
    "gn:asciiname":"Mo",
    "gn:country_code":"PG",
    "gn:dem":1386,
    "gn:feature_class":"P",
    "gn:feature_code":"PPL",
    "gn:name":"Mo",
    "gn:population":0,
    "gn:timezone":"Pacific/Port_Moresby",
    "iso:country":"PG",
    "name:bar_x_preferred":[
        "Mo"
    ],
    "name:hun_x_preferred":[
        "Mo"
    ],
    "name:ind_x_preferred":[
        "Mo"
    ],
    "name:rus_x_preferred":[
        "Mo"
    ],
    "wof:name":"Mo",
    "wof:placetype":"locality"
},
  "geometry": {"coordinates":[145.03333000000001,-6.25],"type":"Point"}
}