{
  "type": "Feature",
  "properties": {
    "gn:admin1_code":"10",
    "gn:asciiname":"Winagut",
    "gn:country_code":"PG",
    "gn:dem":40,
    "gn:feature_class":"P",
    "gn:feature_code":"PPL",
    "gn:name":"Winagut",
    "gn:population":0,
    "gn:timezone":"Pacific/Port_Moresby",
    "iso:country":"PG",
    "wof:name":"Winagut",
    "wof:placetype":"locality"
},
  "geometry": {"coordinates":[152.46666999999999,-4.15],"type":"Point"}
}