{
  "type": "Feature",
  "properties": {
    "gn:admin1_code":"19",
    "gn:asciiname":"Mang",
    "gn:country_code":"PG",
    "gn:dem":2385,
    "gn:feature_class":"P",
    "gn:feature_code":"PPL",
    "gn:name":"Mang",
    "gn:population":0,
    "gn:timezone":"Pacific/Port_Moresby",
    "iso:country":"PG",
    "name:ceb_x_preferred":[
        "Mang"
    ],
    "name:deu_x_preferred":[
        "Mang"
    ],
    "name:fra_x_preferred":[
        "Mang"
    ],
    "name:swe_x_preferred":[
        "Mang"
    ],
    "wof:name":"Mang",
    "wof:placetype":"locality"
},
  "geometry": {"coordinates":[143.46666999999999,-5.71667],"type":"Point"}
}