{
  "type": "Feature",
  "properties": {
    "gn:admin1_code":"12",
    "gn:asciiname":"Garigut",
    "gn:country_code":"PG",
    "gn:dem":285,
    "gn:feature_class":"P",
    "gn:feature_code":"PPL",
    "gn:name":"Garigut",
    "gn:population":0,
    "gn:timezone":"Pacific/Port_Moresby",
    "iso:country":"PG",
    "wof:name":"Garigut",
    "wof:placetype":"locality"
},
  "geometry": {"coordinates":[145.69293999999999,-5.0348],"type":"Point"}
}