{
  "type": "Feature",
  "properties": {
    "gn:admin1_code":"19",
    "gn:asciiname":"Maru",
    "gn:country_code":"PG",
    "gn:dem":2328,
    "gn:feature_class":"P",
    "gn:feature_code":"PPL",
    "gn:name":"Maru",
    "gn:population":0,
    "gn:timezone":"Pacific/Port_Moresby",
    "iso:country":"PG",
    "name:ceb_x_preferred":[
        "Maru"
    ],
    "name:deu_x_preferred":[
        "Maru"
    ],
    "name:est_x_preferred":[
        "Maru"
    ],
    "name:fra_x_preferred":[
        "Maru"
    ],
    "name:rus_x_preferred":[
        "\u041c\u0430\u0440\u0443"
    ],
    "name:srp_x_preferred":[
        "\u041c\u0430\u0440\u0443"
    ],
    "name:swe_x_preferred":[
        "Maru"
    ],
    "name:ukr_x_preferred":[
        "\u041c\u0430\u0440\u0443"
    ],
    "name:zho_x_preferred":[
        "Maru"
    ],
    "wof:name":"Maru",
    "wof:placetype":"locality"
},
  "geometry": {"coordinates":[143.45743000000004,-5.8993],"type":"Point"}
}