{
  "type": "Feature",
  "properties": {
    "gn:admin1_code":"15",
    "gn:asciiname":"Kumparum",
    "gn:country_code":"PG",
    "gn:dem":113,
    "gn:feature_class":"P",
    "gn:feature_code":"PPL",
    "gn:name":"Kumparum",
    "gn:population":0,
    "gn:timezone":"Pacific/Port_Moresby",
    "iso:country":"PG",
    "wof:name":"Kumparum",
    "wof:placetype":"locality"
},
  "geometry": {"coordinates":[153.01741000000001,-4.48492],"type":"Point"}
}