{
  "type": "Feature",
  "properties": {
    "gn:admin1_code":"01",
    "gn:asciiname":"Digurenda",
    "gn:country_code":"PG",
    "gn:dem":1426,
    "gn:feature_class":"P",
    "gn:feature_code":"PPL",
    "gn:name":"Digurenda",
    "gn:population":0,
    "gn:timezone":"Pacific/Port_Moresby",
    "iso:country":"PG",
    "wof:name":"Digurenda",
    "wof:placetype":"locality"
},
  "geometry": {"coordinates":[147.12624,-8.54246],"type":"Point"}
}