{
  "type": "Feature",
  "properties": {
    "gn:admin1_code":"02",
    "gn:asciiname":"Luluapo",
    "gn:country_code":"PG",
    "gn:dem":3,
    "gn:feature_class":"P",
    "gn:feature_code":"PPL",
    "gn:name":"Luluapo",
    "gn:population":0,
    "gn:timezone":"Pacific/Port_Moresby",
    "iso:country":"PG",
    "wof:name":"Luluapo",
    "wof:placetype":"locality"
},
  "geometry": {"coordinates":[146.27919,-8.17052],"type":"Point"}
}