{
  "type": "Feature",
  "properties": {
    "gn:admin1_code":"09",
    "gn:asciiname":"Tatura-Henegaru Number 3",
    "gn:country_code":"PG",
    "gn:dem":2155,
    "gn:feature_class":"P",
    "gn:feature_code":"PPL",
    "gn:name":"Tatura-Henegaru Number 3",
    "gn:population":0,
    "gn:timezone":"Pacific/Port_Moresby",
    "iso:country":"PG",
    "name:und_x_variant":[
        "Tatura-Henegaru 3",
        "Tatura-Henegaru Number 3"
    ],
    "wof:name":"Tatura-Henegaru Number 3",
    "wof:placetype":"locality"
},
  "geometry": {"coordinates":[145.40851000000001,-6.50245],"type":"Point"}
}