{
  "type": "Feature",
  "properties": {
    "gn:admin1_code":"05",
    "gn:asciiname":"Komia",
    "gn:country_code":"PG",
    "gn:dem":2302,
    "gn:feature_class":"P",
    "gn:feature_code":"PPL",
    "gn:name":"Komia",
    "gn:population":0,
    "gn:timezone":"Pacific/Port_Moresby",
    "iso:country":"PG",
    "wof:name":"Komia",
    "wof:placetype":"locality"
},
  "geometry": {"coordinates":[143.74621000000005,-6.02624],"type":"Point"}
}