{
  "type": "Feature",
  "properties": {
    "gn:admin1_code":"11",
    "gn:asciiname":"Old Wawat 2",
    "gn:country_code":"PG",
    "gn:dem":366,
    "gn:feature_class":"P",
    "gn:feature_code":"PPL",
    "gn:name":"Old Wawat 2",
    "gn:population":0,
    "gn:timezone":"Pacific/Port_Moresby",
    "iso:country":"PG",
    "wof:name":"Old Wawat 2",
    "wof:placetype":"locality"
},
  "geometry": {"coordinates":[143.76667,-3.71667],"type":"Point"}
}