{
  "type": "Feature",
  "properties": {
    "gn:admin1_code":"12",
    "gn:asciiname":"Wanuma",
    "gn:country_code":"PG",
    "gn:dem":753,
    "gn:feature_class":"P",
    "gn:feature_code":"PPL",
    "gn:name":"Wanuma",
    "gn:population":0,
    "gn:timezone":"Pacific/Port_Moresby",
    "iso:country":"PG",
    "wof:name":"Wanuma",
    "wof:placetype":"locality"
},
  "geometry": {"coordinates":[145.32846999999995,-4.84392],"type":"Point"}
}