{
  "type": "Feature",
  "properties": {
    "gn:admin1_code":"01",
    "gn:asciiname":"Uberi",
    "gn:country_code":"PG",
    "gn:dem":428,
    "gn:feature_class":"P",
    "gn:feature_code":"PPL",
    "gn:name":"Uberi",
    "gn:population":0,
    "gn:timezone":"Pacific/Port_Moresby",
    "iso:country":"PG",
    "wof:name":"Uberi",
    "wof:placetype":"locality"
},
  "geometry": {"coordinates":[147.49652,-9.35775],"type":"Point"}
}