{
  "type": "Feature",
  "properties": {
    "gn:admin1_code":"14",
    "gn:asciiname":"Yatsing",
    "gn:country_code":"PG",
    "gn:dem":193,
    "gn:feature_class":"P",
    "gn:feature_code":"PPL",
    "gn:name":"Yatsing",
    "gn:population":0,
    "gn:timezone":"Pacific/Port_Moresby",
    "iso:country":"PG",
    "wof:name":"Yatsing",
    "wof:placetype":"locality"
},
  "geometry": {"coordinates":[146.28412,-6.42049],"type":"Point"}
}