{
  "type": "Feature",
  "properties": {
    "gn:admin1_code":"14",
    "gn:asciiname":"Kalasu",
    "gn:country_code":"PG",
    "gn:dem":1113,
    "gn:feature_class":"P",
    "gn:feature_code":"PPL",
    "gn:name":"Kalasu",
    "gn:population":0,
    "gn:timezone":"Pacific/Port_Moresby",
    "iso:country":"PG",
    "wof:name":"Kalasu",
    "wof:placetype":"locality"
},
  "geometry": {"coordinates":[146.24566999999999,-7.42595],"type":"Point"}
}