{
  "type": "Feature",
  "properties": {
    "gn:admin1_code":"11",
    "gn:asciiname":"Bramik",
    "gn:country_code":"PG",
    "gn:dem":6,
    "gn:feature_class":"P",
    "gn:feature_code":"PPL",
    "gn:name":"Bramik",
    "gn:population":0,
    "gn:timezone":"Pacific/Port_Moresby",
    "iso:country":"PG",
    "wof:name":"Bramik",
    "wof:placetype":"locality"
},
  "geometry": {"coordinates":[144.36667,-3.81667],"type":"Point"}
}