{
  "type": "Feature",
  "properties": {
    "gn:admin1_code":"18",
    "gn:asciiname":"Old Fongwinam",
    "gn:country_code":"PG",
    "gn:dem":488,
    "gn:feature_class":"P",
    "gn:feature_code":"PPL",
    "gn:name":"Old Fongwinam",
    "gn:population":0,
    "gn:timezone":"Pacific/Port_Moresby",
    "iso:country":"PG",
    "wof:name":"Old Fongwinam",
    "wof:placetype":"locality"
},
  "geometry": {"coordinates":[141.05000000000001,-3.75],"type":"Point"}
}