{
  "type": "Feature",
  "properties": {
    "gn:admin1_code":"08",
    "gn:asciiname":"Sibaku",
    "gn:country_code":"PG",
    "gn:dem":1979,
    "gn:feature_class":"P",
    "gn:feature_code":"PPL",
    "gn:name":"Sibaku",
    "gn:population":0,
    "gn:timezone":"Pacific/Port_Moresby",
    "iso:country":"PG",
    "wof:name":"Sibaku",
    "wof:placetype":"locality"
},
  "geometry": {"coordinates":[145.06666999999999,-6.15],"type":"Point"}
}