{
  "type": "Feature",
  "properties": {
    "gn:admin1_code":"06",
    "gn:asciiname":"Wombon",
    "gn:country_code":"PG",
    "gn:dem":118,
    "gn:feature_class":"P",
    "gn:feature_code":"PPL",
    "gn:name":"Wombon",
    "gn:population":0,
    "gn:timezone":"Pacific/Port_Moresby",
    "iso:country":"PG",
    "wof:name":"Wombon",
    "wof:placetype":"locality"
},
  "geometry": {"coordinates":[141.11046999999999,-5.63517],"type":"Point"}
}