{
  "type": "Feature",
  "properties": {
    "gn:admin1_code":"11",
    "gn:asciiname":"Kubriwat",
    "gn:country_code":"PG",
    "gn:dem":253,
    "gn:feature_class":"P",
    "gn:feature_code":"PPL",
    "gn:name":"Kubriwat",
    "gn:population":0,
    "gn:timezone":"Pacific/Port_Moresby",
    "iso:country":"PG",
    "name:und_x_variant":[
        "Kubriwato",
        "Kubriwat Villages",
        "Kubriwat"
    ],
    "wof:name":"Kubriwat",
    "wof:placetype":"locality"
},
  "geometry": {"coordinates":[142.66513,-3.65923],"type":"Point"}
}