{
  "type": "Feature",
  "properties": {
    "gn:admin1_code":"11",
    "gn:asciiname":"Aibom",
    "gn:country_code":"PG",
    "gn:dem":4,
    "gn:feature_class":"P",
    "gn:feature_code":"PPL",
    "gn:name":"Aibom",
    "gn:population":0,
    "gn:timezone":"Pacific/Port_Moresby",
    "iso:country":"PG",
    "name:und_x_variant":[
        "Eibom",
        "Aibon",
        "Aibom"
    ],
    "wof:name":"Aibom",
    "wof:placetype":"locality"
},
  "geometry": {"coordinates":[143.12621999999999,-4.22249],"type":"Point"}
}