{
  "type": "Feature",
  "properties": {
    "gn:admin1_code":"11",
    "gn:asciiname":"Molio",
    "gn:country_code":"PG",
    "gn:dem":52,
    "gn:feature_class":"P",
    "gn:feature_code":"PPL",
    "gn:name":"Molio",
    "gn:population":0,
    "gn:timezone":"Pacific/Port_Moresby",
    "iso:country":"PG",
    "name:und_x_variant":[
        "Moli",
        "Molio"
    ],
    "wof:name":"Molio",
    "wof:placetype":"locality"
},
  "geometry": {"coordinates":[142.89944,-4.61654],"type":"Point"}
}