{
  "type": "Feature",
  "properties": {
    "gn:admin1_code":"13",
    "gn:asciiname":"Kapo",
    "gn:cc2":"PG",
    "gn:country_code":"PG",
    "gn:dem":110,
    "gn:feature_class":"P",
    "gn:feature_code":"PPL",
    "gn:name":"Kapo",
    "gn:population":0,
    "gn:timezone":"Pacific/Port_Moresby",
    "iso:country":"PG",
    "name:cat_x_preferred":[
        "Kapo"
    ],
    "name:deu_x_preferred":[
        "Kapo"
    ],
    "name:epo_x_preferred":[
        "Kapo"
    ],
    "name:fin_x_preferred":[
        "Kapo"
    ],
    "name:fra_x_preferred":[
        "Kapo"
    ],
    "name:pol_x_preferred":[
        "Kapo"
    ],
    "name:por_x_preferred":[
        "Kapo"
    ],
    "name:rus_x_preferred":[
        "\u041a\u0430\u043f\u043e"
    ],
    "name:und_x_variant":[
        "Kapor",
        "Kapo"
    ],
    "wof:name":"Kapo",
    "wof:placetype":"locality"
},
  "geometry": {"coordinates":[147.18333000000001,-2.13333],"type":"Point"}
}