{
  "type": "Feature",
  "properties": {
    "gn:admin1_code":"18",
    "gn:asciiname":"Unanklimin Number 2",
    "gn:country_code":"PG",
    "gn:dem":1583,
    "gn:feature_class":"P",
    "gn:feature_code":"PPL",
    "gn:name":"Unanklimin Number 2",
    "gn:population":0,
    "gn:timezone":"Pacific/Port_Moresby",
    "iso:country":"PG",
    "name:und_x_variant":[
        "Unanklimin 2",
        "Unanklimin Number 2"
    ],
    "wof:name":"Unanklimin Number 2",
    "wof:placetype":"locality"
},
  "geometry": {"coordinates":[141.16641999999999,-4.85554],"type":"Point"}
}