{
  "type": "Feature",
  "properties": {
    "gn:admin1_code":"09",
    "gn:asciiname":"Oiafaiyufa",
    "gn:country_code":"PG",
    "gn:dem":1527,
    "gn:feature_class":"P",
    "gn:feature_code":"PPL",
    "gn:name":"Oiafaiyufa",
    "gn:population":0,
    "gn:timezone":"Pacific/Port_Moresby",
    "iso:country":"PG",
    "wof:name":"Oiafaiyufa",
    "wof:placetype":"locality"
},
  "geometry": {"coordinates":[145.34999999999999,-6.16667],"type":"Point"}
}