{
  "type": "Feature",
  "properties": {
    "gn:admin1_code":"11",
    "gn:asciiname":"Numiasoli",
    "gn:country_code":"PG",
    "gn:dem":201,
    "gn:feature_class":"P",
    "gn:feature_code":"PPL",
    "gn:name":"Numiasoli",
    "gn:population":0,
    "gn:timezone":"Pacific/Port_Moresby",
    "iso:country":"PG",
    "wof:name":"Numiasoli",
    "wof:placetype":"locality"
},
  "geometry": {"coordinates":[143.33815000000001,-3.69699],"type":"Point"}
}