{
  "type": "Feature",
  "properties": {
    "gn:admin1_code":"09",
    "gn:asciiname":"Kerebabi",
    "gn:country_code":"PG",
    "gn:dem":1912,
    "gn:feature_class":"P",
    "gn:feature_code":"PPL",
    "gn:name":"Kerebabi",
    "gn:population":0,
    "gn:timezone":"Pacific/Port_Moresby",
    "iso:country":"PG",
    "wof:name":"Kerebabi",
    "wof:placetype":"locality"
},
  "geometry": {"coordinates":[145.62020999999999,-6.34352],"type":"Point"}
}