{
  "type": "Feature",
  "properties": {
    "gn:admin1_code":"12",
    "gn:asciiname":"Barum",
    "gn:country_code":"PG",
    "gn:dem":251,
    "gn:feature_class":"P",
    "gn:feature_code":"PPL",
    "gn:name":"Barum",
    "gn:population":0,
    "gn:timezone":"Pacific/Port_Moresby",
    "iso:country":"PG",
    "name:ceb_x_preferred":[
        "Barum"
    ],
    "name:dan_x_preferred":[
        "Barum"
    ],
    "name:deu_x_preferred":[
        "Barum"
    ],
    "name:epo_x_preferred":[
        "Barum"
    ],
    "name:eus_x_preferred":[
        "Barum"
    ],
    "name:fra_x_preferred":[
        "Barum"
    ],
    "name:hun_x_preferred":[
        "Barum"
    ],
    "name:ita_x_preferred":[
        "Barum"
    ],
    "name:nds_x_preferred":[
        "Barum"
    ],
    "name:nld_x_preferred":[
        "Barum"
    ],
    "name:pol_x_preferred":[
        "Barum"
    ],
    "name:por_x_preferred":[
        "Barum"
    ],
    "name:rus_x_preferred":[
        "\u0411\u0430\u0440\u0443\u043c"
    ],
    "wof:name":"Barum",
    "wof:placetype":"locality"
},
  "geometry": {"coordinates":[145.77396000000005,-5.52093],"type":"Point"}
}