{
  "type": "Feature",
  "properties": {
    "gn:admin1_code":"10",
    "gn:asciiname":"Vunalir",
    "gn:country_code":"PG",
    "gn:dem":36,
    "gn:feature_class":"P",
    "gn:feature_code":"PPL",
    "gn:name":"Vunalir",
    "gn:population":0,
    "gn:timezone":"Pacific/Port_Moresby",
    "iso:country":"PG",
    "wof:name":"Vunalir",
    "wof:placetype":"locality"
},
  "geometry": {"coordinates":[152.05276000000001,-4.20938],"type":"Point"}
}