{
  "type": "Feature",
  "properties": {
    "gn:admin1_code":"09",
    "gn:asciiname":"Waisa",
    "gn:country_code":"PG",
    "gn:dem":1915,
    "gn:feature_class":"P",
    "gn:feature_code":"PPL",
    "gn:name":"Waisa",
    "gn:population":0,
    "gn:timezone":"Pacific/Port_Moresby",
    "iso:country":"PG",
    "wof:name":"Waisa",
    "wof:placetype":"locality"
},
  "geometry": {"coordinates":[145.54321999999999,-6.63359],"type":"Point"}
}