{
  "type": "Feature",
  "properties": {
    "gn:admin1_code":"19",
    "gn:asciiname":"Lajeasa",
    "gn:country_code":"PG",
    "gn:dem":2119,
    "gn:feature_class":"P",
    "gn:feature_code":"PPL",
    "gn:name":"Lajeasa",
    "gn:population":0,
    "gn:timezone":"Pacific/Port_Moresby",
    "iso:country":"PG",
    "wof:name":"Lajeasa",
    "wof:placetype":"locality"
},
  "geometry": {"coordinates":[143.85201999999995,-5.70768],"type":"Point"}
}