{
  "type": "Feature",
  "properties": {
    "gn:admin1_code":"18",
    "gn:asciiname":"Pimon",
    "gn:country_code":"PG",
    "gn:dem":529,
    "gn:feature_class":"P",
    "gn:feature_code":"PPL",
    "gn:name":"Pimon",
    "gn:population":0,
    "gn:timezone":"Pacific/Port_Moresby",
    "iso:country":"PG",
    "wof:name":"Pimon",
    "wof:placetype":"locality"
},
  "geometry": {"coordinates":[142.17493000000005,-3.49683],"type":"Point"}
}