{
  "type": "Feature",
  "properties": {
    "gn:admin1_code":"14",
    "gn:asciiname":"Zitari",
    "gn:country_code":"PG",
    "gn:dem":2170,
    "gn:feature_class":"P",
    "gn:feature_code":"PPL",
    "gn:name":"Zitari",
    "gn:population":0,
    "gn:timezone":"Pacific/Port_Moresby",
    "iso:country":"PG",
    "wof:name":"Zitari",
    "wof:placetype":"locality"
},
  "geometry": {"coordinates":[147.01667,-6.43333],"type":"Point"}
}