{
  "type": "Feature",
  "properties": {
    "gn:admin1_code":"11",
    "gn:asciiname":"Chauche",
    "gn:cc2":"PG",
    "gn:country_code":"PG",
    "gn:dem":26,
    "gn:feature_class":"P",
    "gn:feature_code":"PPL",
    "gn:name":"Chauche",
    "gn:population":0,
    "gn:timezone":"Pacific/Port_Moresby",
    "iso:country":"PG",
    "name:und_x_variant":[
        "Chauache",
        "Chauche"
    ],
    "wof:name":"Chauche",
    "wof:placetype":"locality"
},
  "geometry": {"coordinates":[143.13333,-4.03333],"type":"Point"}
}