{
  "type": "Feature",
  "properties": {
    "gn:admin1_code":"12",
    "gn:asciiname":"Garup",
    "gn:country_code":"PG",
    "gn:dem":8,
    "gn:feature_class":"P",
    "gn:feature_code":"PPL",
    "gn:name":"Garup",
    "gn:population":0,
    "gn:timezone":"Pacific/Port_Moresby",
    "iso:country":"PG",
    "name:eng_x_preferred":[
        "Garup"
    ],
    "wof:name":"Garup",
    "wof:placetype":"locality"
},
  "geometry": {"coordinates":[145.77913000000001,-4.96701],"type":"Point"}
}