{
  "type": "Feature",
  "properties": {
    "gn:admin1_code":"12",
    "gn:admin2_code":"7910339",
    "gn:asciiname":"Silaul",
    "gn:country_code":"PG",
    "gn:dem":82,
    "gn:feature_class":"P",
    "gn:feature_code":"PPL",
    "gn:name":"Silaul",
    "gn:population":0,
    "gn:timezone":"Pacific/Port_Moresby",
    "iso:country":"PG",
    "wof:name":"Silaul",
    "wof:placetype":"locality"
},
  "geometry": {"coordinates":[145.56726,-5.18126],"type":"Point"}
}