{
  "type": "Feature",
  "properties": {
    "gn:admin1_code":"12",
    "gn:asciiname":"Baskan",
    "gn:country_code":"PG",
    "gn:dem":822,
    "gn:feature_class":"P",
    "gn:feature_code":"PPL",
    "gn:name":"Baskan",
    "gn:population":0,
    "gn:timezone":"Pacific/Port_Moresby",
    "iso:country":"PG",
    "name:und_x_variant":[
        "Boskan",
        "Baskan"
    ],
    "wof:name":"Baskan",
    "wof:placetype":"locality"
},
  "geometry": {"coordinates":[145.51487,-4.84018],"type":"Point"}
}