{
  "type": "Feature",
  "properties": {
    "gn:admin1_code":"11",
    "gn:asciiname":"Misim",
    "gn:country_code":"PG",
    "gn:dem":334,
    "gn:feature_class":"P",
    "gn:feature_code":"PPL",
    "gn:name":"Misim",
    "gn:population":0,
    "gn:timezone":"Pacific/Port_Moresby",
    "iso:country":"PG",
    "wof:name":"Misim",
    "wof:placetype":"locality"
},
  "geometry": {"coordinates":[142.80651,-3.55464],"type":"Point"}
}