{
  "type": "Feature",
  "properties": {
    "gn:admin1_code":"04",
    "gn:asciiname":"Iwaia",
    "gn:country_code":"PG",
    "gn:dem":24,
    "gn:feature_class":"P",
    "gn:feature_code":"PPL",
    "gn:name":"Iwaia",
    "gn:population":0,
    "gn:timezone":"Pacific/Port_Moresby",
    "iso:country":"PG",
    "name:und_x_variant":[
        "Iwaia Mission",
        "Iwai\u2019ia",
        "Iwaia"
    ],
    "wof:name":"Iwaia",
    "wof:placetype":"locality"
},
  "geometry": {"coordinates":[148.14102,-8.1391],"type":"Point"}
}