{
  "type": "Feature",
  "properties": {
    "gn:admin1_code":"12",
    "gn:asciiname":"Bimat",
    "gn:country_code":"PG",
    "gn:dem":86,
    "gn:feature_class":"P",
    "gn:feature_code":"PPL",
    "gn:name":"Bimat",
    "gn:population":0,
    "gn:timezone":"Pacific/Port_Moresby",
    "iso:country":"PG",
    "wof:name":"Bimat",
    "wof:placetype":"locality"
},
  "geometry": {"coordinates":[145.08527000000001,-4.36969],"type":"Point"}
}