{
  "type": "Feature",
  "properties": {
    "gn:admin1_code":"17",
    "gn:asciiname":"Lapau",
    "gn:country_code":"PG",
    "gn:dem":37,
    "gn:feature_class":"P",
    "gn:feature_code":"PPL",
    "gn:name":"Lapau",
    "gn:population":0,
    "gn:timezone":"Pacific/Port_Moresby",
    "iso:country":"PG",
    "name:jpn_x_preferred":[
        "\u30e9\u30d1\u30a6"
    ],
    "name:msa_x_preferred":[
        "Lapau"
    ],
    "wof:name":"Lapau",
    "wof:placetype":"locality"
},
  "geometry": {"coordinates":[151.13333,-4.93333],"type":"Point"}
}