{
  "type": "Feature",
  "properties": {
    "gn:admin1_code":"16",
    "gn:asciiname":"Timbunki",
    "gn:country_code":"PG",
    "gn:dem":465,
    "gn:feature_class":"P",
    "gn:feature_code":"PPL",
    "gn:name":"Timbunki",
    "gn:population":0,
    "gn:timezone":"Pacific/Port_Moresby",
    "iso:country":"PG",
    "wof:name":"Timbunki",
    "wof:placetype":"locality"
},
  "geometry": {"coordinates":[144.48228,-5.44799],"type":"Point"}
}