{
  "type": "Feature",
  "properties": {
    "gn:admin1_code":"12",
    "gn:asciiname":"Parawen",
    "gn:country_code":"PG",
    "gn:dem":175,
    "gn:feature_class":"P",
    "gn:feature_code":"PPL",
    "gn:name":"Parawen",
    "gn:population":0,
    "gn:timezone":"Pacific/Port_Moresby",
    "iso:country":"PG",
    "wof:name":"Parawen",
    "wof:placetype":"locality"
},
  "geometry": {"coordinates":[145.40000000000001,-5.03333],"type":"Point"}
}