{
  "type": "Feature",
  "properties": {
    "gn:admin1_code":"11",
    "gn:asciiname":"Yamok",
    "gn:cc2":"PG",
    "gn:country_code":"PG",
    "gn:dem":26,
    "gn:feature_class":"P",
    "gn:feature_code":"PPL",
    "gn:name":"Yamok",
    "gn:population":0,
    "gn:timezone":"Pacific/Port_Moresby",
    "iso:country":"PG",
    "name:und_x_variant":[
        "Wanike",
        "Yamok 3",
        "Yamok"
    ],
    "wof:name":"Yamok",
    "wof:placetype":"locality"
},
  "geometry": {"coordinates":[143.21666999999999,-4.08333],"type":"Point"}
}