{
  "type": "Feature",
  "properties": {
    "gn:admin1_code":"11",
    "gn:asciiname":"W'haukia",
    "gn:country_code":"PG",
    "gn:dem":185,
    "gn:feature_class":"P",
    "gn:feature_code":"PPL",
    "gn:name":"W\u2019haukia",
    "gn:population":0,
    "gn:timezone":"Pacific/Port_Moresby",
    "iso:country":"PG",
    "wof:name":"W'haukia",
    "wof:placetype":"locality"
},
  "geometry": {"coordinates":[142.66588000000004,-3.74468],"type":"Point"}
}