{
  "type": "Feature",
  "properties": {
    "gn:admin1_code":"06",
    "gn:asciiname":"Weam",
    "gn:country_code":"PG",
    "gn:dem":15,
    "gn:feature_class":"P",
    "gn:feature_code":"PPL",
    "gn:name":"Weam",
    "gn:population":0,
    "gn:timezone":"Pacific/Port_Moresby",
    "iso:country":"PG",
    "name:und_x_variant":[
        "Witran",
        "Weam Patrol Post",
        "Witrah",
        "Weam"
    ],
    "wof:name":"Weam",
    "wof:placetype":"locality"
},
  "geometry": {"coordinates":[141.13666000000001,-8.61991],"type":"Point"}
}