{
  "type": "Feature",
  "properties": {
    "gn:admin1_code":"18",
    "gn:asciiname":"Wimurapmin Number 3",
    "gn:country_code":"PG",
    "gn:dem":1226,
    "gn:feature_class":"P",
    "gn:feature_code":"PPL",
    "gn:name":"Wimurapmin Number 3",
    "gn:population":0,
    "gn:timezone":"Pacific/Port_Moresby",
    "iso:country":"PG",
    "name:und_x_variant":[
        "Wimurapmin 3",
        "Wimurapmin Number 3"
    ],
    "wof:name":"Wimurapmin Number 3",
    "wof:placetype":"locality"
},
  "geometry": {"coordinates":[141.08276999999995,-4.80657],"type":"Point"}
}