{
  "type": "Feature",
  "properties": {
    "gn:admin1_code":"09",
    "gn:asciiname":"Sidam",
    "gn:country_code":"PG",
    "gn:dem":1638,
    "gn:feature_class":"P",
    "gn:feature_code":"PPL",
    "gn:name":"Sidam",
    "gn:population":0,
    "gn:timezone":"Pacific/Port_Moresby",
    "iso:country":"PG",
    "wof:name":"Sidam",
    "wof:placetype":"locality"
},
  "geometry": {"coordinates":[145.46666999999999,-6.51667],"type":"Point"}
}