{
  "type": "Feature",
  "properties": {
    "gn:admin1_code":"06",
    "gn:asciiname":"Kukuboio",
    "gn:cc2":"PG",
    "gn:country_code":"PG",
    "gn:dem":21,
    "gn:feature_class":"P",
    "gn:feature_code":"PPL",
    "gn:name":"Kukuboio",
    "gn:population":0,
    "gn:timezone":"Pacific/Port_Moresby",
    "iso:country":"PG",
    "name:und_x_variant":[
        "Kukubaia",
        "Kukuboio"
    ],
    "wof:name":"Kukuboio",
    "wof:placetype":"locality"
},
  "geometry": {"coordinates":[143.21666999999999,-7.63333],"type":"Point"}
}