{
  "type": "Feature",
  "properties": {
    "gn:admin1_code":"11",
    "gn:asciiname":"Japuain",
    "gn:country_code":"PG",
    "gn:dem":671,
    "gn:feature_class":"P",
    "gn:feature_code":"PPL",
    "gn:name":"Japuain",
    "gn:population":0,
    "gn:timezone":"Pacific/Port_Moresby",
    "iso:country":"PG",
    "wof:name":"Japuain",
    "wof:placetype":"locality"
},
  "geometry": {"coordinates":[143.26876999999999,-3.48801],"type":"Point"}
}