{
  "type": "Feature",
  "properties": {
    "gn:admin1_code":"10",
    "gn:asciiname":"Kaitoto",
    "gn:country_code":"PG",
    "gn:dem":579,
    "gn:feature_class":"P",
    "gn:feature_code":"PPL",
    "gn:name":"Kaitoto",
    "gn:population":0,
    "gn:timezone":"Pacific/Port_Moresby",
    "iso:country":"PG",
    "wof:name":"Kaitoto",
    "wof:placetype":"locality"
},
  "geometry": {"coordinates":[151.09999999999999,-5.73333],"type":"Point"}
}