{
  "type": "Feature",
  "properties": {
    "gn:admin1_code":"06",
    "gn:asciiname":"Bubuji",
    "gn:country_code":"PG",
    "gn:dem":53,
    "gn:feature_class":"P",
    "gn:feature_code":"PPL",
    "gn:name":"Bubuji",
    "gn:population":0,
    "gn:timezone":"Pacific/Port_Moresby",
    "iso:country":"PG",
    "wof:name":"Bubuji",
    "wof:placetype":"locality"
},
  "geometry": {"coordinates":[142.48038,-8.78691],"type":"Point"}
}