{
  "type": "Feature",
  "properties": {
    "gn:admin1_code":"14",
    "gn:asciiname":"Safifi",
    "gn:country_code":"PG",
    "gn:dem":845,
    "gn:feature_class":"P",
    "gn:feature_code":"PPL",
    "gn:name":"Safifi",
    "gn:population":0,
    "gn:timezone":"Pacific/Port_Moresby",
    "iso:country":"PG",
    "wof:name":"Safifi",
    "wof:placetype":"locality"
},
  "geometry": {"coordinates":[147.60766999999996,-6.57732],"type":"Point"}
}