{
  "type": "Feature",
  "properties": {
    "gn:admin1_code":"12",
    "gn:asciiname":"Subura",
    "gn:country_code":"PG",
    "gn:dem":253,
    "gn:feature_class":"P",
    "gn:feature_code":"PPL",
    "gn:name":"Subura",
    "gn:population":0,
    "gn:timezone":"Pacific/Port_Moresby",
    "iso:country":"PG",
    "wof:name":"Subura",
    "wof:placetype":"locality"
},
  "geometry": {"coordinates":[146.52802,-5.69663],"type":"Point"}
}