{
  "type": "Feature",
  "properties": {
    "gn:admin1_code":"14",
    "gn:asciiname":"Sambori",
    "gn:country_code":"PG",
    "gn:dem":1150,
    "gn:feature_class":"P",
    "gn:feature_code":"PPL",
    "gn:name":"Sambori",
    "gn:population":0,
    "gn:timezone":"Pacific/Port_Moresby",
    "iso:country":"PG",
    "wof:name":"Sambori",
    "wof:placetype":"locality"
},
  "geometry": {"coordinates":[147.27756000000005,-6.12801],"type":"Point"}
}