{
  "type": "Feature",
  "properties": {
    "gn:admin1_code":"02",
    "gn:asciiname":"Emu Village",
    "gn:country_code":"PG",
    "gn:dem":8,
    "gn:feature_class":"P",
    "gn:feature_code":"PPL",
    "gn:name":"Emu Village",
    "gn:population":0,
    "gn:timezone":"Pacific/Port_Moresby",
    "iso:country":"PG",
    "name:und_x_variant":[
        "Morere",
        "Emu Village"
    ],
    "wof:name":"Emu Village",
    "wof:placetype":"locality"
},
  "geometry": {"coordinates":[144.40378999999999,-7.34555],"type":"Point"}
}