{
  "type": "Feature",
  "properties": {
    "gn:admin1_code":"05",
    "gn:asciiname":"Kelta",
    "gn:country_code":"PG",
    "gn:dem":2099,
    "gn:feature_class":"P",
    "gn:feature_code":"PPL",
    "gn:name":"Kelta",
    "gn:population":0,
    "gn:timezone":"Pacific/Port_Moresby",
    "iso:country":"PG",
    "wof:name":"Kelta",
    "wof:placetype":"locality"
},
  "geometry": {"coordinates":[143.65549999999999,-5.99892],"type":"Point"}
}