{
  "type": "Feature",
  "properties": {
    "gn:admin1_code":"11",
    "gn:asciiname":"Kworabi",
    "gn:country_code":"PG",
    "gn:dem":336,
    "gn:feature_class":"P",
    "gn:feature_code":"PPL",
    "gn:name":"Kworabi",
    "gn:population":0,
    "gn:timezone":"Pacific/Port_Moresby",
    "iso:country":"PG",
    "name:und_x_variant":[
        "Kworabri",
        "Kworabi"
    ],
    "wof:name":"Kworabi",
    "wof:placetype":"locality"
},
  "geometry": {"coordinates":[143.31077999999999,-3.62914],"type":"Point"}
}