{
  "type": "Feature",
  "properties": {
    "gn:admin1_code":"01",
    "gn:asciiname":"Nikura",
    "gn:country_code":"PG",
    "gn:dem":17,
    "gn:feature_class":"P",
    "gn:feature_code":"PPL",
    "gn:name":"Nikura",
    "gn:population":0,
    "gn:timezone":"Pacific/Port_Moresby",
    "iso:country":"PG",
    "name:und_x_variant":[
        "Nikora",
        "Nicora",
        "Nikura"
    ],
    "wof:name":"Nikura",
    "wof:placetype":"locality"
},
  "geometry": {"coordinates":[146.61654999999999,-8.79394],"type":"Point"}
}