{
  "type": "Feature",
  "properties": {
    "gn:admin1_code":"08",
    "gn:asciiname":"Nul",
    "gn:country_code":"PG",
    "gn:dem":1390,
    "gn:feature_class":"P",
    "gn:feature_code":"PPL",
    "gn:name":"Nul",
    "gn:population":0,
    "gn:timezone":"Pacific/Port_Moresby",
    "iso:country":"PG",
    "wof:name":"Nul",
    "wof:placetype":"locality"
},
  "geometry": {"coordinates":[144.94364999999999,-6.13612],"type":"Point"}
}