{
  "type": "Feature",
  "properties": {
    "gn:admin1_code":"12",
    "gn:asciiname":"Waipken",
    "gn:country_code":"PG",
    "gn:dem":481,
    "gn:feature_class":"P",
    "gn:feature_code":"PPL",
    "gn:name":"Waipken",
    "gn:population":0,
    "gn:timezone":"Pacific/Port_Moresby",
    "iso:country":"PG",
    "wof:name":"Waipken",
    "wof:placetype":"locality"
},
  "geometry": {"coordinates":[145.63333,-4.83333],"type":"Point"}
}