{
  "type": "Feature",
  "properties": {
    "gn:admin1_code":"01",
    "gn:asciiname":"Vinigibara",
    "gn:country_code":"PG",
    "gn:dem":39,
    "gn:feature_class":"P",
    "gn:feature_code":"PPL",
    "gn:name":"Vinigibara",
    "gn:population":0,
    "gn:timezone":"Pacific/Port_Moresby",
    "iso:country":"PG",
    "wof:name":"Vinigibara",
    "wof:placetype":"locality"
},
  "geometry": {"coordinates":[147.71666999999999,-9.78333],"type":"Point"}
}