{
  "type": "Feature",
  "properties": {
    "gn:admin1_code":"11",
    "gn:asciiname":"Wingamon",
    "gn:country_code":"PG",
    "gn:dem":352,
    "gn:feature_class":"P",
    "gn:feature_code":"PPL",
    "gn:name":"Wingamon",
    "gn:population":0,
    "gn:timezone":"Pacific/Port_Moresby",
    "iso:country":"PG",
    "wof:name":"Wingamon",
    "wof:placetype":"locality"
},
  "geometry": {"coordinates":[142.67401999999996,-3.5737],"type":"Point"}
}