{
  "type": "Feature",
  "properties": {
    "gn:admin1_code":"04",
    "gn:asciiname":"Moiavi",
    "gn:country_code":"PG",
    "gn:dem":31,
    "gn:feature_class":"P",
    "gn:feature_code":"PPL",
    "gn:name":"Moiavi",
    "gn:population":0,
    "gn:timezone":"Pacific/Port_Moresby",
    "iso:country":"PG",
    "wof:name":"Moiavi",
    "wof:placetype":"locality"
},
  "geometry": {"coordinates":[148.73141000000001,-9.23332],"type":"Point"}
}