{
  "type": "Feature",
  "properties": {
    "gn:admin1_code":"15",
    "gn:asciiname":"Hunabore",
    "gn:country_code":"PG",
    "gn:dem":42,
    "gn:feature_class":"P",
    "gn:feature_code":"PPL",
    "gn:name":"Hunabore",
    "gn:population":0,
    "gn:timezone":"Pacific/Port_Moresby",
    "iso:country":"PG",
    "wof:name":"Hunabore",
    "wof:placetype":"locality"
},
  "geometry": {"coordinates":[152.42389,-3.77677],"type":"Point"}
}