{
  "type": "Feature",
  "properties": {
    "gn:admin1_code":"08",
    "gn:asciiname":"Garinggagu",
    "gn:country_code":"PG",
    "gn:dem":2588,
    "gn:feature_class":"P",
    "gn:feature_code":"PPL",
    "gn:name":"Garinggagu",
    "gn:population":0,
    "gn:timezone":"Pacific/Port_Moresby",
    "iso:country":"PG",
    "wof:name":"Garinggagu",
    "wof:placetype":"locality"
},
  "geometry": {"coordinates":[145.11667,-5.86667],"type":"Point"}
}