{
  "type": "Feature",
  "properties": {
    "gn:admin1_code":"11",
    "gn:asciiname":"Kambaramba",
    "gn:country_code":"PG",
    "gn:dem":5,
    "gn:feature_class":"P",
    "gn:feature_code":"PPL",
    "gn:name":"Kambaramba",
    "gn:population":0,
    "gn:timezone":"Pacific/Port_Moresby",
    "iso:country":"PG",
    "wof:name":"Kambaramba",
    "wof:placetype":"locality"
},
  "geometry": {"coordinates":[144.01116000000005,-4.18396],"type":"Point"}
}