{
  "type": "Feature",
  "properties": {
    "gn:admin1_code":"04",
    "gn:asciiname":"Dabo",
    "gn:country_code":"PG",
    "gn:dem":34,
    "gn:feature_class":"P",
    "gn:feature_code":"PPL",
    "gn:name":"Dabo",
    "gn:population":0,
    "gn:timezone":"Pacific/Port_Moresby",
    "iso:country":"PG",
    "name:eng_x_preferred":[
        "Dabo"
    ],
    "name:fra_x_preferred":[
        "Dabo"
    ],
    "wof:name":"Dabo",
    "wof:placetype":"locality"
},
  "geometry": {"coordinates":[147.84309999999999,-8.43086],"type":"Point"}
}