{
  "type": "Feature",
  "properties": {
    "gn:admin1_code":"10",
    "gn:asciiname":"Alkasam",
    "gn:country_code":"PG",
    "gn:dem":539,
    "gn:feature_class":"P",
    "gn:feature_code":"PPL",
    "gn:name":"Alkasam",
    "gn:population":0,
    "gn:timezone":"Pacific/Port_Moresby",
    "iso:country":"PG",
    "wof:name":"Alkasam",
    "wof:placetype":"locality"
},
  "geometry": {"coordinates":[151.83333000000005,-4.48333],"type":"Point"}
}