{
  "type": "Feature",
  "properties": {
    "gn:country":"PG",
    "gn:fcode":"PPL",
    "gn:pop":11536,
    "iso:country":"PG",
    "name:cat_x_preferred":[
        "Kiunga"
    ],
    "name:chi_x_preferred":[
        "\u57fa\u6eab\u52a0"
    ],
    "name:dut_x_preferred":[
        "Kiunga"
    ],
    "name:eng_x_preferred":[
        "Kiunga"
    ],
    "name:fre_x_preferred":[
        "Kiunga"
    ],
    "name:ger_x_preferred":[
        "Kiunga"
    ],
    "name:jpn_x_preferred":[
        "\u30ad\u30a6\u30f3\u30ac"
    ],
    "name:per_x_preferred":[
        "\u06a9\u06cc\u0648\u0646\u06af\u0627"
    ],
    "name:pol_x_preferred":[
        "Kiunga"
    ],
    "name:por_x_preferred":[
        "Kiunga"
    ],
    "name:rus_x_preferred":[
        "\u041a\u0438\u0443\u043d\u0433\u0430"
    ],
    "name:spa_x_preferred":[
        "Kiunga"
    ],
    "qs:name":"Kiunga",
    "qs:photos_9r":0,
    "qs:photos_sr":0,
    "qs:pop_sr":"6",
    "wd:wordcount":21,
    "wof:name":"Kiunga",
    "wof:placetype":"locality",
    "wof:population":11536
},
  "geometry": {"coordinates":[141.29060999999999,-6.12193],"type":"Point"}
}