{
  "type": "Feature",
  "properties": {
    "gn:admin1_code":"12",
    "gn:asciiname":"Niningo",
    "gn:country_code":"PG",
    "gn:dem":1249,
    "gn:feature_class":"P",
    "gn:feature_code":"PPL",
    "gn:name":"Niningo",
    "gn:population":0,
    "gn:timezone":"Pacific/Port_Moresby",
    "iso:country":"PG",
    "wof:name":"Niningo",
    "wof:placetype":"locality"
},
  "geometry": {"coordinates":[145.94667999999999,-5.8448],"type":"Point"}
}