{
  "type": "Feature",
  "properties": {
    "gn:admin1_code":"15",
    "gn:asciiname":"Galusu",
    "gn:country_code":"PG",
    "gn:dem":29,
    "gn:feature_class":"P",
    "gn:feature_code":"PPL",
    "gn:name":"Galusu",
    "gn:population":0,
    "gn:timezone":"Pacific/Port_Moresby",
    "iso:country":"PG",
    "name:und_x_variant":[
        "Galasu",
        "Galusu"
    ],
    "wof:name":"Galusu",
    "wof:placetype":"locality"
},
  "geometry": {"coordinates":[153.68894,-4.01377],"type":"Point"}
}