{
  "type": "Feature",
  "properties": {
    "gn:admin1_code":"11",
    "gn:asciiname":"Ilahop",
    "gn:country_code":"PG",
    "gn:dem":182,
    "gn:feature_class":"P",
    "gn:feature_code":"PPL",
    "gn:name":"Ilahop",
    "gn:population":0,
    "gn:timezone":"Pacific/Port_Moresby",
    "iso:country":"PG",
    "wof:name":"Ilahop",
    "wof:placetype":"locality"
},
  "geometry": {"coordinates":[142.94761,-3.63553],"type":"Point"}
}