{
  "type": "Feature",
  "properties": {
    "iso:country":"PG",
    "name:ceb_x_preferred":[
        "Ambunti"
    ],
    "name:eng_x_preferred":[
        "Ambunti"
    ],
    "name:fas_x_preferred":[
        "\u0622\u0645\u0628\u0648\u0646\u062a\u06cc"
    ],
    "name:nld_x_preferred":[
        "Ambunti"
    ],
    "name:rus_x_preferred":[
        "\u0410\u043c\u0431\u0443\u043d\u0442\u0438"
    ],
    "name:ukr_x_preferred":[
        "\u0410\u043c\u0431\u0443\u043d\u0442\u0456"
    ],
    "name:zho_x_preferred":[
        "\u5b89\u672c\u8482"
    ],
    "qs:gn_country":"PG",
    "qs:gn_fcode":"PPL",
    "qs:gn_pop":2073,
    "qs:name":"Ambunti",
    "qs:name_adm0":"Papua New Guinea",
    "qs:name_adm1":"East Sepik",
    "qs:photos":0,
    "qs:photos_1k":0,
    "qs:photos_9k":1,
    "qs:photos_9r":1,
    "qs:photos_all":5,
    "qs:photos_sr":0,
    "qs:placetype":"Town",
    "qs:pop_sr":"4",
    "qs:woe_adm0":23424926,
    "wd:wordcount":38,
    "wof:name":"Ambunti",
    "wof:placetype":"locality",
    "wof:population":2073
},
  "geometry": {"coordinates":[142.84485000000001,-4.23653],"type":"Point"}
}