{
  "type": "Feature",
  "properties": {
    "gn:admin1_code":"12",
    "gn:asciiname":"Tsabi",
    "gn:country_code":"PG",
    "gn:dem":1363,
    "gn:feature_class":"P",
    "gn:feature_code":"PPL",
    "gn:name":"Tsabi",
    "gn:population":0,
    "gn:timezone":"Pacific/Port_Moresby",
    "iso:country":"PG",
    "name:und_x_variant":[
        "Isabi",
        "Tsabi"
    ],
    "wof:name":"Tsabi",
    "wof:placetype":"locality"
},
  "geometry": {"coordinates":[145.51955000000001,-5.88835],"type":"Point"}
}