{
  "type": "Feature",
  "properties": {
    "gn:admin1_code":"12",
    "gn:asciiname":"Kul",
    "gn:country_code":"PG",
    "gn:dem":81,
    "gn:feature_class":"P",
    "gn:feature_code":"PPL",
    "gn:name":"Kul",
    "gn:population":0,
    "gn:timezone":"Pacific/Port_Moresby",
    "iso:country":"PG",
    "name:ceb_x_preferred":[
        "Kul"
    ],
    "name:dan_x_preferred":[
        "Kul"
    ],
    "name:deu_x_preferred":[
        "Kul"
    ],
    "name:fas_x_preferred":[
        "\u06a9\u0648\u0644"
    ],
    "name:swe_x_preferred":[
        "Kul"
    ],
    "name:und_x_variant":[
        "Kul 1"
    ],
    "wof:name":"Kul",
    "wof:placetype":"locality"
},
  "geometry": {"coordinates":[145.98025000000001,-5.47517],"type":"Point"}
}