{
  "type": "Feature",
  "properties": {
    "gn:admin1_code":"10",
    "gn:asciiname":"Parol",
    "gn:country_code":"PG",
    "gn:dem":255,
    "gn:feature_class":"P",
    "gn:feature_code":"PPL",
    "gn:name":"Parol",
    "gn:population":0,
    "gn:timezone":"Pacific/Port_Moresby",
    "iso:country":"PG",
    "wof:name":"Parol",
    "wof:placetype":"locality"
},
  "geometry": {"coordinates":[151.43333000000001,-5.55],"type":"Point"}
}