{
  "type": "Feature",
  "properties": {
    "gn:admin1_code":"18",
    "gn:asciiname":"Yilui",
    "gn:country_code":"PG",
    "gn:dem":74,
    "gn:feature_class":"P",
    "gn:feature_code":"PPL",
    "gn:name":"Yilui",
    "gn:population":0,
    "gn:timezone":"Pacific/Port_Moresby",
    "iso:country":"PG",
    "wof:name":"Yilui",
    "wof:placetype":"locality"
},
  "geometry": {"coordinates":[142.20883999999995,-3.93095],"type":"Point"}
}