{
  "type": "Feature",
  "properties": {
    "gn:admin1_code":"05",
    "gn:asciiname":"Kip",
    "gn:country_code":"PG",
    "gn:dem":1821,
    "gn:feature_class":"P",
    "gn:feature_code":"PPL",
    "gn:name":"Kip",
    "gn:population":0,
    "gn:timezone":"Pacific/Port_Moresby",
    "iso:country":"PG",
    "wof:name":"Kip",
    "wof:placetype":"locality"
},
  "geometry": {"coordinates":[143.55333999999999,-6.11577],"type":"Point"}
}