{
  "type": "Feature",
  "properties": {
    "gn:admin1_code":"05",
    "gn:asciiname":"Kip",
    "gn:country_code":"PG",
    "gn:dem":1821,
    "gn:feature_class":"P",
    "gn:feature_code":"PPL",
    "gn:name":"Kip",
    "gn:population":0,
    "gn:timezone":"Pacific/Port_Moresby",
    "iso:country":"PG",
    "name:bos_x_preferred":[
        "Kip"
    ],
    "name:ceb_x_preferred":[
        "Kip"
    ],
    "name:hun_x_preferred":[
        "Kip"
    ],
    "name:jpn_x_preferred":[
        "\u30ad\u30c3\u30d7"
    ],
    "name:nld_x_preferred":[
        "Kip"
    ],
    "name:slv_x_preferred":[
        "Kip"
    ],
    "name:swe_x_preferred":[
        "Kip"
    ],
    "name:tur_x_preferred":[
        "Kip"
    ],
    "wof:name":"Kip",
    "wof:placetype":"locality"
},
  "geometry": {"coordinates":[143.55333999999999,-6.11577],"type":"Point"}
}