{
  "type": "Feature",
  "properties": {
    "gn:admin1_code":"17",
    "gn:asciiname":"Aduap",
    "gn:country_code":"PG",
    "gn:dem":96,
    "gn:feature_class":"P",
    "gn:feature_code":"PPL",
    "gn:name":"Aduap",
    "gn:population":0,
    "gn:timezone":"Pacific/Port_Moresby",
    "iso:country":"PG",
    "wof:name":"Aduap",
    "wof:placetype":"locality"
},
  "geometry": {"coordinates":[149.56666999999999,-6.05],"type":"Point"}
}