{
  "type": "Feature",
  "properties": {
    "gn:admin1_code":"05",
    "gn:asciiname":"Yebi Number 2",
    "gn:country_code":"PG",
    "gn:dem":1535,
    "gn:feature_class":"P",
    "gn:feature_code":"PPL",
    "gn:name":"Yebi Number 2",
    "gn:population":0,
    "gn:timezone":"Pacific/Port_Moresby",
    "iso:country":"PG",
    "name:und_x_variant":[
        "Yebi",
        "Yebi Number 2"
    ],
    "wof:name":"Yebi Number 2",
    "wof:placetype":"locality"
},
  "geometry": {"coordinates":[143.73726000000005,-6.24583],"type":"Point"}
}