{
  "type": "Feature",
  "properties": {
    "gn:admin1_code":"02",
    "gn:asciiname":"Tapala",
    "gn:country_code":"PG",
    "gn:dem":14,
    "gn:feature_class":"P",
    "gn:feature_code":"PPL",
    "gn:name":"Tapala",
    "gn:population":0,
    "gn:timezone":"Pacific/Port_Moresby",
    "iso:country":"PG",
    "wof:name":"Tapala",
    "wof:placetype":"locality"
},
  "geometry": {"coordinates":[146.15198000000001,-8.10921],"type":"Point"}
}