{
  "type": "Feature",
  "properties": {
    "gn:admin1_code":"18",
    "gn:asciiname":"Mantsuku",
    "gn:country_code":"PG",
    "gn:dem":212,
    "gn:feature_class":"P",
    "gn:feature_code":"PPL",
    "gn:name":"Mantsuku",
    "gn:population":0,
    "gn:timezone":"Pacific/Port_Moresby",
    "iso:country":"PG",
    "wof:name":"Mantsuku",
    "wof:placetype":"locality"
},
  "geometry": {"coordinates":[142.46888000000001,-3.69378],"type":"Point"}
}