{
  "type": "Feature",
  "properties": {
    "gn:admin1_code":"14",
    "gn:asciiname":"Bitoi",
    "gn:cc2":"PG",
    "gn:country_code":"PG",
    "gn:dem":10,
    "gn:feature_class":"P",
    "gn:feature_code":"PPL",
    "gn:name":"Bitoi",
    "gn:population":0,
    "gn:timezone":"Pacific/Port_Moresby",
    "iso:country":"PG",
    "name:und_x_variant":[
        "Duali",
        "Bitoi"
    ],
    "wof:name":"Bitoi",
    "wof:placetype":"locality"
},
  "geometry": {"coordinates":[147.13333,-7.25],"type":"Point"}
}