{
  "type": "Feature",
  "properties": {
    "gn:admin1_code":"06",
    "gn:asciiname":"Kodolombia",
    "gn:country_code":"PG",
    "gn:dem":196,
    "gn:feature_class":"P",
    "gn:feature_code":"PPL",
    "gn:name":"Kodolombia",
    "gn:population":0,
    "gn:timezone":"Pacific/Port_Moresby",
    "iso:country":"PG",
    "wof:name":"Kodolombia",
    "wof:placetype":"locality"
},
  "geometry": {"coordinates":[142.36667,-6.25],"type":"Point"}
}