{
  "type": "Feature",
  "properties": {
    "gn:admin1_code":"09",
    "gn:asciiname":"Sasaura",
    "gn:country_code":"PG",
    "gn:dem":1516,
    "gn:feature_class":"P",
    "gn:feature_code":"PPL",
    "gn:name":"Sasaura",
    "gn:population":0,
    "gn:timezone":"Pacific/Port_Moresby",
    "iso:country":"PG",
    "wof:name":"Sasaura",
    "wof:placetype":"locality"
},
  "geometry": {"coordinates":[146.01328000000001,-6.37258],"type":"Point"}
}