{
  "type": "Feature",
  "properties": {
    "gn:admin1_code":"18",
    "gn:asciiname":"Siaute",
    "gn:country_code":"PG",
    "gn:dem":41,
    "gn:feature_class":"P",
    "gn:feature_code":"PPL",
    "gn:name":"Siaute",
    "gn:population":0,
    "gn:timezone":"Pacific/Port_Moresby",
    "iso:country":"PG",
    "name:und_x_variant":[
        "Lalau",
        "Siauti",
        "Siaute"
    ],
    "wof:name":"Siaute",
    "wof:placetype":"locality"
},
  "geometry": {"coordinates":[142.23178999999999,-3.1962],"type":"Point"}
}