{
  "type": "Feature",
  "properties": {
    "gn:admin1_code":"01",
    "gn:asciiname":"Owens Corner",
    "gn:country_code":"PG",
    "gn:dem":623,
    "gn:feature_class":"P",
    "gn:feature_code":"PPL",
    "gn:name":"Owens Corner",
    "gn:population":0,
    "gn:timezone":"Pacific/Port_Moresby",
    "iso:country":"PG",
    "wof:name":"Owens Corner",
    "wof:placetype":"locality"
},
  "geometry": {"coordinates":[147.48333,-9.36667],"type":"Point"}
}