{
  "type": "Feature",
  "properties": {
    "gn:admin1_code":"14",
    "gn:asciiname":"Barim",
    "gn:country_code":"PG",
    "gn:dem":21,
    "gn:feature_class":"P",
    "gn:feature_code":"PPL",
    "gn:name":"Barim",
    "gn:population":0,
    "gn:timezone":"Pacific/Port_Moresby",
    "iso:country":"PG",
    "name:fas_x_preferred":[
        "\u0628\u0631\u06cc\u0645"
    ],
    "wof:name":"Barim",
    "wof:placetype":"locality"
},
  "geometry": {"coordinates":[147.80226999999999,-5.66035],"type":"Point"}
}