{
  "type": "Feature",
  "properties": {
    "gn:admin1_code":"06",
    "gn:asciiname":"Rumae",
    "gn:country_code":"PG",
    "gn:dem":72,
    "gn:feature_class":"P",
    "gn:feature_code":"PPL",
    "gn:name":"Rumae",
    "gn:population":0,
    "gn:timezone":"Pacific/Port_Moresby",
    "iso:country":"PG",
    "wof:name":"Rumae",
    "wof:placetype":"locality"
},
  "geometry": {"coordinates":[141.21357,-5.816],"type":"Point"}
}