{
  "type": "Feature",
  "properties": {
    "gn:admin1_code":"14",
    "gn:asciiname":"Palili",
    "gn:country_code":"PG",
    "gn:dem":35,
    "gn:feature_class":"P",
    "gn:feature_code":"PPL",
    "gn:name":"Palili",
    "gn:population":0,
    "gn:timezone":"Pacific/Port_Moresby",
    "iso:country":"PG",
    "name:eng_x_preferred":[
        "Palili"
    ],
    "wof:name":"Palili",
    "wof:placetype":"locality"
},
  "geometry": {"coordinates":[148.43538000000001,-5.76499],"type":"Point"}
}