{
  "type": "Feature",
  "properties": {
    "gn:admin1_code":"09",
    "gn:asciiname":"Kuru",
    "gn:country_code":"PG",
    "gn:dem":2177,
    "gn:feature_class":"P",
    "gn:feature_code":"PPL",
    "gn:name":"Kuru",
    "gn:population":0,
    "gn:timezone":"Pacific/Port_Moresby",
    "iso:country":"PG",
    "name:bul_x_preferred":[
        "\u041a\u0443\u0440\u0443"
    ],
    "name:cat_x_preferred":[
        "Kuru"
    ],
    "name:ceb_x_preferred":[
        "Kuru"
    ],
    "name:ces_x_preferred":[
        "Kuru"
    ],
    "name:che_x_preferred":[
        "\u041a\u0443\u0440\u0443"
    ],
    "name:deu_x_preferred":[
        "Kuru"
    ],
    "name:est_x_preferred":[
        "Kuru"
    ],
    "name:fin_x_preferred":[
        "Kuru"
    ],
    "name:fra_x_preferred":[
        "Kuru"
    ],
    "name:heb_x_preferred":[
        "\u05e7\u05d5\u05e8\u05d5"
    ],
    "name:hun_x_preferred":[
        "Kuru"
    ],
    "name:ind_x_preferred":[
        "Kuru"
    ],
    "name:ita_x_preferred":[
        "Kuru"
    ],
    "name:nld_x_preferred":[
        "Kuru"
    ],
    "name:rus_x_preferred":[
        "\u041a\u0443\u0440\u0443"
    ],
    "name:slk_x_preferred":[
        "Kuru"
    ],
    "name:spa_x_preferred":[
        "Kuru"
    ],
    "name:srp_x_preferred":[
        "\u041a\u0443\u0440\u0443"
    ],
    "name:swe_x_preferred":[
        "Kuru"
    ],
    "name:tgl_x_preferred":[
        "Kuru"
    ],
    "name:ukr_x_preferred":[
        "\u041a\u0443\u0440\u0443"
    ],
    "name:vol_x_preferred":[
        "Kuru"
    ],
    "wof:name":"Kuru",
    "wof:placetype":"locality"
},
  "geometry": {"coordinates":[145.53333000000001,-6.41667],"type":"Point"}
}