{
  "type": "Feature",
  "properties": {
    "gn:admin1_code":"09",
    "gn:asciiname":"Kuru",
    "gn:country_code":"PG",
    "gn:dem":2177,
    "gn:feature_class":"P",
    "gn:feature_code":"PPL",
    "gn:name":"Kuru",
    "gn:population":0,
    "gn:timezone":"Pacific/Port_Moresby",
    "iso:country":"PG",
    "wof:name":"Kuru",
    "wof:placetype":"locality"
},
  "geometry": {"coordinates":[145.53333000000001,-6.41667],"type":"Point"}
}