{
  "type": "Feature",
  "properties": {
    "gn:admin1_code":"04",
    "gn:asciiname":"Vivisioni",
    "gn:country_code":"PG",
    "gn:dem":50,
    "gn:feature_class":"P",
    "gn:feature_code":"PPL",
    "gn:name":"Vivisioni",
    "gn:population":0,
    "gn:timezone":"Pacific/Port_Moresby",
    "iso:country":"PG",
    "wof:name":"Vivisioni",
    "wof:placetype":"locality"
},
  "geometry": {"coordinates":[148.26667,-8.66667],"type":"Point"}
}