{
  "type": "Feature",
  "properties": {
    "gn:admin1_code":"04",
    "gn:asciiname":"Kwave",
    "gn:country_code":"PG",
    "gn:dem":193,
    "gn:feature_class":"P",
    "gn:feature_code":"PPL",
    "gn:name":"Kwave",
    "gn:population":0,
    "gn:timezone":"Pacific/Port_Moresby",
    "iso:country":"PG",
    "wof:name":"Kwave",
    "wof:placetype":"locality"
},
  "geometry": {"coordinates":[149.28845000000001,-9.10131],"type":"Point"}
}