{
  "type": "Feature",
  "properties": {
    "gn:admin1_code":"11",
    "gn:asciiname":"Amahop 2",
    "gn:country_code":"PG",
    "gn:dem":217,
    "gn:feature_class":"P",
    "gn:feature_code":"PPL",
    "gn:name":"Amahop 2",
    "gn:population":0,
    "gn:timezone":"Pacific/Port_Moresby",
    "iso:country":"PG",
    "wof:name":"Amahop 2",
    "wof:placetype":"locality"
},
  "geometry": {"coordinates":[142.97453999999999,-3.61423],"type":"Point"}
}