{
  "type": "Feature",
  "properties": {
    "gn:admin1_code":"01",
    "gn:asciiname":"Amaraika",
    "gn:country_code":"PG",
    "gn:dem":321,
    "gn:feature_class":"P",
    "gn:feature_code":"PPL",
    "gn:name":"Amaraika",
    "gn:population":0,
    "gn:timezone":"Pacific/Port_Moresby",
    "iso:country":"PG",
    "name:und_x_variant":[
        "Aramaika",
        "Amaraika"
    ],
    "wof:name":"Amaraika",
    "wof:placetype":"locality"
},
  "geometry": {"coordinates":[147.88522,-9.65779],"type":"Point"}
}