{
  "type": "Feature",
  "properties": {
    "gn:admin1_code":"06",
    "gn:asciiname":"Ugumara",
    "gn:country_code":"PG",
    "gn:dem":404,
    "gn:feature_class":"P",
    "gn:feature_code":"PPL",
    "gn:name":"Ugumara",
    "gn:population":0,
    "gn:timezone":"Pacific/Port_Moresby",
    "iso:country":"PG",
    "wof:name":"Ugumara",
    "wof:placetype":"locality"
},
  "geometry": {"coordinates":[142.58333000000005,-6.46667],"type":"Point"}
}