{
  "type": "Feature",
  "properties": {
    "gn:admin1_code":"04",
    "gn:asciiname":"Kwena",
    "gn:country_code":"PG",
    "gn:dem":912,
    "gn:feature_class":"P",
    "gn:feature_code":"PPL",
    "gn:name":"Kwena",
    "gn:population":0,
    "gn:timezone":"Pacific/Port_Moresby",
    "iso:country":"PG",
    "wof:name":"Kwena",
    "wof:placetype":"locality"
},
  "geometry": {"coordinates":[148.35416000000001,-9.05323],"type":"Point"}
}