{
  "type": "Feature",
  "properties": {
    "gn:admin1_code":"02",
    "gn:asciiname":"Mei'i Number 1",
    "gn:country_code":"PG",
    "gn:dem":6,
    "gn:feature_class":"P",
    "gn:feature_code":"PPL",
    "gn:name":"Mei\u2019i Number 1",
    "gn:population":0,
    "gn:timezone":"Pacific/Port_Moresby",
    "iso:country":"PG",
    "name:und_x_variant":[
        "Mei\u2019i l",
        "Mei",
        "Mei\u2019i Number 1"
    ],
    "wof:name":"Mei'i Number 1",
    "wof:placetype":"locality"
},
  "geometry": {"coordinates":[145.71563999999995,-7.95274],"type":"Point"}
}