{
  "type": "Feature",
  "properties": {
    "gn:admin1_code":"05",
    "gn:asciiname":"Uma",
    "gn:country_code":"PG",
    "gn:dem":1654,
    "gn:feature_class":"P",
    "gn:feature_code":"PPL",
    "gn:name":"Uma",
    "gn:population":0,
    "gn:timezone":"Pacific/Port_Moresby",
    "iso:country":"PG",
    "wof:name":"Uma",
    "wof:placetype":"locality"
},
  "geometry": {"coordinates":[143.73701,-6.37988],"type":"Point"}
}