{
  "type": "Feature",
  "properties": {
    "gn:admin1_code":"12",
    "gn:asciiname":"Silahala",
    "gn:country_code":"PG",
    "gn:dem":583,
    "gn:feature_class":"P",
    "gn:feature_code":"PPL",
    "gn:name":"Silahala",
    "gn:population":0,
    "gn:timezone":"Pacific/Port_Moresby",
    "iso:country":"PG",
    "wof:name":"Silahala",
    "wof:placetype":"locality"
},
  "geometry": {"coordinates":[145.59999999999999,-5.06667],"type":"Point"}
}