{
  "type": "Feature",
  "properties": {
    "gn:admin1_code":"04",
    "gn:asciiname":"Sorape",
    "gn:country_code":"PG",
    "gn:dem":257,
    "gn:feature_class":"P",
    "gn:feature_code":"PPL",
    "gn:name":"Sorape",
    "gn:population":0,
    "gn:timezone":"Pacific/Port_Moresby",
    "iso:country":"PG",
    "wof:name":"Sorape",
    "wof:placetype":"locality"
},
  "geometry": {"coordinates":[148.01271,-8.91522],"type":"Point"}
}