{
  "type": "Feature",
  "properties": {
    "gn:admin1_code":"08",
    "gn:asciiname":"Kebamiankani",
    "gn:country_code":"PG",
    "gn:dem":2260,
    "gn:feature_class":"P",
    "gn:feature_code":"PPL",
    "gn:name":"Kebamiankani",
    "gn:population":0,
    "gn:timezone":"Pacific/Port_Moresby",
    "iso:country":"PG",
    "wof:name":"Kebamiankani",
    "wof:placetype":"locality"
},
  "geometry": {"coordinates":[144.87548000000001,-6.10164],"type":"Point"}
}