{
  "type": "Feature",
  "properties": {
    "gn:admin1_code":"14",
    "gn:asciiname":"Opai",
    "gn:country_code":"PG",
    "gn:dem":17,
    "gn:feature_class":"P",
    "gn:feature_code":"PPL",
    "gn:name":"Opai",
    "gn:population":0,
    "gn:timezone":"Pacific/Port_Moresby",
    "iso:country":"PG",
    "wof:name":"Opai",
    "wof:placetype":"locality"
},
  "geometry": {"coordinates":[147.86701000000005,-5.71597],"type":"Point"}
}