{
  "type": "Feature",
  "properties": {
    "gn:admin1_code":"16",
    "gn:asciiname":"Rugi",
    "gn:country_code":"PG",
    "gn:dem":1734,
    "gn:feature_class":"P",
    "gn:feature_code":"PPL",
    "gn:name":"Rugi",
    "gn:population":0,
    "gn:timezone":"Pacific/Port_Moresby",
    "iso:country":"PG",
    "name:ceb_x_preferred":[
        "Rugi"
    ],
    "name:deu_x_preferred":[
        "Rugi"
    ],
    "name:ron_x_preferred":[
        "Rugi"
    ],
    "name:und_x_variant":[
        "Rugli"
    ],
    "wof:name":"Rugi",
    "wof:placetype":"locality"
},
  "geometry": {"coordinates":[144.18852999999999,-5.66995],"type":"Point"}
}