{
  "type": "Feature",
  "properties": {
    "gn:admin1_code":"14",
    "gn:asciiname":"Kusi",
    "gn:country_code":"PG",
    "gn:dem":1711,
    "gn:feature_class":"P",
    "gn:feature_code":"PPL",
    "gn:name":"Kusi",
    "gn:population":0,
    "gn:timezone":"Pacific/Port_Moresby",
    "iso:country":"PG",
    "wof:name":"Kusi",
    "wof:placetype":"locality"
},
  "geometry": {"coordinates":[146.95106000000001,-7.8299],"type":"Point"}
}