{
  "type": "Feature",
  "properties": {
    "gn:admin1_code":"02",
    "gn:asciiname":"Ovahuhu",
    "gn:country_code":"PG",
    "gn:dem":1,
    "gn:feature_class":"P",
    "gn:feature_code":"PPL",
    "gn:name":"Ovahuhu",
    "gn:population":0,
    "gn:timezone":"Pacific/Port_Moresby",
    "iso:country":"PG",
    "wof:name":"Ovahuhu",
    "wof:placetype":"locality"
},
  "geometry": {"coordinates":[145.52945,-7.94382],"type":"Point"}
}