{
  "type": "Feature",
  "properties": {
    "gn:admin1_code":"09",
    "gn:asciiname":"Namaviali",
    "gn:country_code":"PG",
    "gn:dem":1729,
    "gn:feature_class":"P",
    "gn:feature_code":"PPL",
    "gn:name":"Namaviali",
    "gn:population":0,
    "gn:timezone":"Pacific/Port_Moresby",
    "iso:country":"PG",
    "wof:name":"Namaviali",
    "wof:placetype":"locality"
},
  "geometry": {"coordinates":[145.33333000000005,-6.13333],"type":"Point"}
}