{
  "type": "Feature",
  "properties": {
    "gn:admin1_code":"06",
    "gn:asciiname":"Sibara",
    "gn:country_code":"PG",
    "gn:dem":12,
    "gn:feature_class":"P",
    "gn:feature_code":"PPL",
    "gn:name":"Sibara",
    "gn:population":0,
    "gn:timezone":"Pacific/Port_Moresby",
    "iso:country":"PG",
    "name:eng_x_preferred":[
        "Sibara"
    ],
    "wof:name":"Sibara",
    "wof:placetype":"locality"
},
  "geometry": {"coordinates":[143.72023000000004,-8.03407],"type":"Point"}
}