{
  "type": "Feature",
  "properties": {
    "gn:admin1_code":"04",
    "gn:asciiname":"Saraititi",
    "gn:country_code":"PG",
    "gn:dem":46,
    "gn:feature_class":"P",
    "gn:feature_code":"PPL",
    "gn:name":"Saraititi",
    "gn:population":0,
    "gn:timezone":"Pacific/Port_Moresby",
    "iso:country":"PG",
    "wof:name":"Saraititi",
    "wof:placetype":"locality"
},
  "geometry": {"coordinates":[147.90000000000001,-8.56667],"type":"Point"}
}