{
  "type": "Feature",
  "properties": {
    "gn:admin1_code":"13",
    "gn:asciiname":"Penchal",
    "gn:country_code":"PG",
    "gn:dem":40,
    "gn:feature_class":"P",
    "gn:feature_code":"PPL",
    "gn:name":"Penchal",
    "gn:population":0,
    "gn:timezone":"Pacific/Port_Moresby",
    "iso:country":"PG",
    "wof:name":"Penchal",
    "wof:placetype":"locality"
},
  "geometry": {"coordinates":[147.75291999999999,-2.33008],"type":"Point"}
}