{
  "type": "Feature",
  "properties": {
    "gn:admin1_code":"12",
    "gn:asciiname":"Kaukomba",
    "gn:country_code":"PG",
    "gn:dem":26,
    "gn:feature_class":"P",
    "gn:feature_code":"PPL",
    "gn:name":"Kaukomba",
    "gn:population":0,
    "gn:timezone":"Pacific/Port_Moresby",
    "iso:country":"PG",
    "wof:name":"Kaukomba",
    "wof:placetype":"locality"
},
  "geometry": {"coordinates":[145.27571,-4.3894],"type":"Point"}
}