{
  "type": "Feature",
  "properties": {
    "gn:admin1_code":"01",
    "gn:admin2_code":"7668019",
    "gn:asciiname":"Woitape",
    "gn:country_code":"PG",
    "gn:dem":1586,
    "gn:feature_class":"P",
    "gn:feature_code":"PPL",
    "gn:name":"Woitape",
    "gn:population":0,
    "gn:timezone":"Pacific/Port_Moresby",
    "iso:country":"PG",
    "wof:name":"Woitape",
    "wof:placetype":"locality"
},
  "geometry": {"coordinates":[147.24156000000005,-8.61582],"type":"Point"}
}