{
  "type": "Feature",
  "properties": {
    "gn:admin1_code":"01",
    "gn:admin2_code":"2134008",
    "gn:asciiname":"Aroma",
    "gn:country_code":"PG",
    "gn:dem":15,
    "gn:feature_class":"P",
    "gn:feature_code":"PPL",
    "gn:name":"Aroma",
    "gn:population":0,
    "gn:timezone":"Pacific/Port_Moresby",
    "iso:country":"PG",
    "wof:name":"Aroma",
    "wof:placetype":"locality"
},
  "geometry": {"coordinates":[148.01167000000001,-10.14121],"type":"Point"}
}