{
  "type": "Feature",
  "properties": {
    "gn:admin1_code":"11",
    "gn:asciiname":"Bubuamo",
    "gn:country_code":"PG",
    "gn:dem":244,
    "gn:feature_class":"P",
    "gn:feature_code":"PPL",
    "gn:name":"Bubuamo",
    "gn:population":0,
    "gn:timezone":"Pacific/Port_Moresby",
    "iso:country":"PG",
    "wof:name":"Bubuamo",
    "wof:placetype":"locality"
},
  "geometry": {"coordinates":[143.21666999999999,-3.63333],"type":"Point"}
}