{
  "type": "Feature",
  "properties": {
    "gn:admin1_code":"12",
    "gn:asciiname":"Beiamp",
    "gn:country_code":"PG",
    "gn:dem":309,
    "gn:feature_class":"P",
    "gn:feature_code":"PPL",
    "gn:name":"Beiamp",
    "gn:population":0,
    "gn:timezone":"Pacific/Port_Moresby",
    "iso:country":"PG",
    "wof:name":"Beiamp",
    "wof:placetype":"locality"
},
  "geometry": {"coordinates":[144.91666999999995,-4.43333],"type":"Point"}
}