{
  "type": "Feature",
  "properties": {
    "gn:admin1_code":"10",
    "gn:asciiname":"Poman",
    "gn:country_code":"PG",
    "gn:dem":180,
    "gn:feature_class":"P",
    "gn:feature_code":"PPL",
    "gn:name":"Poman",
    "gn:population":0,
    "gn:timezone":"Pacific/Port_Moresby",
    "iso:country":"PG",
    "wof:name":"Poman",
    "wof:placetype":"locality"
},
  "geometry": {"coordinates":[151.84566999999996,-5.54747],"type":"Point"}
}