{
  "type": "Feature",
  "properties": {
    "gn:admin1_code":"12",
    "gn:asciiname":"Gun 2",
    "gn:country_code":"PG",
    "gn:dem":57,
    "gn:feature_class":"P",
    "gn:feature_code":"PPL",
    "gn:name":"Gun 2",
    "gn:population":0,
    "gn:timezone":"Pacific/Port_Moresby",
    "iso:country":"PG",
    "name:und_x_variant":[
        "Gun Number 2",
        "Gun 2"
    ],
    "wof:name":"Gun 2",
    "wof:placetype":"locality"
},
  "geometry": {"coordinates":[144.71539000000001,-4.4264],"type":"Point"}
}