{
  "type": "Feature",
  "properties": {
    "gn:admin1_code":"14",
    "gn:asciiname":"Otete",
    "gn:country_code":"PG",
    "gn:dem":1639,
    "gn:feature_class":"P",
    "gn:feature_code":"PPL",
    "gn:name":"Otete",
    "gn:population":0,
    "gn:timezone":"Pacific/Port_Moresby",
    "iso:country":"PG",
    "wof:name":"Otete",
    "wof:placetype":"locality"
},
  "geometry": {"coordinates":[146.22611000000001,-7.23198],"type":"Point"}
}