{
  "type": "Feature",
  "properties": {
    "gn:admin1_code":"06",
    "gn:asciiname":"Gredemasuk",
    "gn:cc2":"PG",
    "gn:country_code":"PG",
    "gn:dem":60,
    "gn:feature_class":"P",
    "gn:feature_code":"PPL",
    "gn:name":"Gredemasuk",
    "gn:population":0,
    "gn:timezone":"Pacific/Port_Moresby",
    "iso:country":"PG",
    "name:und_x_variant":[
        "Gredemesok",
        "Gredemasuk"
    ],
    "wof:name":"Gredemasuk",
    "wof:placetype":"locality"
},
  "geometry": {"coordinates":[141.34999999999999,-6.05],"type":"Point"}
}