{
  "type": "Feature",
  "properties": {
    "gn:admin1_code":"07",
    "gn:asciiname":"Runai",
    "gn:country_code":"PG",
    "gn:dem":40,
    "gn:feature_class":"P",
    "gn:feature_code":"PPL",
    "gn:name":"Runai",
    "gn:population":0,
    "gn:timezone":"Pacific/Bougainville",
    "iso:country":"PG",
    "wof:name":"Runai",
    "wof:placetype":"locality"
},
  "geometry": {"coordinates":[155.39167,-6.69167],"type":"Point"}
}