{
  "type": "Feature",
  "properties": {
    "gn:admin1_code":"18",
    "gn:asciiname":"Nau'ali",
    "gn:country_code":"PG",
    "gn:dem":41,
    "gn:feature_class":"P",
    "gn:feature_code":"PPL",
    "gn:name":"Nau\u2019ali",
    "gn:population":0,
    "gn:timezone":"Pacific/Port_Moresby",
    "iso:country":"PG",
    "wof:name":"Nau'ali",
    "wof:placetype":"locality"
},
  "geometry": {"coordinates":[142.58581999999996,-4.07951],"type":"Point"}
}