{
  "type": "Feature",
  "properties": {
    "iso:country":"PG",
    "qs:gn_pop":0,
    "qs:name":"Kifamu Mission",
    "qs:name_adm0":"Papua New Guinea",
    "qs:name_adm1":"Eastern Highlands",
    "qs:photos":9,
    "qs:photos_1k":2,
    "qs:photos_9k":1,
    "qs:photos_9r":1,
    "qs:photos_all":9,
    "qs:photos_sr":1,
    "qs:placetype":"Town",
    "qs:pop_sr":"0",
    "qs:woe_adm0":23424926,
    "wof:name":"Kifamu Mission",
    "wof:placetype":"locality"
},
  "geometry": {"coordinates":[145.44064299999999,-6.035345],"type":"Point"}
}