{
  "type": "Feature",
  "properties": {
    "gn:admin1_code":"09",
    "gn:asciiname":"Negire",
    "gn:country_code":"PG",
    "gn:dem":1617,
    "gn:feature_class":"P",
    "gn:feature_code":"PPL",
    "gn:name":"Negire",
    "gn:population":0,
    "gn:timezone":"Pacific/Port_Moresby",
    "iso:country":"PG",
    "wof:name":"Negire",
    "wof:placetype":"locality"
},
  "geometry": {"coordinates":[145.52318,-6.36139],"type":"Point"}
}