{
  "type": "Feature",
  "properties": {
    "gn:admin1_code":"18",
    "gn:asciiname":"Yulem",
    "gn:country_code":"PG",
    "gn:dem":273,
    "gn:feature_class":"P",
    "gn:feature_code":"PPL",
    "gn:name":"Yulem",
    "gn:population":0,
    "gn:timezone":"Pacific/Port_Moresby",
    "iso:country":"PG",
    "wof:name":"Yulem",
    "wof:placetype":"locality"
},
  "geometry": {"coordinates":[142.33132000000001,-3.71138],"type":"Point"}
}