{
  "type": "Feature",
  "properties": {
    "gn:admin1_code":"18",
    "gn:asciiname":"Suriap",
    "gn:cc2":"PG",
    "gn:country_code":"PG",
    "gn:dem":58,
    "gn:feature_class":"P",
    "gn:feature_code":"PPL",
    "gn:name":"Suriap",
    "gn:population":0,
    "gn:timezone":"Pacific/Port_Moresby",
    "iso:country":"PG",
    "name:und_x_variant":[
        "Mabiaru",
        "Suriap"
    ],
    "wof:name":"Suriap",
    "wof:placetype":"locality"
},
  "geometry": {"coordinates":[141.18333000000001,-4.06667],"type":"Point"}
}