{
  "type": "Feature",
  "properties": {
    "gn:admin1_code":"05",
    "gn:asciiname":"Pauoni",
    "gn:country_code":"PG",
    "gn:dem":1711,
    "gn:feature_class":"P",
    "gn:feature_code":"PPL",
    "gn:name":"Pauoni",
    "gn:population":0,
    "gn:timezone":"Pacific/Port_Moresby",
    "iso:country":"PG",
    "wof:name":"Pauoni",
    "wof:placetype":"locality"
},
  "geometry": {"coordinates":[143.88333,-6.41667],"type":"Point"}
}