{
  "type": "Feature",
  "properties": {
    "gn:admin1_code":"01",
    "gn:asciiname":"Subitana Plantation",
    "gn:cc2":"PG",
    "gn:country_code":"PG",
    "gn:dem":497,
    "gn:feature_class":"P",
    "gn:feature_code":"PPL",
    "gn:name":"Subitana Plantation",
    "gn:population":0,
    "gn:timezone":"Pacific/Port_Moresby",
    "iso:country":"PG",
    "name:und_x_variant":[
        "Subitana",
        "Subitana Plantation"
    ],
    "wof:name":"Subitana Plantation",
    "wof:placetype":"locality"
},
  "geometry": {"coordinates":[147.53333000000001,-9.41667],"type":"Point"}
}