{
  "type": "Feature",
  "properties": {
    "gn:admin1_code":"05",
    "gn:asciiname":"Remali",
    "gn:country_code":"PG",
    "gn:dem":1824,
    "gn:feature_class":"P",
    "gn:feature_code":"PPL",
    "gn:name":"Remali",
    "gn:population":0,
    "gn:timezone":"Pacific/Port_Moresby",
    "iso:country":"PG",
    "wof:name":"Remali",
    "wof:placetype":"locality"
},
  "geometry": {"coordinates":[143.94999999999999,-6.36667],"type":"Point"}
}