{
  "type": "Feature",
  "properties": {
    "gn:admin1_code":"05",
    "gn:asciiname":"Limbiali",
    "gn:country_code":"PG",
    "gn:dem":2120,
    "gn:feature_class":"P",
    "gn:feature_code":"PPL",
    "gn:name":"Limbiali",
    "gn:population":0,
    "gn:timezone":"Pacific/Port_Moresby",
    "iso:country":"PG",
    "wof:name":"Limbiali",
    "wof:placetype":"locality"
},
  "geometry": {"coordinates":[143.84999999999999,-6.21667],"type":"Point"}
}