{
  "type": "Feature",
  "properties": {
    "gn:admin1_code":"12",
    "gn:asciiname":"Kempeni",
    "gn:country_code":"PG",
    "gn:dem":1240,
    "gn:feature_class":"P",
    "gn:feature_code":"PPL",
    "gn:name":"Kempeni",
    "gn:population":0,
    "gn:timezone":"Pacific/Port_Moresby",
    "iso:country":"PG",
    "wof:name":"Kempeni",
    "wof:placetype":"locality"
},
  "geometry": {"coordinates":[145.40000000000001,-5.85],"type":"Point"}
}