{
  "type": "Feature",
  "properties": {
    "gn:admin1_code":"04",
    "gn:asciiname":"Duau",
    "gn:country_code":"PG",
    "gn:dem":1255,
    "gn:feature_class":"P",
    "gn:feature_code":"PPL",
    "gn:name":"Duau",
    "gn:population":0,
    "gn:timezone":"Pacific/Port_Moresby",
    "iso:country":"PG",
    "wof:name":"Duau",
    "wof:placetype":"locality"
},
  "geometry": {"coordinates":[148.06666999999999,-9.18333],"type":"Point"}
}