{
  "type": "Feature",
  "properties": {
    "gn:admin1_code":"15",
    "gn:asciiname":"Panangai",
    "gn:country_code":"PG",
    "gn:dem":23,
    "gn:feature_class":"P",
    "gn:feature_code":"PPL",
    "gn:name":"Panangai",
    "gn:population":0,
    "gn:timezone":"Pacific/Port_Moresby",
    "iso:country":"PG",
    "wof:name":"Panangai",
    "wof:placetype":"locality"
},
  "geometry": {"coordinates":[151.18024,-2.90781],"type":"Point"}
}