{
  "type": "Feature",
  "properties": {
    "gn:admin1_code":"06",
    "gn:asciiname":"Bebelubi",
    "gn:country_code":"PG",
    "gn:dem":145,
    "gn:feature_class":"P",
    "gn:feature_code":"PPL",
    "gn:name":"Bebelubi",
    "gn:population":0,
    "gn:timezone":"Pacific/Port_Moresby",
    "iso:country":"PG",
    "wof:name":"Bebelubi",
    "wof:placetype":"locality"
},
  "geometry": {"coordinates":[142.18333000000001,-6.08333],"type":"Point"}
}