{
  "type": "Feature",
  "properties": {
    "gn:admin1_code":"18",
    "gn:asciiname":"Minatei 1",
    "gn:country_code":"PG",
    "gn:dem":987,
    "gn:feature_class":"P",
    "gn:feature_code":"PPL",
    "gn:name":"Minatei 1",
    "gn:population":0,
    "gn:timezone":"Pacific/Port_Moresby",
    "iso:country":"PG",
    "name:und_x_variant":[
        "Minatei",
        "Minate",
        "Minatei 1"
    ],
    "wof:name":"Minatei 1",
    "wof:placetype":"locality"
},
  "geometry": {"coordinates":[142.05047999999999,-3.40064],"type":"Point"}
}