{
  "type": "Feature",
  "properties": {
    "gn:admin1_code":"07",
    "gn:asciiname":"Kunua",
    "gn:country_code":"PG",
    "gn:dem":26,
    "gn:feature_class":"P",
    "gn:feature_code":"PPL",
    "gn:name":"Kunua",
    "gn:population":0,
    "gn:timezone":"Pacific/Bougainville",
    "iso:country":"PG",
    "name:und_x_variant":[
        "Sarime",
        "Konua",
        "Kunua"
    ],
    "wof:name":"Kunua",
    "wof:placetype":"locality"
},
  "geometry": {"coordinates":[154.75173000000001,-5.78205],"type":"Point"}
}