{
  "type": "Feature",
  "properties": {
    "gn:admin1_code":"11",
    "gn:asciiname":"Kumbagora",
    "gn:country_code":"PG",
    "gn:dem":306,
    "gn:feature_class":"P",
    "gn:feature_code":"PPL",
    "gn:name":"Kumbagora",
    "gn:population":0,
    "gn:timezone":"Pacific/Port_Moresby",
    "iso:country":"PG",
    "name:und_x_variant":[
        "Kumbugora Villages",
        "Kumbugora Group",
        "Kumbugora",
        "Kumbagora"
    ],
    "wof:name":"Kumbagora",
    "wof:placetype":"locality"
},
  "geometry": {"coordinates":[143.67684,-3.6983],"type":"Point"}
}