{
  "type": "Feature",
  "properties": {
    "gn:admin1_code":"09",
    "gn:asciiname":"Yagasa",
    "gn:country_code":"PG",
    "gn:dem":1789,
    "gn:feature_class":"P",
    "gn:feature_code":"PPL",
    "gn:name":"Yagasa",
    "gn:population":0,
    "gn:timezone":"Pacific/Port_Moresby",
    "iso:country":"PG",
    "wof:name":"Yagasa",
    "wof:placetype":"locality"
},
  "geometry": {"coordinates":[145.23078999999996,-6.39693],"type":"Point"}
}