{
  "type": "Feature",
  "properties": {
    "gn:admin1_code":"04",
    "gn:asciiname":"Kikinonda",
    "gn:country_code":"PG",
    "gn:dem":43,
    "gn:feature_class":"P",
    "gn:feature_code":"PPL",
    "gn:name":"Kikinonda",
    "gn:population":0,
    "gn:timezone":"Pacific/Port_Moresby",
    "iso:country":"PG",
    "wof:name":"Kikinonda",
    "wof:placetype":"locality"
},
  "geometry": {"coordinates":[147.93430000000001,-8.51617],"type":"Point"}
}