{
  "type": "Feature",
  "properties": {
    "gn:admin1_code":"15",
    "gn:asciiname":"Lemusmus Number 2",
    "gn:country_code":"PG",
    "gn:dem":57,
    "gn:feature_class":"P",
    "gn:feature_code":"PPL",
    "gn:name":"Lemusmus Number 2",
    "gn:population":0,
    "gn:timezone":"Pacific/Port_Moresby",
    "iso:country":"PG",
    "name:und_x_variant":[
        "Lemusmus 2",
        "Lemusmus Number 2"
    ],
    "wof:name":"Lemusmus Number 2",
    "wof:placetype":"locality"
},
  "geometry": {"coordinates":[151.13097999999999,-2.87562],"type":"Point"}
}