{
  "type": "Feature",
  "properties": {
    "gn:admin1_code":"12",
    "gn:asciiname":"Budua",
    "gn:cc2":"PG",
    "gn:country_code":"PG",
    "gn:dem":1,
    "gn:feature_class":"P",
    "gn:feature_code":"PPL",
    "gn:name":"Budua",
    "gn:population":0,
    "gn:timezone":"Pacific/Port_Moresby",
    "iso:country":"PG",
    "name:und_x_variant":[
        "Budum",
        "Bodua",
        "Budua"
    ],
    "wof:name":"Budua",
    "wof:placetype":"locality"
},
  "geometry": {"coordinates":[144.99151000000001,-4.101],"type":"Point"}
}