{
  "type": "Feature",
  "properties": {
    "gn:admin1_code":"17",
    "gn:asciiname":"Gogosi",
    "gn:country_code":"PG",
    "gn:dem":422,
    "gn:feature_class":"P",
    "gn:feature_code":"PPL",
    "gn:name":"Gogosi",
    "gn:population":0,
    "gn:timezone":"Pacific/Port_Moresby",
    "iso:country":"PG",
    "wof:name":"Gogosi",
    "wof:placetype":"locality"
},
  "geometry": {"coordinates":[150.94999999999999,-5.55],"type":"Point"}
}