{
  "type": "Feature",
  "properties": {
    "gn:admin1_code":"09",
    "gn:asciiname":"Komu",
    "gn:country_code":"PG",
    "gn:dem":1582,
    "gn:feature_class":"P",
    "gn:feature_code":"PPL",
    "gn:name":"Komu",
    "gn:population":0,
    "gn:timezone":"Pacific/Port_Moresby",
    "iso:country":"PG",
    "wof:name":"Komu",
    "wof:placetype":"locality"
},
  "geometry": {"coordinates":[145.41954999999999,-6.08369],"type":"Point"}
}