{
  "type": "Feature",
  "properties": {
    "gn:admin1_code":"15",
    "gn:asciiname":"Noipuos",
    "gn:country_code":"PG",
    "gn:dem":25,
    "gn:feature_class":"P",
    "gn:feature_code":"PPL",
    "gn:name":"Noipuos",
    "gn:population":0,
    "gn:timezone":"Pacific/Port_Moresby",
    "iso:country":"PG",
    "name:und_x_variant":[
        "Noipuous",
        "Noipuos"
    ],
    "wof:name":"Noipuos",
    "wof:placetype":"locality"
},
  "geometry": {"coordinates":[150.11237,-2.41115],"type":"Point"}
}