{
  "type": "Feature",
  "properties": {
    "gn:admin1_code":"11",
    "gn:asciiname":"Kwimba",
    "gn:country_code":"PG",
    "gn:dem":53,
    "gn:feature_class":"P",
    "gn:feature_code":"PPL",
    "gn:name":"Kwimba",
    "gn:population":0,
    "gn:timezone":"Pacific/Port_Moresby",
    "iso:country":"PG",
    "name:und_x_variant":[
        "Kwimbu",
        "Kwimba"
    ],
    "wof:name":"Kwimba",
    "wof:placetype":"locality"
},
  "geometry": {"coordinates":[143.12273999999999,-3.92289],"type":"Point"}
}