{
  "type": "Feature",
  "properties": {
    "gn:admin1_code":"18",
    "gn:asciiname":"Swach Baru",
    "gn:country_code":"PG",
    "gn:dem":480,
    "gn:feature_class":"P",
    "gn:feature_code":"PPL",
    "gn:name":"Swach Baru",
    "gn:population":0,
    "gn:timezone":"Pacific/Port_Moresby",
    "iso:country":"PG",
    "name:und_x_variant":[
        "Swach Tua",
        "Swach Baru"
    ],
    "wof:name":"Swach Baru",
    "wof:placetype":"locality"
},
  "geometry": {"coordinates":[141.00371000000001,-3.22973],"type":"Point"}
}