{
  "type": "Feature",
  "properties": {
    "gn:admin1_code":"01",
    "gn:asciiname":"Veiura",
    "gn:country_code":"PG",
    "gn:dem":1058,
    "gn:feature_class":"P",
    "gn:feature_code":"PPL",
    "gn:name":"Veiura",
    "gn:population":0,
    "gn:timezone":"Pacific/Port_Moresby",
    "iso:country":"PG",
    "wof:name":"Veiura",
    "wof:placetype":"locality"
},
  "geometry": {"coordinates":[149.48333,-10.01667],"type":"Point"}
}