{
  "type": "Feature",
  "properties": {
    "gn:admin1_code":"09",
    "gn:asciiname":"Fulsa",
    "gn:country_code":"PG",
    "gn:dem":1796,
    "gn:feature_class":"P",
    "gn:feature_code":"PPL",
    "gn:name":"Fulsa",
    "gn:population":0,
    "gn:timezone":"Pacific/Port_Moresby",
    "iso:country":"PG",
    "wof:name":"Fulsa",
    "wof:placetype":"locality"
},
  "geometry": {"coordinates":[145.43333000000001,-6.38333],"type":"Point"}
}