{
  "type": "Feature",
  "properties": {
    "gn:admin1_code":"15",
    "gn:asciiname":"Nu",
    "gn:country_code":"PG",
    "gn:dem":56,
    "gn:feature_class":"P",
    "gn:feature_code":"PPL",
    "gn:name":"Nu",
    "gn:population":0,
    "gn:timezone":"Pacific/Port_Moresby",
    "iso:country":"PG",
    "name:bos_x_preferred":[
        "Nu"
    ],
    "name:ell_x_preferred":[
        "\u039d\u03bf\u03c5"
    ],
    "name:hun_x_preferred":[
        "Nu"
    ],
    "name:pol_x_preferred":[
        "Nu"
    ],
    "name:urd_x_preferred":[
        "\u0646\u0648"
    ],
    "wof:name":"Nu",
    "wof:placetype":"locality"
},
  "geometry": {"coordinates":[150.32639,-2.65556],"type":"Point"}
}