{
  "type": "Feature",
  "properties": {
    "gn:admin1_code":"08",
    "gn:asciiname":"Kou",
    "gn:country_code":"PG",
    "gn:dem":1830,
    "gn:feature_class":"P",
    "gn:feature_code":"PPL",
    "gn:name":"Kou",
    "gn:population":0,
    "gn:timezone":"Pacific/Port_Moresby",
    "iso:country":"PG",
    "name:ceb_x_preferred":[
        "Kou"
    ],
    "name:fra_x_preferred":[
        "Kou"
    ],
    "name:jpn_x_preferred":[
        "\u30b3\u30a6"
    ],
    "name:nld_x_preferred":[
        "Kou"
    ],
    "name:swe_x_preferred":[
        "Kou"
    ],
    "wof:name":"Kou",
    "wof:placetype":"locality"
},
  "geometry": {"coordinates":[144.98333,-5.98333],"type":"Point"}
}