{
  "type": "Feature",
  "properties": {
    "gn:admin1_code":"10",
    "gn:asciiname":"Rapitok Number 1",
    "gn:country_code":"PG",
    "gn:dem":235,
    "gn:feature_class":"P",
    "gn:feature_code":"PPL",
    "gn:name":"Rapitok Number 1",
    "gn:population":0,
    "gn:timezone":"Pacific/Port_Moresby",
    "iso:country":"PG",
    "wof:name":"Rapitok Number 1",
    "wof:placetype":"locality"
},
  "geometry": {"coordinates":[152.11667,-4.36667],"type":"Point"}
}