{
  "type": "Feature",
  "properties": {
    "gn:admin1_code":"09",
    "gn:asciiname":"Maiva",
    "gn:country_code":"PG",
    "gn:dem":1727,
    "gn:feature_class":"P",
    "gn:feature_code":"PPL",
    "gn:name":"Maiva",
    "gn:population":0,
    "gn:timezone":"Pacific/Port_Moresby",
    "iso:country":"PG",
    "wof:name":"Maiva",
    "wof:placetype":"locality"
},
  "geometry": {"coordinates":[145.15597,-6.44782],"type":"Point"}
}