{
  "type": "Feature",
  "properties": {
    "gn:admin1_code":"15",
    "gn:asciiname":"Balus",
    "gn:country_code":"PG",
    "gn:dem":33,
    "gn:feature_class":"P",
    "gn:feature_code":"PPL",
    "gn:name":"Balus",
    "gn:population":0,
    "gn:timezone":"Pacific/Port_Moresby",
    "iso:country":"PG",
    "wof:name":"Balus",
    "wof:placetype":"locality"
},
  "geometry": {"coordinates":[150.95202,-2.68775],"type":"Point"}
}