{
  "type": "Feature",
  "properties": {
    "gn:country":"PG",
    "gn:fcode":"PPLA",
    "gn:population":26273,
    "iso:country":"PG",
    "name:ast_x_preferred":[
        "Kokopo"
    ],
    "name:bos_x_preferred":[
        "Kokopo"
    ],
    "name:bre_x_preferred":[
        "Kokopo"
    ],
    "name:cat_x_preferred":[
        "Kokopo"
    ],
    "name:ceb_x_preferred":[
        "Kokopo"
    ],
    "name:deu_x_preferred":[
        "Kokopo"
    ],
    "name:eng_x_preferred":[
        "Kokopo"
    ],
    "name:est_x_preferred":[
        "Kokopo"
    ],
    "name:fas_x_preferred":[
        "\u06a9\u0648\u06a9\u0648\u067e\u0648"
    ],
    "name:fra_x_preferred":[
        "Kokopo"
    ],
    "name:gle_x_preferred":[
        "Kokopo"
    ],
    "name:glg_x_preferred":[
        "Kokopo"
    ],
    "name:heb_x_preferred":[
        "\u05e7\u05d5\u05e7\u05d5\u05e4\u05d5"
    ],
    "name:ita_x_preferred":[
        "Kokopo"
    ],
    "name:jpn_x_preferred":[
        "\u30b3\u30b3\u30dd"
    ],
    "name:kor_x_preferred":[
        "\ucf54\ucf54\ud3ec"
    ],
    "name:nld_x_preferred":[
        "Kokopo"
    ],
    "name:pol_x_preferred":[
        "Kokopo"
    ],
    "name:por_x_preferred":[
        "Kokopo"
    ],
    "name:rus_x_preferred":[
        "\u041a\u043e\u043a\u043e\u043f\u043e"
    ],
    "name:spa_x_preferred":[
        "Kokopo"
    ],
    "name:swe_x_preferred":[
        "Kokopo"
    ],
    "name:tpi_x_preferred":[
        "Kokopo"
    ],
    "name:ukr_x_preferred":[
        "\u041a\u043e\u043a\u043e\u043f\u043e"
    ],
    "name:urd_x_preferred":[
        "\u06a9\u0648\u06a9\u0648\u067e\u0648"
    ],
    "name:zho_x_preferred":[
        "\u79d1\u53ef\u6ce2"
    ],
    "name:zho_x_variant":[
        "\u79d1\u79d1\u6ce2"
    ],
    "qs:name":"Kokopo",
    "qs:photos_9r":0,
    "qs:photos_sr":0,
    "qs:pop_sr":"7",
    "wd:elevation":4.0,
    "wd:wordcount":286,
    "wof:name":"Kokopo",
    "wof:placetype":"locality",
    "wof:population":26273
},
  "geometry": {"coordinates":[152.26327000000001,-4.35202],"type":"Point"}
}