{
  "type": "Feature",
  "properties": {
    "gn:admin1_code":"14",
    "gn:asciiname":"Moreng",
    "gn:country_code":"PG",
    "gn:dem":390,
    "gn:feature_class":"P",
    "gn:feature_code":"PPL",
    "gn:name":"Moreng",
    "gn:population":0,
    "gn:timezone":"Pacific/Port_Moresby",
    "iso:country":"PG",
    "wof:name":"Moreng",
    "wof:placetype":"locality"
},
  "geometry": {"coordinates":[147.77248,-6.53467],"type":"Point"}
}