{
  "type": "Feature",
  "properties": {
    "gn:admin1_code":"09",
    "gn:asciiname":"Mogobena",
    "gn:country_code":"PG",
    "gn:dem":1484,
    "gn:feature_class":"P",
    "gn:feature_code":"PPL",
    "gn:name":"Mogobena",
    "gn:population":0,
    "gn:timezone":"Pacific/Port_Moresby",
    "iso:country":"PG",
    "wof:name":"Mogobena",
    "wof:placetype":"locality"
},
  "geometry": {"coordinates":[145.44999999999999,-6.35],"type":"Point"}
}