{
  "type": "Feature",
  "properties": {
    "gn:country":"PG",
    "gn:fcode":"PPL",
    "gn:population":1054,
    "iso:country":"PG",
    "name:ceb_x_preferred":[
        "Finschhafen"
    ],
    "name:ces_x_preferred":[
        "Finschhafen"
    ],
    "name:deu_x_preferred":[
        "Finschhafen"
    ],
    "name:eng_x_preferred":[
        "Finschhafen"
    ],
    "name:fas_x_preferred":[
        "\u0641\u06cc\u0646\u0634\u0647\u0627\u0641\u0646"
    ],
    "name:fin_x_preferred":[
        "Finschhafen"
    ],
    "name:fra_x_preferred":[
        "Finschhafen"
    ],
    "name:glg_x_preferred":[
        "Finschhafen"
    ],
    "name:ita_x_preferred":[
        "Finschhafen"
    ],
    "name:jpn_x_preferred":[
        "\u30d5\u30a3\u30f3\u30b7\u30e5\u30cf\u30fc\u30d5\u30a7\u30f3"
    ],
    "name:nld_x_preferred":[
        "Finschhafen"
    ],
    "name:pol_x_preferred":[
        "Finschhafen"
    ],
    "name:rus_x_preferred":[
        "\u0424\u0438\u043d\u0448\u0445\u0430\u0444\u0435\u043d"
    ],
    "name:spa_x_preferred":[
        "Finschhafen"
    ],
    "name:ukr_x_preferred":[
        "\u0424\u0456\u043d\u0448\u0433\u0430\u0444\u0435\u043d"
    ],
    "name:und_x_variant":[
        "Finschafen"
    ],
    "name:zho_x_preferred":[
        "\u82ac\u4ec0\u6e2f"
    ],
    "qs:name":"Finschhafen",
    "qs:photos_9r":0,
    "qs:photos_sr":0,
    "qs:pop_sr":"3",
    "wd:wordcount":358,
    "wof:name":"Finschhafen",
    "wof:placetype":"locality",
    "wof:population":1054
},
  "geometry": {"coordinates":[147.86814000000001,-6.60243],"type":"Point"}
}