{
  "type": "Feature",
  "properties": {
    "gn:admin1_code":"13",
    "gn:asciiname":"Bulihat",
    "gn:country_code":"PG",
    "gn:dem":13,
    "gn:feature_class":"P",
    "gn:feature_code":"PPL",
    "gn:name":"Bulihat",
    "gn:population":0,
    "gn:timezone":"Pacific/Port_Moresby",
    "iso:country":"PG",
    "wof:name":"Bulihat",
    "wof:placetype":"locality"
},
  "geometry": {"coordinates":[147.21666999999999,-2.01667],"type":"Point"}
}