{
  "type": "Feature",
  "properties": {
    "gn:admin1_code":"09",
    "gn:asciiname":"Bafa",
    "gn:country_code":"PG",
    "gn:dem":1992,
    "gn:feature_class":"P",
    "gn:feature_code":"PPL",
    "gn:name":"Bafa",
    "gn:population":0,
    "gn:timezone":"Pacific/Port_Moresby",
    "iso:country":"PG",
    "name:und_x_variant":[
        "Bafo",
        "Bafa"
    ],
    "wof:name":"Bafa",
    "wof:placetype":"locality"
},
  "geometry": {"coordinates":[145.71292,-6.16934],"type":"Point"}
}