{
  "type": "Feature",
  "properties": {
    "gn:admin1_code":"02",
    "gn:asciiname":"Kivaumai Number 2",
    "gn:country_code":"PG",
    "gn:dem":-9999,
    "gn:feature_class":"P",
    "gn:feature_code":"PPL",
    "gn:name":"Kivaumai Number 2",
    "gn:population":0,
    "gn:timezone":"Pacific/Port_Moresby",
    "iso:country":"PG",
    "name:und_x_variant":[
        "Kivaumai 2",
        "Kivaumai Number 2"
    ],
    "wof:name":"Kivaumai Number 2",
    "wof:placetype":"locality"
},
  "geometry": {"coordinates":[144.62658000000005,-7.65755],"type":"Point"}
}