{
  "type": "Feature",
  "properties": {
    "gn:admin1_code":"14",
    "gn:asciiname":"Bolingbongen",
    "gn:country_code":"PG",
    "gn:dem":787,
    "gn:feature_class":"P",
    "gn:feature_code":"PPL",
    "gn:name":"Bolingbongen",
    "gn:population":0,
    "gn:timezone":"Pacific/Port_Moresby",
    "iso:country":"PG",
    "wof:name":"Bolingbongen",
    "wof:placetype":"locality"
},
  "geometry": {"coordinates":[147.72573,-6.46791],"type":"Point"}
}