{
  "type": "Feature",
  "properties": {
    "gn:admin1_code":"11",
    "gn:asciiname":"Makambu",
    "gn:country_code":"PG",
    "gn:dem":58,
    "gn:feature_class":"P",
    "gn:feature_code":"PPL",
    "gn:name":"Makambu",
    "gn:population":0,
    "gn:timezone":"Pacific/Port_Moresby",
    "iso:country":"PG",
    "wof:name":"Makambu",
    "wof:placetype":"locality"
},
  "geometry": {"coordinates":[143.25898999999995,-3.91515],"type":"Point"}
}