{
  "type": "Feature",
  "properties": {
    "gn:admin1_code":"17",
    "gn:asciiname":"Buluwara",
    "gn:country_code":"PG",
    "gn:dem":28,
    "gn:feature_class":"P",
    "gn:feature_code":"PPL",
    "gn:name":"Buluwara",
    "gn:population":0,
    "gn:timezone":"Pacific/Port_Moresby",
    "iso:country":"PG",
    "wof:name":"Buluwara",
    "wof:placetype":"locality"
},
  "geometry": {"coordinates":[149.95582999999999,-5.27349],"type":"Point"}
}