{
  "type": "Feature",
  "properties": {
    "gn:admin1_code":"14",
    "gn:asciiname":"Bun",
    "gn:country_code":"PG",
    "gn:dem":61,
    "gn:feature_class":"P",
    "gn:feature_code":"PPL",
    "gn:name":"Bun",
    "gn:population":0,
    "gn:timezone":"Pacific/Port_Moresby",
    "iso:country":"PG",
    "wof:name":"Bun",
    "wof:placetype":"locality"
},
  "geometry": {"coordinates":[147.56120000000001,-5.30036],"type":"Point"}
}