{
  "type": "Feature",
  "properties": {
    "gn:admin1_code":"14",
    "gn:asciiname":"Bun",
    "gn:country_code":"PG",
    "gn:dem":61,
    "gn:feature_class":"P",
    "gn:feature_code":"PPL",
    "gn:name":"Bun",
    "gn:population":0,
    "gn:timezone":"Pacific/Port_Moresby",
    "iso:country":"PG",
    "name:cym_x_preferred":[
        "Bynen"
    ],
    "name:deu_x_preferred":[
        "Bun"
    ],
    "name:eus_x_preferred":[
        "Opil"
    ],
    "name:fra_x_preferred":[
        "Bun"
    ],
    "name:hun_x_preferred":[
        "Bollo"
    ],
    "name:ind_x_preferred":[
        "Roti bulat"
    ],
    "name:jpn_x_preferred":[
        "\u30d0\u30f3\u30ba"
    ],
    "name:kan_x_preferred":[
        "\u0cac\u0ca8\u0ccd"
    ],
    "name:kor_x_preferred":[
        "\ubc88"
    ],
    "name:lit_x_preferred":[
        "Bandel\u0117"
    ],
    "name:nld_x_preferred":[
        "Kadetje"
    ],
    "name:nno_x_preferred":[
        "Bolle"
    ],
    "name:rus_x_preferred":[
        "\u0411\u0443\u043b\u043e\u0447\u043a\u0430"
    ],
    "name:spa_x_preferred":[
        "Bollo"
    ],
    "name:srp_x_preferred":[
        "Zemi\u010dka"
    ],
    "name:swe_x_preferred":[
        "Bulle"
    ],
    "name:zho_x_preferred":[
        "\u5c0f\u5706\u9762\u5305"
    ],
    "wof:name":"Bun",
    "wof:placetype":"locality"
},
  "geometry": {"coordinates":[147.56120000000001,-5.30036],"type":"Point"}
}