{
  "type": "Feature",
  "properties": {
    "gn:admin1_code":"03",
    "gn:asciiname":"Pakatutura",
    "gn:country_code":"PG",
    "gn:dem":15,
    "gn:feature_class":"P",
    "gn:feature_code":"PPL",
    "gn:name":"Pakatutura",
    "gn:population":0,
    "gn:timezone":"Pacific/Port_Moresby",
    "iso:country":"PG",
    "wof:name":"Pakatutura",
    "wof:placetype":"locality"
},
  "geometry": {"coordinates":[149.80000000000001,-9.91667],"type":"Point"}
}