{
  "type": "Feature",
  "properties": {
    "gn:admin1_code":"09",
    "gn:asciiname":"Sainapa",
    "gn:country_code":"PG",
    "gn:dem":2209,
    "gn:feature_class":"P",
    "gn:feature_code":"PPL",
    "gn:name":"Sainapa",
    "gn:population":0,
    "gn:timezone":"Pacific/Port_Moresby",
    "iso:country":"PG",
    "wof:name":"Sainapa",
    "wof:placetype":"locality"
},
  "geometry": {"coordinates":[145.75,-6.41667],"type":"Point"}
}