{
  "type": "Feature",
  "properties": {
    "gn:admin1_code":"06",
    "gn:asciiname":"Waiofi",
    "gn:country_code":"PG",
    "gn:dem":257,
    "gn:feature_class":"P",
    "gn:feature_code":"PPL",
    "gn:name":"Waiofi",
    "gn:population":0,
    "gn:timezone":"Pacific/Port_Moresby",
    "iso:country":"PG",
    "wof:name":"Waiofi",
    "wof:placetype":"locality"
},
  "geometry": {"coordinates":[142.41506000000001,-6.35258],"type":"Point"}
}