{
  "type": "Feature",
  "properties": {
    "gn:admin1_code":"09",
    "gn:asciiname":"Wogi",
    "gn:country_code":"PG",
    "gn:dem":1761,
    "gn:feature_class":"P",
    "gn:feature_code":"PPL",
    "gn:name":"Wogi",
    "gn:population":0,
    "gn:timezone":"Pacific/Port_Moresby",
    "iso:country":"PG",
    "wof:name":"Wogi",
    "wof:placetype":"locality"
},
  "geometry": {"coordinates":[145.26667,-5.95],"type":"Point"}
}