{
  "type": "Feature",
  "properties": {
    "gn:admin1_code":"11",
    "gn:asciiname":"Ambukanja",
    "gn:country_code":"PG",
    "gn:dem":358,
    "gn:feature_class":"P",
    "gn:feature_code":"PPL",
    "gn:name":"Ambukanja",
    "gn:population":0,
    "gn:timezone":"Pacific/Port_Moresby",
    "iso:country":"PG",
    "wof:name":"Ambukanja",
    "wof:placetype":"locality"
},
  "geometry": {"coordinates":[143.32689999999999,-3.63128],"type":"Point"}
}