{
  "type": "Feature",
  "properties": {
    "gn:admin1_code":"01",
    "gn:asciiname":"Obakigolo",
    "gn:country_code":"PG",
    "gn:dem":231,
    "gn:feature_class":"P",
    "gn:feature_code":"PPL",
    "gn:name":"Obakigolo",
    "gn:population":0,
    "gn:timezone":"Pacific/Port_Moresby",
    "iso:country":"PG",
    "name:und_x_variant":[
        "Baligoro",
        "Obakigoro",
        "Obakigolo"
    ],
    "wof:name":"Obakigolo",
    "wof:placetype":"locality"
},
  "geometry": {"coordinates":[147.89166,-9.77914],"type":"Point"}
}