{
  "type": "Feature",
  "properties": {
    "gn:admin1_code":"14",
    "gn:asciiname":"Sukurum",
    "gn:country_code":"PG",
    "gn:dem":640,
    "gn:feature_class":"P",
    "gn:feature_code":"PPL",
    "gn:name":"Sukurum",
    "gn:population":0,
    "gn:timezone":"Pacific/Port_Moresby",
    "iso:country":"PG",
    "wof:name":"Sukurum",
    "wof:placetype":"locality"
},
  "geometry": {"coordinates":[146.48889,-6.28316],"type":"Point"}
}