{
  "type": "Feature",
  "properties": {
    "gn:admin1_code":"12",
    "gn:asciiname":"Kerevin",
    "gn:country_code":"PG",
    "gn:dem":2067,
    "gn:feature_class":"P",
    "gn:feature_code":"PPL",
    "gn:name":"Kerevin",
    "gn:population":0,
    "gn:timezone":"Pacific/Port_Moresby",
    "iso:country":"PG",
    "wof:name":"Kerevin",
    "wof:placetype":"locality"
},
  "geometry": {"coordinates":[144.57961,-5.21645],"type":"Point"}
}