{
  "type": "Feature",
  "properties": {
    "gn:admin1_code":"02",
    "gn:asciiname":"Belepa",
    "gn:country_code":"PG",
    "gn:dem":25,
    "gn:feature_class":"P",
    "gn:feature_code":"PPL",
    "gn:name":"Belepa",
    "gn:population":0,
    "gn:timezone":"Pacific/Port_Moresby",
    "iso:country":"PG",
    "name:und_x_variant":[
        "Beleppa",
        "Belepa"
    ],
    "wof:name":"Belepa",
    "wof:placetype":"locality"
},
  "geometry": {"coordinates":[145.47215,-7.90337],"type":"Point"}
}