{
  "type": "Feature",
  "properties": {
    "gn:admin1_code":"09",
    "gn:asciiname":"Gun'yahange",
    "gn:country_code":"PG",
    "gn:dem":1341,
    "gn:feature_class":"P",
    "gn:feature_code":"PPL",
    "gn:name":"Gun\u2019yahange",
    "gn:population":0,
    "gn:timezone":"Pacific/Port_Moresby",
    "iso:country":"PG",
    "wof:name":"Gun'yahange",
    "wof:placetype":"locality"
},
  "geometry": {"coordinates":[145.73333,-7.05],"type":"Point"}
}