{
  "type": "Feature",
  "properties": {
    "gn:admin1_code":"18",
    "gn:asciiname":"Biaka",
    "gn:country_code":"PG",
    "gn:dem":165,
    "gn:feature_class":"P",
    "gn:feature_code":"PPL",
    "gn:name":"Biaka",
    "gn:population":0,
    "gn:timezone":"Pacific/Port_Moresby",
    "iso:country":"PG",
    "wof:name":"Biaka",
    "wof:placetype":"locality"
},
  "geometry": {"coordinates":[141.27956,-3.74063],"type":"Point"}
}