{
  "type": "Feature",
  "properties": {
    "gn:admin1_code":"03",
    "gn:asciiname":"Warawadidi",
    "gn:country_code":"PG",
    "gn:dem":1102,
    "gn:feature_class":"P",
    "gn:feature_code":"PPL",
    "gn:name":"Warawadidi",
    "gn:population":0,
    "gn:timezone":"Pacific/Port_Moresby",
    "iso:country":"PG",
    "wof:name":"Warawadidi",
    "wof:placetype":"locality"
},
  "geometry": {"coordinates":[149.81718999999995,-10.11041],"type":"Point"}
}