{
  "type": "Feature",
  "properties": {
    "gn:admin1_code":"06",
    "gn:asciiname":"Grumena",
    "gn:country_code":"PG",
    "gn:dem":120,
    "gn:feature_class":"P",
    "gn:feature_code":"PPL",
    "gn:name":"Grumena",
    "gn:population":0,
    "gn:timezone":"Pacific/Port_Moresby",
    "iso:country":"PG",
    "wof:name":"Grumena",
    "wof:placetype":"locality"
},
  "geometry": {"coordinates":[141.81666999999999,-5.93333],"type":"Point"}
}