{
  "type": "Feature",
  "properties": {
    "gn:admin1_code":"03",
    "gn:asciiname":"Guasopa",
    "gn:country_code":"PG",
    "gn:dem":23,
    "gn:feature_class":"P",
    "gn:feature_code":"PPL",
    "gn:name":"Guasopa",
    "gn:population":0,
    "gn:timezone":"Pacific/Port_Moresby",
    "iso:country":"PG",
    "name:und_x_variant":[
        "Guasop",
        "Guasopa"
    ],
    "wof:name":"Guasopa",
    "wof:placetype":"locality"
},
  "geometry": {"coordinates":[152.95108000000005,-9.22277],"type":"Point"}
}