{
  "type": "Feature",
  "properties": {
    "gn:admin1_code":"01",
    "gn:asciiname":"Iarumenomu",
    "gn:country_code":"PG",
    "gn:dem":194,
    "gn:feature_class":"P",
    "gn:feature_code":"PPL",
    "gn:name":"Iarumenomu",
    "gn:population":0,
    "gn:timezone":"Pacific/Port_Moresby",
    "iso:country":"PG",
    "wof:name":"Iarumenomu",
    "wof:placetype":"locality"
},
  "geometry": {"coordinates":[147.76331999999999,-9.64239],"type":"Point"}
}