{
  "type": "Feature",
  "properties": {
    "gn:admin1_code":"09",
    "gn:asciiname":"Cherokoro",
    "gn:country_code":"PG",
    "gn:dem":2156,
    "gn:feature_class":"P",
    "gn:feature_code":"PPL",
    "gn:name":"Cherokoro",
    "gn:population":0,
    "gn:timezone":"Pacific/Port_Moresby",
    "iso:country":"PG",
    "wof:name":"Cherokoro",
    "wof:placetype":"locality"
},
  "geometry": {"coordinates":[145.71666999999999,-6.85],"type":"Point"}
}