{
  "type": "Feature",
  "properties": {
    "gn:admin1_code":"01",
    "gn:asciiname":"Keabada",
    "gn:country_code":"PG",
    "gn:dem":8,
    "gn:feature_class":"P",
    "gn:feature_code":"PPL",
    "gn:name":"Keabada",
    "gn:population":0,
    "gn:timezone":"Pacific/Port_Moresby",
    "iso:country":"PG",
    "name:und_x_variant":[
        "Nabuapaka",
        "Kea Pada",
        "Keabada"
    ],
    "wof:name":"Keabada",
    "wof:placetype":"locality"
},
  "geometry": {"coordinates":[146.55976000000001,-8.90173],"type":"Point"}
}