{
  "type": "Feature",
  "properties": {
    "gn:admin1_code":"12",
    "gn:asciiname":"Negiri",
    "gn:country_code":"PG",
    "gn:dem":479,
    "gn:feature_class":"P",
    "gn:feature_code":"PPL",
    "gn:name":"Negiri",
    "gn:population":0,
    "gn:timezone":"Pacific/Port_Moresby",
    "iso:country":"PG",
    "wof:name":"Negiri",
    "wof:placetype":"locality"
},
  "geometry": {"coordinates":[145.50274999999999,-5.40388],"type":"Point"}
}