{
  "type": "Feature",
  "properties": {
    "gn:admin1_code":"09",
    "gn:asciiname":"Kakopi",
    "gn:country_code":"PG",
    "gn:dem":2041,
    "gn:feature_class":"P",
    "gn:feature_code":"PPL",
    "gn:name":"Kakopi",
    "gn:population":0,
    "gn:timezone":"Pacific/Port_Moresby",
    "iso:country":"PG",
    "wof:name":"Kakopi",
    "wof:placetype":"locality"
},
  "geometry": {"coordinates":[145.60298999999995,-6.38942],"type":"Point"}
}