{
  "type": "Feature",
  "properties": {
    "gn:admin1_code":"08",
    "gn:asciiname":"Dunumbiangguna",
    "gn:country_code":"PG",
    "gn:dem":1663,
    "gn:feature_class":"P",
    "gn:feature_code":"PPL",
    "gn:name":"Dunumbiangguna",
    "gn:population":0,
    "gn:timezone":"Pacific/Port_Moresby",
    "iso:country":"PG",
    "wof:name":"Dunumbiangguna",
    "wof:placetype":"locality"
},
  "geometry": {"coordinates":[144.95256000000001,-6.1209],"type":"Point"}
}