{
  "type": "Feature",
  "properties": {
    "gn:admin1_code":"09",
    "gn:asciiname":"Pomasi Number 1",
    "gn:country_code":"PG",
    "gn:dem":1943,
    "gn:feature_class":"P",
    "gn:feature_code":"PPL",
    "gn:name":"Pomasi Number 1",
    "gn:population":0,
    "gn:timezone":"Pacific/Port_Moresby",
    "iso:country":"PG",
    "name:und_x_variant":[
        "New Pumasse",
        "Pumassi",
        "Pomasi 1",
        "Pomasi Number 1"
    ],
    "wof:name":"Pomasi Number 1",
    "wof:placetype":"locality"
},
  "geometry": {"coordinates":[145.82303999999999,-6.17803],"type":"Point"}
}