{
  "type": "Feature",
  "properties": {
    "gn:admin1_code":"02",
    "gn:asciiname":"Kopi",
    "gn:country_code":"PG",
    "gn:dem":26,
    "gn:feature_class":"P",
    "gn:feature_code":"PPL",
    "gn:name":"Kopi",
    "gn:population":0,
    "gn:timezone":"Pacific/Port_Moresby",
    "iso:country":"PG",
    "name:ceb_x_preferred":[
        "Kopi"
    ],
    "name:jav_x_preferred":[
        "Kopi"
    ],
    "name:swe_x_preferred":[
        "Kopi"
    ],
    "wof:name":"Kopi",
    "wof:placetype":"locality"
},
  "geometry": {"coordinates":[144.18096,-7.31593],"type":"Point"}
}