{
  "type": "Feature",
  "properties": {
    "gn:admin1_code":"01",
    "gn:asciiname":"Imounga",
    "gn:country_code":"PG",
    "gn:dem":55,
    "gn:feature_class":"P",
    "gn:feature_code":"PPL",
    "gn:name":"Imounga",
    "gn:population":0,
    "gn:timezone":"Pacific/Port_Moresby",
    "iso:country":"PG",
    "wof:name":"Imounga",
    "wof:placetype":"locality"
},
  "geometry": {"coordinates":[146.64686,-8.40261],"type":"Point"}
}