{
  "type": "Feature",
  "properties": {
    "gn:admin1_code":"14",
    "gn:asciiname":"Koiyan",
    "gn:country_code":"PG",
    "gn:dem":810,
    "gn:feature_class":"P",
    "gn:feature_code":"PPL",
    "gn:name":"Koiyan",
    "gn:population":0,
    "gn:timezone":"Pacific/Port_Moresby",
    "iso:country":"PG",
    "wof:name":"Koiyan",
    "wof:placetype":"locality"
},
  "geometry": {"coordinates":[147.01548,-6.09566],"type":"Point"}
}