{
  "type": "Feature",
  "properties": {
    "gn:admin1_code":"18",
    "gn:asciiname":"Buna",
    "gn:country_code":"PG",
    "gn:dem":50,
    "gn:feature_class":"P",
    "gn:feature_code":"PPL",
    "gn:name":"Buna",
    "gn:population":0,
    "gn:timezone":"Pacific/Port_Moresby",
    "iso:country":"PG",
    "wof:name":"Buna",
    "wof:placetype":"locality"
},
  "geometry": {"coordinates":[141.26304999999999,-3.9659],"type":"Point"}
}