{
  "type": "Feature",
  "properties": {
    "gn:admin1_code":"14",
    "gn:asciiname":"Bantamu",
    "gn:country_code":"PG",
    "gn:dem":827,
    "gn:feature_class":"P",
    "gn:feature_code":"PPL",
    "gn:name":"Bantamu",
    "gn:population":0,
    "gn:timezone":"Pacific/Port_Moresby",
    "iso:country":"PG",
    "wof:name":"Bantamu",
    "wof:placetype":"locality"
},
  "geometry": {"coordinates":[147.52581999999995,-6.45986],"type":"Point"}
}