{
  "type": "Feature",
  "properties": {
    "gn:admin1_code":"02",
    "gn:asciiname":"Lui",
    "gn:country_code":"PG",
    "gn:dem":14,
    "gn:feature_class":"P",
    "gn:feature_code":"PPL",
    "gn:name":"Lui",
    "gn:population":0,
    "gn:timezone":"Pacific/Port_Moresby",
    "iso:country":"PG",
    "name:deu_x_preferred":[
        "Lui"
    ],
    "name:est_x_preferred":[
        "Lui"
    ],
    "name:fra_x_preferred":[
        "Lui"
    ],
    "name:hun_x_preferred":[
        "Lui"
    ],
    "wof:name":"Lui",
    "wof:placetype":"locality"
},
  "geometry": {"coordinates":[145.4487,-7.92296],"type":"Point"}
}