{
  "type": "Feature",
  "properties": {
    "gn:admin1_code":"03",
    "gn:asciiname":"Kebatura",
    "gn:country_code":"PG",
    "gn:dem":660,
    "gn:feature_class":"P",
    "gn:feature_code":"PPL",
    "gn:name":"Kebatura",
    "gn:population":0,
    "gn:timezone":"Pacific/Port_Moresby",
    "iso:country":"PG",
    "wof:name":"Kebatura",
    "wof:placetype":"locality"
},
  "geometry": {"coordinates":[149.96666999999999,-10.16667],"type":"Point"}
}