{
  "type": "Feature",
  "properties": {
    "gn:admin1_code":"14",
    "gn:asciiname":"Yowong",
    "gn:country_code":"PG",
    "gn:dem":396,
    "gn:feature_class":"P",
    "gn:feature_code":"PPL",
    "gn:name":"Yowong",
    "gn:population":0,
    "gn:timezone":"Pacific/Port_Moresby",
    "iso:country":"PG",
    "name:und_x_variant":[
        "Yuwong",
        "Yowong"
    ],
    "wof:name":"Yowong",
    "wof:placetype":"locality"
},
  "geometry": {"coordinates":[146.78016000000005,-5.88094],"type":"Point"}
}