{
  "type": "Feature",
  "properties": {
    "gn:admin1_code":"14",
    "gn:asciiname":"Yambong",
    "gn:country_code":"PG",
    "gn:dem":125,
    "gn:feature_class":"P",
    "gn:feature_code":"PPL",
    "gn:name":"Yambong",
    "gn:population":0,
    "gn:timezone":"Pacific/Port_Moresby",
    "iso:country":"PG",
    "name:und_x_variant":[
        "Yombong",
        "Yambong"
    ],
    "wof:name":"Yambong",
    "wof:placetype":"locality"
},
  "geometry": {"coordinates":[147.62062,-6.67766],"type":"Point"}
}