{
  "type": "Feature",
  "properties": {
    "gn:admin1_code":"05",
    "gn:asciiname":"Tombu",
    "gn:country_code":"PG",
    "gn:dem":2145,
    "gn:feature_class":"P",
    "gn:feature_code":"PPL",
    "gn:name":"Tombu",
    "gn:population":0,
    "gn:timezone":"Pacific/Port_Moresby",
    "iso:country":"PG",
    "wof:name":"Tombu",
    "wof:placetype":"locality"
},
  "geometry": {"coordinates":[143.36667,-6.15],"type":"Point"}
}