{
  "type": "Feature",
  "properties": {
    "gn:admin1_code":"18",
    "gn:asciiname":"Petaineri Number 1",
    "gn:country_code":"PG",
    "gn:dem":381,
    "gn:feature_class":"P",
    "gn:feature_code":"PPL",
    "gn:name":"Petaineri Number 1",
    "gn:population":0,
    "gn:timezone":"Pacific/Port_Moresby",
    "iso:country":"PG",
    "name:und_x_variant":[
        "Petaineri 1",
        "Petaineri Number 1"
    ],
    "wof:name":"Petaineri Number 1",
    "wof:placetype":"locality"
},
  "geometry": {"coordinates":[141.08346,-3.55227],"type":"Point"}
}