{
  "type": "Feature",
  "properties": {
    "gn:admin1_code":"09",
    "gn:asciiname":"Paigatasa",
    "gn:country_code":"PG",
    "gn:dem":1757,
    "gn:feature_class":"P",
    "gn:feature_code":"PPL",
    "gn:name":"Paigatasa",
    "gn:population":0,
    "gn:timezone":"Pacific/Port_Moresby",
    "iso:country":"PG",
    "wof:name":"Paigatasa",
    "wof:placetype":"locality"
},
  "geometry": {"coordinates":[145.48214999999999,-6.53544],"type":"Point"}
}