{
  "type": "Feature",
  "properties": {
    "gn:admin1_code":"06",
    "gn:asciiname":"Tidiebi",
    "gn:country_code":"PG",
    "gn:dem":135,
    "gn:feature_class":"P",
    "gn:feature_code":"PPL",
    "gn:name":"Tidiebi",
    "gn:population":0,
    "gn:timezone":"Pacific/Port_Moresby",
    "iso:country":"PG",
    "wof:name":"Tidiebi",
    "wof:placetype":"locality"
},
  "geometry": {"coordinates":[142.15232,-6.23796],"type":"Point"}
}