{
  "type": "Feature",
  "properties": {
    "gn:admin1_code":"11",
    "gn:asciiname":"Bugitu",
    "gn:country_code":"PG",
    "gn:dem":200,
    "gn:feature_class":"P",
    "gn:feature_code":"PPL",
    "gn:name":"Bugitu",
    "gn:population":0,
    "gn:timezone":"Pacific/Port_Moresby",
    "iso:country":"PG",
    "wof:name":"Bugitu",
    "wof:placetype":"locality"
},
  "geometry": {"coordinates":[143.18154999999999,-3.68867],"type":"Point"}
}