{
  "type": "Feature",
  "properties": {
    "gn:admin1_code":"11",
    "gn:asciiname":"Inakor",
    "gn:country_code":"PG",
    "gn:dem":241,
    "gn:feature_class":"P",
    "gn:feature_code":"PPL",
    "gn:name":"Inakor",
    "gn:population":0,
    "gn:timezone":"Pacific/Port_Moresby",
    "iso:country":"PG",
    "wof:name":"Inakor",
    "wof:placetype":"locality"
},
  "geometry": {"coordinates":[142.84001999999995,-3.68506],"type":"Point"}
}