{
  "type": "Feature",
  "properties": {
    "gn:admin1_code":"03",
    "gn:asciiname":"Dabi",
    "gn:country_code":"PG",
    "gn:dem":87,
    "gn:feature_class":"P",
    "gn:feature_code":"PPL",
    "gn:name":"Dabi",
    "gn:population":0,
    "gn:timezone":"Pacific/Port_Moresby",
    "iso:country":"PG",
    "wof:name":"Dabi",
    "wof:placetype":"locality"
},
  "geometry": {"coordinates":[149.81666999999999,-9.66667],"type":"Point"}
}