{
  "type": "Feature",
  "properties": {
    "gn:admin1_code":"15",
    "gn:asciiname":"Nabumai",
    "gn:cc2":"PG",
    "gn:country_code":"PG",
    "gn:dem":257,
    "gn:feature_class":"P",
    "gn:feature_code":"PPL",
    "gn:name":"Nabumai",
    "gn:population":0,
    "gn:timezone":"Pacific/Port_Moresby",
    "iso:country":"PG",
    "name:und_x_variant":[
        "New Nabumai",
        "Nabumai"
    ],
    "wof:name":"Nabumai",
    "wof:placetype":"locality"
},
  "geometry": {"coordinates":[152.43333000000001,-3.73333],"type":"Point"}
}