{
  "type": "Feature",
  "properties": {
    "gn:admin1_code":"12",
    "gn:asciiname":"Iku",
    "gn:country_code":"PG",
    "gn:dem":27,
    "gn:feature_class":"P",
    "gn:feature_code":"PPL",
    "gn:name":"Iku",
    "gn:population":0,
    "gn:timezone":"Pacific/Port_Moresby",
    "iso:country":"PG",
    "wof:name":"Iku",
    "wof:placetype":"locality"
},
  "geometry": {"coordinates":[144.83698000000001,-4.21753],"type":"Point"}
}