{
  "type": "Feature",
  "properties": {
    "gn:admin1_code":"19",
    "gn:asciiname":"Pundami",
    "gn:country_code":"PG",
    "gn:dem":2071,
    "gn:feature_class":"P",
    "gn:feature_code":"PPL",
    "gn:name":"Pundami",
    "gn:population":0,
    "gn:timezone":"Pacific/Port_Moresby",
    "iso:country":"PG",
    "wof:name":"Pundami",
    "wof:placetype":"locality"
},
  "geometry": {"coordinates":[142.98507000000001,-5.43361],"type":"Point"}
}