{
  "type": "Feature",
  "properties": {
    "gn:admin1_code":"14",
    "gn:asciiname":"Bukum",
    "gn:country_code":"PG",
    "gn:dem":77,
    "gn:feature_class":"P",
    "gn:feature_code":"PPL",
    "gn:name":"Bukum",
    "gn:population":0,
    "gn:timezone":"Pacific/Port_Moresby",
    "iso:country":"PG",
    "wof:name":"Bukum",
    "wof:placetype":"locality"
},
  "geometry": {"coordinates":[147.91666999999995,-5.75],"type":"Point"}
}