{
  "type": "Feature",
  "properties": {
    "gn:admin1_code":"16",
    "gn:asciiname":"Opiabus",
    "gn:country_code":"PG",
    "gn:dem":2480,
    "gn:feature_class":"P",
    "gn:feature_code":"PPL",
    "gn:name":"Opiabus",
    "gn:population":0,
    "gn:timezone":"Pacific/Port_Moresby",
    "iso:country":"PG",
    "wof:name":"Opiabus",
    "wof:placetype":"locality"
},
  "geometry": {"coordinates":[143.95318999999995,-5.921],"type":"Point"}
}