{
  "type": "Feature",
  "properties": {
    "gn:admin1_code":"19",
    "gn:asciiname":"Rambapes",
    "gn:country_code":"PG",
    "gn:dem":2024,
    "gn:feature_class":"P",
    "gn:feature_code":"PPL",
    "gn:name":"Rambapes",
    "gn:population":0,
    "gn:timezone":"Pacific/Port_Moresby",
    "iso:country":"PG",
    "wof:name":"Rambapes",
    "wof:placetype":"locality"
},
  "geometry": {"coordinates":[143.35074,-5.36693],"type":"Point"}
}