{
  "type": "Feature",
  "properties": {
    "gn:admin1_code":"06",
    "gn:asciiname":"Tais",
    "gn:country_code":"PG",
    "gn:dem":18,
    "gn:feature_class":"P",
    "gn:feature_code":"PPL",
    "gn:name":"Tais",
    "gn:population":0,
    "gn:timezone":"Pacific/Port_Moresby",
    "iso:country":"PG",
    "name:deu_x_preferred":[
        "Tais"
    ],
    "wof:name":"Tais",
    "wof:placetype":"locality"
},
  "geometry": {"coordinates":[141.95778000000001,-9.15786],"type":"Point"}
}