{
  "type": "Feature",
  "properties": {
    "gn:admin1_code":"18",
    "gn:asciiname":"Amer",
    "gn:country_code":"PG",
    "gn:dem":158,
    "gn:feature_class":"P",
    "gn:feature_code":"PPL",
    "gn:name":"Amer",
    "gn:population":0,
    "gn:timezone":"Pacific/Port_Moresby",
    "iso:country":"PG",
    "name:ceb_x_preferred":[
        "Amer"
    ],
    "name:deu_x_preferred":[
        "Amer"
    ],
    "name:fra_x_preferred":[
        "Amer"
    ],
    "name:ita_x_preferred":[
        "Amer"
    ],
    "name:nld_x_preferred":[
        "Amer"
    ],
    "name:swe_x_preferred":[
        "Amer"
    ],
    "wof:name":"Amer",
    "wof:placetype":"locality"
},
  "geometry": {"coordinates":[141.78333000000001,-3.56667],"type":"Point"}
}