{
  "type": "Feature",
  "properties": {
    "gn:admin1_code":"14",
    "gn:asciiname":"Atapaura",
    "gn:country_code":"PG",
    "gn:dem":1682,
    "gn:feature_class":"P",
    "gn:feature_code":"PPL",
    "gn:name":"Atapaura",
    "gn:population":0,
    "gn:timezone":"Pacific/Port_Moresby",
    "iso:country":"PG",
    "wof:name":"Atapaura",
    "wof:placetype":"locality"
},
  "geometry": {"coordinates":[146.24601000000001,-7.1971],"type":"Point"}
}