{
  "type": "Feature",
  "properties": {
    "gn:admin1_code":"14",
    "gn:asciiname":"Zezaging",
    "gn:country_code":"PG",
    "gn:dem":742,
    "gn:feature_class":"P",
    "gn:feature_code":"PPL",
    "gn:name":"Zezaging",
    "gn:population":0,
    "gn:timezone":"Pacific/Port_Moresby",
    "iso:country":"PG",
    "wof:name":"Zezaging",
    "wof:placetype":"locality"
},
  "geometry": {"coordinates":[147.18433000000005,-6.5666],"type":"Point"}
}