{
  "type": "Feature",
  "properties": {
    "gn:admin1_code":"10",
    "gn:asciiname":"Worali",
    "gn:country_code":"PG",
    "gn:dem":640,
    "gn:feature_class":"P",
    "gn:feature_code":"PPL",
    "gn:name":"Worali",
    "gn:population":0,
    "gn:timezone":"Pacific/Port_Moresby",
    "iso:country":"PG",
    "wof:name":"Worali",
    "wof:placetype":"locality"
},
  "geometry": {"coordinates":[150.93333000000001,-5.81667],"type":"Point"}
}