{
  "type": "Feature",
  "properties": {
    "gn:admin1_code":"03",
    "gn:asciiname":"Gibara",
    "gn:country_code":"PG",
    "gn:dem":15,
    "gn:feature_class":"P",
    "gn:feature_code":"PPL",
    "gn:name":"Gibara",
    "gn:population":0,
    "gn:timezone":"Pacific/Port_Moresby",
    "iso:country":"PG",
    "name:cat_x_preferred":[
        "Gibara"
    ],
    "name:fra_x_preferred":[
        "Gibara"
    ],
    "name:hat_x_preferred":[
        "Gibara"
    ],
    "name:ita_x_preferred":[
        "Gibara"
    ],
    "name:kat_x_preferred":[
        "\u10ee\u10d8\u10d1\u10d0\u10e0\u10d0"
    ],
    "name:pol_x_preferred":[
        "Gibara"
    ],
    "name:sco_x_preferred":[
        "Gibara"
    ],
    "name:spa_x_preferred":[
        "Gibara"
    ],
    "name:vie_x_preferred":[
        "Gibara"
    ],
    "name:zho_x_preferred":[
        "\u5409\u5e0c\u62c9"
    ],
    "wof:name":"Gibara",
    "wof:placetype":"locality"
},
  "geometry": {"coordinates":[150.37588,-10.40965],"type":"Point"}
}