{
  "type": "Feature",
  "properties": {
    "gn:admin1_code":"09",
    "gn:asciiname":"Gonopiyufa",
    "gn:country_code":"PG",
    "gn:dem":2012,
    "gn:feature_class":"P",
    "gn:feature_code":"PPL",
    "gn:name":"Gonopiyufa",
    "gn:population":0,
    "gn:timezone":"Pacific/Port_Moresby",
    "iso:country":"PG",
    "wof:name":"Gonopiyufa",
    "wof:placetype":"locality"
},
  "geometry": {"coordinates":[145.38333,-5.96667],"type":"Point"}
}