{
  "type": "Feature",
  "properties": {
    "gn:admin1_code":"15",
    "gn:asciiname":"Barau",
    "gn:country_code":"PG",
    "gn:dem":80,
    "gn:feature_class":"P",
    "gn:feature_code":"PPL",
    "gn:name":"Barau",
    "gn:population":0,
    "gn:timezone":"Pacific/Port_Moresby",
    "iso:country":"PG",
    "name:und_x_variant":[
        "Burau",
        "Barau"
    ],
    "wof:name":"Barau",
    "wof:placetype":"locality"
},
  "geometry": {"coordinates":[152.40143999999995,-3.7498],"type":"Point"}
}