{
  "type": "Feature",
  "properties": {
    "gn:admin1_code":"09",
    "gn:asciiname":"Aiyura",
    "gn:country_code":"PG",
    "gn:dem":1630,
    "gn:feature_class":"P",
    "gn:feature_code":"PPL",
    "gn:name":"Aiyura",
    "gn:population":0,
    "gn:timezone":"Pacific/Port_Moresby",
    "iso:country":"PG",
    "name:eng_x_preferred":[
        "Aiyura"
    ],
    "name:und_x_variant":[
        "Aijura",
        "Aiyura"
    ],
    "wof:name":"Aiyura",
    "wof:placetype":"locality"
},
  "geometry": {"coordinates":[145.89608999999999,-6.34234],"type":"Point"}
}