{
  "type": "Feature",
  "properties": {
    "gn:admin1_code":"01",
    "gn:asciiname":"Douramoku",
    "gn:country_code":"PG",
    "gn:dem":19,
    "gn:feature_class":"P",
    "gn:feature_code":"PPL",
    "gn:name":"Douramoku",
    "gn:population":0,
    "gn:timezone":"Pacific/Port_Moresby",
    "iso:country":"PG",
    "wof:name":"Douramoku",
    "wof:placetype":"locality"
},
  "geometry": {"coordinates":[147.11082999999999,-9.10761],"type":"Point"}
}