{
  "type": "Feature",
  "properties": {
    "gn:admin1_code":"08",
    "gn:asciiname":"Simegu",
    "gn:country_code":"PG",
    "gn:dem":1743,
    "gn:feature_class":"P",
    "gn:feature_code":"PPL",
    "gn:name":"Simegu",
    "gn:population":0,
    "gn:timezone":"Pacific/Port_Moresby",
    "iso:country":"PG",
    "wof:name":"Simegu",
    "wof:placetype":"locality"
},
  "geometry": {"coordinates":[144.9759,-6.05433],"type":"Point"}
}