{
  "type": "Feature",
  "properties": {
    "gn:admin1_code":"07",
    "gn:asciiname":"Salapem",
    "gn:country_code":"PG",
    "gn:dem":9,
    "gn:feature_class":"P",
    "gn:feature_code":"PPL",
    "gn:name":"Salapem",
    "gn:population":0,
    "gn:timezone":"Pacific/Bougainville",
    "iso:country":"PG",
    "wof:name":"Salapem",
    "wof:placetype":"locality"
},
  "geometry": {"coordinates":[154.21698000000001,-4.46543],"type":"Point"}
}