{
  "type": "Feature",
  "properties": {
    "gn:admin1_code":"04",
    "gn:asciiname":"Waru",
    "gn:country_code":"PG",
    "gn:dem":118,
    "gn:feature_class":"P",
    "gn:feature_code":"PPL",
    "gn:name":"Waru",
    "gn:population":0,
    "gn:timezone":"Pacific/Port_Moresby",
    "iso:country":"PG",
    "wof:name":"Waru",
    "wof:placetype":"locality"
},
  "geometry": {"coordinates":[148.11667,-8.73333],"type":"Point"}
}