{
  "type": "Feature",
  "properties": {
    "gn:admin1_code":"18",
    "gn:asciiname":"Nimberatoro",
    "gn:country_code":"PG",
    "gn:dem":380,
    "gn:feature_class":"P",
    "gn:feature_code":"PPL",
    "gn:name":"Nimberatoro",
    "gn:population":0,
    "gn:timezone":"Pacific/Port_Moresby",
    "iso:country":"PG",
    "wof:name":"Nimberatoro",
    "wof:placetype":"locality"
},
  "geometry": {"coordinates":[141.0386,-3.62754],"type":"Point"}
}