{
  "type": "Feature",
  "properties": {
    "gn:admin1_code":"12",
    "gn:asciiname":"Gunu",
    "gn:country_code":"PG",
    "gn:dem":489,
    "gn:feature_class":"P",
    "gn:feature_code":"PPL",
    "gn:name":"Gunu",
    "gn:population":0,
    "gn:timezone":"Pacific/Port_Moresby",
    "iso:country":"PG",
    "wof:name":"Gunu",
    "wof:placetype":"locality"
},
  "geometry": {"coordinates":[145.48333,-5.46667],"type":"Point"}
}