{
  "type": "Feature",
  "properties": {
    "gn:admin1_code":"03",
    "gn:asciiname":"Menapi",
    "gn:country_code":"PG",
    "gn:dem":22,
    "gn:feature_class":"P",
    "gn:feature_code":"PPL",
    "gn:name":"Menapi",
    "gn:population":0,
    "gn:timezone":"Pacific/Port_Moresby",
    "iso:country":"PG",
    "wof:name":"Menapi",
    "wof:placetype":"locality"
},
  "geometry": {"coordinates":[149.93188000000001,-9.75998],"type":"Point"}
}