{
  "type": "Feature",
  "properties": {
    "gn:admin1_code":"03",
    "gn:asciiname":"Dara",
    "gn:country_code":"PG",
    "gn:dem":17,
    "gn:feature_class":"P",
    "gn:feature_code":"PPL",
    "gn:name":"Dara",
    "gn:population":0,
    "gn:timezone":"Pacific/Port_Moresby",
    "iso:country":"PG",
    "wof:name":"Dara",
    "wof:placetype":"locality"
},
  "geometry": {"coordinates":[149.76667,-9.78333],"type":"Point"}
}