{
  "type": "Feature",
  "properties": {
    "gn:admin1_code":"18",
    "gn:asciiname":"Druanmin",
    "gn:country_code":"PG",
    "gn:dem":859,
    "gn:feature_class":"P",
    "gn:feature_code":"PPL",
    "gn:name":"Druanmin",
    "gn:population":0,
    "gn:timezone":"Pacific/Port_Moresby",
    "iso:country":"PG",
    "wof:name":"Druanmin",
    "wof:placetype":"locality"
},
  "geometry": {"coordinates":[141.91633999999999,-4.96874],"type":"Point"}
}