{
  "type": "Feature",
  "properties": {
    "gn:admin1_code":"18",
    "gn:asciiname":"Weigin",
    "gn:country_code":"PG",
    "gn:dem":626,
    "gn:feature_class":"P",
    "gn:feature_code":"PPL",
    "gn:name":"Weigin",
    "gn:population":0,
    "gn:timezone":"Pacific/Port_Moresby",
    "iso:country":"PG",
    "wof:name":"Weigin",
    "wof:placetype":"locality"
},
  "geometry": {"coordinates":[142.27482000000001,-3.46531],"type":"Point"}
}