{
  "type": "Feature",
  "properties": {
    "gn:admin1_code":"06",
    "gn:asciiname":"Nanu",
    "gn:country_code":"PG",
    "gn:dem":33,
    "gn:feature_class":"P",
    "gn:feature_code":"PPL",
    "gn:name":"Nanu",
    "gn:population":0,
    "gn:timezone":"Pacific/Port_Moresby",
    "iso:country":"PG",
    "name:deu_x_preferred":[
        "Nanu"
    ],
    "wof:name":"Nanu",
    "wof:placetype":"locality"
},
  "geometry": {"coordinates":[142.72196,-8.90098],"type":"Point"}
}