{
  "type": "Feature",
  "properties": {
    "gn:admin1_code":"10",
    "gn:asciiname":"Merai",
    "gn:country_code":"PG",
    "gn:dem":59,
    "gn:feature_class":"P",
    "gn:feature_code":"PPL",
    "gn:name":"Merai",
    "gn:population":0,
    "gn:timezone":"Pacific/Port_Moresby",
    "iso:country":"PG",
    "wof:name":"Merai",
    "wof:placetype":"locality"
},
  "geometry": {"coordinates":[152.32728999999995,-4.80733],"type":"Point"}
}