{
  "type": "Feature",
  "properties": {
    "gn:admin1_code":"04",
    "gn:asciiname":"Orasusu",
    "gn:country_code":"PG",
    "gn:dem":51,
    "gn:feature_class":"P",
    "gn:feature_code":"PPL",
    "gn:name":"Orasusu",
    "gn:population":0,
    "gn:timezone":"Pacific/Port_Moresby",
    "iso:country":"PG",
    "wof:name":"Orasusu",
    "wof:placetype":"locality"
},
  "geometry": {"coordinates":[148.01667,-8.63333],"type":"Point"}
}