{
  "type": "Feature",
  "properties": {
    "gn:admin1_code":"09",
    "gn:asciiname":"Afamonofi",
    "gn:country_code":"PG",
    "gn:dem":1956,
    "gn:feature_class":"P",
    "gn:feature_code":"PPL",
    "gn:name":"Afamonofi",
    "gn:population":0,
    "gn:timezone":"Pacific/Port_Moresby",
    "iso:country":"PG",
    "wof:name":"Afamonofi",
    "wof:placetype":"locality"
},
  "geometry": {"coordinates":[145.7929,-6.26849],"type":"Point"}
}