{
  "type": "Feature",
  "properties": {
    "gn:admin1_code":"12",
    "gn:asciiname":"Marap Number 2",
    "gn:country_code":"PG",
    "gn:dem":191,
    "gn:feature_class":"P",
    "gn:feature_code":"PPL",
    "gn:name":"Marap Number 2",
    "gn:population":0,
    "gn:timezone":"Pacific/Port_Moresby",
    "iso:country":"PG",
    "name:und_x_variant":[
        "Marup II",
        "Marup",
        "Marap Number 2"
    ],
    "wof:name":"Marap Number 2",
    "wof:placetype":"locality"
},
  "geometry": {"coordinates":[145.91005000000001,-4.6899],"type":"Point"}
}