{
  "type": "Feature",
  "properties": {
    "gn:admin1_code":"05",
    "gn:asciiname":"Suabidigi",
    "gn:cc2":"PG",
    "gn:country_code":"PG",
    "gn:dem":614,
    "gn:feature_class":"P",
    "gn:feature_code":"PPL",
    "gn:name":"Suabidigi",
    "gn:population":0,
    "gn:timezone":"Pacific/Port_Moresby",
    "iso:country":"PG",
    "name:und_x_variant":[
        "Saubidigi",
        "Suabidigi"
    ],
    "wof:name":"Suabidigi",
    "wof:placetype":"locality"
},
  "geometry": {"coordinates":[143.28333000000001,-6.56667],"type":"Point"}
}