{
  "type": "Feature",
  "properties": {
    "gn:admin1_code":"12",
    "gn:asciiname":"Tung",
    "gn:country_code":"PG",
    "gn:dem":57,
    "gn:feature_class":"P",
    "gn:feature_code":"PPL",
    "gn:name":"Tung",
    "gn:population":0,
    "gn:timezone":"Pacific/Port_Moresby",
    "iso:country":"PG",
    "name:ceb_x_preferred":[
        "Tung"
    ],
    "name:deu_x_preferred":[
        "Tung"
    ],
    "name:vie_x_preferred":[
        "Tung"
    ],
    "wof:name":"Tung",
    "wof:placetype":"locality"
},
  "geometry": {"coordinates":[144.73447999999999,-4.27215],"type":"Point"}
}