{
  "type": "Feature",
  "properties": {
    "gn:admin1_code":"14",
    "gn:asciiname":"Emengwaning",
    "gn:country_code":"PG",
    "gn:dem":604,
    "gn:feature_class":"P",
    "gn:feature_code":"PPL",
    "gn:name":"Emengwaning",
    "gn:population":0,
    "gn:timezone":"Pacific/Port_Moresby",
    "iso:country":"PG",
    "name:und_x_variant":[
        "Embengwasing",
        "Emengwaning"
    ],
    "wof:name":"Emengwaning",
    "wof:placetype":"locality"
},
  "geometry": {"coordinates":[147.62639999999999,-6.59517],"type":"Point"}
}