{
  "type": "Feature",
  "properties": {
    "gn:admin1_code":"09",
    "gn:asciiname":"Finintegu",
    "gn:cc2":"PG",
    "gn:country_code":"PG",
    "gn:dem":1672,
    "gn:feature_class":"P",
    "gn:feature_code":"PPL",
    "gn:name":"Finintegu",
    "gn:population":0,
    "gn:timezone":"Pacific/Port_Moresby",
    "iso:country":"PG",
    "name:und_x_variant":[
        "Kumoka",
        "Komaka",
        "Finintegu"
    ],
    "wof:name":"Finintegu",
    "wof:placetype":"locality"
},
  "geometry": {"coordinates":[145.68333000000001,-6.23333],"type":"Point"}
}