{
  "type": "Feature",
  "properties": {
    "gn:admin1_code":"14",
    "gn:asciiname":"Silimana",
    "gn:country_code":"PG",
    "gn:dem":1149,
    "gn:feature_class":"P",
    "gn:feature_code":"PPL",
    "gn:name":"Silimana",
    "gn:population":0,
    "gn:timezone":"Pacific/Port_Moresby",
    "iso:country":"PG",
    "wof:name":"Silimana",
    "wof:placetype":"locality"
},
  "geometry": {"coordinates":[147.58158999999995,-6.4354],"type":"Point"}
}