{
  "type": "Feature",
  "properties": {
    "gn:admin1_code":"11",
    "gn:asciiname":"Saui",
    "gn:country_code":"PG",
    "gn:dem":24,
    "gn:feature_class":"P",
    "gn:feature_code":"PPL",
    "gn:name":"Saui",
    "gn:population":0,
    "gn:timezone":"Pacific/Port_Moresby",
    "iso:country":"PG",
    "name:und_x_variant":[
        "Savi",
        "Saui"
    ],
    "wof:name":"Saui",
    "wof:placetype":"locality"
},
  "geometry": {"coordinates":[143.49985000000001,-4.05919],"type":"Point"}
}