{
  "type": "Feature",
  "properties": {
    "gn:admin1_code":"06",
    "gn:asciiname":"Damera",
    "gn:country_code":"PG",
    "gn:dem":1,
    "gn:feature_class":"P",
    "gn:feature_code":"PPL",
    "gn:name":"Damera",
    "gn:population":0,
    "gn:timezone":"Pacific/Port_Moresby",
    "iso:country":"PG",
    "name:und_x_variant":[
        "Domara",
        "Damara",
        "Damera"
    ],
    "wof:name":"Damera",
    "wof:placetype":"locality"
},
  "geometry": {"coordinates":[143.47367,-8.24481],"type":"Point"}
}