{
  "type": "Feature",
  "properties": {
    "gn:admin1_code":"14",
    "gn:asciiname":"Tereran",
    "gn:country_code":"PG",
    "gn:dem":111,
    "gn:feature_class":"P",
    "gn:feature_code":"PPL",
    "gn:name":"Tereran",
    "gn:population":0,
    "gn:timezone":"Pacific/Port_Moresby",
    "iso:country":"PG",
    "name:und_x_variant":[
        "Talerang",
        "Telerang",
        "Tereran"
    ],
    "wof:name":"Tereran",
    "wof:placetype":"locality"
},
  "geometry": {"coordinates":[146.58987999999999,-6.53887],"type":"Point"}
}