{
  "type": "Feature",
  "properties": {
    "gn:admin1_code":"11",
    "gn:asciiname":"Rumlal",
    "gn:country_code":"PG",
    "gn:dem":67,
    "gn:feature_class":"P",
    "gn:feature_code":"PPL",
    "gn:name":"Rumlal",
    "gn:population":0,
    "gn:timezone":"Pacific/Port_Moresby",
    "iso:country":"PG",
    "wof:name":"Rumlal",
    "wof:placetype":"locality"
},
  "geometry": {"coordinates":[143.55177,-3.31883],"type":"Point"}
}