{
  "type": "Feature",
  "properties": {
    "gn:admin1_code":"08",
    "gn:asciiname":"Gurual",
    "gn:country_code":"PG",
    "gn:dem":1955,
    "gn:feature_class":"P",
    "gn:feature_code":"PPL",
    "gn:name":"Gurual",
    "gn:population":0,
    "gn:timezone":"Pacific/Port_Moresby",
    "iso:country":"PG",
    "wof:name":"Gurual",
    "wof:placetype":"locality"
},
  "geometry": {"coordinates":[144.85431,-6.03604],"type":"Point"}
}