{
  "type": "Feature",
  "properties": {
    "gn:admin1_code":"01",
    "gn:asciiname":"Avaira-Waima",
    "gn:country_code":"PG",
    "gn:dem":7,
    "gn:feature_class":"P",
    "gn:feature_code":"PPL",
    "gn:name":"Avaira-Waima",
    "gn:population":0,
    "gn:timezone":"Pacific/Port_Moresby",
    "iso:country":"PG",
    "name:und_x_variant":[
        "Waima",
        "Maiva Villages",
        "Aviara-Waima",
        "Maiva",
        "Avaira-Waima"
    ],
    "wof:name":"Avaira-Waima",
    "wof:placetype":"locality"
},
  "geometry": {"coordinates":[146.45293999999996,-8.62786],"type":"Point"}
}