{
  "type": "Feature",
  "properties": {
    "gn:admin1_code":"10",
    "gn:asciiname":"Rowan",
    "gn:country_code":"PG",
    "gn:dem":58,
    "gn:feature_class":"P",
    "gn:feature_code":"PPL",
    "gn:name":"Rowan",
    "gn:population":0,
    "gn:timezone":"Pacific/Port_Moresby",
    "iso:country":"PG",
    "name:gla_x_preferred":[
        "Caorann"
    ],
    "wof:name":"Rowan",
    "wof:placetype":"locality"
},
  "geometry": {"coordinates":[151.41666999999995,-5.68333],"type":"Point"}
}