{
  "type": "Feature",
  "properties": {
    "gn:admin1_code":"16",
    "gn:asciiname":"Tsimgil",
    "gn:country_code":"PG",
    "gn:dem":1582,
    "gn:feature_class":"P",
    "gn:feature_code":"PPL",
    "gn:name":"Tsimgil",
    "gn:population":0,
    "gn:timezone":"Pacific/Port_Moresby",
    "iso:country":"PG",
    "wof:name":"Tsimgil",
    "wof:placetype":"locality"
},
  "geometry": {"coordinates":[144.72384,-5.93077],"type":"Point"}
}