{
  "type": "Feature",
  "properties": {
    "gn:admin1_code":"02",
    "gn:asciiname":"Mambainya",
    "gn:country_code":"PG",
    "gn:dem":1122,
    "gn:feature_class":"P",
    "gn:feature_code":"PPL",
    "gn:name":"Mambainya",
    "gn:population":0,
    "gn:timezone":"Pacific/Port_Moresby",
    "iso:country":"PG",
    "name:und_x_variant":[
        "Mambanya",
        "Mambainya"
    ],
    "wof:name":"Mambainya",
    "wof:placetype":"locality"
},
  "geometry": {"coordinates":[145.96761000000001,-7.56024],"type":"Point"}
}