{
  "type": "Feature",
  "properties": {
    "gn:admin1_code":"11",
    "gn:asciiname":"Balmo",
    "gn:country_code":"PG",
    "gn:dem":30,
    "gn:feature_class":"P",
    "gn:feature_code":"PPL",
    "gn:name":"Balmo",
    "gn:population":0,
    "gn:timezone":"Pacific/Port_Moresby",
    "iso:country":"PG",
    "wof:name":"Balmo",
    "wof:placetype":"locality"
},
  "geometry": {"coordinates":[143.31469999999999,-3.97967],"type":"Point"}
}