{
  "type": "Feature",
  "properties": {
    "gn:admin1_code":"14",
    "gn:asciiname":"Alairo",
    "gn:country_code":"PG",
    "gn:dem":11,
    "gn:feature_class":"P",
    "gn:feature_code":"PPL",
    "gn:name":"Alairo",
    "gn:population":0,
    "gn:timezone":"Pacific/Port_Moresby",
    "iso:country":"PG",
    "name:und_x_variant":[
        "Alaro",
        "Alairo"
    ],
    "wof:name":"Alairo",
    "wof:placetype":"locality"
},
  "geometry": {"coordinates":[148.0521,-5.42403],"type":"Point"}
}