{
  "type": "Feature",
  "properties": {
    "gn:admin1_code":"03",
    "gn:asciiname":"Naieta",
    "gn:country_code":"PG",
    "gn:dem":155,
    "gn:feature_class":"P",
    "gn:feature_code":"PPL",
    "gn:name":"Naieta",
    "gn:population":0,
    "gn:timezone":"Pacific/Port_Moresby",
    "iso:country":"PG",
    "wof:name":"Naieta",
    "wof:placetype":"locality"
},
  "geometry": {"coordinates":[150.54292000000001,-9.475],"type":"Point"}
}