{
  "type": "Feature",
  "properties": {
    "gn:admin1_code":"05",
    "gn:asciiname":"Pira",
    "gn:country_code":"PG",
    "gn:dem":1704,
    "gn:feature_class":"P",
    "gn:feature_code":"PPL",
    "gn:name":"Pira",
    "gn:population":0,
    "gn:timezone":"Pacific/Port_Moresby",
    "iso:country":"PG",
    "name:bul_x_preferred":[
        "\u041f\u0438\u0440\u0430"
    ],
    "name:ceb_x_preferred":[
        "Pira"
    ],
    "name:deu_x_preferred":[
        "Pira"
    ],
    "name:fra_x_preferred":[
        "Pira"
    ],
    "name:ita_x_preferred":[
        "Pira"
    ],
    "name:nor_x_preferred":[
        "Pira"
    ],
    "name:por_x_preferred":[
        "Pira"
    ],
    "name:rus_x_preferred":[
        "\u041f\u0438\u0440\u0430"
    ],
    "name:spa_x_preferred":[
        "Pira"
    ],
    "name:srp_x_preferred":[
        "Pira"
    ],
    "name:swe_x_preferred":[
        "Pira"
    ],
    "wof:name":"Pira",
    "wof:placetype":"locality"
},
  "geometry": {"coordinates":[143.75896,-6.41272],"type":"Point"}
}