{
  "type": "Feature",
  "properties": {
    "gn:admin1_code":"16",
    "gn:asciiname":"Agilimka",
    "gn:country_code":"PG",
    "gn:dem":1555,
    "gn:feature_class":"P",
    "gn:feature_code":"PPL",
    "gn:name":"Agilimka",
    "gn:population":0,
    "gn:timezone":"Pacific/Port_Moresby",
    "iso:country":"PG",
    "wof:name":"Agilimka",
    "wof:placetype":"locality"
},
  "geometry": {"coordinates":[144.80000000000001,-5.95],"type":"Point"}
}