{
  "type": "Feature",
  "properties": {
    "gn:admin1_code":"09",
    "gn:asciiname":"Aiguwa",
    "gn:country_code":"PG",
    "gn:dem":1930,
    "gn:feature_class":"P",
    "gn:feature_code":"PPL",
    "gn:name":"Aiguwa",
    "gn:population":0,
    "gn:timezone":"Pacific/Port_Moresby",
    "iso:country":"PG",
    "wof:name":"Aiguwa",
    "wof:placetype":"locality"
},
  "geometry": {"coordinates":[145.16396,-6.46427],"type":"Point"}
}