{
  "type": "Feature",
  "properties": {
    "gn:admin1_code":"06",
    "gn:asciiname":"Bandaber",
    "gn:country_code":"PG",
    "gn:dem":9,
    "gn:feature_class":"P",
    "gn:feature_code":"PPL",
    "gn:name":"Bandaber",
    "gn:population":0,
    "gn:timezone":"Pacific/Port_Moresby",
    "iso:country":"PG",
    "wof:name":"Bandaber",
    "wof:placetype":"locality"
},
  "geometry": {"coordinates":[141.27015,-8.9342],"type":"Point"}
}