{
  "type": "Feature",
  "properties": {
    "gn:admin1_code":"06",
    "gn:asciiname":"Tuidemasuk",
    "gn:cc2":"PG",
    "gn:country_code":"PG",
    "gn:dem":56,
    "gn:feature_class":"P",
    "gn:feature_code":"PPL",
    "gn:name":"Tuidemasuk",
    "gn:population":0,
    "gn:timezone":"Pacific/Port_Moresby",
    "iso:country":"PG",
    "name:und_x_variant":[
        "Tuindemasuk",
        "Tuidemasuk"
    ],
    "wof:name":"Tuidemasuk",
    "wof:placetype":"locality"
},
  "geometry": {"coordinates":[141.36667,-6.06667],"type":"Point"}
}