{
  "type": "Feature",
  "properties": {
    "gn:admin1_code":"04",
    "gn:asciiname":"Marasi",
    "gn:country_code":"PG",
    "gn:dem":807,
    "gn:feature_class":"P",
    "gn:feature_code":"PPL",
    "gn:name":"Marasi",
    "gn:population":0,
    "gn:timezone":"Pacific/Port_Moresby",
    "iso:country":"PG",
    "wof:name":"Marasi",
    "wof:placetype":"locality"
},
  "geometry": {"coordinates":[148.45112,-9.14844],"type":"Point"}
}