{
  "type": "Feature",
  "properties": {
    "gn:asciiname":"Ufaufa",
    "gn:country_code":"PG",
    "gn:dem":3,
    "gn:feature_class":"P",
    "gn:feature_code":"PPL",
    "gn:name":"Ufaufa",
    "gn:population":0,
    "gn:timezone":"Pacific/Port_Moresby",
    "iso:country":"PG",
    "wof:name":"Ufaufa",
    "wof:placetype":"locality"
},
  "geometry": {"coordinates":[150.18976000000001,-9.20831],"type":"Point"}
}