{
  "type": "Feature",
  "properties": {
    "gn:admin1_code":"14",
    "gn:asciiname":"Geraun",
    "gn:country_code":"PG",
    "gn:dem":1743,
    "gn:feature_class":"P",
    "gn:feature_code":"PPL",
    "gn:name":"Geraun",
    "gn:population":0,
    "gn:timezone":"Pacific/Port_Moresby",
    "iso:country":"PG",
    "wof:name":"Geraun",
    "wof:placetype":"locality"
},
  "geometry": {"coordinates":[147.24572000000001,-6.24345],"type":"Point"}
}