{
  "type": "Feature",
  "properties": {
    "gn:admin1_code":"07",
    "gn:asciiname":"Kapana",
    "gn:country_code":"PG",
    "gn:dem":100,
    "gn:feature_class":"P",
    "gn:feature_code":"PPL",
    "gn:name":"Kapana",
    "gn:population":0,
    "gn:timezone":"Pacific/Bougainville",
    "iso:country":"PG",
    "wof:name":"Kapana",
    "wof:placetype":"locality"
},
  "geometry": {"coordinates":[155.43333000000001,-6.64444],"type":"Point"}
}