{
  "type": "Feature",
  "properties": {
    "gn:admin1_code":"11",
    "gn:asciiname":"Kairuru",
    "gn:country_code":"PG",
    "gn:dem":417,
    "gn:feature_class":"P",
    "gn:feature_code":"PPL",
    "gn:name":"Kairuru",
    "gn:population":0,
    "gn:timezone":"Pacific/Port_Moresby",
    "iso:country":"PG",
    "name:und_x_variant":[
        "Kairiru",
        "Kairuru"
    ],
    "wof:name":"Kairuru",
    "wof:placetype":"locality"
},
  "geometry": {"coordinates":[143.20863,-3.60801],"type":"Point"}
}