{
  "type": "Feature",
  "properties": {
    "gn:admin1_code":"12",
    "gn:asciiname":"Sepen Number 2",
    "gn:country_code":"PG",
    "gn:dem":54,
    "gn:feature_class":"P",
    "gn:feature_code":"PPL",
    "gn:name":"Sepen Number 2",
    "gn:population":0,
    "gn:timezone":"Pacific/Port_Moresby",
    "iso:country":"PG",
    "wof:name":"Sepen Number 2",
    "wof:placetype":"locality"
},
  "geometry": {"coordinates":[144.80654999999999,-4.23694],"type":"Point"}
}