{
  "type": "Feature",
  "properties": {
    "gn:admin1_code":"14",
    "gn:asciiname":"Koi Iavi",
    "gn:country_code":"PG",
    "gn:dem":1919,
    "gn:feature_class":"P",
    "gn:feature_code":"PPL",
    "gn:name":"Koi Iavi",
    "gn:population":0,
    "gn:timezone":"Pacific/Port_Moresby",
    "iso:country":"PG",
    "wof:name":"Koi Iavi",
    "wof:placetype":"locality"
},
  "geometry": {"coordinates":[146.94999999999999,-7.75],"type":"Point"}
}