{
  "type": "Feature",
  "properties": {
    "gn:admin1_code":"09",
    "gn:asciiname":"Meiauna",
    "gn:country_code":"PG",
    "gn:dem":1728,
    "gn:feature_class":"P",
    "gn:feature_code":"PPL",
    "gn:name":"Meiauna",
    "gn:population":0,
    "gn:timezone":"Pacific/Port_Moresby",
    "iso:country":"PG",
    "wof:name":"Meiauna",
    "wof:placetype":"locality"
},
  "geometry": {"coordinates":[145.83408,-6.62681],"type":"Point"}
}