{
  "type": "Feature",
  "properties": {
    "gn:admin1_code":"02",
    "gn:asciiname":"Marekea",
    "gn:country_code":"PG",
    "gn:dem":12,
    "gn:feature_class":"P",
    "gn:feature_code":"PPL",
    "gn:name":"Marekea",
    "gn:population":0,
    "gn:timezone":"Pacific/Port_Moresby",
    "iso:country":"PG",
    "name:und_x_variant":[
        "Keowat",
        "Marekea"
    ],
    "wof:name":"Marekea",
    "wof:placetype":"locality"
},
  "geometry": {"coordinates":[146.10512,-8.16556],"type":"Point"}
}