{
  "type": "Feature",
  "properties": {
    "gn:admin1_code":"12",
    "gn:asciiname":"Watang",
    "gn:cc2":"PG",
    "gn:country_code":"PG",
    "gn:dem":621,
    "gn:feature_class":"P",
    "gn:feature_code":"PPL",
    "gn:name":"Watang",
    "gn:population":0,
    "gn:timezone":"Pacific/Port_Moresby",
    "iso:country":"PG",
    "name:und_x_variant":[
        "Walang",
        "Walong",
        "Watang"
    ],
    "wof:name":"Watang",
    "wof:placetype":"locality"
},
  "geometry": {"coordinates":[146.59999999999999,-5.78333],"type":"Point"}
}