{
  "type": "Feature",
  "properties": {
    "gn:admin1_code":"18",
    "gn:asciiname":"Konabasi",
    "gn:country_code":"PG",
    "gn:dem":121,
    "gn:feature_class":"P",
    "gn:feature_code":"PPL",
    "gn:name":"Konabasi",
    "gn:population":0,
    "gn:timezone":"Pacific/Port_Moresby",
    "iso:country":"PG",
    "wof:name":"Konabasi",
    "wof:placetype":"locality"
},
  "geometry": {"coordinates":[141.33185,-3.6873],"type":"Point"}
}