{
  "type": "Feature",
  "properties": {
    "gn:admin1_code":"14",
    "gn:asciiname":"Mutsing",
    "gn:country_code":"PG",
    "gn:dem":246,
    "gn:feature_class":"P",
    "gn:feature_code":"PPL",
    "gn:name":"Mutsing",
    "gn:population":0,
    "gn:timezone":"Pacific/Port_Moresby",
    "iso:country":"PG",
    "wof:name":"Mutsing",
    "wof:placetype":"locality"
},
  "geometry": {"coordinates":[146.24858,-6.3469],"type":"Point"}
}