{
  "type": "Feature",
  "properties": {
    "gn:admin1_code":"18",
    "gn:asciiname":"Ulau 2",
    "gn:country_code":"PG",
    "gn:dem":0,
    "gn:feature_class":"P",
    "gn:feature_code":"PPL",
    "gn:name":"Ulau 2",
    "gn:population":0,
    "gn:timezone":"Pacific/Port_Moresby",
    "iso:country":"PG",
    "name:und_x_variant":[
        "Ulau Number 2",
        "Ulau Mission",
        "Ulau",
        "Ulau 2"
    ],
    "wof:name":"Ulau 2",
    "wof:placetype":"locality"
},
  "geometry": {"coordinates":[142.79445000000001,-3.30199],"type":"Point"}
}