{
  "type": "Feature",
  "properties": {
    "gn:admin1_code":"14",
    "gn:asciiname":"Kiwsawa",
    "gn:country_code":"PG",
    "gn:dem":166,
    "gn:feature_class":"P",
    "gn:feature_code":"PPL",
    "gn:name":"Kiwsawa",
    "gn:population":0,
    "gn:timezone":"Pacific/Port_Moresby",
    "iso:country":"PG",
    "name:und_x_variant":[
        "Kiwisawa",
        "Kiwsawa"
    ],
    "wof:name":"Kiwsawa",
    "wof:placetype":"locality"
},
  "geometry": {"coordinates":[147.81774999999999,-6.53878],"type":"Point"}
}