{
  "type": "Feature",
  "properties": {
    "gn:admin1_code":"17",
    "gn:asciiname":"Maklongmerang",
    "gn:country_code":"PG",
    "gn:dem":93,
    "gn:feature_class":"P",
    "gn:feature_code":"PPL",
    "gn:name":"Maklongmerang",
    "gn:population":0,
    "gn:timezone":"Pacific/Port_Moresby",
    "iso:country":"PG",
    "wof:name":"Maklongmerang",
    "wof:placetype":"locality"
},
  "geometry": {"coordinates":[149.56666999999999,-6.06667],"type":"Point"}
}