{
  "type": "Feature",
  "properties": {
    "gn:admin1_code":"12",
    "gn:asciiname":"Siniap",
    "gn:country_code":"PG",
    "gn:dem":83,
    "gn:feature_class":"P",
    "gn:feature_code":"PPL",
    "gn:name":"Siniap",
    "gn:population":0,
    "gn:timezone":"Pacific/Port_Moresby",
    "iso:country":"PG",
    "wof:name":"Siniap",
    "wof:placetype":"locality"
},
  "geometry": {"coordinates":[145.08333000000005,-5.15],"type":"Point"}
}