{
  "type": "Feature",
  "properties": {
    "gn:admin1_code":"06",
    "gn:asciiname":"Emmissuna",
    "gn:country_code":"PG",
    "gn:dem":135,
    "gn:feature_class":"P",
    "gn:feature_code":"PPL",
    "gn:name":"Emmissuna",
    "gn:population":0,
    "gn:timezone":"Pacific/Port_Moresby",
    "iso:country":"PG",
    "wof:name":"Emmissuna",
    "wof:placetype":"locality"
},
  "geometry": {"coordinates":[141.93333000000001,-6.18333],"type":"Point"}
}