{
  "type": "Feature",
  "properties": {
    "gn:admin1_code":"14",
    "gn:asciiname":"Kopa",
    "gn:country_code":"PG",
    "gn:dem":1629,
    "gn:feature_class":"P",
    "gn:feature_code":"PPL",
    "gn:name":"Kopa",
    "gn:population":0,
    "gn:timezone":"Pacific/Port_Moresby",
    "iso:country":"PG",
    "wof:name":"Kopa",
    "wof:placetype":"locality"
},
  "geometry": {"coordinates":[147.25763000000001,-6.20491],"type":"Point"}
}