{
  "type": "Feature",
  "properties": {
    "gn:admin1_code":"07",
    "gn:asciiname":"Malasang",
    "gn:country_code":"PG",
    "gn:dem":63,
    "gn:feature_class":"P",
    "gn:feature_code":"PPL",
    "gn:name":"Malasang",
    "gn:population":0,
    "gn:timezone":"Pacific/Bougainville",
    "iso:country":"PG",
    "name:und_x_variant":[
        "Melasang",
        "Malassang",
        "Malasang"
    ],
    "wof:name":"Malasang",
    "wof:placetype":"locality"
},
  "geometry": {"coordinates":[154.68066999999999,-5.36059],"type":"Point"}
}