{
  "type": "Feature",
  "properties": {
    "gn:admin1_code":"08",
    "gn:asciiname":"Komonokane",
    "gn:country_code":"PG",
    "gn:dem":1904,
    "gn:feature_class":"P",
    "gn:feature_code":"PPL",
    "gn:name":"Komonokane",
    "gn:population":0,
    "gn:timezone":"Pacific/Port_Moresby",
    "iso:country":"PG",
    "wof:name":"Komonokane",
    "wof:placetype":"locality"
},
  "geometry": {"coordinates":[144.95857000000001,-6.12763],"type":"Point"}
}