{
  "type": "Feature",
  "properties": {
    "gn:admin1_code":"09",
    "gn:asciiname":"Koritafa",
    "gn:country_code":"PG",
    "gn:dem":2152,
    "gn:feature_class":"P",
    "gn:feature_code":"PPL",
    "gn:name":"Koritafa",
    "gn:population":0,
    "gn:timezone":"Pacific/Port_Moresby",
    "iso:country":"PG",
    "wof:name":"Koritafa",
    "wof:placetype":"locality"
},
  "geometry": {"coordinates":[145.52378000000004,-6.04081],"type":"Point"}
}