{
  "type": "Feature",
  "properties": {
    "gn:admin1_code":"05",
    "gn:asciiname":"Pagluga",
    "gn:country_code":"PG",
    "gn:dem":2146,
    "gn:feature_class":"P",
    "gn:feature_code":"PPL",
    "gn:name":"Pagluga",
    "gn:population":0,
    "gn:timezone":"Pacific/Port_Moresby",
    "iso:country":"PG",
    "wof:name":"Pagluga",
    "wof:placetype":"locality"
},
  "geometry": {"coordinates":[143.91495,-6.21051],"type":"Point"}
}