{
  "type": "Feature",
  "properties": {
    "gn:admin1_code":"12",
    "gn:asciiname":"Kubam",
    "gn:country_code":"PG",
    "gn:dem":276,
    "gn:feature_class":"P",
    "gn:feature_code":"PPL",
    "gn:name":"Kubam",
    "gn:population":0,
    "gn:timezone":"Pacific/Port_Moresby",
    "iso:country":"PG",
    "name:und_x_variant":[
        "Kabam",
        "Kubam"
    ],
    "wof:name":"Kubam",
    "wof:placetype":"locality"
},
  "geometry": {"coordinates":[146.01013,-4.70184],"type":"Point"}
}