{
  "type": "Feature",
  "properties": {
    "gn:admin1_code":"11",
    "gn:asciiname":"Wangan",
    "gn:country_code":"PG",
    "gn:dem":7,
    "gn:feature_class":"P",
    "gn:feature_code":"PPL",
    "gn:name":"Wangan",
    "gn:population":0,
    "gn:timezone":"Pacific/Port_Moresby",
    "iso:country":"PG",
    "name:ceb_x_preferred":[
        "Wangan"
    ],
    "name:jpn_x_preferred":[
        "\u6e7e\u5cb8\u7dda"
    ],
    "name:und_x_variant":[
        "Wongan",
        "Wongun"
    ],
    "name:zho_x_preferred":[
        "\u7063\u5cb8\u7dda"
    ],
    "wof:name":"Wangan",
    "wof:placetype":"locality"
},
  "geometry": {"coordinates":[144.54989,-4.00626],"type":"Point"}
}