{
  "type": "Feature",
  "properties": {
    "gn:admin1_code":"01",
    "gn:asciiname":"Kodige",
    "gn:country_code":"PG",
    "gn:dem":1362,
    "gn:feature_class":"P",
    "gn:feature_code":"PPL",
    "gn:name":"Kodige",
    "gn:population":0,
    "gn:timezone":"Pacific/Port_Moresby",
    "iso:country":"PG",
    "wof:name":"Kodige",
    "wof:placetype":"locality"
},
  "geometry": {"coordinates":[147.10863000000001,-8.63218],"type":"Point"}
}