{
  "type": "Feature",
  "properties": {
    "gn:admin1_code":"19",
    "gn:asciiname":"Biakamanda",
    "gn:country_code":"PG",
    "gn:dem":1969,
    "gn:feature_class":"P",
    "gn:feature_code":"PPL",
    "gn:name":"Biakamanda",
    "gn:population":0,
    "gn:timezone":"Pacific/Port_Moresby",
    "iso:country":"PG",
    "wof:name":"Biakamanda",
    "wof:placetype":"locality"
},
  "geometry": {"coordinates":[143.87343999999999,-5.36878],"type":"Point"}
}