{
  "type": "Feature",
  "properties": {
    "gn:admin1_code":"14",
    "gn:asciiname":"Lengbati",
    "gn:country_code":"PG",
    "gn:dem":1758,
    "gn:feature_class":"P",
    "gn:feature_code":"PPL",
    "gn:name":"Lengbati",
    "gn:population":0,
    "gn:timezone":"Pacific/Port_Moresby",
    "iso:country":"PG",
    "wof:name":"Lengbati",
    "wof:placetype":"locality"
},
  "geometry": {"coordinates":[147.36667,-6.38333],"type":"Point"}
}