{
  "type": "Feature",
  "properties": {
    "gn:admin1_code":"08",
    "gn:asciiname":"H'walia",
    "gn:country_code":"PG",
    "gn:dem":1021,
    "gn:feature_class":"P",
    "gn:feature_code":"PPL",
    "gn:name":"H\u2019walia",
    "gn:population":0,
    "gn:timezone":"Pacific/Port_Moresby",
    "iso:country":"PG",
    "wof:name":"H'walia",
    "wof:placetype":"locality"
},
  "geometry": {"coordinates":[145.09863999999999,-6.71825],"type":"Point"}
}