{
  "type": "Feature",
  "properties": {
    "gn:admin1_code":"12",
    "gn:asciiname":"Roumirap",
    "gn:country_code":"PG",
    "gn:dem":491,
    "gn:feature_class":"P",
    "gn:feature_code":"PPL",
    "gn:name":"Roumirap",
    "gn:population":0,
    "gn:timezone":"Pacific/Port_Moresby",
    "iso:country":"PG",
    "wof:name":"Roumirap",
    "wof:placetype":"locality"
},
  "geometry": {"coordinates":[145.09999999999999,-4.48333],"type":"Point"}
}