{
  "type": "Feature",
  "properties": {
    "gn:admin1_code":"11",
    "gn:asciiname":"Kwaunjama 1",
    "gn:cc2":"PG",
    "gn:country_code":"PG",
    "gn:dem":68,
    "gn:feature_class":"P",
    "gn:feature_code":"PPL",
    "gn:name":"Kwaunjama 1",
    "gn:population":0,
    "gn:timezone":"Pacific/Port_Moresby",
    "iso:country":"PG",
    "name:und_x_variant":[
        "Kwaunjama Number 1",
        "Kwaunjama 1"
    ],
    "wof:name":"Kwaunjama 1",
    "wof:placetype":"locality"
},
  "geometry": {"coordinates":[142.98333,-3.83333],"type":"Point"}
}