{
  "type": "Feature",
  "properties": {
    "gn:admin1_code":"14",
    "gn:asciiname":"Mulumia",
    "gn:country_code":"PG",
    "gn:dem":2270,
    "gn:feature_class":"P",
    "gn:feature_code":"PPL",
    "gn:name":"Mulumia",
    "gn:population":0,
    "gn:timezone":"Pacific/Port_Moresby",
    "iso:country":"PG",
    "wof:name":"Mulumia",
    "wof:placetype":"locality"
},
  "geometry": {"coordinates":[145.86667,-6.96667],"type":"Point"}
}