{
  "type": "Feature",
  "properties": {
    "gn:admin1_code":"11",
    "gn:asciiname":"Uwu",
    "gn:country_code":"PG",
    "gn:dem":30,
    "gn:feature_class":"P",
    "gn:feature_code":"PPL",
    "gn:name":"Uwu",
    "gn:population":0,
    "gn:timezone":"Pacific/Port_Moresby",
    "iso:country":"PG",
    "wof:name":"Uwu",
    "wof:placetype":"locality"
},
  "geometry": {"coordinates":[142.48333,-4.48333],"type":"Point"}
}