{
  "type": "Feature",
  "properties": {
    "gn:admin1_code":"12",
    "gn:asciiname":"Gasua",
    "gn:country_code":"PG",
    "gn:dem":369,
    "gn:feature_class":"P",
    "gn:feature_code":"PPL",
    "gn:name":"Gasua",
    "gn:population":0,
    "gn:timezone":"Pacific/Port_Moresby",
    "iso:country":"PG",
    "wof:name":"Gasua",
    "wof:placetype":"locality"
},
  "geometry": {"coordinates":[145.52946,-5.37084],"type":"Point"}
}