{
  "type": "Feature",
  "properties": {
    "gn:admin1_code":"02",
    "gn:admin2_code":"2094002",
    "gn:asciiname":"Ihu",
    "gn:country_code":"PG",
    "gn:dem":11,
    "gn:feature_class":"P",
    "gn:feature_code":"PPLA3",
    "gn:name":"Ihu",
    "gn:population":0,
    "gn:timezone":"Pacific/Port_Moresby",
    "iso:country":"PG",
    "wof:name":"Ihu",
    "wof:placetype":"locality"
},
  "geometry": {"coordinates":[145.39404999999999,-7.89569],"type":"Point"}
}