{
  "type": "Feature",
  "properties": {
    "gn:admin1_code":"01",
    "gn:asciiname":"Orai'ia",
    "gn:country_code":"PG",
    "gn:dem":596,
    "gn:feature_class":"P",
    "gn:feature_code":"PPL",
    "gn:name":"Orai\u2019ia",
    "gn:population":0,
    "gn:timezone":"Pacific/Port_Moresby",
    "iso:country":"PG",
    "wof:name":"Orai'ia",
    "wof:placetype":"locality"
},
  "geometry": {"coordinates":[148.06868,-9.74861],"type":"Point"}
}