{
  "type": "Feature",
  "properties": {
    "gn:admin1_code":"19",
    "gn:asciiname":"Kasap",
    "gn:country_code":"PG",
    "gn:dem":2233,
    "gn:feature_class":"P",
    "gn:feature_code":"PPL",
    "gn:name":"Kasap",
    "gn:population":0,
    "gn:timezone":"Pacific/Port_Moresby",
    "iso:country":"PG",
    "wof:name":"Kasap",
    "wof:placetype":"locality"
},
  "geometry": {"coordinates":[143.42019999999999,-5.40416],"type":"Point"}
}