{
  "type": "Feature",
  "properties": {
    "gn:admin1_code":"16",
    "gn:asciiname":"Kwibin",
    "gn:cc2":"PG",
    "gn:country_code":"PG",
    "gn:dem":1231,
    "gn:feature_class":"P",
    "gn:feature_code":"PPL",
    "gn:name":"Kwibin",
    "gn:population":0,
    "gn:timezone":"Pacific/Port_Moresby",
    "iso:country":"PG",
    "name:und_x_variant":[
        "Kwibum",
        "Kwibin"
    ],
    "wof:name":"Kwibin",
    "wof:placetype":"locality"
},
  "geometry": {"coordinates":[144.65000000000001,-5.56667],"type":"Point"}
}