{
  "type": "Feature",
  "properties": {
    "gn:admin1_code":"05",
    "gn:asciiname":"Waluboi",
    "gn:country_code":"PG",
    "gn:dem":1722,
    "gn:feature_class":"P",
    "gn:feature_code":"PPL",
    "gn:name":"Waluboi",
    "gn:population":0,
    "gn:timezone":"Pacific/Port_Moresby",
    "iso:country":"PG",
    "wof:name":"Waluboi",
    "wof:placetype":"locality"
},
  "geometry": {"coordinates":[144.01667,-6.38333],"type":"Point"}
}