{
  "type": "Feature",
  "properties": {
    "gn:admin1_code":"06",
    "gn:asciiname":"Sangamm",
    "gn:country_code":"PG",
    "gn:dem":64,
    "gn:feature_class":"P",
    "gn:feature_code":"PPL",
    "gn:name":"Sangamm",
    "gn:population":0,
    "gn:timezone":"Pacific/Port_Moresby",
    "iso:country":"PG",
    "wof:name":"Sangamm",
    "wof:placetype":"locality"
},
  "geometry": {"coordinates":[141.59999999999999,-6.16667],"type":"Point"}
}