{
  "type": "Feature",
  "properties": {
    "gn:admin1_code":"11",
    "gn:asciiname":"Waskuk",
    "gn:country_code":"PG",
    "gn:dem":23,
    "gn:feature_class":"P",
    "gn:feature_code":"PPL",
    "gn:name":"Waskuk",
    "gn:population":0,
    "gn:timezone":"Pacific/Port_Moresby",
    "iso:country":"PG",
    "name:und_x_variant":[
        "Washkuk",
        "Waskuk"
    ],
    "wof:name":"Waskuk",
    "wof:placetype":"locality"
},
  "geometry": {"coordinates":[142.40887000000001,-4.22759],"type":"Point"}
}