{
  "type": "Feature",
  "properties": {
    "gn:admin1_code":"03",
    "gn:asciiname":"Laiwai-Ia",
    "gn:country_code":"PG",
    "gn:dem":352,
    "gn:feature_class":"P",
    "gn:feature_code":"PPL",
    "gn:name":"Laiwai-Ia",
    "gn:population":0,
    "gn:timezone":"Pacific/Port_Moresby",
    "iso:country":"PG",
    "wof:name":"Laiwai-Ia",
    "wof:placetype":"locality"
},
  "geometry": {"coordinates":[150.28404,-9.44231],"type":"Point"}
}