{
  "type": "Feature",
  "properties": {
    "gn:admin1_code":"08",
    "gn:asciiname":"Kumon",
    "gn:cc2":"PG",
    "gn:country_code":"PG",
    "gn:dem":1728,
    "gn:feature_class":"P",
    "gn:feature_code":"PPL",
    "gn:name":"Kumon",
    "gn:population":0,
    "gn:timezone":"Pacific/Port_Moresby",
    "iso:country":"PG",
    "name:cat_x_preferred":[
        "M\u00e8tode Kumon"
    ],
    "name:deu_x_preferred":[
        "Kumon"
    ],
    "name:ind_x_preferred":[
        "Metode Kumon"
    ],
    "name:ita_x_preferred":[
        "Metodo Kumon"
    ],
    "name:jpn_x_preferred":[
        "\u65e5\u672c\u516c\u6587\u6559\u80b2\u7814\u7a76\u4f1a"
    ],
    "name:kor_x_preferred":[
        "\uad6c\ubaac\ud559\uc2b5"
    ],
    "name:por_x_preferred":[
        "Kumon"
    ],
    "name:spa_x_preferred":[
        "M\u00e9todo Kumon"
    ],
    "name:sun_x_preferred":[
        "Padika Kumon"
    ],
    "name:swe_x_preferred":[
        "Kumonshiki"
    ],
    "name:tgl_x_preferred":[
        "Kumon"
    ],
    "name:tha_x_preferred":[
        "\u0e04\u0e38\u0e21\u0e2d\u0e07"
    ],
    "name:und_x_variant":[
        "Kumom"
    ],
    "name:zho_x_preferred":[
        "\u516c\u6587\u5f0f"
    ],
    "wof:name":"Kumon",
    "wof:placetype":"locality"
},
  "geometry": {"coordinates":[145.11667,-6.21667],"type":"Point"}
}