{
  "type": "Feature",
  "properties": {
    "gn:admin1_code":"08",
    "gn:asciiname":"Kumon",
    "gn:cc2":"PG",
    "gn:country_code":"PG",
    "gn:dem":1728,
    "gn:feature_class":"P",
    "gn:feature_code":"PPL",
    "gn:name":"Kumon",
    "gn:population":0,
    "gn:timezone":"Pacific/Port_Moresby",
    "iso:country":"PG",
    "name:und_x_variant":[
        "Kumom",
        "Kumon"
    ],
    "wof:name":"Kumon",
    "wof:placetype":"locality"
},
  "geometry": {"coordinates":[145.11667,-6.21667],"type":"Point"}
}