{
  "type": "Feature",
  "properties": {
    "gn:admin1_code":"06",
    "gn:asciiname":"New Fegigapu",
    "gn:country_code":"PG",
    "gn:dem":11,
    "gn:feature_class":"P",
    "gn:feature_code":"PPL",
    "gn:name":"New Fegigapu",
    "gn:population":0,
    "gn:timezone":"Pacific/Port_Moresby",
    "iso:country":"PG",
    "wof:name":"New Fegigapu",
    "wof:placetype":"locality"
},
  "geometry": {"coordinates":[141.08864,-7.10099],"type":"Point"}
}