{
  "type": "Feature",
  "properties": {
    "gn:admin1_code":"18",
    "gn:asciiname":"Mambu",
    "gn:country_code":"PG",
    "gn:dem":224,
    "gn:feature_class":"P",
    "gn:feature_code":"PPL",
    "gn:name":"Mambu",
    "gn:population":0,
    "gn:timezone":"Pacific/Port_Moresby",
    "iso:country":"PG",
    "name:ceb_x_preferred":[
        "Mambu"
    ],
    "name:swe_x_preferred":[
        "Mambu"
    ],
    "wof:name":"Mambu",
    "wof:placetype":"locality"
},
  "geometry": {"coordinates":[142.56666999999999,-3.68333],"type":"Point"}
}