{
  "type": "Feature",
  "properties": {
    "gn:admin1_code":"06",
    "gn:asciiname":"Malam",
    "gn:country_code":"PG",
    "gn:dem":48,
    "gn:feature_class":"P",
    "gn:feature_code":"PPL",
    "gn:name":"Malam",
    "gn:population":0,
    "gn:timezone":"Pacific/Port_Moresby",
    "iso:country":"PG",
    "wof:name":"Malam",
    "wof:placetype":"locality"
},
  "geometry": {"coordinates":[142.61168000000001,-8.74304],"type":"Point"}
}