{
  "type": "Feature",
  "properties": {
    "gn:admin1_code":"14",
    "gn:asciiname":"Tangiawa",
    "gn:country_code":"PG",
    "gn:dem":753,
    "gn:feature_class":"P",
    "gn:feature_code":"PPL",
    "gn:name":"Tangiawa",
    "gn:population":0,
    "gn:timezone":"Pacific/Port_Moresby",
    "iso:country":"PG",
    "wof:name":"Tangiawa",
    "wof:placetype":"locality"
},
  "geometry": {"coordinates":[146.27566999999999,-7.48827],"type":"Point"}
}