{
  "type": "Feature",
  "properties": {
    "gn:admin1_code":"09",
    "gn:asciiname":"Amufi",
    "gn:country_code":"PG",
    "gn:dem":2210,
    "gn:feature_class":"P",
    "gn:feature_code":"PPL",
    "gn:name":"Amufi",
    "gn:population":0,
    "gn:timezone":"Pacific/Port_Moresby",
    "iso:country":"PG",
    "wof:name":"Amufi",
    "wof:placetype":"locality"
},
  "geometry": {"coordinates":[145.55000000000001,-6.43333],"type":"Point"}
}