{
  "type": "Feature",
  "properties": {
    "gn:admin1_code":"14",
    "gn:asciiname":"Kisengam",
    "gn:cc2":"PG",
    "gn:country_code":"PG",
    "gn:dem":1518,
    "gn:feature_class":"P",
    "gn:feature_code":"PPL",
    "gn:name":"Kisengam",
    "gn:population":0,
    "gn:timezone":"Pacific/Port_Moresby",
    "iso:country":"PG",
    "name:und_x_variant":[
        "Kisenden",
        "Kisengam"
    ],
    "wof:name":"Kisengam",
    "wof:placetype":"locality"
},
  "geometry": {"coordinates":[146.71666999999999,-6.35],"type":"Point"}
}