{
  "type": "Feature",
  "properties": {
    "gn:admin1_code":"06",
    "gn:asciiname":"Enkaiakmin",
    "gn:country_code":"PG",
    "gn:dem":2912,
    "gn:feature_class":"P",
    "gn:feature_code":"PPL",
    "gn:name":"Enkaiakmin",
    "gn:population":0,
    "gn:timezone":"Pacific/Port_Moresby",
    "iso:country":"PG",
    "wof:name":"Enkaiakmin",
    "wof:placetype":"locality"
},
  "geometry": {"coordinates":[141.69999999999999,-5.35],"type":"Point"}
}