{
  "type": "Feature",
  "properties": {
    "gn:admin1_code":"14",
    "gn:asciiname":"Puahom Yanga",
    "gn:country_code":"PG",
    "gn:dem":65,
    "gn:feature_class":"P",
    "gn:feature_code":"PPL",
    "gn:name":"Puahom Yanga",
    "gn:population":0,
    "gn:timezone":"Pacific/Port_Moresby",
    "iso:country":"PG",
    "wof:name":"Puahom Yanga",
    "wof:placetype":"locality"
},
  "geometry": {"coordinates":[147.03333000000001,-6.66667],"type":"Point"}
}