{
  "type": "Feature",
  "properties": {
    "gn:admin1_code":"12",
    "gn:asciiname":"Pukisak",
    "gn:country_code":"PG",
    "gn:dem":522,
    "gn:feature_class":"P",
    "gn:feature_code":"PPL",
    "gn:name":"Pukisak",
    "gn:population":0,
    "gn:timezone":"Pacific/Port_Moresby",
    "iso:country":"PG",
    "wof:name":"Pukisak",
    "wof:placetype":"locality"
},
  "geometry": {"coordinates":[145.44943000000001,-5.47862],"type":"Point"}
}