{
  "type": "Feature",
  "properties": {
    "gn:admin1_code":"16",
    "gn:asciiname":"Pinapais",
    "gn:cc2":"PG",
    "gn:country_code":"PG",
    "gn:dem":1493,
    "gn:feature_class":"P",
    "gn:feature_code":"PPL",
    "gn:name":"Pinapais",
    "gn:population":0,
    "gn:timezone":"Pacific/Port_Moresby",
    "iso:country":"PG",
    "name:und_x_variant":[
        "Pinyapais",
        "Pinapais"
    ],
    "wof:name":"Pinapais",
    "wof:placetype":"locality"
},
  "geometry": {"coordinates":[144.06666999999999,-5.53333],"type":"Point"}
}