{
  "type": "Feature",
  "properties": {
    "gn:admin1_code":"05",
    "gn:asciiname":"Kero",
    "gn:country_code":"PG",
    "gn:dem":2121,
    "gn:feature_class":"P",
    "gn:feature_code":"PPL",
    "gn:name":"Kero",
    "gn:population":0,
    "gn:timezone":"Pacific/Port_Moresby",
    "iso:country":"PG",
    "wof:name":"Kero",
    "wof:placetype":"locality"
},
  "geometry": {"coordinates":[144.00259,-6.19221],"type":"Point"}
}