{
  "type": "Feature",
  "properties": {
    "gn:admin1_code":"11",
    "gn:asciiname":"Lembun",
    "gn:cc2":"PG",
    "gn:country_code":"PG",
    "gn:dem":16,
    "gn:feature_class":"P",
    "gn:feature_code":"PPL",
    "gn:name":"Lembun",
    "gn:population":0,
    "gn:timezone":"Pacific/Port_Moresby",
    "iso:country":"PG",
    "name:und_x_variant":[
        "Lembum",
        "Lembun"
    ],
    "wof:name":"Lembun",
    "wof:placetype":"locality"
},
  "geometry": {"coordinates":[144.31666999999999,-4.46667],"type":"Point"}
}