{
  "type": "Feature",
  "properties": {
    "gn:admin1_code":"14",
    "gn:asciiname":"Bospaira",
    "gn:country_code":"PG",
    "gn:dem":-9999,
    "gn:feature_class":"P",
    "gn:feature_code":"PPL",
    "gn:name":"Bospaira",
    "gn:population":0,
    "gn:timezone":"Pacific/Port_Moresby",
    "iso:country":"PG",
    "wof:name":"Bospaira",
    "wof:placetype":"locality"
},
  "geometry": {"coordinates":[147.58333000000005,-7.71667],"type":"Point"}
}