{
  "type": "Feature",
  "properties": {
    "gn:admin1_code":"16",
    "gn:asciiname":"Yim",
    "gn:country_code":"PG",
    "gn:dem":2083,
    "gn:feature_class":"P",
    "gn:feature_code":"PPL",
    "gn:name":"Yim",
    "gn:population":0,
    "gn:timezone":"Pacific/Port_Moresby",
    "iso:country":"PG",
    "wof:name":"Yim",
    "wof:placetype":"locality"
},
  "geometry": {"coordinates":[144.29307,-5.64083],"type":"Point"}
}