{
  "type": "Feature",
  "properties": {
    "gn:admin1_code":"05",
    "gn:asciiname":"Tobandi",
    "gn:country_code":"PG",
    "gn:dem":2143,
    "gn:feature_class":"P",
    "gn:feature_code":"PPL",
    "gn:name":"Tobandi",
    "gn:population":0,
    "gn:timezone":"Pacific/Port_Moresby",
    "iso:country":"PG",
    "wof:name":"Tobandi",
    "wof:placetype":"locality"
},
  "geometry": {"coordinates":[142.98333,-5.71667],"type":"Point"}
}