{
  "type": "Feature",
  "properties": {
    "gn:admin1_code":"06",
    "gn:asciiname":"Gesoa",
    "gn:country_code":"PG",
    "gn:dem":22,
    "gn:feature_class":"P",
    "gn:feature_code":"PPL",
    "gn:name":"Gesoa",
    "gn:population":0,
    "gn:timezone":"Pacific/Port_Moresby",
    "iso:country":"PG",
    "name:und_x_variant":[
        "Gesed",
        "Gesco",
        "Geseo",
        "Gesoa"
    ],
    "wof:name":"Gesoa",
    "wof:placetype":"locality"
},
  "geometry": {"coordinates":[143.63658999999996,-8.41123],"type":"Point"}
}