{
  "type": "Feature",
  "properties": {
    "gn:admin1_code":"05",
    "gn:asciiname":"Orae",
    "gn:country_code":"PG",
    "gn:dem":1844,
    "gn:feature_class":"P",
    "gn:feature_code":"PPL",
    "gn:name":"Orae",
    "gn:population":0,
    "gn:timezone":"Pacific/Port_Moresby",
    "iso:country":"PG",
    "wof:name":"Orae",
    "wof:placetype":"locality"
},
  "geometry": {"coordinates":[144.11070000000001,-6.12727],"type":"Point"}
}