{
  "type": "Feature",
  "properties": {
    "gn:admin1_code":"01",
    "gn:asciiname":"Kapogere",
    "gn:cc2":"PG",
    "gn:country_code":"PG",
    "gn:dem":35,
    "gn:feature_class":"P",
    "gn:feature_code":"PPL",
    "gn:name":"Kapogere",
    "gn:population":0,
    "gn:timezone":"Pacific/Port_Moresby",
    "iso:country":"PG",
    "name:und_x_variant":[
        "Kapagere",
        "Kapogere"
    ],
    "wof:name":"Kapogere",
    "wof:placetype":"locality"
},
  "geometry": {"coordinates":[147.72861,-9.79],"type":"Point"}
}