{
  "type": "Feature",
  "properties": {
    "gn:admin1_code":"09",
    "gn:asciiname":"Magahiyufa",
    "gn:country_code":"PG",
    "gn:dem":1502,
    "gn:feature_class":"P",
    "gn:feature_code":"PPL",
    "gn:name":"Magahiyufa",
    "gn:population":0,
    "gn:timezone":"Pacific/Port_Moresby",
    "iso:country":"PG",
    "wof:name":"Magahiyufa",
    "wof:placetype":"locality"
},
  "geometry": {"coordinates":[145.50626,-6.1683],"type":"Point"}
}