{
  "type": "Feature",
  "properties": {
    "gn:admin1_code":"08",
    "gn:asciiname":"Mogomane",
    "gn:country_code":"PG",
    "gn:dem":1594,
    "gn:feature_class":"P",
    "gn:feature_code":"PPL",
    "gn:name":"Mogomane",
    "gn:population":0,
    "gn:timezone":"Pacific/Port_Moresby",
    "iso:country":"PG",
    "wof:name":"Mogomane",
    "wof:placetype":"locality"
},
  "geometry": {"coordinates":[145.09999999999999,-6.28333],"type":"Point"}
}