{
  "type": "Feature",
  "properties": {
    "gn:admin1_code":"06",
    "gn:asciiname":"Dadbia",
    "gn:country_code":"PG",
    "gn:dem":170,
    "gn:feature_class":"P",
    "gn:feature_code":"PPL",
    "gn:name":"Dadbia",
    "gn:population":0,
    "gn:timezone":"Pacific/Port_Moresby",
    "iso:country":"PG",
    "wof:name":"Dadbia",
    "wof:placetype":"locality"
},
  "geometry": {"coordinates":[142.39218,-6.33254],"type":"Point"}
}