{
  "type": "Feature",
  "properties": {
    "gn:admin1_code":"06",
    "gn:asciiname":"Kwiloknai",
    "gn:country_code":"PG",
    "gn:dem":197,
    "gn:feature_class":"P",
    "gn:feature_code":"PPL",
    "gn:name":"Kwiloknai",
    "gn:population":0,
    "gn:timezone":"Pacific/Port_Moresby",
    "iso:country":"PG",
    "wof:name":"Kwiloknai",
    "wof:placetype":"locality"
},
  "geometry": {"coordinates":[141.29038,-5.56652],"type":"Point"}
}