{
  "type": "Feature",
  "properties": {
    "gn:admin1_code":"12",
    "gn:asciiname":"Funyende",
    "gn:country_code":"PG",
    "gn:dem":2015,
    "gn:feature_class":"P",
    "gn:feature_code":"PPL",
    "gn:name":"Funyende",
    "gn:population":0,
    "gn:timezone":"Pacific/Port_Moresby",
    "iso:country":"PG",
    "wof:name":"Funyende",
    "wof:placetype":"locality"
},
  "geometry": {"coordinates":[146.21190000000001,-5.77936],"type":"Point"}
}