{
  "type": "Feature",
  "properties": {
    "gn:admin1_code":"12",
    "gn:asciiname":"Suvat",
    "gn:country_code":"PG",
    "gn:dem":268,
    "gn:feature_class":"P",
    "gn:feature_code":"PPL",
    "gn:name":"Suvat",
    "gn:population":0,
    "gn:timezone":"Pacific/Port_Moresby",
    "iso:country":"PG",
    "name:und_x_variant":[
        "Suat",
        "Suvat"
    ],
    "wof:name":"Suvat",
    "wof:placetype":"locality"
},
  "geometry": {"coordinates":[145.22381999999999,-4.47965],"type":"Point"}
}