{
  "type": "Feature",
  "properties": {
    "gn:admin1_code":"17",
    "gn:asciiname":"Gilinit",
    "gn:country_code":"PG",
    "gn:dem":41,
    "gn:feature_class":"P",
    "gn:feature_code":"PPL",
    "gn:name":"Gilinit",
    "gn:population":0,
    "gn:timezone":"Pacific/Port_Moresby",
    "iso:country":"PG",
    "wof:name":"Gilinit",
    "wof:placetype":"locality"
},
  "geometry": {"coordinates":[148.53527,-5.76333],"type":"Point"}
}