{
  "type": "Feature",
  "properties": {
    "gn:admin1_code":"14",
    "gn:asciiname":"Hudewa",
    "gn:country_code":"PG",
    "gn:dem":344,
    "gn:feature_class":"P",
    "gn:feature_code":"PPL",
    "gn:name":"Hudewa",
    "gn:population":0,
    "gn:timezone":"Pacific/Port_Moresby",
    "iso:country":"PG",
    "wof:name":"Hudewa",
    "wof:placetype":"locality"
},
  "geometry": {"coordinates":[147.65000000000001,-6.25],"type":"Point"}
}