{
  "type": "Feature",
  "properties": {
    "gn:admin1_code":"18",
    "gn:asciiname":"Miniaburu",
    "gn:country_code":"PG",
    "gn:dem":66,
    "gn:feature_class":"P",
    "gn:feature_code":"PPL",
    "gn:name":"Miniaburu",
    "gn:population":0,
    "gn:timezone":"Pacific/Port_Moresby",
    "iso:country":"PG",
    "wof:name":"Miniaburu",
    "wof:placetype":"locality"
},
  "geometry": {"coordinates":[141.04093,-3.9628],"type":"Point"}
}