{
  "type": "Feature",
  "properties": {
    "gn:admin1_code":"02",
    "gn:asciiname":"Hauakampka",
    "gn:country_code":"PG",
    "gn:dem":776,
    "gn:feature_class":"P",
    "gn:feature_code":"PPL",
    "gn:name":"Hauakampka",
    "gn:population":0,
    "gn:timezone":"Pacific/Port_Moresby",
    "iso:country":"PG",
    "wof:name":"Hauakampka",
    "wof:placetype":"locality"
},
  "geometry": {"coordinates":[145.98333,-7.65],"type":"Point"}
}