{
  "type": "Feature",
  "properties": {
    "gn:admin1_code":"01",
    "gn:asciiname":"Kokorogoro",
    "gn:country_code":"PG",
    "gn:dem":275,
    "gn:feature_class":"P",
    "gn:feature_code":"PPL",
    "gn:name":"Kokorogoro",
    "gn:population":0,
    "gn:timezone":"Pacific/Port_Moresby",
    "iso:country":"PG",
    "wof:name":"Kokorogoro",
    "wof:placetype":"locality"
},
  "geometry": {"coordinates":[147.80038999999999,-9.69406],"type":"Point"}
}