{
  "type": "Feature",
  "properties": {
    "gn:admin1_code":"15",
    "gn:asciiname":"Kabien Number 1",
    "gn:country_code":"PG",
    "gn:dem":11,
    "gn:feature_class":"P",
    "gn:feature_code":"PPL",
    "gn:name":"Kabien Number 1",
    "gn:population":0,
    "gn:timezone":"Pacific/Port_Moresby",
    "iso:country":"PG",
    "name:und_x_variant":[
        "Kabien",
        "Kabien 1",
        "Kabien Number 1"
    ],
    "wof:name":"Kabien Number 1",
    "wof:placetype":"locality"
},
  "geometry": {"coordinates":[150.76563000000004,-2.76249],"type":"Point"}
}