{
  "type": "Feature",
  "properties": {
    "gn:admin1_code":"05",
    "gn:asciiname":"Heabo",
    "gn:country_code":"PG",
    "gn:dem":1051,
    "gn:feature_class":"P",
    "gn:feature_code":"PPL",
    "gn:name":"Heabo",
    "gn:population":0,
    "gn:timezone":"Pacific/Port_Moresby",
    "iso:country":"PG",
    "wof:name":"Heabo",
    "wof:placetype":"locality"
},
  "geometry": {"coordinates":[142.93333000000001,-6.65],"type":"Point"}
}