{
  "type": "Feature",
  "properties": {
    "gn:admin1_code":"14",
    "gn:asciiname":"Buso",
    "gn:country_code":"PG",
    "gn:dem":57,
    "gn:feature_class":"P",
    "gn:feature_code":"PPL",
    "gn:name":"Buso",
    "gn:population":0,
    "gn:timezone":"Pacific/Port_Moresby",
    "iso:country":"PG",
    "name:und_x_variant":[
        "Buso 3",
        "Buso"
    ],
    "wof:name":"Buso",
    "wof:placetype":"locality"
},
  "geometry": {"coordinates":[147.22358,-6.68405],"type":"Point"}
}