{
  "type": "Feature",
  "properties": {
    "gn:admin1_code":"16",
    "gn:asciiname":"Komboga",
    "gn:country_code":"PG",
    "gn:dem":569,
    "gn:feature_class":"P",
    "gn:feature_code":"PPL",
    "gn:name":"Komboga",
    "gn:population":0,
    "gn:timezone":"Pacific/Port_Moresby",
    "iso:country":"PG",
    "name:und_x_variant":[
        "Kombogo",
        "Komboga"
    ],
    "wof:name":"Komboga",
    "wof:placetype":"locality"
},
  "geometry": {"coordinates":[144.50866000000005,-5.47295],"type":"Point"}
}