{
  "type": "Feature",
  "properties": {
    "gn:admin1_code":"01",
    "gn:asciiname":"Aduai",
    "gn:country_code":"PG",
    "gn:dem":1132,
    "gn:feature_class":"P",
    "gn:feature_code":"PPL",
    "gn:name":"Aduai",
    "gn:population":0,
    "gn:timezone":"Pacific/Port_Moresby",
    "iso:country":"PG",
    "wof:name":"Aduai",
    "wof:placetype":"locality"
},
  "geometry": {"coordinates":[147.29882000000001,-8.71132],"type":"Point"}
}