{
  "type": "Feature",
  "properties": {
    "gn:admin1_code":"01",
    "gn:asciiname":"Inawaia",
    "gn:country_code":"PG",
    "gn:dem":17,
    "gn:feature_class":"P",
    "gn:feature_code":"PPL",
    "gn:name":"Inawaia",
    "gn:population":0,
    "gn:timezone":"Pacific/Port_Moresby",
    "iso:country":"PG",
    "name:und_x_variant":[
        "Inauaia",
        "Inawaia"
    ],
    "wof:name":"Inawaia",
    "wof:placetype":"locality"
},
  "geometry": {"coordinates":[146.57533000000001,-8.63433],"type":"Point"}
}