{
  "type": "Feature",
  "properties": {
    "gn:admin1_code":"17",
    "gn:asciiname":"Taveliai",
    "gn:cc2":"PG",
    "gn:country_code":"PG",
    "gn:dem":8,
    "gn:feature_class":"P",
    "gn:feature_code":"PPL",
    "gn:name":"Taveliai",
    "gn:population":0,
    "gn:timezone":"Pacific/Port_Moresby",
    "iso:country":"PG",
    "name:und_x_variant":[
        "Taveliaio",
        "Taveliai"
    ],
    "wof:name":"Taveliai",
    "wof:placetype":"locality"
},
  "geometry": {"coordinates":[149.11667,-5.51667],"type":"Point"}
}