{
  "type": "Feature",
  "properties": {
    "gn:admin1_code":"06",
    "gn:asciiname":"Keabunna",
    "gn:country_code":"PG",
    "gn:dem":76,
    "gn:feature_class":"P",
    "gn:feature_code":"PPL",
    "gn:name":"Keabunna",
    "gn:population":0,
    "gn:timezone":"Pacific/Port_Moresby",
    "iso:country":"PG",
    "wof:name":"Keabunna",
    "wof:placetype":"locality"
},
  "geometry": {"coordinates":[141.86667,-6.56667],"type":"Point"}
}