{
  "type": "Feature",
  "properties": {
    "gn:admin1_code":"06",
    "gn:asciiname":"Metaba",
    "gn:country_code":"PG",
    "gn:dem":59,
    "gn:feature_class":"P",
    "gn:feature_code":"PPL",
    "gn:name":"Metaba",
    "gn:population":0,
    "gn:timezone":"Pacific/Port_Moresby",
    "iso:country":"PG",
    "wof:name":"Metaba",
    "wof:placetype":"locality"
},
  "geometry": {"coordinates":[142.83333000000005,-8.76667],"type":"Point"}
}