{
  "type": "Feature",
  "properties": {
    "gn:admin1_code":"01",
    "gn:asciiname":"Uwaia",
    "gn:country_code":"PG",
    "gn:dem":662,
    "gn:feature_class":"P",
    "gn:feature_code":"PPL",
    "gn:name":"Uwaia",
    "gn:population":0,
    "gn:timezone":"Pacific/Port_Moresby",
    "iso:country":"PG",
    "wof:name":"Uwaia",
    "wof:placetype":"locality"
},
  "geometry": {"coordinates":[148.05226000000005,-9.68773],"type":"Point"}
}