{
  "type": "Feature",
  "properties": {
    "gn:admin1_code":"08",
    "gn:asciiname":"Numanena",
    "gn:country_code":"PG",
    "gn:dem":2244,
    "gn:feature_class":"P",
    "gn:feature_code":"PPL",
    "gn:name":"Numanena",
    "gn:population":0,
    "gn:timezone":"Pacific/Port_Moresby",
    "iso:country":"PG",
    "wof:name":"Numanena",
    "wof:placetype":"locality"
},
  "geometry": {"coordinates":[145.18333000000001,-6.13333],"type":"Point"}
}