{
  "type": "Feature",
  "properties": {
    "gn:admin1_code":"16",
    "gn:asciiname":"Kaikona",
    "gn:country_code":"PG",
    "gn:dem":934,
    "gn:feature_class":"P",
    "gn:feature_code":"PPL",
    "gn:name":"Kaikona",
    "gn:population":0,
    "gn:timezone":"Pacific/Port_Moresby",
    "iso:country":"PG",
    "wof:name":"Kaikona",
    "wof:placetype":"locality"
},
  "geometry": {"coordinates":[144.38333,-5.23333],"type":"Point"}
}