{
  "type": "Feature",
  "properties": {
    "gn:admin1_code":"06",
    "gn:asciiname":"Sawanam",
    "gn:country_code":"PG",
    "gn:dem":338,
    "gn:feature_class":"P",
    "gn:feature_code":"PPL",
    "gn:name":"Sawanam",
    "gn:population":0,
    "gn:timezone":"Pacific/Port_Moresby",
    "iso:country":"PG",
    "name:und_x_variant":[
        "Sowanam",
        "Sawanam"
    ],
    "wof:name":"Sawanam",
    "wof:placetype":"locality"
},
  "geometry": {"coordinates":[141.06224,-5.42776],"type":"Point"}
}