{
  "type": "Feature",
  "properties": {
    "gn:admin1_code":"09",
    "gn:asciiname":"Gohenayuno",
    "gn:country_code":"PG",
    "gn:dem":1859,
    "gn:feature_class":"P",
    "gn:feature_code":"PPL",
    "gn:name":"Gohenayuno",
    "gn:population":0,
    "gn:timezone":"Pacific/Port_Moresby",
    "iso:country":"PG",
    "wof:name":"Gohenayuno",
    "wof:placetype":"locality"
},
  "geometry": {"coordinates":[145.31666999999999,-5.95],"type":"Point"}
}