{
  "type": "Feature",
  "properties": {
    "gn:admin1_code":"12",
    "gn:asciiname":"Nabringi",
    "gn:country_code":"PG",
    "gn:dem":47,
    "gn:feature_class":"P",
    "gn:feature_code":"PPL",
    "gn:name":"Nabringi",
    "gn:population":0,
    "gn:timezone":"Pacific/Port_Moresby",
    "iso:country":"PG",
    "wof:name":"Nabringi",
    "wof:placetype":"locality"
},
  "geometry": {"coordinates":[144.58333000000005,-4.78333],"type":"Point"}
}