{
  "type": "Feature",
  "properties": {
    "gn:admin1_code":"16",
    "gn:asciiname":"Tomba",
    "gn:country_code":"PG",
    "gn:dem":2567,
    "gn:feature_class":"P",
    "gn:feature_code":"PPL",
    "gn:name":"Tomba",
    "gn:population":0,
    "gn:timezone":"Pacific/Port_Moresby",
    "iso:country":"PG",
    "name:cat_x_preferred":[
        "Tomba"
    ],
    "name:ceb_x_preferred":[
        "Tomba"
    ],
    "name:ces_x_preferred":[
        "Tomba"
    ],
    "name:fin_x_preferred":[
        "Tomba"
    ],
    "name:fra_x_preferred":[
        "Tomba"
    ],
    "name:ita_x_preferred":[
        "Tomba"
    ],
    "name:jpn_x_preferred":[
        "\u30c8\u30f3\u30d0"
    ],
    "name:por_x_preferred":[
        "Tomba"
    ],
    "name:ron_x_preferred":[
        "Tomba"
    ],
    "name:srp_x_preferred":[
        "Tomba"
    ],
    "name:swe_x_preferred":[
        "Tomba"
    ],
    "wof:name":"Tomba",
    "wof:placetype":"locality"
},
  "geometry": {"coordinates":[144.01897,-5.82111],"type":"Point"}
}