{
  "type": "Feature",
  "properties": {
    "gn:admin1_code":"18",
    "gn:asciiname":"Wabuf",
    "gn:country_code":"PG",
    "gn:dem":513,
    "gn:feature_class":"P",
    "gn:feature_code":"PPL",
    "gn:name":"Wabuf",
    "gn:population":0,
    "gn:timezone":"Pacific/Port_Moresby",
    "iso:country":"PG",
    "wof:name":"Wabuf",
    "wof:placetype":"locality"
},
  "geometry": {"coordinates":[142.02431999999999,-3.4883],"type":"Point"}
}