{
  "type": "Feature",
  "properties": {
    "gn:admin1_code":"12",
    "gn:asciiname":"Aiambi",
    "gn:country_code":"PG",
    "gn:dem":173,
    "gn:feature_class":"P",
    "gn:feature_code":"PPL",
    "gn:name":"Aiambi",
    "gn:population":0,
    "gn:timezone":"Pacific/Port_Moresby",
    "iso:country":"PG",
    "wof:name":"Aiambi",
    "wof:placetype":"locality"
},
  "geometry": {"coordinates":[145.46666999999999,-5.61667],"type":"Point"}
}