{
  "type": "Feature",
  "properties": {
    "gn:admin1_code":"06",
    "gn:asciiname":"Kibuli",
    "gn:country_code":"PG",
    "gn:dem":17,
    "gn:feature_class":"P",
    "gn:feature_code":"PPL",
    "gn:name":"Kibuli",
    "gn:population":0,
    "gn:timezone":"Pacific/Port_Moresby",
    "iso:country":"PG",
    "name:eng_x_preferred":[
        "Kibuli"
    ],
    "name:und_x_variant":[
        "Kibui"
    ],
    "wof:name":"Kibuli",
    "wof:placetype":"locality"
},
  "geometry": {"coordinates":[142.70236,-9.01607],"type":"Point"}
}