{
  "type": "Feature",
  "properties": {
    "gn:admin1_code":"14",
    "gn:asciiname":"Masangko",
    "gn:country_code":"PG",
    "gn:dem":668,
    "gn:feature_class":"P",
    "gn:feature_code":"PPL",
    "gn:name":"Masangko",
    "gn:population":0,
    "gn:timezone":"Pacific/Port_Moresby",
    "iso:country":"PG",
    "wof:name":"Masangko",
    "wof:placetype":"locality"
},
  "geometry": {"coordinates":[147.77531999999999,-6.48644],"type":"Point"}
}