{
  "type": "Feature",
  "properties": {
    "gn:admin1_code":"05",
    "gn:asciiname":"Omai",
    "gn:country_code":"PG",
    "gn:dem":2113,
    "gn:feature_class":"P",
    "gn:feature_code":"PPL",
    "gn:name":"Omai",
    "gn:population":0,
    "gn:timezone":"Pacific/Port_Moresby",
    "iso:country":"PG",
    "name:ces_x_preferred":[
        "Omai"
    ],
    "name:deu_x_preferred":[
        "Omai"
    ],
    "name:epo_x_preferred":[
        "Omai"
    ],
    "name:fra_x_preferred":[
        "Omai"
    ],
    "name:hrv_x_preferred":[
        "Omai"
    ],
    "name:nor_x_preferred":[
        "Omai"
    ],
    "wof:name":"Omai",
    "wof:placetype":"locality"
},
  "geometry": {"coordinates":[143.77634,-6.2255],"type":"Point"}
}