{
  "type": "Feature",
  "properties": {
    "gn:admin1_code":"07",
    "gn:asciiname":"Okomo",
    "gn:country_code":"PG",
    "gn:dem":339,
    "gn:feature_class":"P",
    "gn:feature_code":"PPL",
    "gn:name":"Okomo",
    "gn:population":0,
    "gn:timezone":"Pacific/Bougainville",
    "iso:country":"PG",
    "name:und_x_variant":[
        "Okoma",
        "Okomo"
    ],
    "wof:name":"Okomo",
    "wof:placetype":"locality"
},
  "geometry": {"coordinates":[155.61792,-6.63269],"type":"Point"}
}