{
  "type": "Feature",
  "properties": {
    "gn:admin1_code":"08",
    "gn:asciiname":"Gunuamarime",
    "gn:country_code":"PG",
    "gn:dem":1699,
    "gn:feature_class":"P",
    "gn:feature_code":"PPL",
    "gn:name":"Gunuamarime",
    "gn:population":0,
    "gn:timezone":"Pacific/Port_Moresby",
    "iso:country":"PG",
    "wof:name":"Gunuamarime",
    "wof:placetype":"locality"
},
  "geometry": {"coordinates":[144.90889000000001,-6.16214],"type":"Point"}
}