{
  "type": "Feature",
  "properties": {
    "gn:admin1_code":"18",
    "gn:asciiname":"Arimin Number 2",
    "gn:country_code":"PG",
    "gn:dem":2528,
    "gn:feature_class":"P",
    "gn:feature_code":"PPL",
    "gn:name":"Arimin Number 2",
    "gn:population":0,
    "gn:timezone":"Pacific/Port_Moresby",
    "iso:country":"PG",
    "name:und_x_variant":[
        "Arimin 2",
        "Arimin Number 2"
    ],
    "wof:name":"Arimin Number 2",
    "wof:placetype":"locality"
},
  "geometry": {"coordinates":[141.01106999999999,-4.83104],"type":"Point"}
}