{
  "type": "Feature",
  "properties": {
    "gn:admin1_code":"03",
    "gn:asciiname":"Talaha",
    "gn:country_code":"PG",
    "gn:dem":527,
    "gn:feature_class":"P",
    "gn:feature_code":"PPL",
    "gn:name":"Talaha",
    "gn:population":0,
    "gn:timezone":"Pacific/Port_Moresby",
    "iso:country":"PG",
    "wof:name":"Talaha",
    "wof:placetype":"locality"
},
  "geometry": {"coordinates":[151.26667,-10.01667],"type":"Point"}
}