{
  "type": "Feature",
  "properties": {
    "gn:admin1_code":"18",
    "gn:asciiname":"Kine",
    "gn:country_code":"PG",
    "gn:dem":494,
    "gn:feature_class":"P",
    "gn:feature_code":"PPL",
    "gn:name":"Kine",
    "gn:population":0,
    "gn:timezone":"Pacific/Port_Moresby",
    "iso:country":"PG",
    "name:wln_x_preferred":[
        "Kine"
    ],
    "wof:name":"Kine",
    "wof:placetype":"locality"
},
  "geometry": {"coordinates":[142.62266,-3.45708],"type":"Point"}
}