{
  "type": "Feature",
  "properties": {
    "gn:admin1_code":"12",
    "gn:asciiname":"Urirai",
    "gn:country_code":"PG",
    "gn:dem":320,
    "gn:feature_class":"P",
    "gn:feature_code":"PPL",
    "gn:name":"Urirai",
    "gn:population":0,
    "gn:timezone":"Pacific/Port_Moresby",
    "iso:country":"PG",
    "wof:name":"Urirai",
    "wof:placetype":"locality"
},
  "geometry": {"coordinates":[145.44999999999999,-5.38333],"type":"Point"}
}