{
  "type": "Feature",
  "properties": {
    "gn:admin1_code":"06",
    "gn:asciiname":"Deikwi",
    "gn:country_code":"PG",
    "gn:dem":186,
    "gn:feature_class":"P",
    "gn:feature_code":"PPL",
    "gn:name":"Deikwi",
    "gn:population":0,
    "gn:timezone":"Pacific/Port_Moresby",
    "iso:country":"PG",
    "name:und_x_variant":[
        "Deikui",
        "Deikwi"
    ],
    "wof:name":"Deikwi",
    "wof:placetype":"locality"
},
  "geometry": {"coordinates":[141.03981000000005,-5.52312],"type":"Point"}
}