{
  "type": "Feature",
  "properties": {
    "gn:admin1_code":"09",
    "gn:asciiname":"Kami Number 2",
    "gn:country_code":"PG",
    "gn:dem":1473,
    "gn:feature_class":"P",
    "gn:feature_code":"PPL",
    "gn:name":"Kami Number 2",
    "gn:population":0,
    "gn:timezone":"Pacific/Port_Moresby",
    "iso:country":"PG",
    "name:und_x_variant":[
        "Kami 2",
        "Kami Number 2"
    ],
    "wof:name":"Kami Number 2",
    "wof:placetype":"locality"
},
  "geometry": {"coordinates":[145.40929,-6.11336],"type":"Point"}
}