{
  "type": "Feature",
  "properties": {
    "gn:admin1_code":"09",
    "gn:asciiname":"Taianga",
    "gn:country_code":"PG",
    "gn:dem":1913,
    "gn:feature_class":"P",
    "gn:feature_code":"PPL",
    "gn:name":"Taianga",
    "gn:population":0,
    "gn:timezone":"Pacific/Port_Moresby",
    "iso:country":"PG",
    "wof:name":"Taianga",
    "wof:placetype":"locality"
},
  "geometry": {"coordinates":[145.86667,-6.81667],"type":"Point"}
}