{
  "type": "Feature",
  "properties": {
    "gn:admin1_code":"03",
    "gn:asciiname":"Wapon",
    "gn:country_code":"PG",
    "gn:dem":177,
    "gn:feature_class":"P",
    "gn:feature_code":"PPL",
    "gn:name":"Wapon",
    "gn:population":0,
    "gn:timezone":"Pacific/Port_Moresby",
    "iso:country":"PG",
    "name:und_x_variant":[
        "Wapona",
        "Wapon"
    ],
    "wof:name":"Wapon",
    "wof:placetype":"locality"
},
  "geometry": {"coordinates":[149.39518000000001,-9.68047],"type":"Point"}
}