{
  "type": "Feature",
  "properties": {
    "gn:admin1_code":"11",
    "gn:asciiname":"Bepandu",
    "gn:country_code":"PG",
    "gn:dem":163,
    "gn:feature_class":"P",
    "gn:feature_code":"PPL",
    "gn:name":"Bepandu",
    "gn:population":0,
    "gn:timezone":"Pacific/Port_Moresby",
    "iso:country":"PG",
    "wof:name":"Bepandu",
    "wof:placetype":"locality"
},
  "geometry": {"coordinates":[143.19611,-3.68179],"type":"Point"}
}