{
  "type": "Feature",
  "properties": {
    "gn:admin1_code":"11",
    "gn:asciiname":"Uragembi 1",
    "gn:country_code":"PG",
    "gn:dem":208,
    "gn:feature_class":"P",
    "gn:feature_code":"PPL",
    "gn:name":"Uragembi 1",
    "gn:population":0,
    "gn:timezone":"Pacific/Port_Moresby",
    "iso:country":"PG",
    "wof:name":"Uragembi 1",
    "wof:placetype":"locality"
},
  "geometry": {"coordinates":[143.55500000000001,-3.71854],"type":"Point"}
}