{
  "type": "Feature",
  "properties": {
    "gn:admin1_code":"12",
    "gn:asciiname":"Gaven",
    "gn:country_code":"PG",
    "gn:dem":1921,
    "gn:feature_class":"P",
    "gn:feature_code":"PPL",
    "gn:name":"Gaven",
    "gn:population":0,
    "gn:timezone":"Pacific/Port_Moresby",
    "iso:country":"PG",
    "wof:name":"Gaven",
    "wof:placetype":"locality"
},
  "geometry": {"coordinates":[144.55000000000001,-5.26667],"type":"Point"}
}