{
  "type": "Feature",
  "properties": {
    "gn:admin1_code":"06",
    "gn:asciiname":"Wasu",
    "gn:country_code":"PG",
    "gn:dem":142,
    "gn:feature_class":"P",
    "gn:feature_code":"PPL",
    "gn:name":"Wasu",
    "gn:population":0,
    "gn:timezone":"Pacific/Port_Moresby",
    "iso:country":"PG",
    "wof:name":"Wasu",
    "wof:placetype":"locality"
},
  "geometry": {"coordinates":[142.15000000000001,-6.08333],"type":"Point"}
}