{
  "type": "Feature",
  "properties": {
    "gn:admin1_code":"01",
    "gn:admin2_code":"2087633",
    "gn:asciiname":"Walai",
    "gn:country_code":"PG",
    "gn:dem":0,
    "gn:feature_class":"P",
    "gn:feature_code":"PPL",
    "gn:name":"Walai",
    "gn:population":0,
    "gn:timezone":"Pacific/Port_Moresby",
    "iso:country":"PG",
    "wof:name":"Walai",
    "wof:placetype":"locality"
},
  "geometry": {"coordinates":[147.63783000000001,-9.99421],"type":"Point"}
}