{
  "type": "Feature",
  "properties": {
    "gn:admin1_code":"02",
    "gn:asciiname":"Minagoiravi",
    "gn:country_code":"PG",
    "gn:dem":14,
    "gn:feature_class":"P",
    "gn:feature_code":"PPL",
    "gn:name":"Minagoiravi",
    "gn:population":0,
    "gn:timezone":"Pacific/Port_Moresby",
    "iso:country":"PG",
    "name:und_x_variant":[
        "Koirava",
        "Koiravi",
        "Minagoiravi"
    ],
    "wof:name":"Minagoiravi",
    "wof:placetype":"locality"
},
  "geometry": {"coordinates":[144.57238999999996,-7.38327],"type":"Point"}
}