{
  "type": "Feature",
  "properties": {
    "gn:admin1_code":"03",
    "gn:asciiname":"Siasiada",
    "gn:country_code":"PG",
    "gn:dem":39,
    "gn:feature_class":"P",
    "gn:feature_code":"PPL",
    "gn:name":"Siasiada",
    "gn:population":0,
    "gn:timezone":"Pacific/Port_Moresby",
    "iso:country":"PG",
    "wof:name":"Siasiada",
    "wof:placetype":"locality"
},
  "geometry": {"coordinates":[150.15000000000001,-10.46667],"type":"Point"}
}