{
  "type": "Feature",
  "properties": {
    "gn:admin1_code":"18",
    "gn:asciiname":"Bibriari Number 1",
    "gn:country_code":"PG",
    "gn:dem":198,
    "gn:feature_class":"P",
    "gn:feature_code":"PPL",
    "gn:name":"Bibriari Number 1",
    "gn:population":0,
    "gn:timezone":"Pacific/Port_Moresby",
    "iso:country":"PG",
    "name:und_x_variant":[
        "Bibriari",
        "Bibriari Number 1"
    ],
    "wof:name":"Bibriari Number 1",
    "wof:placetype":"locality"
},
  "geometry": {"coordinates":[141.20338000000001,-3.67359],"type":"Point"}
}