{
  "type": "Feature",
  "properties": {
    "gn:admin1_code":"10",
    "gn:asciiname":"Napapar Number 1",
    "gn:country_code":"PG",
    "gn:dem":294,
    "gn:feature_class":"P",
    "gn:feature_code":"PPL",
    "gn:name":"Napapar Number 1",
    "gn:population":0,
    "gn:timezone":"Pacific/Port_Moresby",
    "iso:country":"PG",
    "wof:name":"Napapar Number 1",
    "wof:placetype":"locality"
},
  "geometry": {"coordinates":[152.11667,-4.33333],"type":"Point"}
}