{
  "type": "Feature",
  "properties": {
    "gn:admin1_code":"11",
    "gn:asciiname":"Slei Number 2",
    "gn:country_code":"PG",
    "gn:dem":34,
    "gn:feature_class":"P",
    "gn:feature_code":"PPL",
    "gn:name":"Slei Number 2",
    "gn:population":0,
    "gn:timezone":"Pacific/Port_Moresby",
    "iso:country":"PG",
    "name:und_x_variant":[
        "Slei 2",
        "Slei Number 2"
    ],
    "wof:name":"Slei Number 2",
    "wof:placetype":"locality"
},
  "geometry": {"coordinates":[143.16293000000005,-4.01872],"type":"Point"}
}