{
  "type": "Feature",
  "properties": {
    "gn:admin1_code":"03",
    "gn:asciiname":"Taupota Number 2",
    "gn:country_code":"PG",
    "gn:dem":11,
    "gn:feature_class":"P",
    "gn:feature_code":"PPL",
    "gn:name":"Taupota Number 2",
    "gn:population":0,
    "gn:timezone":"Pacific/Port_Moresby",
    "iso:country":"PG",
    "name:und_x_variant":[
        "Taupota 2",
        "Taupota Number 2"
    ],
    "wof:name":"Taupota Number 2",
    "wof:placetype":"locality"
},
  "geometry": {"coordinates":[150.46608000000001,-10.20875],"type":"Point"}
}