{
  "type": "Feature",
  "properties": {
    "gn:admin1_code":"09",
    "gn:asciiname":"Araaira",
    "gn:country_code":"PG",
    "gn:dem":1894,
    "gn:feature_class":"P",
    "gn:feature_code":"PPL",
    "gn:name":"Araaira",
    "gn:population":0,
    "gn:timezone":"Pacific/Port_Moresby",
    "iso:country":"PG",
    "wof:name":"Araaira",
    "wof:placetype":"locality"
},
  "geometry": {"coordinates":[145.80635000000001,-6.51284],"type":"Point"}
}