{
  "type": "Feature",
  "properties": {
    "gn:admin1_code":"06",
    "gn:asciiname":"Irinkwi",
    "gn:country_code":"PG",
    "gn:dem":173,
    "gn:feature_class":"P",
    "gn:feature_code":"PPL",
    "gn:name":"Irinkwi",
    "gn:population":0,
    "gn:timezone":"Pacific/Port_Moresby",
    "iso:country":"PG",
    "name:und_x_variant":[
        "Irimkwi",
        "Irinkui",
        "Irinkwi"
    ],
    "wof:name":"Irinkwi",
    "wof:placetype":"locality"
},
  "geometry": {"coordinates":[141.01626000000005,-5.49359],"type":"Point"}
}