{
  "type": "Feature",
  "properties": {
    "gn:admin1_code":"05",
    "gn:asciiname":"Kobilinye",
    "gn:cc2":"PG",
    "gn:country_code":"PG",
    "gn:dem":2171,
    "gn:feature_class":"P",
    "gn:feature_code":"PPL",
    "gn:name":"Kobilinye",
    "gn:population":0,
    "gn:timezone":"Pacific/Port_Moresby",
    "iso:country":"PG",
    "name:und_x_variant":[
        "Kombilinye",
        "Kobilinye"
    ],
    "wof:name":"Kobilinye",
    "wof:placetype":"locality"
},
  "geometry": {"coordinates":[143.94999999999999,-6.18333],"type":"Point"}
}