{
  "type": "Feature",
  "properties": {
    "gn:admin1_code":"08",
    "gn:asciiname":"Kaifo",
    "gn:country_code":"PG",
    "gn:dem":2067,
    "gn:feature_class":"P",
    "gn:feature_code":"PPL",
    "gn:name":"Kaifo",
    "gn:population":0,
    "gn:timezone":"Pacific/Port_Moresby",
    "iso:country":"PG",
    "wof:name":"Kaifo",
    "wof:placetype":"locality"
},
  "geometry": {"coordinates":[145.16666999999995,-6.15],"type":"Point"}
}