{
  "type": "Feature",
  "properties": {
    "gn:admin1_code":"06",
    "gn:asciiname":"Umbunantap",
    "gn:country_code":"PG",
    "gn:dem":477,
    "gn:feature_class":"P",
    "gn:feature_code":"PPL",
    "gn:name":"Umbunantap",
    "gn:population":0,
    "gn:timezone":"Pacific/Port_Moresby",
    "iso:country":"PG",
    "wof:name":"Umbunantap",
    "wof:placetype":"locality"
},
  "geometry": {"coordinates":[141.06666999999999,-5.31667],"type":"Point"}
}