{
  "type": "Feature",
  "properties": {
    "gn:admin1_code":"05",
    "gn:asciiname":"Paura",
    "gn:country_code":"PG",
    "gn:dem":1682,
    "gn:feature_class":"P",
    "gn:feature_code":"PPL",
    "gn:name":"Paura",
    "gn:population":0,
    "gn:timezone":"Pacific/Port_Moresby",
    "iso:country":"PG",
    "wof:name":"Paura",
    "wof:placetype":"locality"
},
  "geometry": {"coordinates":[144.01175000000001,-6.39467],"type":"Point"}
}