{
  "type": "Feature",
  "properties": {
    "gn:admin1_code":"09",
    "gn:asciiname":"Yagareba",
    "gn:country_code":"PG",
    "gn:dem":1831,
    "gn:feature_class":"P",
    "gn:feature_code":"PPL",
    "gn:name":"Yagareba",
    "gn:population":0,
    "gn:timezone":"Pacific/Port_Moresby",
    "iso:country":"PG",
    "wof:name":"Yagareba",
    "wof:placetype":"locality"
},
  "geometry": {"coordinates":[145.58100000000005,-6.58548],"type":"Point"}
}