{
  "type": "Feature",
  "properties": {
    "gn:admin1_code":"06",
    "gn:asciiname":"Pampenai",
    "gn:country_code":"PG",
    "gn:dem":69,
    "gn:feature_class":"P",
    "gn:feature_code":"PPL",
    "gn:name":"Pampenai",
    "gn:population":0,
    "gn:timezone":"Pacific/Port_Moresby",
    "iso:country":"PG",
    "wof:name":"Pampenai",
    "wof:placetype":"locality"
},
  "geometry": {"coordinates":[141.21526,-5.73853],"type":"Point"}
}