{
  "type": "Feature",
  "properties": {
    "gn:admin1_code":"05",
    "gn:asciiname":"Tongka",
    "gn:country_code":"PG",
    "gn:dem":1588,
    "gn:feature_class":"P",
    "gn:feature_code":"PPL",
    "gn:name":"Tongka",
    "gn:population":0,
    "gn:timezone":"Pacific/Port_Moresby",
    "iso:country":"PG",
    "wof:name":"Tongka",
    "wof:placetype":"locality"
},
  "geometry": {"coordinates":[143.80000000000001,-6.48333],"type":"Point"}
}