{
  "type": "Feature",
  "properties": {
    "gn:admin1_code":"12",
    "gn:asciiname":"Kowat",
    "gn:country_code":"PG",
    "gn:dem":1133,
    "gn:feature_class":"P",
    "gn:feature_code":"PPL",
    "gn:name":"Kowat",
    "gn:population":0,
    "gn:timezone":"Pacific/Port_Moresby",
    "iso:country":"PG",
    "wof:name":"Kowat",
    "wof:placetype":"locality"
},
  "geometry": {"coordinates":[145.36258000000001,-4.82191],"type":"Point"}
}