{
  "type": "Feature",
  "properties": {
    "gn:admin1_code":"12",
    "gn:asciiname":"Suaru",
    "gn:country_code":"PG",
    "gn:dem":141,
    "gn:feature_class":"P",
    "gn:feature_code":"PPL",
    "gn:name":"Suaru",
    "gn:population":0,
    "gn:timezone":"Pacific/Port_Moresby",
    "iso:country":"PG",
    "wof:name":"Suaru",
    "wof:placetype":"locality"
},
  "geometry": {"coordinates":[145.09743999999995,-4.38636],"type":"Point"}
}