{
  "type": "Feature",
  "properties": {
    "gn:admin1_code":"11",
    "gn:asciiname":"Mari",
    "gn:country_code":"PG",
    "gn:dem":123,
    "gn:feature_class":"P",
    "gn:feature_code":"PPL",
    "gn:name":"Mari",
    "gn:population":0,
    "gn:timezone":"Pacific/Port_Moresby",
    "iso:country":"PG",
    "name:ara_x_preferred":[
        "\u0645\u0627\u0631\u064a"
    ],
    "name:arg_x_preferred":[
        "Mari"
    ],
    "name:aze_x_preferred":[
        "Mari"
    ],
    "name:bul_x_preferred":[
        "\u041c\u0430\u0440\u0438"
    ],
    "name:cat_x_preferred":[
        "Mari"
    ],
    "name:ceb_x_preferred":[
        "Mari"
    ],
    "name:deu_x_preferred":[
        "Mari"
    ],
    "name:est_x_preferred":[
        "Mari"
    ],
    "name:eus_x_preferred":[
        "Mari"
    ],
    "name:fas_x_preferred":[
        "\u0645\u0627\u0631\u06cc"
    ],
    "name:fin_x_preferred":[
        "Mari"
    ],
    "name:fra_x_preferred":[
        "Mari"
    ],
    "name:glg_x_preferred":[
        "Mari"
    ],
    "name:heb_x_preferred":[
        "\u05de\u05d0\u05e8\u05d9"
    ],
    "name:hrv_x_preferred":[
        "Mari"
    ],
    "name:hun_x_preferred":[
        "Mari"
    ],
    "name:hye_x_preferred":[
        "\u0544\u0561\u0580\u056b"
    ],
    "name:ita_x_preferred":[
        "Mari"
    ],
    "name:kat_x_preferred":[
        "\u10db\u10d0\u10e0\u10d8"
    ],
    "name:kom_x_preferred":[
        "\u041c\u0430\u0440\u0438"
    ],
    "name:nld_x_preferred":[
        "Mari"
    ],
    "name:nno_x_preferred":[
        "Mari"
    ],
    "name:nor_x_preferred":[
        "Mari"
    ],
    "name:oci_x_preferred":[
        "Mari"
    ],
    "name:pol_x_preferred":[
        "Mari"
    ],
    "name:por_x_preferred":[
        "Mari"
    ],
    "name:rus_x_preferred":[
        "\u041c\u0430\u0440\u0438"
    ],
    "name:slk_x_preferred":[
        "Mari"
    ],
    "name:slv_x_preferred":[
        "Mari"
    ],
    "name:spa_x_preferred":[
        "Mari"
    ],
    "name:srp_x_preferred":[
        "\u041c\u0430\u0440\u0438"
    ],
    "name:swe_x_preferred":[
        "Mari"
    ],
    "name:tur_x_preferred":[
        "Mari"
    ],
    "name:ukr_x_preferred":[
        "\u041c\u0430\u0440\u0456"
    ],
    "wof:name":"Mari",
    "wof:placetype":"locality"
},
  "geometry": {"coordinates":[142.97953000000001,-4.3947],"type":"Point"}
}