{
  "type": "Feature",
  "properties": {
    "gn:admin1_code":"11",
    "gn:asciiname":"Mari",
    "gn:country_code":"PG",
    "gn:dem":123,
    "gn:feature_class":"P",
    "gn:feature_code":"PPL",
    "gn:name":"Mari",
    "gn:population":0,
    "gn:timezone":"Pacific/Port_Moresby",
    "iso:country":"PG",
    "wof:name":"Mari",
    "wof:placetype":"locality"
},
  "geometry": {"coordinates":[142.97953000000001,-4.3947],"type":"Point"}
}