{
  "type": "Feature",
  "properties": {
    "gn:admin1_code":"06",
    "gn:asciiname":"Kukodobi",
    "gn:country_code":"PG",
    "gn:dem":110,
    "gn:feature_class":"P",
    "gn:feature_code":"PPL",
    "gn:name":"Kukodobi",
    "gn:population":0,
    "gn:timezone":"Pacific/Port_Moresby",
    "iso:country":"PG",
    "wof:name":"Kukodobi",
    "wof:placetype":"locality"
},
  "geometry": {"coordinates":[142.17972,-6.33169],"type":"Point"}
}