{
  "type": "Feature",
  "properties": {
    "gn:admin1_code":"04",
    "gn:asciiname":"Simumu",
    "gn:country_code":"PG",
    "gn:dem":10,
    "gn:feature_class":"P",
    "gn:feature_code":"PPL",
    "gn:name":"Simumu",
    "gn:population":0,
    "gn:timezone":"Pacific/Port_Moresby",
    "iso:country":"PG",
    "wof:name":"Simumu",
    "wof:placetype":"locality"
},
  "geometry": {"coordinates":[149.25,-9.18333],"type":"Point"}
}