{
  "type": "Feature",
  "properties": {
    "gn:admin1_code":"05",
    "gn:asciiname":"Kupari",
    "gn:country_code":"PG",
    "gn:dem":1635,
    "gn:feature_class":"P",
    "gn:feature_code":"PPL",
    "gn:name":"Kupari",
    "gn:population":0,
    "gn:timezone":"Pacific/Port_Moresby",
    "iso:country":"PG",
    "wof:name":"Kupari",
    "wof:placetype":"locality"
},
  "geometry": {"coordinates":[142.96061,-5.85929],"type":"Point"}
}