{
  "type": "Feature",
  "properties": {
    "gn:admin1_code":"09",
    "gn:asciiname":"Haga Number 2",
    "gn:cc2":"PG",
    "gn:country_code":"PG",
    "gn:dem":2139,
    "gn:feature_class":"P",
    "gn:feature_code":"PPL",
    "gn:name":"Haga Number 2",
    "gn:population":0,
    "gn:timezone":"Pacific/Port_Moresby",
    "iso:country":"PG",
    "name:und_x_variant":[
        "Haga 2",
        "Haga Number 2"
    ],
    "wof:name":"Haga Number 2",
    "wof:placetype":"locality"
},
  "geometry": {"coordinates":[145.40000000000001,-6.35],"type":"Point"}
}