{
  "type": "Feature",
  "properties": {
    "gn:admin1_code":"12",
    "gn:asciiname":"Gongeia",
    "gn:country_code":"PG",
    "gn:dem":1734,
    "gn:feature_class":"P",
    "gn:feature_code":"PPL",
    "gn:name":"Gongeia",
    "gn:population":0,
    "gn:timezone":"Pacific/Port_Moresby",
    "iso:country":"PG",
    "name:und_x_variant":[
        "Gonogeia",
        "Gongeia"
    ],
    "wof:name":"Gongeia",
    "wof:placetype":"locality"
},
  "geometry": {"coordinates":[146.02757,-5.90209],"type":"Point"}
}