{
  "type": "Feature",
  "properties": {
    "gn:admin1_code":"06",
    "gn:asciiname":"Madrere",
    "gn:country_code":"PG",
    "gn:dem":42,
    "gn:feature_class":"P",
    "gn:feature_code":"PPL",
    "gn:name":"Madrere",
    "gn:population":0,
    "gn:timezone":"Pacific/Port_Moresby",
    "iso:country":"PG",
    "wof:name":"Madrere",
    "wof:placetype":"locality"
},
  "geometry": {"coordinates":[142.78333000000001,-8.88333],"type":"Point"}
}