{
  "type": "Feature",
  "properties": {
    "gn:admin1_code":"01",
    "gn:asciiname":"Muianomu",
    "gn:country_code":"PG",
    "gn:dem":191,
    "gn:feature_class":"P",
    "gn:feature_code":"PPL",
    "gn:name":"Muianomu",
    "gn:population":0,
    "gn:timezone":"Pacific/Port_Moresby",
    "iso:country":"PG",
    "name:und_x_variant":[
        "Sirum 2",
        "Muianomu"
    ],
    "wof:name":"Muianomu",
    "wof:placetype":"locality"
},
  "geometry": {"coordinates":[147.75632999999999,-9.5992],"type":"Point"}
}