{
  "type": "Feature",
  "properties": {
    "gn:admin1_code":"05",
    "gn:asciiname":"Injip",
    "gn:country_code":"PG",
    "gn:dem":1777,
    "gn:feature_class":"P",
    "gn:feature_code":"PPL",
    "gn:name":"Injip",
    "gn:population":0,
    "gn:timezone":"Pacific/Port_Moresby",
    "iso:country":"PG",
    "wof:name":"Injip",
    "wof:placetype":"locality"
},
  "geometry": {"coordinates":[143.44999999999999,-6.16667],"type":"Point"}
}