{
  "type": "Feature",
  "properties": {
    "gn:admin1_code":"02",
    "gn:asciiname":"Iosiko",
    "gn:country_code":"PG",
    "gn:dem":24,
    "gn:feature_class":"P",
    "gn:feature_code":"PPL",
    "gn:name":"Iosiko",
    "gn:population":0,
    "gn:timezone":"Pacific/Port_Moresby",
    "iso:country":"PG",
    "wof:name":"Iosiko",
    "wof:placetype":"locality"
},
  "geometry": {"coordinates":[143.68333000000001,-7.36667],"type":"Point"}
}