{
  "type": "Feature",
  "properties": {
    "gn:admin1_code":"01",
    "gn:admin2_code":"7668019",
    "gn:asciiname":"Hula",
    "gn:country_code":"PG",
    "gn:dem":11,
    "gn:feature_class":"P",
    "gn:feature_code":"PPL",
    "gn:name":"Hula",
    "gn:population":0,
    "gn:timezone":"Pacific/Port_Moresby",
    "iso:country":"PG",
    "name:afr_x_preferred":[
        "Hula"
    ],
    "name:ara_x_preferred":[
        "\u0647\u0648\u0644\u0627"
    ],
    "name:bel_x_preferred":[
        "\u0422\u0430\u043d\u0435\u0446 \u0445\u0443\u043b\u0430"
    ],
    "name:deu_x_preferred":[
        "Hula"
    ],
    "name:epo_x_preferred":[
        "Hula danco"
    ],
    "name:fas_x_preferred":[
        "\u0631\u0642\u0635 \u0647\u0648\u0644\u0627"
    ],
    "name:fin_x_preferred":[
        "Hula"
    ],
    "name:fra_x_preferred":[
        "Hula"
    ],
    "name:ind_x_preferred":[
        "Hula"
    ],
    "name:ita_x_preferred":[
        "Hula"
    ],
    "name:msa_x_preferred":[
        "Hula-hula"
    ],
    "name:nld_x_preferred":[
        "Hula"
    ],
    "name:nno_x_preferred":[
        "Hula"
    ],
    "name:pol_x_preferred":[
        "Hula"
    ],
    "name:por_x_preferred":[
        "Hula"
    ],
    "name:rus_x_preferred":[
        "\u0425\u0443\u043b\u0430"
    ],
    "name:spa_x_preferred":[
        "Hula"
    ],
    "name:tur_x_preferred":[
        "Hula dans\u0131"
    ],
    "name:ukr_x_preferred":[
        "\u0425\u0443\u043b\u0430"
    ],
    "name:zho_x_preferred":[
        "\u8349\u88d9\u821e"
    ],
    "wof:name":"Hula",
    "wof:placetype":"locality"
},
  "geometry": {"coordinates":[147.72765999999999,-10.09459],"type":"Point"}
}