{
  "type": "Feature",
  "properties": {
    "gn:admin1_code":"01",
    "gn:admin2_code":"7668019",
    "gn:asciiname":"Hula",
    "gn:country_code":"PG",
    "gn:dem":11,
    "gn:feature_class":"P",
    "gn:feature_code":"PPL",
    "gn:name":"Hula",
    "gn:population":0,
    "gn:timezone":"Pacific/Port_Moresby",
    "iso:country":"PG",
    "wof:name":"Hula",
    "wof:placetype":"locality"
},
  "geometry": {"coordinates":[147.72765999999999,-10.09459],"type":"Point"}
}