{
  "type": "Feature",
  "properties": {
    "gn:admin1_code":"07",
    "gn:asciiname":"Mupesi",
    "gn:country_code":"PG",
    "gn:dem":8,
    "gn:feature_class":"P",
    "gn:feature_code":"PPL",
    "gn:name":"Mupesi",
    "gn:population":0,
    "gn:timezone":"Pacific/Bougainville",
    "iso:country":"PG",
    "wof:name":"Mupesi",
    "wof:placetype":"locality"
},
  "geometry": {"coordinates":[155.22499999999999,-6.45],"type":"Point"}
}