{
  "type": "Feature",
  "properties": {
    "gn:admin1_code":"15",
    "gn:asciiname":"Mipang",
    "gn:country_code":"PG",
    "gn:dem":24,
    "gn:feature_class":"P",
    "gn:feature_code":"PPL",
    "gn:name":"Mipang",
    "gn:population":0,
    "gn:timezone":"Pacific/Port_Moresby",
    "iso:country":"PG",
    "wof:name":"Mipang",
    "wof:placetype":"locality"
},
  "geometry": {"coordinates":[151.14851999999999,-2.78939],"type":"Point"}
}