{
  "type": "Feature",
  "properties": {
    "gn:admin1_code":"17",
    "gn:asciiname":"Gogola",
    "gn:country_code":"PG",
    "gn:dem":31,
    "gn:feature_class":"P",
    "gn:feature_code":"PPL",
    "gn:name":"Gogola",
    "gn:population":0,
    "gn:timezone":"Pacific/Port_Moresby",
    "iso:country":"PG",
    "wof:name":"Gogola",
    "wof:placetype":"locality"
},
  "geometry": {"coordinates":[149.16666999999995,-5.58333],"type":"Point"}
}