{
  "type": "Feature",
  "properties": {
    "gn:admin1_code":"16",
    "gn:asciiname":"Korn",
    "gn:country_code":"PG",
    "gn:dem":1629,
    "gn:feature_class":"P",
    "gn:feature_code":"PPL",
    "gn:name":"Korn",
    "gn:population":0,
    "gn:timezone":"Pacific/Port_Moresby",
    "iso:country":"PG",
    "wof:name":"Korn",
    "wof:placetype":"locality"
},
  "geometry": {"coordinates":[144.30937,-5.84179],"type":"Point"}
}