{
  "type": "Feature",
  "properties": {
    "gn:admin1_code":"11",
    "gn:asciiname":"Tegoi",
    "gn:cc2":"PG",
    "gn:country_code":"PG",
    "gn:dem":7,
    "gn:feature_class":"P",
    "gn:feature_code":"PPL",
    "gn:name":"Tegoi",
    "gn:population":0,
    "gn:timezone":"Pacific/Port_Moresby",
    "iso:country":"PG",
    "name:und_x_variant":[
        "Togovi",
        "Tegoi"
    ],
    "wof:name":"Tegoi",
    "wof:placetype":"locality"
},
  "geometry": {"coordinates":[143.31666999999999,-4.21667],"type":"Point"}
}