{
  "type": "Feature",
  "properties": {
    "gn:admin1_code":"01",
    "gn:asciiname":"Kemaea",
    "gn:country_code":"PG",
    "gn:dem":162,
    "gn:feature_class":"P",
    "gn:feature_code":"PPL",
    "gn:name":"Kemaea",
    "gn:population":0,
    "gn:timezone":"Pacific/Port_Moresby",
    "iso:country":"PG",
    "name:und_x_variant":[
        "Kemaia",
        "Kemaea"
    ],
    "wof:name":"Kemaea",
    "wof:placetype":"locality"
},
  "geometry": {"coordinates":[147.57841000000005,-9.80709],"type":"Point"}
}