{
  "type": "Feature",
  "properties": {
    "gn:admin1_code":"03",
    "gn:asciiname":"Leipla",
    "gn:country_code":"PG",
    "gn:dem":47,
    "gn:feature_class":"P",
    "gn:feature_code":"PPL",
    "gn:name":"Leipla",
    "gn:population":0,
    "gn:timezone":"Pacific/Port_Moresby",
    "iso:country":"PG",
    "wof:name":"Leipla",
    "wof:placetype":"locality"
},
  "geometry": {"coordinates":[150.56666999999999,-10.55],"type":"Point"}
}