{
  "type": "Feature",
  "properties": {
    "gn:admin1_code":"05",
    "gn:asciiname":"Iaro",
    "gn:country_code":"PG",
    "gn:dem":1882,
    "gn:feature_class":"P",
    "gn:feature_code":"PPL",
    "gn:name":"Iaro",
    "gn:population":0,
    "gn:timezone":"Pacific/Port_Moresby",
    "iso:country":"PG",
    "wof:name":"Iaro",
    "wof:placetype":"locality"
},
  "geometry": {"coordinates":[144.07841999999999,-6.45297],"type":"Point"}
}