{
  "type": "Feature",
  "properties": {
    "gn:admin1_code":"05",
    "gn:asciiname":"Pinjib",
    "gn:country_code":"PG",
    "gn:dem":1840,
    "gn:feature_class":"P",
    "gn:feature_code":"PPL",
    "gn:name":"Pinjib",
    "gn:population":0,
    "gn:timezone":"Pacific/Port_Moresby",
    "iso:country":"PG",
    "name:und_x_variant":[
        "Pinjip",
        "Pinjib"
    ],
    "wof:name":"Pinjib",
    "wof:placetype":"locality"
},
  "geometry": {"coordinates":[143.37275,-6.24044],"type":"Point"}
}