{
  "type": "Feature",
  "properties": {
    "gn:admin1_code":"14",
    "gn:asciiname":"Etep",
    "gn:country_code":"PG",
    "gn:dem":765,
    "gn:feature_class":"P",
    "gn:feature_code":"PPL",
    "gn:name":"Etep",
    "gn:population":0,
    "gn:timezone":"Pacific/Port_Moresby",
    "iso:country":"PG",
    "wof:name":"Etep",
    "wof:placetype":"locality"
},
  "geometry": {"coordinates":[147.19999999999999,-6.03333],"type":"Point"}
}