{
  "type": "Feature",
  "properties": {
    "gn:admin1_code":"01",
    "gn:asciiname":"Gomore",
    "gn:country_code":"PG",
    "gn:dem":43,
    "gn:feature_class":"P",
    "gn:feature_code":"PPL",
    "gn:name":"Gomore",
    "gn:population":0,
    "gn:timezone":"Pacific/Port_Moresby",
    "iso:country":"PG",
    "wof:name":"Gomore",
    "wof:placetype":"locality"
},
  "geometry": {"coordinates":[147.56188,-9.79703],"type":"Point"}
}