{
  "type": "Feature",
  "properties": {
    "gn:admin1_code":"05",
    "gn:asciiname":"Iarena",
    "gn:country_code":"PG",
    "gn:dem":1923,
    "gn:feature_class":"P",
    "gn:feature_code":"PPL",
    "gn:name":"Iarena",
    "gn:population":0,
    "gn:timezone":"Pacific/Port_Moresby",
    "iso:country":"PG",
    "wof:name":"Iarena",
    "wof:placetype":"locality"
},
  "geometry": {"coordinates":[143.93333000000001,-6.31667],"type":"Point"}
}