{
  "type": "Feature",
  "properties": {
    "gn:admin1_code":"04",
    "gn:asciiname":"Marasa",
    "gn:country_code":"PG",
    "gn:dem":1,
    "gn:feature_class":"P",
    "gn:feature_code":"PPL",
    "gn:name":"Marasa",
    "gn:population":0,
    "gn:timezone":"Pacific/Port_Moresby",
    "iso:country":"PG",
    "wof:name":"Marasa",
    "wof:placetype":"locality"
},
  "geometry": {"coordinates":[149.25913,-9.17923],"type":"Point"}
}