{
  "type": "Feature",
  "properties": {
    "gn:admin1_code":"06",
    "gn:asciiname":"Unewa",
    "gn:country_code":"PG",
    "gn:dem":44,
    "gn:feature_class":"P",
    "gn:feature_code":"PPL",
    "gn:name":"Unewa",
    "gn:population":0,
    "gn:timezone":"Pacific/Port_Moresby",
    "iso:country":"PG",
    "wof:name":"Unewa",
    "wof:placetype":"locality"
},
  "geometry": {"coordinates":[141.44999999999999,-6.58333],"type":"Point"}
}