{
  "type": "Feature",
  "properties": {
    "gn:admin1_code":"08",
    "gn:asciiname":"Bianggau",
    "gn:country_code":"PG",
    "gn:dem":1942,
    "gn:feature_class":"P",
    "gn:feature_code":"PPL",
    "gn:name":"Bianggau",
    "gn:population":0,
    "gn:timezone":"Pacific/Port_Moresby",
    "iso:country":"PG",
    "wof:name":"Bianggau",
    "wof:placetype":"locality"
},
  "geometry": {"coordinates":[144.93256,-6.07311],"type":"Point"}
}