{
  "type": "Feature",
  "properties": {
    "gn:admin1_code":"18",
    "gn:asciiname":"Kumalvu",
    "gn:country_code":"PG",
    "gn:dem":321,
    "gn:feature_class":"P",
    "gn:feature_code":"PPL",
    "gn:name":"Kumalvu",
    "gn:population":0,
    "gn:timezone":"Pacific/Port_Moresby",
    "iso:country":"PG",
    "wof:name":"Kumalvu",
    "wof:placetype":"locality"
},
  "geometry": {"coordinates":[142.48136,-3.59775],"type":"Point"}
}