{
  "type": "Feature",
  "properties": {
    "gn:admin1_code":"15",
    "gn:asciiname":"Rukaliklik",
    "gn:country_code":"PG",
    "gn:dem":-9999,
    "gn:feature_class":"P",
    "gn:feature_code":"PPL",
    "gn:name":"Rukaliklik",
    "gn:population":0,
    "gn:timezone":"Pacific/Port_Moresby",
    "iso:country":"PG",
    "name:und_x_variant":[
        "Rukalik",
        "Rukaliklik"
    ],
    "wof:name":"Rukaliklik",
    "wof:placetype":"locality"
},
  "geometry": {"coordinates":[152.86546000000001,-3.98095],"type":"Point"}
}