{
  "type": "Feature",
  "properties": {
    "gn:admin1_code":"10",
    "gn:asciiname":"Malakur",
    "gn:country_code":"PG",
    "gn:dem":57,
    "gn:feature_class":"P",
    "gn:feature_code":"PPL",
    "gn:name":"Malakur",
    "gn:population":0,
    "gn:timezone":"Pacific/Port_Moresby",
    "iso:country":"PG",
    "name:und_x_variant":[
        "Malakua",
        "Malakuna",
        "Malakur"
    ],
    "wof:name":"Malakur",
    "wof:placetype":"locality"
},
  "geometry": {"coordinates":[151.44099,-5.56112],"type":"Point"}
}