{
  "type": "Feature",
  "properties": {
    "gn:admin1_code":"09",
    "gn:asciiname":"Iuwane",
    "gn:country_code":"PG",
    "gn:dem":1716,
    "gn:feature_class":"P",
    "gn:feature_code":"PPL",
    "gn:name":"Iuwane",
    "gn:population":0,
    "gn:timezone":"Pacific/Port_Moresby",
    "iso:country":"PG",
    "wof:name":"Iuwane",
    "wof:placetype":"locality"
},
  "geometry": {"coordinates":[145.65000000000001,-6.91667],"type":"Point"}
}