{
  "type": "Feature",
  "properties": {
    "gn:admin1_code":"15",
    "gn:asciiname":"Hibaling",
    "gn:country_code":"PG",
    "gn:dem":71,
    "gn:feature_class":"P",
    "gn:feature_code":"PPL",
    "gn:name":"Hibaling",
    "gn:population":0,
    "gn:timezone":"Pacific/Port_Moresby",
    "iso:country":"PG",
    "wof:name":"Hibaling",
    "wof:placetype":"locality"
},
  "geometry": {"coordinates":[152.62782000000001,-3.83128],"type":"Point"}
}