{
  "type": "Feature",
  "properties": {
    "gn:admin1_code":"15",
    "gn:asciiname":"Sewason",
    "gn:country_code":"PG",
    "gn:dem":-9999,
    "gn:feature_class":"P",
    "gn:feature_code":"PPL",
    "gn:name":"Sewason",
    "gn:population":0,
    "gn:timezone":"Pacific/Port_Moresby",
    "iso:country":"PG",
    "wof:name":"Sewason",
    "wof:placetype":"locality"
},
  "geometry": {"coordinates":[151.93333000000001,-2.65],"type":"Point"}
}