{
  "type": "Feature",
  "properties": {
    "gn:admin1_code":"11",
    "gn:asciiname":"Aman",
    "gn:country_code":"PG",
    "gn:dem":640,
    "gn:feature_class":"P",
    "gn:feature_code":"PPL",
    "gn:name":"Aman",
    "gn:population":0,
    "gn:timezone":"Pacific/Port_Moresby",
    "iso:country":"PG",
    "name:ara_x_preferred":[
        "\u0623\u0645\u0627\u0646"
    ],
    "name:bul_x_preferred":[
        "\u0410\u043c\u0430\u043d"
    ],
    "name:ceb_x_preferred":[
        "Aman"
    ],
    "name:ces_x_preferred":[
        "Aman"
    ],
    "name:dan_x_preferred":[
        "Aman"
    ],
    "name:deu_x_preferred":[
        "Aman"
    ],
    "name:fas_x_preferred":[
        "\u0622\u0645\u0627\u0646"
    ],
    "name:fra_x_preferred":[
        "Aman"
    ],
    "name:ita_x_preferred":[
        "Aman"
    ],
    "name:jpn_x_preferred":[
        "\u30a2\u30de\u30f3"
    ],
    "name:pol_x_preferred":[
        "Aman"
    ],
    "name:por_x_preferred":[
        "Aman"
    ],
    "name:ron_x_preferred":[
        "Aman"
    ],
    "name:rus_x_preferred":[
        "\u0410\u043c\u0430\u043d"
    ],
    "name:slv_x_preferred":[
        "Aman"
    ],
    "name:spa_x_preferred":[
        "Aman"
    ],
    "name:swe_x_preferred":[
        "Aman"
    ],
    "name:tur_x_preferred":[
        "Aman"
    ],
    "name:ukr_x_preferred":[
        "\u0410\u043c\u0430\u043d"
    ],
    "name:und_x_variant":[
        "Amam"
    ],
    "wof:name":"Aman",
    "wof:placetype":"locality"
},
  "geometry": {"coordinates":[142.97843999999995,-3.5246],"type":"Point"}
}