{
  "type": "Feature",
  "properties": {
    "gn:admin1_code":"11",
    "gn:asciiname":"Aman",
    "gn:country_code":"PG",
    "gn:dem":640,
    "gn:feature_class":"P",
    "gn:feature_code":"PPL",
    "gn:name":"Aman",
    "gn:population":0,
    "gn:timezone":"Pacific/Port_Moresby",
    "iso:country":"PG",
    "name:und_x_variant":[
        "Amam",
        "Aman"
    ],
    "wof:name":"Aman",
    "wof:placetype":"locality"
},
  "geometry": {"coordinates":[142.97843999999995,-3.5246],"type":"Point"}
}