{
  "type": "Feature",
  "properties": {
    "gn:admin1_code":"17",
    "gn:asciiname":"Talasea",
    "gn:country_code":"PG",
    "gn:dem":20,
    "gn:feature_class":"P",
    "gn:feature_code":"PPL",
    "gn:name":"Talasea",
    "gn:population":0,
    "gn:timezone":"Pacific/Port_Moresby",
    "iso:country":"PG",
    "name:und_x_variant":[
        "Garua Harbour",
        "Talasfa",
        "Hannam Harbour",
        "Talasea"
    ],
    "wof:name":"Talasea",
    "wof:placetype":"locality"
},
  "geometry": {"coordinates":[150.01131000000001,-5.27985],"type":"Point"}
}