{
  "type": "Feature",
  "properties": {
    "gn:admin1_code":"18",
    "gn:asciiname":"Bipan",
    "gn:country_code":"PG",
    "gn:dem":297,
    "gn:feature_class":"P",
    "gn:feature_code":"PPL",
    "gn:name":"Bipan",
    "gn:population":0,
    "gn:timezone":"Pacific/Port_Moresby",
    "iso:country":"PG",
    "wof:name":"Bipan",
    "wof:placetype":"locality"
},
  "geometry": {"coordinates":[141.22583,-3.49144],"type":"Point"}
}