{
  "type": "Feature",
  "properties": {
    "gn:admin1_code":"17",
    "gn:asciiname":"Bali",
    "gn:country_code":"PG",
    "gn:dem":12,
    "gn:feature_class":"P",
    "gn:feature_code":"PPL",
    "gn:name":"Bali",
    "gn:population":0,
    "gn:timezone":"Pacific/Port_Moresby",
    "iso:country":"PG",
    "wof:name":"Bali",
    "wof:placetype":"locality"
},
  "geometry": {"coordinates":[149.13459,-4.92217],"type":"Point"}
}