{
  "type": "Feature",
  "properties": {
    "iso:country":"PG",
    "name:ceb_x_preferred":[
        "Buin"
    ],
    "name:eng_x_preferred":[
        "Buin"
    ],
    "name:fas_x_preferred":[
        "\u0628\u0648\u0626\u06cc\u0646"
    ],
    "name:fra_x_preferred":[
        "Buin"
    ],
    "name:ita_x_preferred":[
        "Buin"
    ],
    "name:jpn_x_preferred":[
        "\u30d6\u30a4\u30f3"
    ],
    "name:kor_x_preferred":[
        "\ubd80\uc778"
    ],
    "name:nld_x_preferred":[
        "Buin"
    ],
    "name:ukr_x_preferred":[
        "\u0411\u0443\u0457\u043d"
    ],
    "name:zho_x_preferred":[
        "\u5e03\u56e0"
    ],
    "qs:gn_country":"PG",
    "qs:gn_fcode":"PPL",
    "qs:gn_pop":750,
    "qs:name":"Buin",
    "qs:name_adm0":"Papua New Guinea",
    "qs:name_adm1":"North Solomons",
    "qs:photos":0,
    "qs:photos_1k":0,
    "qs:photos_9k":1,
    "qs:photos_9r":1,
    "qs:photos_all":1,
    "qs:photos_sr":0,
    "qs:placetype":"Town",
    "qs:pop_sr":"2",
    "qs:woe_adm0":23424926,
    "wd:wordcount":4070,
    "wof:name":"Buin",
    "wof:placetype":"locality",
    "wof:population":750
},
  "geometry": {"coordinates":[155.66147000000001,-6.73362],"type":"Point"}
}