{
  "type": "Feature",
  "properties": {
    "gn:admin1_code":"15",
    "gn:asciiname":"Neikapatuk",
    "gn:country_code":"PG",
    "gn:dem":111,
    "gn:feature_class":"P",
    "gn:feature_code":"PPL",
    "gn:name":"Neikapatuk",
    "gn:population":0,
    "gn:timezone":"Pacific/Port_Moresby",
    "iso:country":"PG",
    "wof:name":"Neikapatuk",
    "wof:placetype":"locality"
},
  "geometry": {"coordinates":[150.40000000000001,-2.65],"type":"Point"}
}