{
  "type": "Feature",
  "properties": {
    "gn:admin1_code":"11",
    "gn:asciiname":"Saulik",
    "gn:country_code":"PG",
    "gn:dem":278,
    "gn:feature_class":"P",
    "gn:feature_code":"PPL",
    "gn:name":"Saulik",
    "gn:population":0,
    "gn:timezone":"Pacific/Port_Moresby",
    "iso:country":"PG",
    "wof:name":"Saulik",
    "wof:placetype":"locality"
},
  "geometry": {"coordinates":[143.02843999999999,-3.58753],"type":"Point"}
}