{
  "type": "Feature",
  "properties": {
    "gn:admin1_code":"15",
    "gn:asciiname":"Pakene",
    "gn:country_code":"PG",
    "gn:dem":16,
    "gn:feature_class":"P",
    "gn:feature_code":"PPL",
    "gn:name":"Pakene",
    "gn:population":0,
    "gn:timezone":"Pacific/Port_Moresby",
    "iso:country":"PG",
    "name:und_x_variant":[
        "Pakane",
        "Pakene"
    ],
    "wof:name":"Pakene",
    "wof:placetype":"locality"
},
  "geometry": {"coordinates":[149.92938000000001,-1.66951],"type":"Point"}
}