{
  "type": "Feature",
  "properties": {
    "gn:admin1_code":"18",
    "gn:asciiname":"Laiangim 2",
    "gn:country_code":"PG",
    "gn:dem":547,
    "gn:feature_class":"P",
    "gn:feature_code":"PPL",
    "gn:name":"Laiangim 2",
    "gn:population":0,
    "gn:timezone":"Pacific/Port_Moresby",
    "iso:country":"PG",
    "wof:name":"Laiangim 2",
    "wof:placetype":"locality"
},
  "geometry": {"coordinates":[142.22824,-3.51232],"type":"Point"}
}