{
  "type": "Feature",
  "properties": {
    "gn:admin1_code":"14",
    "gn:asciiname":"Sangas",
    "gn:country_code":"PG",
    "gn:dem":734,
    "gn:feature_class":"P",
    "gn:feature_code":"PPL",
    "gn:name":"Sangas",
    "gn:population":0,
    "gn:timezone":"Pacific/Port_Moresby",
    "iso:country":"PG",
    "wof:name":"Sangas",
    "wof:placetype":"locality"
},
  "geometry": {"coordinates":[146.64067,-7.10737],"type":"Point"}
}