{
  "type": "Feature",
  "properties": {
    "gn:admin1_code":"06",
    "gn:asciiname":"Korombo",
    "gn:country_code":"PG",
    "gn:dem":30,
    "gn:feature_class":"P",
    "gn:feature_code":"PPL",
    "gn:name":"Korombo",
    "gn:population":0,
    "gn:timezone":"Pacific/Port_Moresby",
    "iso:country":"PG",
    "name:und_x_variant":[
        "Korumbo",
        "Korombo"
    ],
    "wof:name":"Korombo",
    "wof:placetype":"locality"
},
  "geometry": {"coordinates":[141.30071999999996,-8.73603],"type":"Point"}
}