{
  "type": "Feature",
  "properties": {
    "gn:admin1_code":"15",
    "gn:asciiname":"Rasirik",
    "gn:country_code":"PG",
    "gn:dem":240,
    "gn:feature_class":"P",
    "gn:feature_code":"PPL",
    "gn:name":"Rasirik",
    "gn:population":0,
    "gn:timezone":"Pacific/Port_Moresby",
    "iso:country":"PG",
    "name:und_x_variant":[
        "Rasarik",
        "Rasirik"
    ],
    "wof:name":"Rasirik",
    "wof:placetype":"locality"
},
  "geometry": {"coordinates":[152.35847999999999,-3.67635],"type":"Point"}
}