{
  "type": "Feature",
  "properties": {
    "gn:admin1_code":"15",
    "gn:asciiname":"Daskigi",
    "gn:country_code":"PG",
    "gn:dem":16,
    "gn:feature_class":"P",
    "gn:feature_code":"PPL",
    "gn:name":"Daskigi",
    "gn:population":0,
    "gn:timezone":"Pacific/Port_Moresby",
    "iso:country":"PG",
    "wof:name":"Daskigi",
    "wof:placetype":"locality"
},
  "geometry": {"coordinates":[151.67175,-3.05434],"type":"Point"}
}