{
  "type": "Feature",
  "properties": {
    "gn:admin1_code":"09",
    "gn:asciiname":"Arovaraisa",
    "gn:country_code":"PG",
    "gn:dem":1857,
    "gn:feature_class":"P",
    "gn:feature_code":"PPL",
    "gn:name":"Arovaraisa",
    "gn:population":0,
    "gn:timezone":"Pacific/Port_Moresby",
    "iso:country":"PG",
    "wof:name":"Arovaraisa",
    "wof:placetype":"locality"
},
  "geometry": {"coordinates":[145.44351,-6.58406],"type":"Point"}
}