{
  "type": "Feature",
  "properties": {
    "gn:admin1_code":"12",
    "gn:asciiname":"Ginam",
    "gn:country_code":"PG",
    "gn:dem":125,
    "gn:feature_class":"P",
    "gn:feature_code":"PPL",
    "gn:name":"Ginam",
    "gn:population":0,
    "gn:timezone":"Pacific/Port_Moresby",
    "iso:country":"PG",
    "wof:name":"Ginam",
    "wof:placetype":"locality"
},
  "geometry": {"coordinates":[145.26667,-5.58333],"type":"Point"}
}