{
  "type": "Feature",
  "properties": {
    "gn:admin1_code":"09",
    "gn:asciiname":"Mani-Hurai",
    "gn:country_code":"PG",
    "gn:dem":2146,
    "gn:feature_class":"P",
    "gn:feature_code":"PPL",
    "gn:name":"Mani-Hurai",
    "gn:population":0,
    "gn:timezone":"Pacific/Port_Moresby",
    "iso:country":"PG",
    "name:und_x_variant":[
        "Osavitei",
        "Mani-Hurai"
    ],
    "wof:name":"Mani-Hurai",
    "wof:placetype":"locality"
},
  "geometry": {"coordinates":[145.36252999999999,-6.51349],"type":"Point"}
}