{
  "type": "Feature",
  "properties": {
    "gn:admin1_code":"08",
    "gn:asciiname":"Komagam",
    "gn:country_code":"PG",
    "gn:dem":1986,
    "gn:feature_class":"P",
    "gn:feature_code":"PPL",
    "gn:name":"Komagam",
    "gn:population":0,
    "gn:timezone":"Pacific/Port_Moresby",
    "iso:country":"PG",
    "wof:name":"Komagam",
    "wof:placetype":"locality"
},
  "geometry": {"coordinates":[145.13325,-6.16612],"type":"Point"}
}