{
  "type": "Feature",
  "properties": {
    "gn:admin1_code":"02",
    "gn:asciiname":"Kaingo",
    "gn:country_code":"PG",
    "gn:dem":1345,
    "gn:feature_class":"P",
    "gn:feature_code":"PPL",
    "gn:name":"Kaingo",
    "gn:population":0,
    "gn:timezone":"Pacific/Port_Moresby",
    "iso:country":"PG",
    "wof:name":"Kaingo",
    "wof:placetype":"locality"
},
  "geometry": {"coordinates":[146.01667,-7.43333],"type":"Point"}
}