{
  "type": "Feature",
  "properties": {
    "gn:admin1_code":"15",
    "gn:asciiname":"Matakan Mission",
    "gn:country_code":"PG",
    "gn:dem":23,
    "gn:feature_class":"P",
    "gn:feature_code":"PPL",
    "gn:name":"Matakan Mission",
    "gn:population":0,
    "gn:timezone":"Pacific/Port_Moresby",
    "iso:country":"PG",
    "wof:name":"Matakan Mission",
    "wof:placetype":"locality"
},
  "geometry": {"coordinates":[152.44212999999999,-3.80825],"type":"Point"}
}