{
  "type": "Feature",
  "properties": {
    "gn:admin1_code":"11",
    "gn:asciiname":"Abauia 1",
    "gn:country_code":"PG",
    "gn:dem":284,
    "gn:feature_class":"P",
    "gn:feature_code":"PPL",
    "gn:name":"Abauia 1",
    "gn:population":0,
    "gn:timezone":"Pacific/Port_Moresby",
    "iso:country":"PG",
    "name:und_x_variant":[
        "Abauia",
        "Abauia 1"
    ],
    "wof:name":"Abauia 1",
    "wof:placetype":"locality"
},
  "geometry": {"coordinates":[143.43048000000005,-3.70241],"type":"Point"}
}