{
  "type": "Feature",
  "properties": {
    "gn:admin1_code":"12",
    "gn:asciiname":"Damanti",
    "gn:country_code":"PG",
    "gn:dem":1286,
    "gn:feature_class":"P",
    "gn:feature_code":"PPL",
    "gn:name":"Damanti",
    "gn:population":0,
    "gn:timezone":"Pacific/Port_Moresby",
    "iso:country":"PG",
    "wof:name":"Damanti",
    "wof:placetype":"locality"
},
  "geometry": {"coordinates":[145.96493000000001,-5.91696],"type":"Point"}
}