{
  "type": "Feature",
  "properties": {
    "gn:admin1_code":"14",
    "gn:admin2_code":"8657188",
    "gn:asciiname":"Omalai",
    "gn:country_code":"PG",
    "gn:dem":521,
    "gn:feature_class":"P",
    "gn:feature_code":"PPL",
    "gn:name":"Omalai",
    "gn:population":0,
    "gn:timezone":"Pacific/Port_Moresby",
    "iso:country":"PG",
    "name:und_x_variant":[
        "Omala",
        "Omalai"
    ],
    "wof:name":"Omalai",
    "wof:placetype":"locality"
},
  "geometry": {"coordinates":[146.60959,-6.82549],"type":"Point"}
}