{
  "type": "Feature",
  "properties": {
    "gn:admin1_code":"10",
    "gn:asciiname":"Paliavalu",
    "gn:country_code":"PG",
    "gn:dem":120,
    "gn:feature_class":"P",
    "gn:feature_code":"PPL",
    "gn:name":"Paliavalu",
    "gn:population":0,
    "gn:timezone":"Pacific/Port_Moresby",
    "iso:country":"PG",
    "wof:name":"Paliavalu",
    "wof:placetype":"locality"
},
  "geometry": {"coordinates":[151.18333000000001,-5.75],"type":"Point"}
}