{
  "type": "Feature",
  "properties": {
    "gn:admin1_code":"12",
    "gn:asciiname":"Mangar Number 2",
    "gn:country_code":"PG",
    "gn:dem":73,
    "gn:feature_class":"P",
    "gn:feature_code":"PPL",
    "gn:name":"Mangar Number 2",
    "gn:population":0,
    "gn:timezone":"Pacific/Port_Moresby",
    "iso:country":"PG",
    "wof:name":"Mangar Number 2",
    "wof:placetype":"locality"
},
  "geometry": {"coordinates":[145.87998000000005,-4.66908],"type":"Point"}
}