{
  "type": "Feature",
  "properties": {
    "gn:admin1_code":"06",
    "gn:asciiname":"Gubam",
    "gn:country_code":"PG",
    "gn:dem":28,
    "gn:feature_class":"P",
    "gn:feature_code":"PPL",
    "gn:name":"Gubam",
    "gn:population":0,
    "gn:timezone":"Pacific/Port_Moresby",
    "iso:country":"PG",
    "wof:name":"Gubam",
    "wof:placetype":"locality"
},
  "geometry": {"coordinates":[141.87781000000001,-8.64396],"type":"Point"}
}