{
  "type": "Feature",
  "properties": {
    "gn:admin1_code":"17",
    "gn:asciiname":"Tekarapana",
    "gn:cc2":"PG",
    "gn:country_code":"PG",
    "gn:dem":119,
    "gn:feature_class":"P",
    "gn:feature_code":"PPL",
    "gn:name":"Tekarapana",
    "gn:population":0,
    "gn:timezone":"Pacific/Port_Moresby",
    "iso:country":"PG",
    "name:und_x_variant":[
        "Tekerapna",
        "Tekarapana"
    ],
    "wof:name":"Tekarapana",
    "wof:placetype":"locality"
},
  "geometry": {"coordinates":[149.21666999999999,-5.98333],"type":"Point"}
}