{
  "type": "Feature",
  "properties": {
    "gn:admin1_code":"18",
    "gn:asciiname":"Gwidami",
    "gn:country_code":"PG",
    "gn:dem":53,
    "gn:feature_class":"P",
    "gn:feature_code":"PPL",
    "gn:name":"Gwidami",
    "gn:population":0,
    "gn:timezone":"Pacific/Port_Moresby",
    "iso:country":"PG",
    "wof:name":"Gwidami",
    "wof:placetype":"locality"
},
  "geometry": {"coordinates":[141.73436000000001,-3.8597],"type":"Point"}
}