{
  "type": "Feature",
  "properties": {
    "gn:admin1_code":"03",
    "gn:asciiname":"Banapa",
    "gn:country_code":"PG",
    "gn:dem":33,
    "gn:feature_class":"P",
    "gn:feature_code":"PPL",
    "gn:name":"Banapa",
    "gn:population":0,
    "gn:timezone":"Pacific/Port_Moresby",
    "iso:country":"PG",
    "wof:name":"Banapa",
    "wof:placetype":"locality"
},
  "geometry": {"coordinates":[149.96868999999995,-9.7451],"type":"Point"}
}