{
  "type": "Feature",
  "properties": {
    "gn:admin1_code":"14",
    "gn:asciiname":"Kangulat",
    "gn:country_code":"PG",
    "gn:dem":2581,
    "gn:feature_class":"P",
    "gn:feature_code":"PPL",
    "gn:name":"Kangulat",
    "gn:population":0,
    "gn:timezone":"Pacific/Port_Moresby",
    "iso:country":"PG",
    "name:und_x_variant":[
        "Kangalut",
        "Kangulat"
    ],
    "wof:name":"Kangulat",
    "wof:placetype":"locality"
},
  "geometry": {"coordinates":[146.58340999999999,-5.95707],"type":"Point"}
}