{
  "type": "Feature",
  "properties": {
    "gn:admin1_code":"18",
    "gn:asciiname":"Marakwini",
    "gn:country_code":"PG",
    "gn:dem":89,
    "gn:feature_class":"P",
    "gn:feature_code":"PPL",
    "gn:name":"Marakwini",
    "gn:population":0,
    "gn:timezone":"Pacific/Port_Moresby",
    "iso:country":"PG",
    "name:und_x_variant":[
        "Morakuinina",
        "Marakwini"
    ],
    "wof:name":"Marakwini",
    "wof:placetype":"locality"
},
  "geometry": {"coordinates":[141.52401,-3.70514],"type":"Point"}
}