{
  "type": "Feature",
  "properties": {
    "gn:admin1_code":"12",
    "gn:asciiname":"Saidor",
    "gn:country_code":"PG",
    "gn:dem":32,
    "gn:feature_class":"P",
    "gn:feature_code":"PPL",
    "gn:name":"Saidor",
    "gn:population":0,
    "gn:timezone":"Pacific/Port_Moresby",
    "iso:country":"PG",
    "name:epo_x_preferred":[
        "Saidor"
    ],
    "name:spa_x_preferred":[
        "Saidor"
    ],
    "wof:name":"Saidor",
    "wof:placetype":"locality"
},
  "geometry": {"coordinates":[146.45831999999999,-5.62831],"type":"Point"}
}