{
  "type": "Feature",
  "properties": {
    "gn:admin1_code":"06",
    "gn:asciiname":"Mavlok",
    "gn:country_code":"PG",
    "gn:dem":5,
    "gn:feature_class":"P",
    "gn:feature_code":"PPL",
    "gn:name":"Mavlok",
    "gn:population":0,
    "gn:timezone":"Pacific/Port_Moresby",
    "iso:country":"PG",
    "name:eng_x_preferred":[
        "Mavlok"
    ],
    "wof:name":"Mavlok",
    "wof:placetype":"locality"
},
  "geometry": {"coordinates":[141.61809,-9.20424],"type":"Point"}
}