{
  "type": "Feature",
  "properties": {
    "gn:admin1_code":"19",
    "gn:asciiname":"Peragoia",
    "gn:country_code":"PG",
    "gn:dem":1389,
    "gn:feature_class":"P",
    "gn:feature_code":"PPL",
    "gn:name":"Peragoia",
    "gn:population":0,
    "gn:timezone":"Pacific/Port_Moresby",
    "iso:country":"PG",
    "wof:name":"Peragoia",
    "wof:placetype":"locality"
},
  "geometry": {"coordinates":[142.51879,-5.3979],"type":"Point"}
}