{
  "type": "Feature",
  "properties": {
    "gn:admin1_code":"05",
    "gn:asciiname":"Yo'obo",
    "gn:country_code":"PG",
    "gn:dem":827,
    "gn:feature_class":"P",
    "gn:feature_code":"PPL",
    "gn:name":"Yo\u2019obo",
    "gn:population":0,
    "gn:timezone":"Pacific/Port_Moresby",
    "iso:country":"PG",
    "wof:name":"Yo'obo",
    "wof:placetype":"locality"
},
  "geometry": {"coordinates":[143.33333000000005,-6.41667],"type":"Point"}
}