{
  "type": "Feature",
  "properties": {
    "gn:admin1_code":"08",
    "gn:asciiname":"Kumbaro",
    "gn:country_code":"PG",
    "gn:dem":1852,
    "gn:feature_class":"P",
    "gn:feature_code":"PPL",
    "gn:name":"Kumbaro",
    "gn:population":0,
    "gn:timezone":"Pacific/Port_Moresby",
    "iso:country":"PG",
    "wof:name":"Kumbaro",
    "wof:placetype":"locality"
},
  "geometry": {"coordinates":[145.19999999999999,-6.15],"type":"Point"}
}