{
  "type": "Feature",
  "properties": {
    "gn:admin1_code":"01",
    "gn:asciiname":"Sivil",
    "gn:cc2":"PG",
    "gn:country_code":"PG",
    "gn:dem":1581,
    "gn:feature_class":"P",
    "gn:feature_code":"PPL",
    "gn:name":"Sivil",
    "gn:population":0,
    "gn:timezone":"Pacific/Port_Moresby",
    "iso:country":"PG",
    "name:und_x_variant":[
        "Baruku",
        "Sivil"
    ],
    "wof:name":"Sivil",
    "wof:placetype":"locality"
},
  "geometry": {"coordinates":[147.25,-8.61667],"type":"Point"}
}