{
  "type": "Feature",
  "properties": {
    "gn:admin1_code":"09",
    "gn:asciiname":"Hepavina",
    "gn:country_code":"PG",
    "gn:dem":1791,
    "gn:feature_class":"P",
    "gn:feature_code":"PPL",
    "gn:name":"Hepavina",
    "gn:population":0,
    "gn:timezone":"Pacific/Port_Moresby",
    "iso:country":"PG",
    "wof:name":"Hepavina",
    "wof:placetype":"locality"
},
  "geometry": {"coordinates":[145.44999999999999,-6.55],"type":"Point"}
}