{
  "type": "Feature",
  "properties": {
    "gn:admin1_code":"05",
    "gn:asciiname":"Kume",
    "gn:country_code":"PG",
    "gn:dem":1876,
    "gn:feature_class":"P",
    "gn:feature_code":"PPL",
    "gn:name":"Kume",
    "gn:population":0,
    "gn:timezone":"Pacific/Port_Moresby",
    "iso:country":"PG",
    "wof:name":"Kume",
    "wof:placetype":"locality"
},
  "geometry": {"coordinates":[144.07624999999999,-6.11896],"type":"Point"}
}