{
  "type": "Feature",
  "properties": {
    "gn:admin1_code":"07",
    "gn:asciiname":"Torokina",
    "gn:cc2":"PG",
    "gn:country_code":"PG",
    "gn:dem":15,
    "gn:feature_class":"P",
    "gn:feature_code":"PPL",
    "gn:name":"Torokina",
    "gn:population":0,
    "gn:timezone":"Pacific/Bougainville",
    "iso:country":"PG",
    "name:eng_x_preferred":[
        "Torokina"
    ],
    "name:fas_x_preferred":[
        "\u062a\u0648\u0631\u0648\u06a9\u06cc\u0646\u0627"
    ],
    "name:und_x_variant":[
        "Torakina"
    ],
    "wof:name":"Torokina",
    "wof:placetype":"locality"
},
  "geometry": {"coordinates":[155.05000000000001,-6.23333],"type":"Point"}
}