{
  "type": "Feature",
  "properties": {
    "gn:admin1_code":"18",
    "gn:asciiname":"Flobum",
    "gn:country_code":"PG",
    "gn:dem":698,
    "gn:feature_class":"P",
    "gn:feature_code":"PPL",
    "gn:name":"Flobum",
    "gn:population":0,
    "gn:timezone":"Pacific/Port_Moresby",
    "iso:country":"PG",
    "wof:name":"Flobum",
    "wof:placetype":"locality"
},
  "geometry": {"coordinates":[142.07778000000005,-3.43957],"type":"Point"}
}