{
  "type": "Feature",
  "properties": {
    "gn:admin1_code":"18",
    "gn:asciiname":"Kuauk Baru",
    "gn:country_code":"PG",
    "gn:dem":632,
    "gn:feature_class":"P",
    "gn:feature_code":"PPL",
    "gn:name":"Kuauk Baru",
    "gn:population":0,
    "gn:timezone":"Pacific/Port_Moresby",
    "iso:country":"PG",
    "name:und_x_variant":[
        "Kok",
        "Kuauk Baru"
    ],
    "wof:name":"Kuauk Baru",
    "wof:placetype":"locality"
},
  "geometry": {"coordinates":[141.01058999999995,-3.23954],"type":"Point"}
}