{
  "type": "Feature",
  "properties": {
    "gn:admin1_code":"04",
    "gn:asciiname":"Angorogo",
    "gn:country_code":"PG",
    "gn:dem":23,
    "gn:feature_class":"P",
    "gn:feature_code":"PPL",
    "gn:name":"Angorogo",
    "gn:population":0,
    "gn:timezone":"Pacific/Port_Moresby",
    "iso:country":"PG",
    "wof:name":"Angorogo",
    "wof:placetype":"locality"
},
  "geometry": {"coordinates":[149.09887000000001,-9.02247],"type":"Point"}
}