{
  "type": "Feature",
  "properties": {
    "gn:admin1_code":"06",
    "gn:asciiname":"Old Somaidemasuk",
    "gn:cc2":"PG",
    "gn:country_code":"PG",
    "gn:dem":59,
    "gn:feature_class":"P",
    "gn:feature_code":"PPL",
    "gn:name":"Old Somaidemasuk",
    "gn:population":0,
    "gn:timezone":"Pacific/Port_Moresby",
    "iso:country":"PG",
    "name:und_x_variant":[
        "Somaidemasuk",
        "Old Somaidemasuk"
    ],
    "wof:name":"Old Somaidemasuk",
    "wof:placetype":"locality"
},
  "geometry": {"coordinates":[141.33333000000005,-5.91667],"type":"Point"}
}