{
  "type": "Feature",
  "properties": {
    "gn:admin1_code":"15",
    "gn:asciiname":"Tasingina",
    "gn:country_code":"PG",
    "gn:dem":10,
    "gn:feature_class":"P",
    "gn:feature_code":"PPL",
    "gn:name":"Tasingina",
    "gn:population":0,
    "gn:timezone":"Pacific/Port_Moresby",
    "iso:country":"PG",
    "name:und_x_variant":[
        "Tasagina",
        "Tasingina"
    ],
    "wof:name":"Tasingina",
    "wof:placetype":"locality"
},
  "geometry": {"coordinates":[149.98441,-1.68206],"type":"Point"}
}