{
  "type": "Feature",
  "properties": {
    "gn:admin1_code":"14",
    "gn:asciiname":"Anggaie",
    "gn:country_code":"PG",
    "gn:dem":1451,
    "gn:feature_class":"P",
    "gn:feature_code":"PPL",
    "gn:name":"Anggaie",
    "gn:population":0,
    "gn:timezone":"Pacific/Port_Moresby",
    "iso:country":"PG",
    "wof:name":"Anggaie",
    "wof:placetype":"locality"
},
  "geometry": {"coordinates":[146.39991000000001,-7.238],"type":"Point"}
}