{
  "type": "Feature",
  "properties": {
    "gn:admin1_code":"05",
    "gn:asciiname":"Nipa",
    "gn:country_code":"PG",
    "gn:dem":1865,
    "gn:feature_class":"P",
    "gn:feature_code":"PPL",
    "gn:name":"Nipa",
    "gn:population":0,
    "gn:timezone":"Pacific/Port_Moresby",
    "iso:country":"PG",
    "name:ceb_x_preferred":[
        "Nipa"
    ],
    "name:swe_x_preferred":[
        "Nipa"
    ],
    "wof:name":"Nipa",
    "wof:placetype":"locality"
},
  "geometry": {"coordinates":[143.44120000000001,-6.18019],"type":"Point"}
}