{
  "type": "Feature",
  "properties": {
    "gn:admin1_code":"11",
    "gn:asciiname":"Shagur",
    "gn:country_code":"PG",
    "gn:dem":97,
    "gn:feature_class":"P",
    "gn:feature_code":"PPL",
    "gn:name":"Shagur",
    "gn:population":0,
    "gn:timezone":"Pacific/Port_Moresby",
    "iso:country":"PG",
    "wof:name":"Shagur",
    "wof:placetype":"locality"
},
  "geometry": {"coordinates":[143.56994,-3.32968],"type":"Point"}
}