{
  "type": "Feature",
  "properties": {
    "gn:admin1_code":"12",
    "gn:asciiname":"Moban",
    "gn:country_code":"PG",
    "gn:dem":110,
    "gn:feature_class":"P",
    "gn:feature_code":"PPL",
    "gn:name":"Moban",
    "gn:population":0,
    "gn:timezone":"Pacific/Port_Moresby",
    "iso:country":"PG",
    "wof:name":"Moban",
    "wof:placetype":"locality"
},
  "geometry": {"coordinates":[145.89691000000005,-4.68021],"type":"Point"}
}