{
  "type": "Feature",
  "properties": {
    "gn:admin1_code":"18",
    "gn:asciiname":"Bibia",
    "gn:country_code":"PG",
    "gn:dem":230,
    "gn:feature_class":"P",
    "gn:feature_code":"PPL",
    "gn:name":"Bibia",
    "gn:population":0,
    "gn:timezone":"Pacific/Port_Moresby",
    "iso:country":"PG",
    "name:lug_x_preferred":[
        "Bibia"
    ],
    "wof:name":"Bibia",
    "wof:placetype":"locality"
},
  "geometry": {"coordinates":[141.21666999999999,-3.66667],"type":"Point"}
}