{
  "type": "Feature",
  "properties": {
    "gn:admin1_code":"14",
    "gn:asciiname":"Gofan",
    "gn:country_code":"PG",
    "gn:dem":1177,
    "gn:feature_class":"P",
    "gn:feature_code":"PPL",
    "gn:name":"Gofan",
    "gn:population":0,
    "gn:timezone":"Pacific/Port_Moresby",
    "iso:country":"PG",
    "wof:name":"Gofan",
    "wof:placetype":"locality"
},
  "geometry": {"coordinates":[146.61001999999999,-6.35724],"type":"Point"}
}