{
  "type": "Feature",
  "properties": {
    "gn:admin1_code":"16",
    "gn:asciiname":"Walia",
    "gn:country_code":"PG",
    "gn:dem":1754,
    "gn:feature_class":"P",
    "gn:feature_code":"PPL",
    "gn:name":"Walia",
    "gn:population":0,
    "gn:timezone":"Pacific/Port_Moresby",
    "iso:country":"PG",
    "wof:name":"Walia",
    "wof:placetype":"locality"
},
  "geometry": {"coordinates":[144.24331999999995,-5.89182],"type":"Point"}
}