{
  "type": "Feature",
  "properties": {
    "gn:admin1_code":"01",
    "gn:asciiname":"Genera",
    "gn:country_code":"PG",
    "gn:dem":728,
    "gn:feature_class":"P",
    "gn:feature_code":"PPL",
    "gn:name":"Genera",
    "gn:population":0,
    "gn:timezone":"Pacific/Port_Moresby",
    "iso:country":"PG",
    "name:und_x_variant":[
        "Genara",
        "Genera"
    ],
    "wof:name":"Genera",
    "wof:placetype":"locality"
},
  "geometry": {"coordinates":[147.55122,-8.54448],"type":"Point"}
}