{
  "type": "Feature",
  "properties": {
    "gn:admin1_code":"12",
    "gn:asciiname":"Tana",
    "gn:country_code":"PG",
    "gn:dem":238,
    "gn:feature_class":"P",
    "gn:feature_code":"PPL",
    "gn:name":"Tana",
    "gn:population":0,
    "gn:timezone":"Pacific/Port_Moresby",
    "iso:country":"PG",
    "name:bel_x_preferred":[
        "\u0422\u0430\u043d\u0430"
    ],
    "name:cat_x_preferred":[
        "Tana"
    ],
    "name:ceb_x_preferred":[
        "Tana"
    ],
    "name:ces_x_preferred":[
        "Tana"
    ],
    "name:deu_x_preferred":[
        "Tana"
    ],
    "name:est_x_preferred":[
        "Tana"
    ],
    "name:fin_x_preferred":[
        "Tana"
    ],
    "name:fra_x_preferred":[
        "Tana"
    ],
    "name:heb_x_preferred":[
        "\u05d8\u05e0\u05d4"
    ],
    "name:hrv_x_preferred":[
        "Tana"
    ],
    "name:hun_x_preferred":[
        "Tana"
    ],
    "name:ita_x_preferred":[
        "Tana"
    ],
    "name:kat_x_preferred":[
        "\u10e2\u10d0\u10dc\u10d0"
    ],
    "name:lim_x_preferred":[
        "Tana"
    ],
    "name:lit_x_preferred":[
        "Tana"
    ],
    "name:nld_x_preferred":[
        "Tana"
    ],
    "name:pol_x_preferred":[
        "Tana"
    ],
    "name:por_x_preferred":[
        "Tana"
    ],
    "name:ron_x_preferred":[
        "Tana"
    ],
    "name:rus_x_preferred":[
        "\u0422\u0430\u043d\u0430"
    ],
    "name:spa_x_preferred":[
        "Tana"
    ],
    "name:srp_x_preferred":[
        "\u0422\u0430\u043d\u0430"
    ],
    "name:swa_x_preferred":[
        "Tana"
    ],
    "name:swe_x_preferred":[
        "Tana"
    ],
    "name:ukr_x_preferred":[
        "\u0422\u0430\u043d\u0430"
    ],
    "name:uzb_x_preferred":[
        "Tana"
    ],
    "wof:name":"Tana",
    "wof:placetype":"locality"
},
  "geometry": {"coordinates":[145.69999999999999,-4.98333],"type":"Point"}
}