{
  "type": "Feature",
  "properties": {
    "gn:admin1_code":"12",
    "gn:asciiname":"Tana",
    "gn:country_code":"PG",
    "gn:dem":238,
    "gn:feature_class":"P",
    "gn:feature_code":"PPL",
    "gn:name":"Tana",
    "gn:population":0,
    "gn:timezone":"Pacific/Port_Moresby",
    "iso:country":"PG",
    "wof:name":"Tana",
    "wof:placetype":"locality"
},
  "geometry": {"coordinates":[145.69999999999999,-4.98333],"type":"Point"}
}