{
  "type": "Feature",
  "properties": {
    "gn:admin1_code":"15",
    "gn:asciiname":"Belifu Number 1",
    "gn:country_code":"PG",
    "gn:dem":337,
    "gn:feature_class":"P",
    "gn:feature_code":"PPL",
    "gn:name":"Belifu Number 1",
    "gn:population":0,
    "gn:timezone":"Pacific/Port_Moresby",
    "iso:country":"PG",
    "name:und_x_variant":[
        "Belifu",
        "Belifu 1",
        "Belifu Number 1"
    ],
    "wof:name":"Belifu Number 1",
    "wof:placetype":"locality"
},
  "geometry": {"coordinates":[151.25961999999996,-2.94986],"type":"Point"}
}