{
  "type": "Feature",
  "properties": {
    "gn:admin1_code":"14",
    "gn:asciiname":"Bupu",
    "gn:country_code":"PG",
    "gn:dem":948,
    "gn:feature_class":"P",
    "gn:feature_code":"PPL",
    "gn:name":"Bupu",
    "gn:population":0,
    "gn:timezone":"Pacific/Port_Moresby",
    "iso:country":"PG",
    "wof:name":"Bupu",
    "wof:placetype":"locality"
},
  "geometry": {"coordinates":[146.59934999999999,-6.85272],"type":"Point"}
}