{
  "type": "Feature",
  "properties": {
    "gn:admin1_code":"12",
    "gn:asciiname":"Ibinoro",
    "gn:country_code":"PG",
    "gn:dem":694,
    "gn:feature_class":"P",
    "gn:feature_code":"PPL",
    "gn:name":"Ibinoro",
    "gn:population":0,
    "gn:timezone":"Pacific/Port_Moresby",
    "iso:country":"PG",
    "wof:name":"Ibinoro",
    "wof:placetype":"locality"
},
  "geometry": {"coordinates":[145.43011000000001,-5.41588],"type":"Point"}
}