{
  "type": "Feature",
  "properties": {
    "gn:admin1_code":"01",
    "gn:asciiname":"Uberegoro",
    "gn:country_code":"PG",
    "gn:dem":559,
    "gn:feature_class":"P",
    "gn:feature_code":"PPL",
    "gn:name":"Uberegoro",
    "gn:population":0,
    "gn:timezone":"Pacific/Port_Moresby",
    "iso:country":"PG",
    "wof:name":"Uberegoro",
    "wof:placetype":"locality"
},
  "geometry": {"coordinates":[147.96317999999999,-9.70223],"type":"Point"}
}