{
  "type": "Feature",
  "properties": {
    "gn:admin1_code":"12",
    "gn:asciiname":"Wamambre",
    "gn:cc2":"PG",
    "gn:country_code":"PG",
    "gn:dem":937,
    "gn:feature_class":"P",
    "gn:feature_code":"PPL",
    "gn:name":"Wamambre",
    "gn:population":0,
    "gn:timezone":"Pacific/Port_Moresby",
    "iso:country":"PG",
    "name:und_x_variant":[
        "Wanambre",
        "Wamambre"
    ],
    "wof:name":"Wamambre",
    "wof:placetype":"locality"
},
  "geometry": {"coordinates":[145.34999999999999,-4.76667],"type":"Point"}
}