{
  "type": "Feature",
  "properties": {
    "gn:admin1_code":"12",
    "gn:asciiname":"Usino",
    "gn:country_code":"PG",
    "gn:dem":125,
    "gn:feature_class":"P",
    "gn:feature_code":"PPL",
    "gn:name":"Usino",
    "gn:population":0,
    "gn:timezone":"Pacific/Port_Moresby",
    "iso:country":"PG",
    "name:und_x_variant":[
        "Usini",
        "Usino"
    ],
    "wof:name":"Usino",
    "wof:placetype":"locality"
},
  "geometry": {"coordinates":[145.37062,-5.52161],"type":"Point"}
}