{
  "type": "Feature",
  "properties": {
    "gn:admin1_code":"11",
    "gn:asciiname":"Kagiru",
    "gn:country_code":"PG",
    "gn:dem":38,
    "gn:feature_class":"P",
    "gn:feature_code":"PPL",
    "gn:name":"Kagiru",
    "gn:population":0,
    "gn:timezone":"Pacific/Port_Moresby",
    "iso:country":"PG",
    "wof:name":"Kagiru",
    "wof:placetype":"locality"
},
  "geometry": {"coordinates":[142.47718,-4.48587],"type":"Point"}
}