{
  "type": "Feature",
  "properties": {
    "gn:admin1_code":"12",
    "gn:asciiname":"Babangaua",
    "gn:country_code":"PG",
    "gn:dem":6,
    "gn:feature_class":"P",
    "gn:feature_code":"PPL",
    "gn:name":"Babangaua",
    "gn:population":0,
    "gn:timezone":"Pacific/Port_Moresby",
    "iso:country":"PG",
    "wof:name":"Babangaua",
    "wof:placetype":"locality"
},
  "geometry": {"coordinates":[145.00056000000001,-4.32295],"type":"Point"}
}