{
  "type": "Feature",
  "properties": {
    "gn:admin1_code":"07",
    "gn:asciiname":"Sibai",
    "gn:country_code":"PG",
    "gn:dem":16,
    "gn:feature_class":"P",
    "gn:feature_code":"PPL",
    "gn:name":"Sibai",
    "gn:population":0,
    "gn:timezone":"Pacific/Bougainville",
    "iso:country":"PG",
    "wof:name":"Sibai",
    "wof:placetype":"locality"
},
  "geometry": {"coordinates":[154.74844999999999,-5.84588],"type":"Point"}
}