{
  "type": "Feature",
  "properties": {
    "gn:admin1_code":"06",
    "gn:asciiname":"Iekenai",
    "gn:country_code":"PG",
    "gn:dem":82,
    "gn:feature_class":"P",
    "gn:feature_code":"PPL",
    "gn:name":"Iekenai",
    "gn:population":0,
    "gn:timezone":"Pacific/Port_Moresby",
    "iso:country":"PG",
    "name:und_x_variant":[
        "Ienkenai",
        "Iekenai"
    ],
    "wof:name":"Iekenai",
    "wof:placetype":"locality"
},
  "geometry": {"coordinates":[141.12063000000001,-5.76804],"type":"Point"}
}