{
  "type": "Feature",
  "properties": {
    "gn:admin1_code":"05",
    "gn:asciiname":"One",
    "gn:country_code":"PG",
    "gn:dem":1841,
    "gn:feature_class":"P",
    "gn:feature_code":"PPL",
    "gn:name":"One",
    "gn:population":0,
    "gn:timezone":"Pacific/Port_Moresby",
    "iso:country":"PG",
    "wof:name":"One",
    "wof:placetype":"locality"
},
  "geometry": {"coordinates":[143.65158,-6.21364],"type":"Point"}
}