{
  "type": "Feature",
  "properties": {
    "gn:admin1_code":"12",
    "gn:asciiname":"Wagum",
    "gn:country_code":"PG",
    "gn:dem":35,
    "gn:feature_class":"P",
    "gn:feature_code":"PPL",
    "gn:name":"Wagum",
    "gn:population":0,
    "gn:timezone":"Pacific/Port_Moresby",
    "iso:country":"PG",
    "wof:name":"Wagum",
    "wof:placetype":"locality"
},
  "geometry": {"coordinates":[145.62052,-5.26138],"type":"Point"}
}