{
  "type": "Feature",
  "properties": {
    "gn:admin1_code":"18",
    "gn:asciiname":"Norambalip",
    "gn:country_code":"PG",
    "gn:dem":64,
    "gn:feature_class":"P",
    "gn:feature_code":"PPL",
    "gn:name":"Norambalip",
    "gn:population":0,
    "gn:timezone":"Pacific/Port_Moresby",
    "iso:country":"PG",
    "wof:name":"Norambalip",
    "wof:placetype":"locality"
},
  "geometry": {"coordinates":[141.82283000000001,-3.82807],"type":"Point"}
}