{
  "type": "Feature",
  "properties": {
    "gn:admin1_code":"11",
    "gn:asciiname":"Higiabin",
    "gn:country_code":"PG",
    "gn:dem":202,
    "gn:feature_class":"P",
    "gn:feature_code":"PPL",
    "gn:name":"Higiabin",
    "gn:population":0,
    "gn:timezone":"Pacific/Port_Moresby",
    "iso:country":"PG",
    "wof:name":"Higiabin",
    "wof:placetype":"locality"
},
  "geometry": {"coordinates":[142.95706999999999,-3.57693],"type":"Point"}
}