{
  "type": "Feature",
  "properties": {
    "gn:admin1_code":"02",
    "gn:asciiname":"Kisikude",
    "gn:country_code":"PG",
    "gn:dem":235,
    "gn:feature_class":"P",
    "gn:feature_code":"PPL",
    "gn:name":"Kisikude",
    "gn:population":0,
    "gn:timezone":"Pacific/Port_Moresby",
    "iso:country":"PG",
    "wof:name":"Kisikude",
    "wof:placetype":"locality"
},
  "geometry": {"coordinates":[143.66666999999995,-7.01667],"type":"Point"}
}