{
  "type": "Feature",
  "properties": {
    "gn:admin1_code":"13",
    "gn:asciiname":"Massis",
    "gn:country_code":"PG",
    "gn:dem":-9999,
    "gn:feature_class":"P",
    "gn:feature_code":"PPL",
    "gn:name":"Massis",
    "gn:population":0,
    "gn:timezone":"Pacific/Port_Moresby",
    "iso:country":"PG",
    "wof:name":"Massis",
    "wof:placetype":"locality"
},
  "geometry": {"coordinates":[147.08333000000005,-1.96667],"type":"Point"}
}