{
  "type": "Feature",
  "properties": {
    "gn:admin1_code":"09",
    "gn:asciiname":"Yonufu",
    "gn:country_code":"PG",
    "gn:dem":1698,
    "gn:feature_class":"P",
    "gn:feature_code":"PPL",
    "gn:name":"Yonufu",
    "gn:population":0,
    "gn:timezone":"Pacific/Port_Moresby",
    "iso:country":"PG",
    "wof:name":"Yonufu",
    "wof:placetype":"locality"
},
  "geometry": {"coordinates":[145.97234,-6.55248],"type":"Point"}
}