{
  "type": "Feature",
  "properties": {
    "gn:admin1_code":"12",
    "gn:asciiname":"Korigei",
    "gn:country_code":"PG",
    "gn:dem":170,
    "gn:feature_class":"P",
    "gn:feature_code":"PPL",
    "gn:name":"Korigei",
    "gn:population":0,
    "gn:timezone":"Pacific/Port_Moresby",
    "iso:country":"PG",
    "wof:name":"Korigei",
    "wof:placetype":"locality"
},
  "geometry": {"coordinates":[145.53333000000001,-5.78333],"type":"Point"}
}