{
  "type": "Feature",
  "properties": {
    "gn:admin1_code":"18",
    "gn:asciiname":"Butultman",
    "gn:country_code":"PG",
    "gn:dem":1330,
    "gn:feature_class":"P",
    "gn:feature_code":"PPL",
    "gn:name":"Butultman",
    "gn:population":0,
    "gn:timezone":"Pacific/Port_Moresby",
    "iso:country":"PG",
    "wof:name":"Butultman",
    "wof:placetype":"locality"
},
  "geometry": {"coordinates":[141.18333000000001,-4.85],"type":"Point"}
}