{
  "type": "Feature",
  "properties": {
    "gn:admin1_code":"02",
    "gn:asciiname":"Omagiowe",
    "gn:country_code":"PG",
    "gn:dem":376,
    "gn:feature_class":"P",
    "gn:feature_code":"PPL",
    "gn:name":"Omagiowe",
    "gn:population":0,
    "gn:timezone":"Pacific/Port_Moresby",
    "iso:country":"PG",
    "wof:name":"Omagiowe",
    "wof:placetype":"locality"
},
  "geometry": {"coordinates":[143.65000000000001,-7.05],"type":"Point"}
}