{
  "type": "Feature",
  "properties": {
    "gn:admin1_code":"18",
    "gn:asciiname":"Wantipi",
    "gn:country_code":"PG",
    "gn:dem":422,
    "gn:feature_class":"P",
    "gn:feature_code":"PPL",
    "gn:name":"Wantipi",
    "gn:population":0,
    "gn:timezone":"Pacific/Port_Moresby",
    "iso:country":"PG",
    "wof:name":"Wantipi",
    "wof:placetype":"locality"
},
  "geometry": {"coordinates":[141.97641000000004,-3.32829],"type":"Point"}
}