{
  "type": "Feature",
  "properties": {
    "gn:admin1_code":"08",
    "gn:asciiname":"Komun",
    "gn:country_code":"PG",
    "gn:dem":2250,
    "gn:feature_class":"P",
    "gn:feature_code":"PPL",
    "gn:name":"Komun",
    "gn:population":0,
    "gn:timezone":"Pacific/Port_Moresby",
    "iso:country":"PG",
    "wof:name":"Komun",
    "wof:placetype":"locality"
},
  "geometry": {"coordinates":[145.05000000000001,-5.91667],"type":"Point"}
}