{
  "type": "Feature",
  "properties": {
    "gn:admin1_code":"15",
    "gn:asciiname":"Lambuso",
    "gn:country_code":"PG",
    "gn:dem":22,
    "gn:feature_class":"P",
    "gn:feature_code":"PPL",
    "gn:name":"Lambuso",
    "gn:population":0,
    "gn:timezone":"Pacific/Port_Moresby",
    "iso:country":"PG",
    "wof:name":"Lambuso",
    "wof:placetype":"locality"
},
  "geometry": {"coordinates":[151.81611999999996,-3.1931],"type":"Point"}
}