{
  "type": "Feature",
  "properties": {
    "gn:admin1_code":"18",
    "gn:asciiname":"Woloso",
    "gn:country_code":"PG",
    "gn:dem":87,
    "gn:feature_class":"P",
    "gn:feature_code":"PPL",
    "gn:name":"Woloso",
    "gn:population":0,
    "gn:timezone":"Pacific/Port_Moresby",
    "iso:country":"PG",
    "wof:name":"Woloso",
    "wof:placetype":"locality"
},
  "geometry": {"coordinates":[142.44999999999999,-3.81667],"type":"Point"}
}