{
  "type": "Feature",
  "properties": {
    "gn:admin1_code":"01",
    "gn:asciiname":"Ilai",
    "gn:country_code":"PG",
    "gn:dem":1511,
    "gn:feature_class":"P",
    "gn:feature_code":"PPL",
    "gn:name":"Ilai",
    "gn:population":0,
    "gn:timezone":"Pacific/Port_Moresby",
    "iso:country":"PG",
    "wof:name":"Ilai",
    "wof:placetype":"locality"
},
  "geometry": {"coordinates":[147.10048999999995,-8.24345],"type":"Point"}
}