{
  "type": "Feature",
  "properties": {
    "gn:admin1_code":"12",
    "gn:asciiname":"Kausi",
    "gn:country_code":"PG",
    "gn:dem":147,
    "gn:feature_class":"P",
    "gn:feature_code":"PPL",
    "gn:name":"Kausi",
    "gn:population":0,
    "gn:timezone":"Pacific/Port_Moresby",
    "iso:country":"PG",
    "wof:name":"Kausi",
    "wof:placetype":"locality"
},
  "geometry": {"coordinates":[145.36667,-5.71667],"type":"Point"}
}