{
  "type": "Feature",
  "properties": {
    "gn:admin1_code":"05",
    "gn:asciiname":"Wasa",
    "gn:country_code":"PG",
    "gn:dem":1737,
    "gn:feature_class":"P",
    "gn:feature_code":"PPL",
    "gn:name":"Wasa",
    "gn:population":0,
    "gn:timezone":"Pacific/Port_Moresby",
    "iso:country":"PG",
    "name:ceb_x_preferred":[
        "Wasa"
    ],
    "name:fin_x_preferred":[
        "Wasa"
    ],
    "name:ita_x_preferred":[
        "Wasa"
    ],
    "name:nld_x_preferred":[
        "Wasa"
    ],
    "name:nor_x_preferred":[
        "Wasa"
    ],
    "name:swe_x_preferred":[
        "Wasa"
    ],
    "name:zho_x_preferred":[
        "Wasa"
    ],
    "wof:name":"Wasa",
    "wof:placetype":"locality"
},
  "geometry": {"coordinates":[143.7886,-6.41133],"type":"Point"}
}