{
  "type": "Feature",
  "properties": {
    "gn:admin1_code":"06",
    "gn:asciiname":"Bultem",
    "gn:country_code":"PG",
    "gn:dem":1294,
    "gn:feature_class":"P",
    "gn:feature_code":"PPL",
    "gn:name":"Bultem",
    "gn:population":0,
    "gn:timezone":"Pacific/Port_Moresby",
    "iso:country":"PG",
    "wof:name":"Bultem",
    "wof:placetype":"locality"
},
  "geometry": {"coordinates":[141.25359,-5.1783],"type":"Point"}
}