{
  "type": "Feature",
  "properties": {
    "gn:admin1_code":"03",
    "gn:asciiname":"Ubu",
    "gn:country_code":"PG",
    "gn:dem":311,
    "gn:feature_class":"P",
    "gn:feature_code":"PPL",
    "gn:name":"Ubu",
    "gn:population":0,
    "gn:timezone":"Pacific/Port_Moresby",
    "iso:country":"PG",
    "name:ceb_x_preferred":[
        "Ubu"
    ],
    "name:ces_x_preferred":[
        "Ubu"
    ],
    "name:fra_x_preferred":[
        "Ubu"
    ],
    "name:new_x_preferred":[
        "\u0909\u092c\u0942"
    ],
    "name:nld_x_preferred":[
        "Ubu"
    ],
    "name:spa_x_preferred":[
        "Ubu"
    ],
    "wof:name":"Ubu",
    "wof:placetype":"locality"
},
  "geometry": {"coordinates":[149.93333000000001,-10.06667],"type":"Point"}
}