{
  "type": "Feature",
  "properties": {
    "gn:admin1_code":"09",
    "gn:asciiname":"Numbaira",
    "gn:country_code":"PG",
    "gn:dem":1689,
    "gn:feature_class":"P",
    "gn:feature_code":"PPL",
    "gn:name":"Numbaira",
    "gn:population":0,
    "gn:timezone":"Pacific/Port_Moresby",
    "iso:country":"PG",
    "wof:name":"Numbaira",
    "wof:placetype":"locality"
},
  "geometry": {"coordinates":[145.91768999999999,-6.59024],"type":"Point"}
}