{
  "type": "Feature",
  "properties": {
    "gn:admin1_code":"06",
    "gn:asciiname":"Griengas",
    "gn:country_code":"PG",
    "gn:dem":72,
    "gn:feature_class":"P",
    "gn:feature_code":"PPL",
    "gn:name":"Griengas",
    "gn:population":0,
    "gn:timezone":"Pacific/Port_Moresby",
    "iso:country":"PG",
    "wof:name":"Griengas",
    "wof:placetype":"locality"
},
  "geometry": {"coordinates":[141.34999999999999,-5.91667],"type":"Point"}
}