{
  "type": "Feature",
  "properties": {
    "gn:admin1_code":"03",
    "gn:asciiname":"Wadobuna",
    "gn:country_code":"PG",
    "gn:dem":23,
    "gn:feature_class":"P",
    "gn:feature_code":"PPL",
    "gn:name":"Wadobuna",
    "gn:population":0,
    "gn:timezone":"Pacific/Port_Moresby",
    "iso:country":"PG",
    "wof:name":"Wadobuna",
    "wof:placetype":"locality"
},
  "geometry": {"coordinates":[149.88966000000005,-10.02538],"type":"Point"}
}