{
  "type": "Feature",
  "properties": {
    "gn:admin1_code":"05",
    "gn:asciiname":"Fugwa",
    "gn:country_code":"PG",
    "gn:dem":1831,
    "gn:feature_class":"P",
    "gn:feature_code":"PPL",
    "gn:name":"Fugwa",
    "gn:population":0,
    "gn:timezone":"Pacific/Port_Moresby",
    "iso:country":"PG",
    "wof:name":"Fugwa",
    "wof:placetype":"locality"
},
  "geometry": {"coordinates":[142.68906000000001,-5.69636],"type":"Point"}
}