{
  "type": "Feature",
  "properties": {
    "gn:admin1_code":"04",
    "gn:asciiname":"Kinjaki",
    "gn:country_code":"PG",
    "gn:dem":30,
    "gn:feature_class":"P",
    "gn:feature_code":"PPL",
    "gn:name":"Kinjaki",
    "gn:population":0,
    "gn:timezone":"Pacific/Port_Moresby",
    "iso:country":"PG",
    "wof:name":"Kinjaki",
    "wof:placetype":"locality"
},
  "geometry": {"coordinates":[148.60547,-9.20631],"type":"Point"}
}