{
  "type": "Feature",
  "properties": {
    "gn:admin1_code":"12",
    "gn:asciiname":"Balaia",
    "gn:country_code":"PG",
    "gn:dem":571,
    "gn:feature_class":"P",
    "gn:feature_code":"PPL",
    "gn:name":"Balaia",
    "gn:population":0,
    "gn:timezone":"Pacific/Port_Moresby",
    "iso:country":"PG",
    "wof:name":"Balaia",
    "wof:placetype":"locality"
},
  "geometry": {"coordinates":[145.63397000000001,-5.52171],"type":"Point"}
}