{
  "type": "Feature",
  "properties": {
    "gn:admin1_code":"12",
    "gn:asciiname":"Balima",
    "gn:country_code":"PG",
    "gn:dem":22,
    "gn:feature_class":"P",
    "gn:feature_code":"PPL",
    "gn:name":"Balima",
    "gn:population":0,
    "gn:timezone":"Pacific/Port_Moresby",
    "iso:country":"PG",
    "wof:name":"Balima",
    "wof:placetype":"locality"
},
  "geometry": {"coordinates":[145.72946000000005,-5.37355],"type":"Point"}
}