{
  "type": "Feature",
  "properties": {
    "gn:admin1_code":"18",
    "gn:asciiname":"Green River",
    "gn:country_code":"PG",
    "gn:dem":77,
    "gn:feature_class":"P",
    "gn:feature_code":"PPL",
    "gn:name":"Green River",
    "gn:population":0,
    "gn:timezone":"Pacific/Port_Moresby",
    "iso:country":"PG",
    "wof:name":"Green River",
    "wof:placetype":"locality"
},
  "geometry": {"coordinates":[141.19175000000001,-3.89308],"type":"Point"}
}