{
  "type": "Feature",
  "properties": {
    "gn:admin1_code":"18",
    "gn:asciiname":"Green River",
    "gn:country_code":"PG",
    "gn:dem":77,
    "gn:feature_class":"P",
    "gn:feature_code":"PPL",
    "gn:name":"Green River",
    "gn:population":0,
    "gn:timezone":"Pacific/Port_Moresby",
    "iso:country":"PG",
    "name:bel_x_preferred":[
        "\u0413\u0440\u044b\u043d-\u0420\u044b\u0432\u0435\u0440"
    ],
    "name:ben_x_preferred":[
        "\u0997\u09cd\u09b0\u09c0\u09a8 \u09b0\u09bf\u09ad\u09be\u09b0"
    ],
    "name:ceb_x_preferred":[
        "Green River"
    ],
    "name:ces_x_preferred":[
        "Green River"
    ],
    "name:deu_x_preferred":[
        "Green River"
    ],
    "name:ell_x_preferred":[
        "\u0393\u03ba\u03c1\u03b9\u03bd \u03a1\u03af\u03b2\u03b5\u03c1"
    ],
    "name:est_x_preferred":[
        "Green River"
    ],
    "name:fin_x_preferred":[
        "Green River"
    ],
    "name:fra_x_preferred":[
        "Green River"
    ],
    "name:heb_x_preferred":[
        "\u05d2\u05e8\u05d9\u05df \u05e8\u05d9\u05d5\u05d5\u05e8"
    ],
    "name:hin_x_preferred":[
        "\u0917\u094d\u0930\u0940\u0928 \u0930\u093f\u0935\u0930"
    ],
    "name:hun_x_preferred":[
        "Green River"
    ],
    "name:ind_x_preferred":[
        "Green River"
    ],
    "name:ita_x_preferred":[
        "Green River"
    ],
    "name:jpn_x_preferred":[
        "\u30b0\u30ea\u30fc\u30f3\u30fb\u30ea\u30d0\u30fc"
    ],
    "name:kor_x_preferred":[
        "\uadf8\ub9b0 \ub9ac\ubc84"
    ],
    "name:nds_x_preferred":[
        "Green River"
    ],
    "name:nld_x_preferred":[
        "Green River"
    ],
    "name:nor_x_preferred":[
        "Green River"
    ],
    "name:pol_x_preferred":[
        "Green River"
    ],
    "name:por_x_preferred":[
        "Green River"
    ],
    "name:ron_x_preferred":[
        "Green River"
    ],
    "name:rus_x_preferred":[
        "\u0413\u0440\u0438\u043d-\u0420\u0438\u0432\u0435\u0440"
    ],
    "name:slk_x_preferred":[
        "Green River"
    ],
    "name:spa_x_preferred":[
        "Green River"
    ],
    "name:srp_x_preferred":[
        "\u0413\u0440\u0438\u043d \u0420\u0438\u0432\u0435\u0440"
    ],
    "name:swe_x_preferred":[
        "Green River"
    ],
    "name:ukr_x_preferred":[
        "\u0490\u0440\u0456\u043d-\u0420\u0456\u0432\u0435\u0440"
    ],
    "name:vie_x_preferred":[
        "Green River"
    ],
    "name:vol_x_preferred":[
        "Green River"
    ],
    "wof:name":"Green River",
    "wof:placetype":"locality"
},
  "geometry": {"coordinates":[141.19175000000001,-3.89308],"type":"Point"}
}