{
  "type": "Feature",
  "properties": {
    "gn:admin1_code":"15",
    "gn:asciiname":"Mesi Number 2",
    "gn:country_code":"PG",
    "gn:dem":158,
    "gn:feature_class":"P",
    "gn:feature_code":"PPL",
    "gn:name":"Mesi Number 2",
    "gn:population":0,
    "gn:timezone":"Pacific/Port_Moresby",
    "iso:country":"PG",
    "name:und_x_variant":[
        "Mesi 2",
        "Mesi Number 2"
    ],
    "wof:name":"Mesi Number 2",
    "wof:placetype":"locality"
},
  "geometry": {"coordinates":[151.91316,-3.41713],"type":"Point"}
}