{
  "type": "Feature",
  "properties": {
    "gn:admin1_code":"06",
    "gn:asciiname":"Aumi",
    "gn:country_code":"PG",
    "gn:dem":193,
    "gn:feature_class":"P",
    "gn:feature_code":"PPL",
    "gn:name":"Aumi",
    "gn:population":0,
    "gn:timezone":"Pacific/Port_Moresby",
    "iso:country":"PG",
    "name:azb_x_preferred":[
        "\u0622\u0645\u06cc"
    ],
    "name:ceb_x_preferred":[
        "Aumi"
    ],
    "name:fas_x_preferred":[
        "\u0622\u0645\u06cc"
    ],
    "name:ita_x_preferred":[
        "Aumi"
    ],
    "name:swe_x_preferred":[
        "Aumi"
    ],
    "wof:name":"Aumi",
    "wof:placetype":"locality"
},
  "geometry": {"coordinates":[142.34999999999999,-6.38333],"type":"Point"}
}