{
  "type": "Feature",
  "properties": {
    "gn:admin1_code":"02",
    "gn:asciiname":"Wandi",
    "gn:country_code":"PG",
    "gn:dem":932,
    "gn:feature_class":"P",
    "gn:feature_code":"PPL",
    "gn:name":"Wandi",
    "gn:population":0,
    "gn:timezone":"Pacific/Port_Moresby",
    "iso:country":"PG",
    "name:ceb_x_preferred":[
        "Wandi"
    ],
    "name:swe_x_preferred":[
        "Wandi"
    ],
    "wof:name":"Wandi",
    "wof:placetype":"locality"
},
  "geometry": {"coordinates":[146.18315000000001,-7.60232],"type":"Point"}
}