{
  "type": "Feature",
  "properties": {
    "gn:admin1_code":"11",
    "gn:asciiname":"Maremuen",
    "gn:country_code":"PG",
    "gn:dem":38,
    "gn:feature_class":"P",
    "gn:feature_code":"PPL",
    "gn:name":"Maremuen",
    "gn:population":0,
    "gn:timezone":"Pacific/Port_Moresby",
    "iso:country":"PG",
    "wof:name":"Maremuen",
    "wof:placetype":"locality"
},
  "geometry": {"coordinates":[143.75,-4.05],"type":"Point"}
}