{
  "type": "Feature",
  "properties": {
    "gn:admin1_code":"03",
    "gn:asciiname":"Sirisiri",
    "gn:country_code":"PG",
    "gn:dem":224,
    "gn:feature_class":"P",
    "gn:feature_code":"PPL",
    "gn:name":"Sirisiri",
    "gn:population":0,
    "gn:timezone":"Pacific/Port_Moresby",
    "iso:country":"PG",
    "name:und_x_variant":[
        "Silisiti",
        "Siri Siri Mission",
        "Sirisiri"
    ],
    "wof:name":"Sirisiri",
    "wof:placetype":"locality"
},
  "geometry": {"coordinates":[149.71728000000004,-9.86869],"type":"Point"}
}