{
  "type": "Feature",
  "properties": {
    "gn:admin1_code":"09",
    "gn:asciiname":"Guselevi",
    "gn:country_code":"PG",
    "gn:dem":1237,
    "gn:feature_class":"P",
    "gn:feature_code":"PPL",
    "gn:name":"Guselevi",
    "gn:population":0,
    "gn:timezone":"Pacific/Port_Moresby",
    "iso:country":"PG",
    "wof:name":"Guselevi",
    "wof:placetype":"locality"
},
  "geometry": {"coordinates":[145.23333,-6.35],"type":"Point"}
}