{
  "type": "Feature",
  "properties": {
    "gn:admin1_code":"12",
    "gn:asciiname":"Warekam",
    "gn:country_code":"PG",
    "gn:dem":143,
    "gn:feature_class":"P",
    "gn:feature_code":"PPL",
    "gn:name":"Warekam",
    "gn:population":0,
    "gn:timezone":"Pacific/Port_Moresby",
    "iso:country":"PG",
    "wof:name":"Warekam",
    "wof:placetype":"locality"
},
  "geometry": {"coordinates":[144.85703999999996,-4.35876],"type":"Point"}
}