{
  "type": "Feature",
  "properties": {
    "gn:admin1_code":"02",
    "gn:asciiname":"Orovoi",
    "gn:country_code":"PG",
    "gn:dem":49,
    "gn:feature_class":"P",
    "gn:feature_code":"PPL",
    "gn:name":"Orovoi",
    "gn:population":0,
    "gn:timezone":"Pacific/Port_Moresby",
    "iso:country":"PG",
    "wof:name":"Orovoi",
    "wof:placetype":"locality"
},
  "geometry": {"coordinates":[145.43333000000001,-7.73333],"type":"Point"}
}