{
  "type": "Feature",
  "properties": {
    "gn:admin1_code":"19",
    "gn:asciiname":"Tsak",
    "gn:country_code":"PG",
    "gn:dem":1987,
    "gn:feature_class":"P",
    "gn:feature_code":"PPL",
    "gn:name":"Tsak",
    "gn:population":0,
    "gn:timezone":"Pacific/Port_Moresby",
    "iso:country":"PG",
    "wof:name":"Tsak",
    "wof:placetype":"locality"
},
  "geometry": {"coordinates":[143.83333000000005,-5.66667],"type":"Point"}
}