{
  "type": "Feature",
  "properties": {
    "gn:admin1_code":"04",
    "gn:asciiname":"Kurereda",
    "gn:country_code":"PG",
    "gn:dem":15,
    "gn:feature_class":"P",
    "gn:feature_code":"PPL",
    "gn:name":"Kurereda",
    "gn:population":0,
    "gn:timezone":"Pacific/Port_Moresby",
    "iso:country":"PG",
    "name:und_x_variant":[
        "Kurureda",
        "Kurenada",
        "Kurereda"
    ],
    "wof:name":"Kurereda",
    "wof:placetype":"locality"
},
  "geometry": {"coordinates":[148.22146999999995,-8.47169],"type":"Point"}
}