{
  "type": "Feature",
  "properties": {
    "gn:admin1_code":"11",
    "gn:asciiname":"Fumatambu",
    "gn:country_code":"PG",
    "gn:dem":123,
    "gn:feature_class":"P",
    "gn:feature_code":"PPL",
    "gn:name":"Fumatambu",
    "gn:population":0,
    "gn:timezone":"Pacific/Port_Moresby",
    "iso:country":"PG",
    "name:und_x_variant":[
        "Fumatumbu",
        "Fumatambu"
    ],
    "wof:name":"Fumatambu",
    "wof:placetype":"locality"
},
  "geometry": {"coordinates":[142.62673000000001,-3.75248],"type":"Point"}
}