{
  "type": "Feature",
  "properties": {
    "gn:admin1_code":"02",
    "gn:asciiname":"Pau",
    "gn:country_code":"PG",
    "gn:dem":1288,
    "gn:feature_class":"P",
    "gn:feature_code":"PPL",
    "gn:name":"Pau",
    "gn:population":0,
    "gn:timezone":"Pacific/Port_Moresby",
    "iso:country":"PG",
    "name:arg_x_preferred":[
        "Pau"
    ],
    "name:cat_x_preferred":[
        "Pau"
    ],
    "name:ceb_x_preferred":[
        "Pau"
    ],
    "name:ces_x_preferred":[
        "Pau"
    ],
    "name:deu_x_preferred":[
        "Pau"
    ],
    "name:epo_x_preferred":[
        "Pau"
    ],
    "name:eus_x_preferred":[
        "Pau"
    ],
    "name:fin_x_preferred":[
        "Pau"
    ],
    "name:fra_x_preferred":[
        "Pau"
    ],
    "name:glg_x_preferred":[
        "Pau"
    ],
    "name:ind_x_preferred":[
        "Pau"
    ],
    "name:msa_x_preferred":[
        "Pau"
    ],
    "name:nld_x_preferred":[
        "Pau"
    ],
    "name:pol_x_preferred":[
        "Pau"
    ],
    "name:por_x_preferred":[
        "Pau"
    ],
    "name:scn_x_preferred":[
        "Pau"
    ],
    "name:slk_x_preferred":[
        "Pau"
    ],
    "name:slv_x_preferred":[
        "Pau"
    ],
    "name:spa_x_preferred":[
        "Pau"
    ],
    "name:sqi_x_preferred":[
        "Pau"
    ],
    "name:swe_x_preferred":[
        "Pau"
    ],
    "name:szl_x_preferred":[
        "Pau"
    ],
    "name:vie_x_preferred":[
        "Pau"
    ],
    "name:vol_x_preferred":[
        "Pau"
    ],
    "name:war_x_preferred":[
        "Pau"
    ],
    "wof:name":"Pau",
    "wof:placetype":"locality"
},
  "geometry": {"coordinates":[145.91585000000001,-7.46404],"type":"Point"}
}