{
  "type": "Feature",
  "properties": {
    "gn:admin1_code":"02",
    "gn:asciiname":"Pau",
    "gn:country_code":"PG",
    "gn:dem":1288,
    "gn:feature_class":"P",
    "gn:feature_code":"PPL",
    "gn:name":"Pau",
    "gn:population":0,
    "gn:timezone":"Pacific/Port_Moresby",
    "iso:country":"PG",
    "wof:name":"Pau",
    "wof:placetype":"locality"
},
  "geometry": {"coordinates":[145.91585000000001,-7.46404],"type":"Point"}
}