{
  "type": "Feature",
  "properties": {
    "gn:admin1_code":"18",
    "gn:asciiname":"Purumun",
    "gn:country_code":"PG",
    "gn:dem":490,
    "gn:feature_class":"P",
    "gn:feature_code":"PPL",
    "gn:name":"Purumun",
    "gn:population":0,
    "gn:timezone":"Pacific/Port_Moresby",
    "iso:country":"PG",
    "wof:name":"Purumun",
    "wof:placetype":"locality"
},
  "geometry": {"coordinates":[141.16066000000001,-3.67081],"type":"Point"}
}