{
  "type": "Feature",
  "properties": {
    "gn:admin1_code":"12",
    "gn:asciiname":"Meiwok",
    "gn:country_code":"PG",
    "gn:dem":34,
    "gn:feature_class":"P",
    "gn:feature_code":"PPL",
    "gn:name":"Meiwok",
    "gn:population":0,
    "gn:timezone":"Pacific/Port_Moresby",
    "iso:country":"PG",
    "name:und_x_variant":[
        "Mawock Plantation",
        "Mawock",
        "Meivok",
        "Mewok",
        "Meiwok"
    ],
    "wof:name":"Meiwok",
    "wof:placetype":"locality"
},
  "geometry": {"coordinates":[145.44333999999995,-4.49509],"type":"Point"}
}