{
  "type": "Feature",
  "properties": {
    "gn:admin1_code":"10",
    "gn:asciiname":"Bakirua",
    "gn:country_code":"PG",
    "gn:dem":394,
    "gn:feature_class":"P",
    "gn:feature_code":"PPL",
    "gn:name":"Bakirua",
    "gn:population":0,
    "gn:timezone":"Pacific/Port_Moresby",
    "iso:country":"PG",
    "wof:name":"Bakirua",
    "wof:placetype":"locality"
},
  "geometry": {"coordinates":[151.66666999999995,-5.33333],"type":"Point"}
}