{
  "type": "Feature",
  "properties": {
    "gn:admin1_code":"16",
    "gn:asciiname":"Geg",
    "gn:country_code":"PG",
    "gn:dem":1963,
    "gn:feature_class":"P",
    "gn:feature_code":"PPL",
    "gn:name":"Geg",
    "gn:population":0,
    "gn:timezone":"Pacific/Port_Moresby",
    "iso:country":"PG",
    "name:und_x_variant":[
        "Gegl",
        "Geg"
    ],
    "wof:name":"Geg",
    "wof:placetype":"locality"
},
  "geometry": {"coordinates":[144.27482000000001,-5.50138],"type":"Point"}
}