{
  "type": "Feature",
  "properties": {
    "gn:admin1_code":"02",
    "gn:asciiname":"Pekoi",
    "gn:country_code":"PG",
    "gn:dem":6,
    "gn:feature_class":"P",
    "gn:feature_code":"PPL",
    "gn:name":"Pekoi",
    "gn:population":0,
    "gn:timezone":"Pacific/Port_Moresby",
    "iso:country":"PG",
    "name:und_x_variant":[
        "Pekoe",
        "Pekoi"
    ],
    "wof:name":"Pekoi",
    "wof:placetype":"locality"
},
  "geometry": {"coordinates":[145.53251,-7.92035],"type":"Point"}
}