{
  "type": "Feature",
  "properties": {
    "gn:admin1_code":"06",
    "gn:asciiname":"Igimi",
    "gn:country_code":"PG",
    "gn:dem":194,
    "gn:feature_class":"P",
    "gn:feature_code":"PPL",
    "gn:name":"Igimi",
    "gn:population":0,
    "gn:timezone":"Pacific/Port_Moresby",
    "iso:country":"PG",
    "wof:name":"Igimi",
    "wof:placetype":"locality"
},
  "geometry": {"coordinates":[142.37368999999995,-6.259],"type":"Point"}
}