{
  "type": "Feature",
  "properties": {
    "gn:admin1_code":"17",
    "gn:asciiname":"Siamatai",
    "gn:country_code":"PG",
    "gn:dem":31,
    "gn:feature_class":"P",
    "gn:feature_code":"PPL",
    "gn:name":"Siamatai",
    "gn:population":0,
    "gn:timezone":"Pacific/Port_Moresby",
    "iso:country":"PG",
    "wof:name":"Siamatai",
    "wof:placetype":"locality"
},
  "geometry": {"coordinates":[148.75,-5.51667],"type":"Point"}
}