{
  "type": "Feature",
  "properties": {
    "gn:admin1_code":"01",
    "gn:asciiname":"Bulidobu",
    "gn:country_code":"PG",
    "gn:dem":64,
    "gn:feature_class":"P",
    "gn:feature_code":"PPL",
    "gn:name":"Bulidobu",
    "gn:population":0,
    "gn:timezone":"Pacific/Port_Moresby",
    "iso:country":"PG",
    "wof:name":"Bulidobu",
    "wof:placetype":"locality"
},
  "geometry": {"coordinates":[147.77566000000004,-9.65278],"type":"Point"}
}