{
  "type": "Feature",
  "properties": {
    "gn:admin1_code":"03",
    "gn:asciiname":"Garuai",
    "gn:country_code":"PG",
    "gn:dem":14,
    "gn:feature_class":"P",
    "gn:feature_code":"PPL",
    "gn:name":"Garuai",
    "gn:population":0,
    "gn:timezone":"Pacific/Port_Moresby",
    "iso:country":"PG",
    "name:und_x_variant":[
        "Garuwai",
        "Garuai"
    ],
    "wof:name":"Garuai",
    "wof:placetype":"locality"
},
  "geometry": {"coordinates":[150.49458999999999,-10.22329],"type":"Point"}
}