{
  "type": "Feature",
  "properties": {
    "gn:admin1_code":"04",
    "gn:asciiname":"Mosou",
    "gn:cc2":"PG",
    "gn:country_code":"PG",
    "gn:dem":107,
    "gn:feature_class":"P",
    "gn:feature_code":"PPL",
    "gn:name":"Mosou",
    "gn:population":0,
    "gn:timezone":"Pacific/Port_Moresby",
    "iso:country":"PG",
    "name:und_x_variant":[
        "Inonda",
        "Mosou"
    ],
    "wof:name":"Mosou",
    "wof:placetype":"locality"
},
  "geometry": {"coordinates":[148.30000000000001,-8.81667],"type":"Point"}
}