{
  "type": "Feature",
  "properties": {
    "gn:admin1_code":"14",
    "gn:asciiname":"Lumbaip",
    "gn:country_code":"PG",
    "gn:dem":870,
    "gn:feature_class":"P",
    "gn:feature_code":"PPL",
    "gn:name":"Lumbaip",
    "gn:population":0,
    "gn:timezone":"Pacific/Port_Moresby",
    "iso:country":"PG",
    "name:und_x_variant":[
        "Lambaip",
        "Lumbiap",
        "Lumbaip"
    ],
    "wof:name":"Lumbaip",
    "wof:placetype":"locality"
},
  "geometry": {"coordinates":[146.91326000000001,-6.46342],"type":"Point"}
}