{
  "type": "Feature",
  "properties": {
    "gn:admin1_code":"21",
    "gn:asciiname":"Koroba",
    "gn:country_code":"PG",
    "gn:dem":1735,
    "gn:feature_class":"P",
    "gn:feature_code":"PPL",
    "gn:name":"Koroba",
    "gn:population":0,
    "gn:timezone":"Pacific/Port_Moresby",
    "iso:country":"PG",
    "name:eng_x_preferred":[
        "Koroba"
    ],
    "name:und_x_variant":[
        "Kuruba",
        "Koroba"
    ],
    "wof:name":"Koroba",
    "wof:placetype":"locality"
},
  "geometry": {"coordinates":[142.73661000000001,-5.70567],"type":"Point"}
}