{
  "type": "Feature",
  "properties": {
    "gn:admin1_code":"12",
    "gn:asciiname":"Arimatau Number 1",
    "gn:country_code":"PG",
    "gn:dem":730,
    "gn:feature_class":"P",
    "gn:feature_code":"PPL",
    "gn:name":"Arimatau Number 1",
    "gn:population":0,
    "gn:timezone":"Pacific/Port_Moresby",
    "iso:country":"PG",
    "name:und_x_variant":[
        "Arimetau Number 1",
        "Arimatau Number 1"
    ],
    "wof:name":"Arimatau Number 1",
    "wof:placetype":"locality"
},
  "geometry": {"coordinates":[145.29471999999996,-4.82303],"type":"Point"}
}