{
  "type": "Feature",
  "properties": {
    "gn:admin1_code":"08",
    "gn:asciiname":"Korokoa",
    "gn:country_code":"PG",
    "gn:dem":1691,
    "gn:feature_class":"P",
    "gn:feature_code":"PPL",
    "gn:name":"Korokoa",
    "gn:population":0,
    "gn:timezone":"Pacific/Port_Moresby",
    "iso:country":"PG",
    "wof:name":"Korokoa",
    "wof:placetype":"locality"
},
  "geometry": {"coordinates":[144.94999999999999,-6.05],"type":"Point"}
}