{
  "type": "Feature",
  "properties": {
    "gn:admin1_code":"08",
    "gn:asciiname":"Haia",
    "gn:country_code":"PG",
    "gn:dem":1341,
    "gn:feature_class":"P",
    "gn:feature_code":"PPL",
    "gn:name":"Haia",
    "gn:population":0,
    "gn:timezone":"Pacific/Port_Moresby",
    "iso:country":"PG",
    "wof:name":"Haia",
    "wof:placetype":"locality"
},
  "geometry": {"coordinates":[145.06327999999999,-6.70246],"type":"Point"}
}