{
  "type": "Feature",
  "properties": {
    "gn:admin1_code":"07",
    "gn:asciiname":"Namatoa",
    "gn:country_code":"PG",
    "gn:dem":381,
    "gn:feature_class":"P",
    "gn:feature_code":"PPL",
    "gn:name":"Namatoa",
    "gn:population":0,
    "gn:timezone":"Pacific/Bougainville",
    "iso:country":"PG",
    "wof:name":"Namatoa",
    "wof:placetype":"locality"
},
  "geometry": {"coordinates":[155.04593,-5.63377],"type":"Point"}
}