{
  "type": "Feature",
  "properties": {
    "gn:admin1_code":"01",
    "gn:asciiname":"Senunu",
    "gn:country_code":"PG",
    "gn:dem":60,
    "gn:feature_class":"P",
    "gn:feature_code":"PPL",
    "gn:name":"Senunu",
    "gn:population":0,
    "gn:timezone":"Pacific/Port_Moresby",
    "iso:country":"PG",
    "wof:name":"Senunu",
    "wof:placetype":"locality"
},
  "geometry": {"coordinates":[147.46778,-9.64126],"type":"Point"}
}