{
  "type": "Feature",
  "properties": {
    "gn:admin1_code":"09",
    "gn:asciiname":"Gimiseiyufo",
    "gn:cc2":"PG",
    "gn:country_code":"PG",
    "gn:dem":2354,
    "gn:feature_class":"P",
    "gn:feature_code":"PPL",
    "gn:name":"Gimiseiyufo",
    "gn:population":0,
    "gn:timezone":"Pacific/Port_Moresby",
    "iso:country":"PG",
    "name:und_x_variant":[
        "Gimiseiyufa",
        "Gimiseiyufo"
    ],
    "wof:name":"Gimiseiyufo",
    "wof:placetype":"locality"
},
  "geometry": {"coordinates":[145.21666999999999,-5.91667],"type":"Point"}
}