{
  "type": "Feature",
  "properties": {
    "gn:admin1_code":"13",
    "gn:asciiname":"Johan",
    "gn:country_code":"PG",
    "gn:dem":0,
    "gn:feature_class":"P",
    "gn:feature_code":"PPL",
    "gn:name":"Johan",
    "gn:population":0,
    "gn:timezone":"Pacific/Port_Moresby",
    "iso:country":"PG",
    "name:bul_x_preferred":[
        "\u0419\u043e\u0445\u0430\u043d"
    ],
    "name:ita_x_preferred":[
        "Johan"
    ],
    "name:nld_x_preferred":[
        "Johan"
    ],
    "name:rus_x_preferred":[
        "\u042e\u0445\u0430\u043d"
    ],
    "name:spa_x_preferred":[
        "Johan"
    ],
    "wof:name":"Johan",
    "wof:placetype":"locality"
},
  "geometry": {"coordinates":[146.57746,-1.99167],"type":"Point"}
}