{
  "type": "Feature",
  "properties": {
    "gn:admin1_code":"14",
    "gn:asciiname":"Malasanga",
    "gn:country_code":"PG",
    "gn:dem":10,
    "gn:feature_class":"P",
    "gn:feature_code":"PPL",
    "gn:name":"Malasanga",
    "gn:population":0,
    "gn:timezone":"Pacific/Port_Moresby",
    "iso:country":"PG",
    "wof:name":"Malasanga",
    "wof:placetype":"locality"
},
  "geometry": {"coordinates":[147.05000000000001,-5.91667],"type":"Point"}
}