{
  "type": "Feature",
  "properties": {
    "gn:admin1_code":"12",
    "gn:asciiname":"Ensagobu",
    "gn:country_code":"PG",
    "gn:dem":40,
    "gn:feature_class":"P",
    "gn:feature_code":"PPL",
    "gn:name":"Ensagobu",
    "gn:population":0,
    "gn:timezone":"Pacific/Port_Moresby",
    "iso:country":"PG",
    "wof:name":"Ensagobu",
    "wof:placetype":"locality"
},
  "geometry": {"coordinates":[144.69999999999999,-5.01667],"type":"Point"}
}