{
  "type": "Feature",
  "properties": {
    "gn:admin1_code":"14",
    "gn:asciiname":"Dona",
    "gn:country_code":"PG",
    "gn:dem":11,
    "gn:feature_class":"P",
    "gn:feature_code":"PPL",
    "gn:name":"Dona",
    "gn:population":0,
    "gn:timezone":"Pacific/Port_Moresby",
    "iso:country":"PG",
    "name:cat_x_preferred":[
        "Dona"
    ],
    "name:ceb_x_preferred":[
        "Dona"
    ],
    "name:deu_x_preferred":[
        "Dona"
    ],
    "name:fra_x_preferred":[
        "Dona"
    ],
    "name:ita_x_preferred":[
        "Dona"
    ],
    "name:pol_x_preferred":[
        "Dona"
    ],
    "name:spa_x_preferred":[
        "Dona"
    ],
    "name:swe_x_preferred":[
        "Dona"
    ],
    "name:ukr_x_preferred":[
        "\u0414\u043e\u043d\u0430"
    ],
    "wof:name":"Dona",
    "wof:placetype":"locality"
},
  "geometry": {"coordinates":[147.66603000000001,-7.80628],"type":"Point"}
}