{
  "type": "Feature",
  "properties": {
    "gn:admin1_code":"11",
    "gn:asciiname":"Sikaium",
    "gn:country_code":"PG",
    "gn:dem":39,
    "gn:feature_class":"P",
    "gn:feature_code":"PPL",
    "gn:name":"Sikaium",
    "gn:population":0,
    "gn:timezone":"Pacific/Port_Moresby",
    "iso:country":"PG",
    "wof:name":"Sikaium",
    "wof:placetype":"locality"
},
  "geometry": {"coordinates":[143.37511999999995,-4.7113],"type":"Point"}
}