{
  "type": "Feature",
  "properties": {
    "gn:admin1_code":"04",
    "gn:asciiname":"Inawai",
    "gn:country_code":"PG",
    "gn:dem":29,
    "gn:feature_class":"P",
    "gn:feature_code":"PPL",
    "gn:name":"Inawai",
    "gn:population":0,
    "gn:timezone":"Pacific/Port_Moresby",
    "iso:country":"PG",
    "wof:name":"Inawai",
    "wof:placetype":"locality"
},
  "geometry": {"coordinates":[141.36667,-8.21667],"type":"Point"}
}