{
  "type": "Feature",
  "properties": {
    "gn:admin1_code":"18",
    "gn:asciiname":"Suain Number 2",
    "gn:country_code":"PG",
    "gn:dem":18,
    "gn:feature_class":"P",
    "gn:feature_code":"PPL",
    "gn:name":"Suain Number 2",
    "gn:population":0,
    "gn:timezone":"Pacific/Port_Moresby",
    "iso:country":"PG",
    "name:und_x_variant":[
        "Suain 2",
        "Suain Number 2"
    ],
    "wof:name":"Suain Number 2",
    "wof:placetype":"locality"
},
  "geometry": {"coordinates":[142.93385000000001,-3.34224],"type":"Point"}
}