{
  "type": "Feature",
  "properties": {
    "gn:admin1_code":"10",
    "gn:asciiname":"Matawan",
    "gn:country_code":"PG",
    "gn:dem":316,
    "gn:feature_class":"P",
    "gn:feature_code":"PPL",
    "gn:name":"Matawan",
    "gn:population":0,
    "gn:timezone":"Pacific/Port_Moresby",
    "iso:country":"PG",
    "wof:name":"Matawan",
    "wof:placetype":"locality"
},
  "geometry": {"coordinates":[150.99966000000001,-5.83406],"type":"Point"}
}