{
  "type": "Feature",
  "properties": {
    "gn:admin1_code":"12",
    "gn:asciiname":"Kupi",
    "gn:country_code":"PG",
    "gn:dem":82,
    "gn:feature_class":"P",
    "gn:feature_code":"PPL",
    "gn:name":"Kupi",
    "gn:population":0,
    "gn:timezone":"Pacific/Port_Moresby",
    "iso:country":"PG",
    "wof:name":"Kupi",
    "wof:placetype":"locality"
},
  "geometry": {"coordinates":[144.83623,-5.26115],"type":"Point"}
}