{
  "type": "Feature",
  "properties": {
    "gn:admin1_code":"11",
    "gn:asciiname":"Kandai",
    "gn:country_code":"PG",
    "gn:dem":37,
    "gn:feature_class":"P",
    "gn:feature_code":"PPL",
    "gn:name":"Kandai",
    "gn:population":0,
    "gn:timezone":"Pacific/Port_Moresby",
    "iso:country":"PG",
    "name:und_x_variant":[
        "Kandi"
    ],
    "wof:name":"Kandai",
    "wof:placetype":"locality"
},
  "geometry": {"coordinates":[143.77906000000004,-3.6583],"type":"Point"}
}