{
  "type": "Feature",
  "properties": {
    "gn:admin1_code":"17",
    "gn:asciiname":"Asepsep",
    "gn:cc2":"PG",
    "gn:country_code":"PG",
    "gn:dem":1,
    "gn:feature_class":"P",
    "gn:feature_code":"PPL",
    "gn:name":"Asepsep",
    "gn:population":0,
    "gn:timezone":"Pacific/Port_Moresby",
    "iso:country":"PG",
    "name:und_x_variant":[
        "Sep Sep",
        "Asepsep"
    ],
    "wof:name":"Asepsep",
    "wof:placetype":"locality"
},
  "geometry": {"coordinates":[149.78333000000001,-6.31667],"type":"Point"}
}