{
  "type": "Feature",
  "properties": {
    "gn:admin1_code":"08",
    "gn:asciiname":"Kombukane",
    "gn:country_code":"PG",
    "gn:dem":1761,
    "gn:feature_class":"P",
    "gn:feature_code":"PPL",
    "gn:name":"Kombukane",
    "gn:population":0,
    "gn:timezone":"Pacific/Port_Moresby",
    "iso:country":"PG",
    "wof:name":"Kombukane",
    "wof:placetype":"locality"
},
  "geometry": {"coordinates":[144.89229,-6.0232],"type":"Point"}
}