{
  "type": "Feature",
  "properties": {
    "gn:admin1_code":"14",
    "gn:asciiname":"Wongat",
    "gn:country_code":"PG",
    "gn:dem":642,
    "gn:feature_class":"P",
    "gn:feature_code":"PPL",
    "gn:name":"Wongat",
    "gn:population":0,
    "gn:timezone":"Pacific/Port_Moresby",
    "iso:country":"PG",
    "wof:name":"Wongat",
    "wof:placetype":"locality"
},
  "geometry": {"coordinates":[146.41829999999999,-6.34884],"type":"Point"}
}