{
  "type": "Feature",
  "properties": {
    "iso:country":"PG",
    "name:ceb_x_preferred":[
        "Lae Nadzab Airport"
    ],
    "name:deu_x_preferred":[
        "Flughafen Lae Nadzab"
    ],
    "name:eng_x_preferred":[
        "Lae Nadzab Airport"
    ],
    "name:fas_x_preferred":[
        "\u0641\u0631\u0648\u062f\u06af\u0627\u0647 \u0644\u0627\u06cc \u0646\u0627\u062f\u0632\u0627\u0628"
    ],
    "name:ind_x_preferred":[
        "Bandar Udara Lae Nadzab"
    ],
    "name:jpn_x_preferred":[
        "\u30e9\u30a8\u30fb\u30ca\u30d6\u30b6\u30d6\u7a7a\u6e2f"
    ],
    "name:msa_x_preferred":[
        "Lapangan Terbang Nadzab"
    ],
    "name:pol_x_preferred":[
        "Port lotniczy Lae Nadzab"
    ],
    "name:ron_x_preferred":[
        "Aeroportul Lae Nadzab"
    ],
    "name:tgk_x_preferred":[
        "\u0424\u0443\u0440\u0443\u0434\u0433\u043e\u04b3\u0438 \u043b\u043e \u043d\u043e\u0434\u0437\u043e\u0431"
    ],
    "name:zho_x_preferred":[
        "\u840a\u57ce\u7d0d\u624e\u5e03\u6a5f\u5834"
    ],
    "oa:elevation_ft":"239",
    "oa:type":"medium_airport",
    "wd:wordcount":871,
    "woe:hierarchy":{
        "country_id":23424926,
        "planet_id":1,
        "state_id":2346594
    },
    "wof:name":"Nadzab Airport",
    "wof:placetype":"campus"
},
  "geometry": {"coordinates":[146.72611111110999,-6.5697222222222],"type":"Point"}
}