{
  "type": "Feature",
  "properties": {
    "gn:admin1_code":"09",
    "gn:asciiname":"Onaningka",
    "gn:country_code":"PG",
    "gn:dem":1489,
    "gn:feature_class":"P",
    "gn:feature_code":"PPL",
    "gn:name":"Onaningka",
    "gn:population":0,
    "gn:timezone":"Pacific/Port_Moresby",
    "iso:country":"PG",
    "wof:name":"Onaningka",
    "wof:placetype":"locality"
},
  "geometry": {"coordinates":[145.99341999999999,-6.36181],"type":"Point"}
}