{
  "type": "Feature",
  "properties": {
    "gn:admin1_code":"07",
    "gn:asciiname":"Umum",
    "gn:country_code":"PG",
    "gn:dem":49,
    "gn:feature_class":"P",
    "gn:feature_code":"PPL",
    "gn:name":"Umum",
    "gn:population":0,
    "gn:timezone":"Pacific/Bougainville",
    "iso:country":"PG",
    "wof:name":"Umum",
    "wof:placetype":"locality"
},
  "geometry": {"coordinates":[154.84999999999999,-5.53333],"type":"Point"}
}