{
  "type": "Feature",
  "properties": {
    "gn:admin1_code":"14",
    "gn:asciiname":"Finungwa",
    "gn:country_code":"PG",
    "gn:dem":1043,
    "gn:feature_class":"P",
    "gn:feature_code":"PPL",
    "gn:name":"Finungwa",
    "gn:population":0,
    "gn:timezone":"Pacific/Port_Moresby",
    "iso:country":"PG",
    "wof:name":"Finungwa",
    "wof:placetype":"locality"
},
  "geometry": {"coordinates":[146.62145000000001,-6.34337],"type":"Point"}
}