{
  "type": "Feature",
  "properties": {
    "gn:admin1_code":"11",
    "gn:asciiname":"Wrau Yommi",
    "gn:country_code":"PG",
    "gn:dem":32,
    "gn:feature_class":"P",
    "gn:feature_code":"PPL",
    "gn:name":"Wrau Yommi",
    "gn:population":0,
    "gn:timezone":"Pacific/Port_Moresby",
    "iso:country":"PG",
    "wof:name":"Wrau Yommi",
    "wof:placetype":"locality"
},
  "geometry": {"coordinates":[141.80000000000001,-4.03333],"type":"Point"}
}