{
  "type": "Feature",
  "properties": {
    "gn:admin1_code":"12",
    "gn:asciiname":"Erima",
    "gn:country_code":"PG",
    "gn:dem":19,
    "gn:feature_class":"P",
    "gn:feature_code":"PPL",
    "gn:name":"Erima",
    "gn:population":0,
    "gn:timezone":"Pacific/Port_Moresby",
    "iso:country":"PG",
    "wof:name":"Erima",
    "wof:placetype":"locality"
},
  "geometry": {"coordinates":[145.72619,-5.40252],"type":"Point"}
}