{
  "type": "Feature",
  "properties": {
    "gn:admin1_code":"06",
    "gn:asciiname":"Debionne",
    "gn:country_code":"PG",
    "gn:dem":67,
    "gn:feature_class":"P",
    "gn:feature_code":"PPL",
    "gn:name":"Debionne",
    "gn:population":0,
    "gn:timezone":"Pacific/Port_Moresby",
    "iso:country":"PG",
    "wof:name":"Debionne",
    "wof:placetype":"locality"
},
  "geometry": {"coordinates":[141.61667,-6.21667],"type":"Point"}
}