{
  "type": "Feature",
  "properties": {
    "gn:admin1_code":"01",
    "gn:asciiname":"Riwalirubu",
    "gn:country_code":"PG",
    "gn:dem":119,
    "gn:feature_class":"P",
    "gn:feature_code":"PPL",
    "gn:name":"Riwalirubu",
    "gn:population":0,
    "gn:timezone":"Pacific/Port_Moresby",
    "iso:country":"PG",
    "name:und_x_variant":[
        "Riwalirupu",
        "Riwalirubu"
    ],
    "wof:name":"Riwalirubu",
    "wof:placetype":"locality"
},
  "geometry": {"coordinates":[147.68509,-9.95279],"type":"Point"}
}