{
  "type": "Feature",
  "properties": {
    "gn:admin1_code":"06",
    "gn:asciiname":"Kwowowinna",
    "gn:country_code":"PG",
    "gn:dem":62,
    "gn:feature_class":"P",
    "gn:feature_code":"PPL",
    "gn:name":"Kwowowinna",
    "gn:population":0,
    "gn:timezone":"Pacific/Port_Moresby",
    "iso:country":"PG",
    "wof:name":"Kwowowinna",
    "wof:placetype":"locality"
},
  "geometry": {"coordinates":[141.51667,-6.41667],"type":"Point"}
}