{
  "type": "Feature",
  "properties": {
    "gn:admin1_code":"19",
    "gn:asciiname":"Wamatesa",
    "gn:country_code":"PG",
    "gn:dem":2270,
    "gn:feature_class":"P",
    "gn:feature_code":"PPL",
    "gn:name":"Wamatesa",
    "gn:population":0,
    "gn:timezone":"Pacific/Port_Moresby",
    "iso:country":"PG",
    "wof:name":"Wamatesa",
    "wof:placetype":"locality"
},
  "geometry": {"coordinates":[143.78757999999999,-5.62003],"type":"Point"}
}