{
  "type": "Feature",
  "properties": {
    "gn:admin1_code":"12",
    "gn:asciiname":"Dangale",
    "gn:country_code":"PG",
    "gn:dem":84,
    "gn:feature_class":"P",
    "gn:feature_code":"PPL",
    "gn:name":"Dangale",
    "gn:population":0,
    "gn:timezone":"Pacific/Port_Moresby",
    "iso:country":"PG",
    "wof:name":"Dangale",
    "wof:placetype":"locality"
},
  "geometry": {"coordinates":[145.06433000000001,-4.04886],"type":"Point"}
}