{
  "type": "Feature",
  "properties": {
    "gn:admin1_code":"06",
    "gn:asciiname":"Tebuda",
    "gn:country_code":"PG",
    "gn:dem":110,
    "gn:feature_class":"P",
    "gn:feature_code":"PPL",
    "gn:name":"Tebuda",
    "gn:population":0,
    "gn:timezone":"Pacific/Port_Moresby",
    "iso:country":"PG",
    "wof:name":"Tebuda",
    "wof:placetype":"locality"
},
  "geometry": {"coordinates":[141.91666999999995,-6.13333],"type":"Point"}
}