{
  "type": "Feature",
  "properties": {
    "gn:admin1_code":"05",
    "gn:asciiname":"Map",
    "gn:country_code":"PG",
    "gn:dem":1836,
    "gn:feature_class":"P",
    "gn:feature_code":"PPL",
    "gn:name":"Map",
    "gn:population":0,
    "gn:timezone":"Pacific/Port_Moresby",
    "iso:country":"PG",
    "wof:name":"Map",
    "wof:placetype":"locality"
},
  "geometry": {"coordinates":[143.61418999999995,-6.07898],"type":"Point"}
}