{
  "type": "Feature",
  "properties": {
    "gn:admin1_code":"19",
    "gn:asciiname":"Londo",
    "gn:country_code":"PG",
    "gn:dem":1945,
    "gn:feature_class":"P",
    "gn:feature_code":"PPL",
    "gn:name":"Londo",
    "gn:population":0,
    "gn:timezone":"Pacific/Port_Moresby",
    "iso:country":"PG",
    "wof:name":"Londo",
    "wof:placetype":"locality"
},
  "geometry": {"coordinates":[143.86479,-5.66284],"type":"Point"}
}