{
  "type": "Feature",
  "properties": {
    "gn:admin1_code":"09",
    "gn:asciiname":"Amamonta",
    "gn:country_code":"PG",
    "gn:dem":1610,
    "gn:feature_class":"P",
    "gn:feature_code":"PPL",
    "gn:name":"Amamonta",
    "gn:population":0,
    "gn:timezone":"Pacific/Port_Moresby",
    "iso:country":"PG",
    "wof:name":"Amamonta",
    "wof:placetype":"locality"
},
  "geometry": {"coordinates":[145.94163999999995,-6.35827],"type":"Point"}
}