{
  "type": "Feature",
  "properties": {
    "gn:admin1_code":"11",
    "gn:asciiname":"Hereng",
    "gn:country_code":"PG",
    "gn:dem":356,
    "gn:feature_class":"P",
    "gn:feature_code":"PPL",
    "gn:name":"Hereng",
    "gn:population":0,
    "gn:timezone":"Pacific/Port_Moresby",
    "iso:country":"PG",
    "name:und_x_variant":[
        "Hering",
        "Hereng"
    ],
    "wof:name":"Hereng",
    "wof:placetype":"locality"
},
  "geometry": {"coordinates":[143.77995000000001,-3.73556],"type":"Point"}
}