{
  "type": "Feature",
  "properties": {
    "gn:admin1_code":"01",
    "gn:asciiname":"Fofo Fofo",
    "gn:cc2":"PG",
    "gn:country_code":"PG",
    "gn:dem":700,
    "gn:feature_class":"P",
    "gn:feature_code":"PPL",
    "gn:name":"Fofo Fofo",
    "gn:population":0,
    "gn:timezone":"Pacific/Port_Moresby",
    "iso:country":"PG",
    "name:und_x_variant":[
        "Foto Foto",
        "Fofo Fofo"
    ],
    "wof:name":"Fofo Fofo",
    "wof:placetype":"locality"
},
  "geometry": {"coordinates":[146.88333,-8.61667],"type":"Point"}
}