{
  "type": "Feature",
  "properties": {
    "gn:admin1_code":"09",
    "gn:asciiname":"Punano Number 2",
    "gn:country_code":"PG",
    "gn:dem":1593,
    "gn:feature_class":"P",
    "gn:feature_code":"PPL",
    "gn:name":"Punano Number 2",
    "gn:population":0,
    "gn:timezone":"Pacific/Port_Moresby",
    "iso:country":"PG",
    "name:und_x_variant":[
        "Punano 2",
        "Punano Number 2"
    ],
    "wof:name":"Punano Number 2",
    "wof:placetype":"locality"
},
  "geometry": {"coordinates":[145.92341999999999,-6.26885],"type":"Point"}
}