{
  "type": "Feature",
  "properties": {
    "gn:admin1_code":"05",
    "gn:asciiname":"Egenda",
    "gn:country_code":"PG",
    "gn:dem":1808,
    "gn:feature_class":"P",
    "gn:feature_code":"PPL",
    "gn:name":"Egenda",
    "gn:population":0,
    "gn:timezone":"Pacific/Port_Moresby",
    "iso:country":"PG",
    "wof:name":"Egenda",
    "wof:placetype":"locality"
},
  "geometry": {"coordinates":[143.47314,-6.16461],"type":"Point"}
}