{
  "type": "Feature",
  "properties": {
    "gn:admin1_code":"11",
    "gn:asciiname":"Wum",
    "gn:country_code":"PG",
    "gn:dem":378,
    "gn:feature_class":"P",
    "gn:feature_code":"PPL",
    "gn:name":"Wum",
    "gn:population":0,
    "gn:timezone":"Pacific/Port_Moresby",
    "iso:country":"PG",
    "name:ceb_x_preferred":[
        "Wum"
    ],
    "name:deu_x_preferred":[
        "Wum"
    ],
    "name:fra_x_preferred":[
        "Wum"
    ],
    "name:heb_x_preferred":[
        "\u05d5\u05d5\u05dd"
    ],
    "name:ita_x_preferred":[
        "Wum"
    ],
    "name:msa_x_preferred":[
        "Wum"
    ],
    "name:pol_x_preferred":[
        "Wum"
    ],
    "name:por_x_preferred":[
        "Wum"
    ],
    "name:ron_x_preferred":[
        "Wum"
    ],
    "name:spa_x_preferred":[
        "Wum"
    ],
    "name:swe_x_preferred":[
        "Wum"
    ],
    "name:yor_x_preferred":[
        "Wum"
    ],
    "wof:name":"Wum",
    "wof:placetype":"locality"
},
  "geometry": {"coordinates":[142.74907999999999,-3.51261],"type":"Point"}
}