{
  "type": "Feature",
  "properties": {
    "gn:admin1_code":"11",
    "gn:asciiname":"Wum",
    "gn:country_code":"PG",
    "gn:dem":378,
    "gn:feature_class":"P",
    "gn:feature_code":"PPL",
    "gn:name":"Wum",
    "gn:population":0,
    "gn:timezone":"Pacific/Port_Moresby",
    "iso:country":"PG",
    "name:ben_x_preferred":[
        "\u0993\u0989\u09ae"
    ],
    "name:ceb_x_preferred":[
        "Wum"
    ],
    "name:deu_x_preferred":[
        "Wum"
    ],
    "name:ell_x_preferred":[
        "\u0393\u03bf\u03c5\u03bc"
    ],
    "name:fas_x_preferred":[
        "\u0648\u0648\u0645"
    ],
    "name:fra_x_preferred":[
        "Wum"
    ],
    "name:heb_x_preferred":[
        "\u05d5\u05d5\u05dd"
    ],
    "name:hin_x_preferred":[
        "\u0935\u092e"
    ],
    "name:hun_x_preferred":[
        "Wum"
    ],
    "name:ind_x_preferred":[
        "Wum"
    ],
    "name:ita_x_preferred":[
        "Wum"
    ],
    "name:jpn_x_preferred":[
        "\u30a6\u30e0"
    ],
    "name:kor_x_preferred":[
        "\uc6c0"
    ],
    "name:msa_x_preferred":[
        "Wum"
    ],
    "name:pol_x_preferred":[
        "Wum"
    ],
    "name:por_x_preferred":[
        "Wum"
    ],
    "name:ron_x_preferred":[
        "Wum"
    ],
    "name:rus_x_preferred":[
        "\u0412\u0443\u043c"
    ],
    "name:spa_x_preferred":[
        "Wum"
    ],
    "name:swe_x_preferred":[
        "Wum"
    ],
    "name:tur_x_preferred":[
        "Wum"
    ],
    "name:ukr_x_preferred":[
        "\u0412\u0443\u043c"
    ],
    "name:urd_x_preferred":[
        "\u0648\u0645"
    ],
    "name:vie_x_preferred":[
        "Wum"
    ],
    "name:yor_x_preferred":[
        "Wum"
    ],
    "wof:name":"Wum",
    "wof:placetype":"locality"
},
  "geometry": {"coordinates":[142.74907999999999,-3.51261],"type":"Point"}
}