{
  "type": "Feature",
  "properties": {
    "gn:admin1_code":"11",
    "gn:asciiname":"Wum",
    "gn:country_code":"PG",
    "gn:dem":378,
    "gn:feature_class":"P",
    "gn:feature_code":"PPL",
    "gn:name":"Wum",
    "gn:population":0,
    "gn:timezone":"Pacific/Port_Moresby",
    "iso:country":"PG",
    "wof:name":"Wum",
    "wof:placetype":"locality"
},
  "geometry": {"coordinates":[142.74907999999999,-3.51261],"type":"Point"}
}