{
  "type": "Feature",
  "properties": {
    "gn:admin1_code":"05",
    "gn:asciiname":"Sorotagi",
    "gn:country_code":"PG",
    "gn:dem":919,
    "gn:feature_class":"P",
    "gn:feature_code":"PPL",
    "gn:name":"Sorotagi",
    "gn:population":0,
    "gn:timezone":"Pacific/Port_Moresby",
    "iso:country":"PG",
    "wof:name":"Sorotagi",
    "wof:placetype":"locality"
},
  "geometry": {"coordinates":[143.38333,-6.53333],"type":"Point"}
}