{
  "type": "Feature",
  "properties": {
    "gn:admin1_code":"15",
    "gn:asciiname":"Ratavis",
    "gn:country_code":"PG",
    "gn:dem":-9999,
    "gn:feature_class":"P",
    "gn:feature_code":"PPL",
    "gn:name":"Ratavis",
    "gn:population":0,
    "gn:timezone":"Pacific/Port_Moresby",
    "iso:country":"PG",
    "name:und_x_variant":[
        "Retuis",
        "Rataris",
        "Rativis",
        "Ratavis"
    ],
    "wof:name":"Ratavis",
    "wof:placetype":"locality"
},
  "geometry": {"coordinates":[152.56384,-3.81166],"type":"Point"}
}