{
  "type": "Feature",
  "properties": {
    "gn:admin1_code":"12",
    "gn:asciiname":"Yandera",
    "gn:country_code":"PG",
    "gn:dem":1722,
    "gn:feature_class":"P",
    "gn:feature_code":"PPL",
    "gn:name":"Yandera",
    "gn:population":0,
    "gn:timezone":"Pacific/Port_Moresby",
    "iso:country":"PG",
    "wof:name":"Yandera",
    "wof:placetype":"locality"
},
  "geometry": {"coordinates":[145.14534,-5.72944],"type":"Point"}
}