{
  "type": "Feature",
  "properties": {
    "gn:admin1_code":"12",
    "gn:asciiname":"Gabutamon",
    "gn:country_code":"PG",
    "gn:dem":1009,
    "gn:feature_class":"P",
    "gn:feature_code":"PPL",
    "gn:name":"Gabutamon",
    "gn:population":0,
    "gn:timezone":"Pacific/Port_Moresby",
    "iso:country":"PG",
    "wof:name":"Gabutamon",
    "wof:placetype":"locality"
},
  "geometry": {"coordinates":[146.61912000000001,-5.81291],"type":"Point"}
}