{
  "type": "Feature",
  "properties": {
    "gn:admin1_code":"12",
    "gn:asciiname":"Bafor",
    "gn:country_code":"PG",
    "gn:dem":167,
    "gn:feature_class":"P",
    "gn:feature_code":"PPL",
    "gn:name":"Bafor",
    "gn:population":0,
    "gn:timezone":"Pacific/Port_Moresby",
    "iso:country":"PG",
    "name:und_x_variant":[
        "Bator",
        "Bafor"
    ],
    "wof:name":"Bafor",
    "wof:placetype":"locality"
},
  "geometry": {"coordinates":[145.89874,-4.67008],"type":"Point"}
}