{
  "type": "Feature",
  "properties": {
    "gn:admin1_code":"18",
    "gn:asciiname":"Fisi",
    "gn:country_code":"PG",
    "gn:dem":424,
    "gn:feature_class":"P",
    "gn:feature_code":"PPL",
    "gn:name":"Fisi",
    "gn:population":0,
    "gn:timezone":"Pacific/Port_Moresby",
    "iso:country":"PG",
    "wof:name":"Fisi",
    "wof:placetype":"locality"
},
  "geometry": {"coordinates":[141.16723000000005,-3.65601],"type":"Point"}
}