{
  "type": "Feature",
  "properties": {
    "gn:admin1_code":"03",
    "gn:asciiname":"Giwa",
    "gn:country_code":"PG",
    "gn:dem":14,
    "gn:feature_class":"P",
    "gn:feature_code":"PPL",
    "gn:name":"Giwa",
    "gn:population":0,
    "gn:timezone":"Pacific/Port_Moresby",
    "iso:country":"PG",
    "name:und_x_variant":[
        "Giwa Mission",
        "Giwa"
    ],
    "wof:name":"Giwa",
    "wof:placetype":"locality"
},
  "geometry": {"coordinates":[149.79518999999999,-9.78083],"type":"Point"}
}