{
  "type": "Feature",
  "properties": {
    "gn:admin1_code":"18",
    "gn:asciiname":"Airu",
    "gn:country_code":"PG",
    "gn:dem":66,
    "gn:feature_class":"P",
    "gn:feature_code":"PPL",
    "gn:name":"Airu",
    "gn:population":0,
    "gn:timezone":"Pacific/Port_Moresby",
    "iso:country":"PG",
    "wof:name":"Airu",
    "wof:placetype":"locality"
},
  "geometry": {"coordinates":[141.28531000000001,-2.91906],"type":"Point"}
}