{
  "type": "Feature",
  "properties": {
    "gn:admin1_code":"02",
    "gn:asciiname":"Sari",
    "gn:country_code":"PG",
    "gn:dem":215,
    "gn:feature_class":"P",
    "gn:feature_code":"PPL",
    "gn:name":"Sari",
    "gn:population":0,
    "gn:timezone":"Pacific/Port_Moresby",
    "iso:country":"PG",
    "wof:name":"Sari",
    "wof:placetype":"locality"
},
  "geometry": {"coordinates":[143.93333000000001,-7.26667],"type":"Point"}
}