{
  "type": "Feature",
  "properties": {
    "gn:admin1_code":"01",
    "gn:asciiname":"Kwalimurubu",
    "gn:country_code":"PG",
    "gn:dem":70,
    "gn:feature_class":"P",
    "gn:feature_code":"PPL",
    "gn:name":"Kwalimurubu",
    "gn:population":0,
    "gn:timezone":"Pacific/Port_Moresby",
    "iso:country":"PG",
    "name:und_x_variant":[
        "Kwalimurupu",
        "Kwalimurubu"
    ],
    "wof:name":"Kwalimurubu",
    "wof:placetype":"locality"
},
  "geometry": {"coordinates":[147.54956000000001,-9.78862],"type":"Point"}
}