{
  "type": "Feature",
  "properties": {
    "gn:admin1_code":"03",
    "gn:asciiname":"Kuraba",
    "gn:country_code":"PG",
    "gn:dem":299,
    "gn:feature_class":"P",
    "gn:feature_code":"PPL",
    "gn:name":"Kuraba",
    "gn:population":0,
    "gn:timezone":"Pacific/Port_Moresby",
    "iso:country":"PG",
    "wof:name":"Kuraba",
    "wof:placetype":"locality"
},
  "geometry": {"coordinates":[149.65013000000005,-9.85312],"type":"Point"}
}