{
  "type": "Feature",
  "properties": {
    "gn:admin1_code":"06",
    "gn:asciiname":"Gomskai",
    "gn:country_code":"PG",
    "gn:dem":55,
    "gn:feature_class":"P",
    "gn:feature_code":"PPL",
    "gn:name":"Gomskai",
    "gn:population":0,
    "gn:timezone":"Pacific/Port_Moresby",
    "iso:country":"PG",
    "wof:name":"Gomskai",
    "wof:placetype":"locality"
},
  "geometry": {"coordinates":[141.39771000000005,-6.1571],"type":"Point"}
}