{
  "type": "Feature",
  "properties": {
    "gn:admin1_code":"10",
    "gn:asciiname":"Warangoi",
    "gn:country_code":"PG",
    "gn:dem":127,
    "gn:feature_class":"P",
    "gn:feature_code":"PPL",
    "gn:name":"Warangoi",
    "gn:population":0,
    "gn:timezone":"Pacific/Port_Moresby",
    "iso:country":"PG",
    "wof:name":"Warangoi",
    "wof:placetype":"locality"
},
  "geometry": {"coordinates":[152.15000000000001,-4.48333],"type":"Point"}
}