{
  "type": "Feature",
  "properties": {
    "gn:admin1_code":"14",
    "gn:asciiname":"Wuru",
    "gn:country_code":"PG",
    "gn:dem":105,
    "gn:feature_class":"P",
    "gn:feature_code":"PPL",
    "gn:name":"Wuru",
    "gn:population":0,
    "gn:timezone":"Pacific/Port_Moresby",
    "iso:country":"PG",
    "wof:name":"Wuru",
    "wof:placetype":"locality"
},
  "geometry": {"coordinates":[146.38333,-6.78333],"type":"Point"}
}