{
  "type": "Feature",
  "properties": {
    "gn:admin1_code":"18",
    "gn:asciiname":"Dimansigan",
    "gn:country_code":"PG",
    "gn:dem":545,
    "gn:feature_class":"P",
    "gn:feature_code":"PPL",
    "gn:name":"Dimansigan",
    "gn:population":0,
    "gn:timezone":"Pacific/Port_Moresby",
    "iso:country":"PG",
    "wof:name":"Dimansigan",
    "wof:placetype":"locality"
},
  "geometry": {"coordinates":[141.14997,-4.81317],"type":"Point"}
}