{
  "type": "Feature",
  "properties": {
    "gn:admin1_code":"02",
    "gn:asciiname":"Hiloi",
    "gn:country_code":"PG",
    "gn:dem":32,
    "gn:feature_class":"P",
    "gn:feature_code":"PPL",
    "gn:name":"Hiloi",
    "gn:population":0,
    "gn:timezone":"Pacific/Port_Moresby",
    "iso:country":"PG",
    "wof:name":"Hiloi",
    "wof:placetype":"locality"
},
  "geometry": {"coordinates":[145.46446,-7.90243],"type":"Point"}
}