{
  "type": "Feature",
  "properties": {
    "gn:admin1_code":"07",
    "gn:asciiname":"Maika",
    "gn:country_code":"PG",
    "gn:dem":23,
    "gn:feature_class":"P",
    "gn:feature_code":"PPL",
    "gn:name":"Maika",
    "gn:population":0,
    "gn:timezone":"Pacific/Bougainville",
    "iso:country":"PG",
    "name:und_x_variant":[
        "Maiki",
        "Maika"
    ],
    "wof:name":"Maika",
    "wof:placetype":"locality"
},
  "geometry": {"coordinates":[155.77095,-6.74847],"type":"Point"}
}