{
  "type": "Feature",
  "properties": {
    "gn:admin1_code":"09",
    "gn:asciiname":"Habaru Number 2",
    "gn:cc2":"PG",
    "gn:country_code":"PG",
    "gn:dem":1620,
    "gn:feature_class":"P",
    "gn:feature_code":"PPL",
    "gn:name":"Habaru Number 2",
    "gn:population":0,
    "gn:timezone":"Pacific/Port_Moresby",
    "iso:country":"PG",
    "name:und_x_variant":[
        "Habaru 2",
        "Habaru Number 2"
    ],
    "wof:name":"Habaru Number 2",
    "wof:placetype":"locality"
},
  "geometry": {"coordinates":[145.43333000000001,-6.36667],"type":"Point"}
}