{
  "type": "Feature",
  "properties": {
    "gn:admin1_code":"17",
    "gn:asciiname":"Aka",
    "gn:cc2":"PG",
    "gn:country_code":"PG",
    "gn:dem":289,
    "gn:feature_class":"P",
    "gn:feature_code":"PPL",
    "gn:name":"Aka",
    "gn:population":0,
    "gn:timezone":"Pacific/Port_Moresby",
    "iso:country":"PG",
    "name:ceb_x_preferred":[
        "Aka"
    ],
    "name:ces_x_preferred":[
        "Aka"
    ],
    "name:deu_x_preferred":[
        "Aka"
    ],
    "name:fra_x_preferred":[
        "Aka"
    ],
    "name:lav_x_preferred":[
        "AKA"
    ],
    "name:nld_x_preferred":[
        "Aka"
    ],
    "name:pol_x_preferred":[
        "Aka"
    ],
    "name:rus_x_preferred":[
        "\u0410\u043a\u0430"
    ],
    "name:spa_x_preferred":[
        "Aka"
    ],
    "name:swe_x_preferred":[
        "Aka"
    ],
    "name:ukr_x_preferred":[
        "Aka"
    ],
    "name:und_x_variant":[
        "Ka"
    ],
    "wof:name":"Aka",
    "wof:placetype":"locality"
},
  "geometry": {"coordinates":[149.61667,-6.13333],"type":"Point"}
}