{
  "type": "Feature",
  "properties": {
    "gn:admin1_code":"18",
    "gn:asciiname":"Betelvip",
    "gn:country_code":"PG",
    "gn:dem":1076,
    "gn:feature_class":"P",
    "gn:feature_code":"PPL",
    "gn:name":"Betelvip",
    "gn:population":0,
    "gn:timezone":"Pacific/Port_Moresby",
    "iso:country":"PG",
    "name:und_x_variant":[
        "Biltavip",
        "Betelvip"
    ],
    "wof:name":"Betelvip",
    "wof:placetype":"locality"
},
  "geometry": {"coordinates":[141.51086999999995,-5.04958],"type":"Point"}
}