{
  "type": "Feature",
  "properties": {
    "gn:admin1_code":"06",
    "gn:asciiname":"Apkomrae",
    "gn:country_code":"PG",
    "gn:dem":80,
    "gn:feature_class":"P",
    "gn:feature_code":"PPL",
    "gn:name":"Apkomrae",
    "gn:population":0,
    "gn:timezone":"Pacific/Port_Moresby",
    "iso:country":"PG",
    "wof:name":"Apkomrae",
    "wof:placetype":"locality"
},
  "geometry": {"coordinates":[141.43319,-5.82802],"type":"Point"}
}