{
  "type": "Feature",
  "properties": {
    "gn:admin1_code":"02",
    "gn:asciiname":"Ovavaha",
    "gn:country_code":"PG",
    "gn:dem":9,
    "gn:feature_class":"P",
    "gn:feature_code":"PPL",
    "gn:name":"Ovavaha",
    "gn:population":0,
    "gn:timezone":"Pacific/Port_Moresby",
    "iso:country":"PG",
    "name:und_x_variant":[
        "Ovahaha",
        "Ovavaha"
    ],
    "wof:name":"Ovavaha",
    "wof:placetype":"locality"
},
  "geometry": {"coordinates":[145.54391000000001,-7.94137],"type":"Point"}
}