{
  "type": "Feature",
  "properties": {
    "gn:admin1_code":"08",
    "gn:asciiname":"Komungam",
    "gn:country_code":"PG",
    "gn:dem":1648,
    "gn:feature_class":"P",
    "gn:feature_code":"PPL",
    "gn:name":"Komungam",
    "gn:population":0,
    "gn:timezone":"Pacific/Port_Moresby",
    "iso:country":"PG",
    "wof:name":"Komungam",
    "wof:placetype":"locality"
},
  "geometry": {"coordinates":[145.11667,-6.11667],"type":"Point"}
}