{
  "type": "Feature",
  "properties": {
    "gn:admin1_code":"15",
    "gn:asciiname":"Patlangat",
    "gn:country_code":"PG",
    "gn:dem":21,
    "gn:feature_class":"P",
    "gn:feature_code":"PPL",
    "gn:name":"Patlangat",
    "gn:population":0,
    "gn:timezone":"Pacific/Port_Moresby",
    "iso:country":"PG",
    "wof:name":"Patlangat",
    "wof:placetype":"locality"
},
  "geometry": {"coordinates":[151.59999999999999,-3.16667],"type":"Point"}
}