{
  "type": "Feature",
  "properties": {
    "gn:admin1_code":"01",
    "gn:asciiname":"Burevi",
    "gn:country_code":"PG",
    "gn:dem":512,
    "gn:feature_class":"P",
    "gn:feature_code":"PPL",
    "gn:name":"Burevi",
    "gn:population":0,
    "gn:timezone":"Pacific/Port_Moresby",
    "iso:country":"PG",
    "wof:name":"Burevi",
    "wof:placetype":"locality"
},
  "geometry": {"coordinates":[149.28333000000001,-9.98333],"type":"Point"}
}