{
  "type": "Feature",
  "properties": {
    "gn:admin1_code":"09",
    "gn:asciiname":"Lolu",
    "gn:country_code":"PG",
    "gn:dem":1903,
    "gn:feature_class":"P",
    "gn:feature_code":"PPL",
    "gn:name":"Lolu",
    "gn:population":0,
    "gn:timezone":"Pacific/Port_Moresby",
    "iso:country":"PG",
    "wof:name":"Lolu",
    "wof:placetype":"locality"
},
  "geometry": {"coordinates":[145.25,-6.03333],"type":"Point"}
}