{
  "type": "Feature",
  "properties": {
    "gn:admin1_code":"12",
    "gn:asciiname":"Silopi",
    "gn:country_code":"PG",
    "gn:dem":527,
    "gn:feature_class":"P",
    "gn:feature_code":"PPL",
    "gn:name":"Silopi",
    "gn:population":0,
    "gn:timezone":"Pacific/Port_Moresby",
    "iso:country":"PG",
    "name:und_x_variant":[
        "Silipi",
        "Silopi"
    ],
    "wof:name":"Silopi",
    "wof:placetype":"locality"
},
  "geometry": {"coordinates":[145.57380000000001,-5.12728],"type":"Point"}
}