{
  "type": "Feature",
  "properties": {
    "gn:admin1_code":"12",
    "gn:asciiname":"Silopi",
    "gn:country_code":"PG",
    "gn:dem":527,
    "gn:feature_class":"P",
    "gn:feature_code":"PPL",
    "gn:name":"Silopi",
    "gn:population":0,
    "gn:timezone":"Pacific/Port_Moresby",
    "iso:country":"PG",
    "name:ara_x_preferred":[
        "\u0633\u064a\u0644\u0648\u0628\u064a"
    ],
    "name:azb_x_preferred":[
        "\u0633\u06cc\u0644\u0648\u067e\u06cc"
    ],
    "name:ceb_x_preferred":[
        "Silopi \u0130l\u00e7esi"
    ],
    "name:deu_x_preferred":[
        "Silopi"
    ],
    "name:fas_x_preferred":[
        "\u0633\u06cc\u0644\u0648\u067e\u06cc"
    ],
    "name:fra_x_preferred":[
        "Silopi"
    ],
    "name:gag_x_preferred":[
        "Silopi"
    ],
    "name:kur_x_preferred":[
        "Silopiya"
    ],
    "name:min_x_preferred":[
        "Silopi"
    ],
    "name:mrj_x_preferred":[
        "\u0421\u0438\u043b\u043e\u043f\u0438"
    ],
    "name:msa_x_preferred":[
        "Silopi"
    ],
    "name:nld_x_preferred":[
        "Silopi"
    ],
    "name:nno_x_preferred":[
        "Silopi"
    ],
    "name:nor_x_preferred":[
        "Silopi"
    ],
    "name:pnb_x_preferred":[
        "\u0636\u0644\u0639 \u0633\u06cc\u0644\u0648\u067e\u06cc"
    ],
    "name:pol_x_preferred":[
        "Silopi"
    ],
    "name:rus_x_preferred":[
        "\u0421\u0438\u043b\u043e\u043f\u0438"
    ],
    "name:swa_x_preferred":[
        "Silopi"
    ],
    "name:swe_x_preferred":[
        "Silopi"
    ],
    "name:tur_x_preferred":[
        "Silopi"
    ],
    "name:ukr_x_preferred":[
        "\u0421\u0438\u043b\u043e\u043f\u0456"
    ],
    "name:und_x_variant":[
        "Silipi",
        "Silopi"
    ],
    "name:urd_x_preferred":[
        "\u0633\u06cc\u0644\u0648\u067e\u06cc"
    ],
    "name:vie_x_preferred":[
        "Silopi"
    ],
    "name:zho_x_preferred":[
        "\u65af\u6d1b\u6bd4"
    ],
    "wof:name":"Silopi",
    "wof:placetype":"locality"
},
  "geometry": {"coordinates":[145.57380000000001,-5.12728],"type":"Point"}
}