{
  "type": "Feature",
  "properties": {
    "gn:admin1_code":"11",
    "gn:asciiname":"Namareb",
    "gn:country_code":"PG",
    "gn:dem":326,
    "gn:feature_class":"P",
    "gn:feature_code":"PPL",
    "gn:name":"Namareb",
    "gn:population":0,
    "gn:timezone":"Pacific/Port_Moresby",
    "iso:country":"PG",
    "wof:name":"Namareb",
    "wof:placetype":"locality"
},
  "geometry": {"coordinates":[143.78566000000001,-3.71337],"type":"Point"}
}