{
  "type": "Feature",
  "properties": {
    "gn:admin1_code":"06",
    "gn:asciiname":"Gwiribiana",
    "gn:country_code":"PG",
    "gn:dem":111,
    "gn:feature_class":"P",
    "gn:feature_code":"PPL",
    "gn:name":"Gwiribiana",
    "gn:population":0,
    "gn:timezone":"Pacific/Port_Moresby",
    "iso:country":"PG",
    "wof:name":"Gwiribiana",
    "wof:placetype":"locality"
},
  "geometry": {"coordinates":[142.10733999999999,-6.2009],"type":"Point"}
}